Workbook
Name ANN: Parametres!$A$116
Name ATR: Parametres!$A$129
Name BDG_DIR: #REF!
Name BDG_FAM: #REF!
Name BDG_MNT: #REF!
Name BDG_NAT: #REF!
Name BUDGET: 'ENGAGEMENTS 2026'!$M:$M
Name cc: Parametres!$A$80:$A$94
Name DIRECTION: #REF!
Name ENGAGE: Parametres!$A$99
Name Estimation: 'ENGAGEMENTS 2026'!$P:$P
Name Excep: Parametres!$A$5
Name FON: Parametres!$A$7
Name FONCTIONNEMENT: Parametres!$A$10:$A$32
Name INF: Parametres!$A$115
Name INV: Parametres!$A$8
Name INVESTISSEMENT: Parametres!$A$34:$A$44
Name LBDG: 'ENGAGEMENTS 2026'!$N:$N
Name MntENG: 'ENGAGEMENTS 2026'!$AE:$AE
Name MTP: Parametres!$B$48
Name MTT: Parametres!$B$46
Name NA: Parametres!$A$113
Name Ordn: Parametres!$A$4
Name PhaAo: Parametres!$A$134
Name PREENGAGE: Parametres!$A$97
Name qq: Parametres!$A$80:$A$94
Name SSENG: #REF!
Name StatutEng: 'ENGAGEMENTS 2026'!$AF:$AF
Name TypBudget: Parametres!$A$2:$A$5
Name TypeBudget: 'ENGAGEMENTS 2026'!$L:$L
Name xBesoin: Parametres!$A$146:$A$149
Name xBUDGET: Parametres!$A$7:$A$8
Name xCATEGORIES: Parametres!$A$137:$A$139
Name xDIRECTION: Parametres!$A$51:$A$78
Name xENG: Parametres!$A$99
Name XLB: Parametres!$A$80:$A$94
Name xNatype: Parametres!$A$142:$A$144
Name xRec: Parametres!$A$149
Name xStatut1: Parametres!$A$113:$A$118
Name xSTATUTSUP: Parametres!$A$128:$A$135
Name xStEng: Parametres!$A$96:$A$100
Name xTYPE1: Parametres!$A$102:$A$111
Name xTYPSUP: Parametres!$A$120:$A$126

Sheet Tableau de Bord
A1: TABLEAU DE BORD DES ENGAGEMENTS BUDGÉTAIRES 2026 — SNRT
A2: Montants en MAD TTC — calculés dynamiquement (SUMIFS) depuis la feuille « Données Suivi »
A3: DIRECTION | B3: FONCTIONNEMENT | H3: INVESTISSEMENT | N3: TOTAL GÉNÉRAL
B4: ENGAGE | C4: PREENGAGE | D4: EN COURS D'ENGAGEMENT | E4: EN COURS DE PREENGAGEMENT | F4: NON ENGAGE | G4: TOTAL FONC. | H4: ENGAGE | I4: PREENGAGE | J4: EN COURS D'ENGAGEMENT | K4: EN COURS DE PREENGAGEMENT | L4: NON ENGAGE | M4: TOTAL INVE.
A5: ARRIYADIA | B5: =SUMIFS('Données Suivi'!$J$2:$J$3000,'Données Suivi'!$A$2:$A$3000,$A5,'Données Suivi'!$O$2:$O$3000,"FONCTIONNEMENT",'Données Suivi'!$H$2:$H$3000,"ENGAGE") -> 1.8046948e+08 | C5: =SUMIFS('Données Suivi'!$J$2:$J$3000,'Données Suivi'!$A$2:$A$3000,$A5,'Données Suivi'!$O$2:$O$3000,"FONCTIONNEMENT",'Données Suivi'!$H$2:$H$3000,"PREENGAGE") -> 0 | D5: =SUMIFS('Données Suivi'!$J$2:$J$3000,'Données Suivi'!$A$2:$A$3000,$A5,'Données Suivi'!$O$2:$O$3000,"FONCTIONNEMENT",'Données Suivi'!$H$2:$H$3000,"EN COURS D'ENGAGEMENT") -> 73224.48 | E5: =SUMIFS('Données Suivi'!$J$2:$J$3000,'Données Suivi'!$A$2:$A$3000,$A5,'Données Suivi'!$O$2:$O$3000,"FONCTIONNEMENT",'Données Suivi'!$H$2:$H$3000,"EN COURS DE PREENGAGEMENT") -> 0 | F5: =SUMIFS('Données Suivi'!$J$2:$J$3000,'Données Suivi'!$A$2:$A$3000,$A5,'Données Suivi'!$O$2:$O$3000,"FONCTIONNEMENT",'Données Suivi'!$H$2:$H$3000,"NON ENGAGE") -> 0 | G5: =B5+C5+D5+E5+F5 -> 1.805427e+08 | H5: =SUMIFS('Données Suivi'!$J$2:$J$3000,'Données Suivi'!$A$2:$A$3000,$A5,'Données Suivi'!$O$2:$O$3000,"INVESTISSEMENT",'Données Suivi'!$H$2:$H$3000,"ENGAGE") -> 0 | I5: =SUMIFS('Données Suivi'!$J$2:$J$3000,'Données Suivi'!$A$2:$A$3000,$A5,'Données Suivi'!$O$2:$O$3000,"INVESTISSEMENT",'Données Suivi'!$H$2:$H$3000,"PREENGAGE") -> 0 | J5: =SUMIFS('Données Suivi'!$J$2:$J$3000,'Données Suivi'!$A$2:$A$3000,$A5,'Données Suivi'!$O$2:$O$3000,"INVESTISSEMENT",'Données Suivi'!$H$2:$H$3000,"EN COURS D'ENGAGEMENT") -> 0 | K5: =SUMIFS('Données Suivi'!$J$2:$J$3000,'Données Suivi'!$A$2:$A$3000,$A5,'Données Suivi'!$O$2:$O$3000,"INVESTISSEMENT",'Données Suivi'!$H$2:$H$3000,"EN COURS DE PREENGAGEMENT") -> 0 | L5: =SUMIFS('Données Suivi'!$J$2:$J$3000,'Données Suivi'!$A$2:$A$3000,$A5,'Données Suivi'!$O$2:$O$3000,"INVESTISSEMENT",'Données Suivi'!$H$2:$H$3000,"NON ENGAGE") -> 0 | M5: =H5+I5+J5+K5+L5 -> 0 | N5: =G5+M5 -> 1.805427e+08
A6: ASSADISSA | B6: =SUMIFS('Données Suivi'!$J$2:$J$3000,'Données Suivi'!$A$2:$A$3000,$A6,'Données Suivi'!$O$2:$O$3000,"FONCTIONNEMENT",'Données Suivi'!$H$2:$H$3000,"ENGAGE") -> 8022706.3 | C6: =SUMIFS('Données Suivi'!$J$2:$J$3000,'Données Suivi'!$A$2:$A$3000,$A6,'Données Suivi'!$O$2:$O$3000,"FONCTIONNEMENT",'Données Suivi'!$H$2:$H$3000,"PREENGAGE") -> 0 | D6: =SUMIFS('Données Suivi'!$J$2:$J$3000,'Données Suivi'!$A$2:$A$3000,$A6,'Données Suivi'!$O$2:$O$3000,"FONCTIONNEMENT",'Données Suivi'!$H$2:$H$3000,"EN COURS D'ENGAGEMENT") -> 0 | E6: =SUMIFS('Données Suivi'!$J$2:$J$3000,'Données Suivi'!$A$2:$A$3000,$A6,'Données Suivi'!$O$2:$O$3000,"FONCTIONNEMENT",'Données Suivi'!$H$2:$H$3000,"EN COURS DE PREENGAGEMENT") -> 0 | F6: =SUMIFS('Données Suivi'!$J$2:$J$3000,'Données Suivi'!$A$2:$A$3000,$A6,'Données Suivi'!$O$2:$O$3000,"FONCTIONNEMENT",'Données Suivi'!$H$2:$H$3000,"NON ENGAGE") -> 0 | G6: =B6+C6+D6+E6+F6 -> 8022706.3 | H6: =SUMIFS('Données Suivi'!$J$2:$J$3000,'Données Suivi'!$A$2:$A$3000,$A6,'Données Suivi'!$O$2:$O$3000,"INVESTISSEMENT",'Données Suivi'!$H$2:$H$3000,"ENGAGE") -> 0 | I6: =SUMIFS('Données Suivi'!$J$2:$J$3000,'Données Suivi'!$A$2:$A$3000,$A6,'Données Suivi'!$O$2:$O$3000,"INVESTISSEMENT",'Données Suivi'!$H$2:$H$3000,"PREENGAGE") -> 0 | J6: =SUMIFS('Données Suivi'!$J$2:$J$3000,'Données Suivi'!$A$2:$A$3000,$A6,'Données Suivi'!$O$2:$O$3000,"INVESTISSEMENT",'Données Suivi'!$H$2:$H$3000,"EN COURS D'ENGAGEMENT") -> 0 | K6: =SUMIFS('Données Suivi'!$J$2:$J$3000,'Données Suivi'!$A$2:$A$3000,$A6,'Données Suivi'!$O$2:$O$3000,"INVESTISSEMENT",'Données Suivi'!$H$2:$H$3000,"EN COURS DE PREENGAGEMENT") -> 0 | L6: =SUMIFS('Données Suivi'!$J$2:$J$3000,'Données Suivi'!$A$2:$A$3000,$A6,'Données Suivi'!$O$2:$O$3000,"INVESTISSEMENT",'Données Suivi'!$H$2:$H$3000,"NON ENGAGE") -> 0 | M6: =H6+I6+J6+K6+L6 -> 0 | N6: =G6+M6 -> 8022706.3
A7: DA | B7: =SUMIFS('Données Suivi'!$J$2:$J$3000,'Données Suivi'!$A$2:$A$3000,$A7,'Données Suivi'!$O$2:$O$3000,"FONCTIONNEMENT",'Données Suivi'!$H$2:$H$3000,"ENGAGE") -> 427760 | C7: =SUMIFS('Données Suivi'!$J$2:$J$3000,'Données Suivi'!$A$2:$A$3000,$A7,'Données Suivi'!$O$2:$O$3000,"FONCTIONNEMENT",'Données Suivi'!$H$2:$H$3000,"PREENGAGE") -> 0 | D7: =SUMIFS('Données Suivi'!$J$2:$J$3000,'Données Suivi'!$A$2:$A$3000,$A7,'Données Suivi'!$O$2:$O$3000,"FONCTIONNEMENT",'Données Suivi'!$H$2:$H$3000,"EN COURS D'ENGAGEMENT") -> 0 | E7: =SUMIFS('Données Suivi'!$J$2:$J$3000,'Données Suivi'!$A$2:$A$3000,$A7,'Données Suivi'!$O$2:$O$3000,"FONCTIONNEMENT",'Données Suivi'!$H$2:$H$3000,"EN COURS DE PREENGAGEMENT") -> 0 | F7: =SUMIFS('Données Suivi'!$J$2:$J$3000,'Données Suivi'!$A$2:$A$3000,$A7,'Données Suivi'!$O$2:$O$3000,"FONCTIONNEMENT",'Données Suivi'!$H$2:$H$3000,"NON ENGAGE") -> 0 | G7: =B7+C7+D7+E7+F7 -> 427760 | H7: =SUMIFS('Données Suivi'!$J$2:$J$3000,'Données Suivi'!$A$2:$A$3000,$A7,'Données Suivi'!$O$2:$O$3000,"INVESTISSEMENT",'Données Suivi'!$H$2:$H$3000,"ENGAGE") -> 0 | I7: =SUMIFS('Données Suivi'!$J$2:$J$3000,'Données Suivi'!$A$2:$A$3000,$A7,'Données Suivi'!$O$2:$O$3000,"INVESTISSEMENT",'Données Suivi'!$H$2:$H$3000,"PREENGAGE") -> 0 | J7: =SUMIFS('Données Suivi'!$J$2:$J$3000,'Données Suivi'!$A$2:$A$3000,$A7,'Données Suivi'!$O$2:$O$3000,"INVESTISSEMENT",'Données Suivi'!$H$2:$H$3000,"EN COURS D'ENGAGEMENT") -> 0 | K7: =SUMIFS('Données Suivi'!$J$2:$J$3000,'Données Suivi'!$A$2:$A$3000,$A7,'Données Suivi'!$O$2:$O$3000,"INVESTISSEMENT",'Données Suivi'!$H$2:$H$3000,"EN COURS DE PREENGAGEMENT") -> 0 | L7: =SUMIFS('Données Suivi'!$J$2:$J$3000,'Données Suivi'!$A$2:$A$3000,$A7,'Données Suivi'!$O$2:$O$3000,"INVESTISSEMENT",'Données Suivi'!$H$2:$H$3000,"NON ENGAGE") -> 0 | M7: =H7+I7+J7+K7+L7 -> 0 | N7: =G7+M7 -> 427760
A8: DACG | B8: =SUMIFS('Données Suivi'!$J$2:$J$3000,'Données Suivi'!$A$2:$A$3000,$A8,'Données Suivi'!$O$2:$O$3000,"FONCTIONNEMENT",'Données Suivi'!$H$2:$H$3000,"ENGAGE") -> 318500 | C8: =SUMIFS('Données Suivi'!$J$2:$J$3000,'Données Suivi'!$A$2:$A$3000,$A8,'Données Suivi'!$O$2:$O$3000,"FONCTIONNEMENT",'Données Suivi'!$H$2:$H$3000,"PREENGAGE") -> 0 | D8: =SUMIFS('Données Suivi'!$J$2:$J$3000,'Données Suivi'!$A$2:$A$3000,$A8,'Données Suivi'!$O$2:$O$3000,"FONCTIONNEMENT",'Données Suivi'!$H$2:$H$3000,"EN COURS D'ENGAGEMENT") -> 0 | E8: =SUMIFS('Données Suivi'!$J$2:$J$3000,'Données Suivi'!$A$2:$A$3000,$A8,'Données Suivi'!$O$2:$O$3000,"FONCTIONNEMENT",'Données Suivi'!$H$2:$H$3000,"EN COURS DE PREENGAGEMENT") -> 144000 | F8: =SUMIFS('Données Suivi'!$J$2:$J$3000,'Données Suivi'!$A$2:$A$3000,$A8,'Données Suivi'!$O$2:$O$3000,"FONCTIONNEMENT",'Données Suivi'!$H$2:$H$3000,"NON ENGAGE") -> 0 | G8: =B8+C8+D8+E8+F8 -> 462500 | H8: =SUMIFS('Données Suivi'!$J$2:$J$3000,'Données Suivi'!$A$2:$A$3000,$A8,'Données Suivi'!$O$2:$O$3000,"INVESTISSEMENT",'Données Suivi'!$H$2:$H$3000,"ENGAGE") -> 0 | I8: =SUMIFS('Données Suivi'!$J$2:$J$3000,'Données Suivi'!$A$2:$A$3000,$A8,'Données Suivi'!$O$2:$O$3000,"INVESTISSEMENT",'Données Suivi'!$H$2:$H$3000,"PREENGAGE") -> 0 | J8: =SUMIFS('Données Suivi'!$J$2:$J$3000,'Données Suivi'!$A$2:$A$3000,$A8,'Données Suivi'!$O$2:$O$3000,"INVESTISSEMENT",'Données Suivi'!$H$2:$H$3000,"EN COURS D'ENGAGEMENT") -> 0 | K8: =SUMIFS('Données Suivi'!$J$2:$J$3000,'Données Suivi'!$A$2:$A$3000,$A8,'Données Suivi'!$O$2:$O$3000,"INVESTISSEMENT",'Données Suivi'!$H$2:$H$3000,"EN COURS DE PREENGAGEMENT") -> 0 | L8: =SUMIFS('Données Suivi'!$J$2:$J$3000,'Données Suivi'!$A$2:$A$3000,$A8,'Données Suivi'!$O$2:$O$3000,"INVESTISSEMENT",'Données Suivi'!$H$2:$H$3000,"NON ENGAGE") -> 0 | M8: =H8+I8+J8+K8+L8 -> 0 | N8: =G8+M8 -> 462500
A9: DAR | B9: =SUMIFS('Données Suivi'!$J$2:$J$3000,'Données Suivi'!$A$2:$A$3000,$A9,'Données Suivi'!$O$2:$O$3000,"FONCTIONNEMENT",'Données Suivi'!$H$2:$H$3000,"ENGAGE") -> 108000 | C9: =SUMIFS('Données Suivi'!$J$2:$J$3000,'Données Suivi'!$A$2:$A$3000,$A9,'Données Suivi'!$O$2:$O$3000,"FONCTIONNEMENT",'Données Suivi'!$H$2:$H$3000,"PREENGAGE") -> 0 | D9: =SUMIFS('Données Suivi'!$J$2:$J$3000,'Données Suivi'!$A$2:$A$3000,$A9,'Données Suivi'!$O$2:$O$3000,"FONCTIONNEMENT",'Données Suivi'!$H$2:$H$3000,"EN COURS D'ENGAGEMENT") -> 0 | E9: =SUMIFS('Données Suivi'!$J$2:$J$3000,'Données Suivi'!$A$2:$A$3000,$A9,'Données Suivi'!$O$2:$O$3000,"FONCTIONNEMENT",'Données Suivi'!$H$2:$H$3000,"EN COURS DE PREENGAGEMENT") -> 0 | F9: =SUMIFS('Données Suivi'!$J$2:$J$3000,'Données Suivi'!$A$2:$A$3000,$A9,'Données Suivi'!$O$2:$O$3000,"FONCTIONNEMENT",'Données Suivi'!$H$2:$H$3000,"NON ENGAGE") -> 0 | G9: =B9+C9+D9+E9+F9 -> 108000 | H9: =SUMIFS('Données Suivi'!$J$2:$J$3000,'Données Suivi'!$A$2:$A$3000,$A9,'Données Suivi'!$O$2:$O$3000,"INVESTISSEMENT",'Données Suivi'!$H$2:$H$3000,"ENGAGE") -> 0 | I9: =SUMIFS('Données Suivi'!$J$2:$J$3000,'Données Suivi'!$A$2:$A$3000,$A9,'Données Suivi'!$O$2:$O$3000,"INVESTISSEMENT",'Données Suivi'!$H$2:$H$3000,"PREENGAGE") -> 0 | J9: =SUMIFS('Données Suivi'!$J$2:$J$3000,'Données Suivi'!$A$2:$A$3000,$A9,'Données Suivi'!$O$2:$O$3000,"INVESTISSEMENT",'Données Suivi'!$H$2:$H$3000,"EN COURS D'ENGAGEMENT") -> 0 | K9: =SUMIFS('Données Suivi'!$J$2:$J$3000,'Données Suivi'!$A$2:$A$3000,$A9,'Données Suivi'!$O$2:$O$3000,"INVESTISSEMENT",'Données Suivi'!$H$2:$H$3000,"EN COURS DE PREENGAGEMENT") -> 0 | L9: =SUMIFS('Données Suivi'!$J$2:$J$3000,'Données Suivi'!$A$2:$A$3000,$A9,'Données Suivi'!$O$2:$O$3000,"INVESTISSEMENT",'Données Suivi'!$H$2:$H$3000,"NON ENGAGE") -> 0 | M9: =H9+I9+J9+K9+L9 -> 0 | N9: =G9+M9 -> 108000
A10: DCPA | B10: =SUMIFS('Données Suivi'!$J$2:$J$3000,'Données Suivi'!$A$2:$A$3000,$A10,'Données Suivi'!$O$2:$O$3000,"FONCTIONNEMENT",'Données Suivi'!$H$2:$H$3000,"ENGAGE") -> 61489072 | C10: =SUMIFS('Données Suivi'!$J$2:$J$3000,'Données Suivi'!$A$2:$A$3000,$A10,'Données Suivi'!$O$2:$O$3000,"FONCTIONNEMENT",'Données Suivi'!$H$2:$H$3000,"PREENGAGE") -> 0 | D10: =SUMIFS('Données Suivi'!$J$2:$J$3000,'Données Suivi'!$A$2:$A$3000,$A10,'Données Suivi'!$O$2:$O$3000,"FONCTIONNEMENT",'Données Suivi'!$H$2:$H$3000,"EN COURS D'ENGAGEMENT") -> 9889068 | E10: =SUMIFS('Données Suivi'!$J$2:$J$3000,'Données Suivi'!$A$2:$A$3000,$A10,'Données Suivi'!$O$2:$O$3000,"FONCTIONNEMENT",'Données Suivi'!$H$2:$H$3000,"EN COURS DE PREENGAGEMENT") -> 0 | F10: =SUMIFS('Données Suivi'!$J$2:$J$3000,'Données Suivi'!$A$2:$A$3000,$A10,'Données Suivi'!$O$2:$O$3000,"FONCTIONNEMENT",'Données Suivi'!$H$2:$H$3000,"NON ENGAGE") -> 0 | G10: =B10+C10+D10+E10+F10 -> 71378140 | H10: =SUMIFS('Données Suivi'!$J$2:$J$3000,'Données Suivi'!$A$2:$A$3000,$A10,'Données Suivi'!$O$2:$O$3000,"INVESTISSEMENT",'Données Suivi'!$H$2:$H$3000,"ENGAGE") -> 0 | I10: =SUMIFS('Données Suivi'!$J$2:$J$3000,'Données Suivi'!$A$2:$A$3000,$A10,'Données Suivi'!$O$2:$O$3000,"INVESTISSEMENT",'Données Suivi'!$H$2:$H$3000,"PREENGAGE") -> 0 | J10: =SUMIFS('Données Suivi'!$J$2:$J$3000,'Données Suivi'!$A$2:$A$3000,$A10,'Données Suivi'!$O$2:$O$3000,"INVESTISSEMENT",'Données Suivi'!$H$2:$H$3000,"EN COURS D'ENGAGEMENT") -> 0 | K10: =SUMIFS('Données Suivi'!$J$2:$J$3000,'Données Suivi'!$A$2:$A$3000,$A10,'Données Suivi'!$O$2:$O$3000,"INVESTISSEMENT",'Données Suivi'!$H$2:$H$3000,"EN COURS DE PREENGAGEMENT") -> 0 | L10: =SUMIFS('Données Suivi'!$J$2:$J$3000,'Données Suivi'!$A$2:$A$3000,$A10,'Données Suivi'!$O$2:$O$3000,"INVESTISSEMENT",'Données Suivi'!$H$2:$H$3000,"NON ENGAGE") -> 0 | M10: =H10+I10+J10+K10+L10 -> 0 | N10: =G10+M10 -> 71378140
A11: DCRI | B11: =SUMIFS('Données Suivi'!$J$2:$J$3000,'Données Suivi'!$A$2:$A$3000,$A11,'Données Suivi'!$O$2:$O$3000,"FONCTIONNEMENT",'Données Suivi'!$H$2:$H$3000,"ENGAGE") -> 318240 | C11: =SUMIFS('Données Suivi'!$J$2:$J$3000,'Données Suivi'!$A$2:$A$3000,$A11,'Données Suivi'!$O$2:$O$3000,"FONCTIONNEMENT",'Données Suivi'!$H$2:$H$3000,"PREENGAGE") -> 0 | D11: =SUMIFS('Données Suivi'!$J$2:$J$3000,'Données Suivi'!$A$2:$A$3000,$A11,'Données Suivi'!$O$2:$O$3000,"FONCTIONNEMENT",'Données Suivi'!$H$2:$H$3000,"EN COURS D'ENGAGEMENT") -> 0 | E11: =SUMIFS('Données Suivi'!$J$2:$J$3000,'Données Suivi'!$A$2:$A$3000,$A11,'Données Suivi'!$O$2:$O$3000,"FONCTIONNEMENT",'Données Suivi'!$H$2:$H$3000,"EN COURS DE PREENGAGEMENT") -> 0 | F11: =SUMIFS('Données Suivi'!$J$2:$J$3000,'Données Suivi'!$A$2:$A$3000,$A11,'Données Suivi'!$O$2:$O$3000,"FONCTIONNEMENT",'Données Suivi'!$H$2:$H$3000,"NON ENGAGE") -> 0 | G11: =B11+C11+D11+E11+F11 -> 318240 | H11: =SUMIFS('Données Suivi'!$J$2:$J$3000,'Données Suivi'!$A$2:$A$3000,$A11,'Données Suivi'!$O$2:$O$3000,"INVESTISSEMENT",'Données Suivi'!$H$2:$H$3000,"ENGAGE") -> 0 | I11: =SUMIFS('Données Suivi'!$J$2:$J$3000,'Données Suivi'!$A$2:$A$3000,$A11,'Données Suivi'!$O$2:$O$3000,"INVESTISSEMENT",'Données Suivi'!$H$2:$H$3000,"PREENGAGE") -> 0 | J11: =SUMIFS('Données Suivi'!$J$2:$J$3000,'Données Suivi'!$A$2:$A$3000,$A11,'Données Suivi'!$O$2:$O$3000,"INVESTISSEMENT",'Données Suivi'!$H$2:$H$3000,"EN COURS D'ENGAGEMENT") -> 0 | K11: =SUMIFS('Données Suivi'!$J$2:$J$3000,'Données Suivi'!$A$2:$A$3000,$A11,'Données Suivi'!$O$2:$O$3000,"INVESTISSEMENT",'Données Suivi'!$H$2:$H$3000,"EN COURS DE PREENGAGEMENT") -> 0 | L11: =SUMIFS('Données Suivi'!$J$2:$J$3000,'Données Suivi'!$A$2:$A$3000,$A11,'Données Suivi'!$O$2:$O$3000,"INVESTISSEMENT",'Données Suivi'!$H$2:$H$3000,"NON ENGAGE") -> 0 | M11: =H11+I11+J11+K11+L11 -> 0 | N11: =G11+M11 -> 318240
A12: DCT | B12: =SUMIFS('Données Suivi'!$J$2:$J$3000,'Données Suivi'!$A$2:$A$3000,$A12,'Données Suivi'!$O$2:$O$3000,"FONCTIONNEMENT",'Données Suivi'!$H$2:$H$3000,"ENGAGE") -> 8945954.8 | C12: =SUMIFS('Données Suivi'!$J$2:$J$3000,'Données Suivi'!$A$2:$A$3000,$A12,'Données Suivi'!$O$2:$O$3000,"FONCTIONNEMENT",'Données Suivi'!$H$2:$H$3000,"PREENGAGE") -> 135388.8 | D12: =SUMIFS('Données Suivi'!$J$2:$J$3000,'Données Suivi'!$A$2:$A$3000,$A12,'Données Suivi'!$O$2:$O$3000,"FONCTIONNEMENT",'Données Suivi'!$H$2:$H$3000,"EN COURS D'ENGAGEMENT") -> 970159.68 | E12: =SUMIFS('Données Suivi'!$J$2:$J$3000,'Données Suivi'!$A$2:$A$3000,$A12,'Données Suivi'!$O$2:$O$3000,"FONCTIONNEMENT",'Données Suivi'!$H$2:$H$3000,"EN COURS DE PREENGAGEMENT") -> 0 | F12: =SUMIFS('Données Suivi'!$J$2:$J$3000,'Données Suivi'!$A$2:$A$3000,$A12,'Données Suivi'!$O$2:$O$3000,"FONCTIONNEMENT",'Données Suivi'!$H$2:$H$3000,"NON ENGAGE") -> 616128 | G12: =B12+C12+D12+E12+F12 -> 10667631 | H12: =SUMIFS('Données Suivi'!$J$2:$J$3000,'Données Suivi'!$A$2:$A$3000,$A12,'Données Suivi'!$O$2:$O$3000,"INVESTISSEMENT",'Données Suivi'!$H$2:$H$3000,"ENGAGE") -> 10359432 | I12: =SUMIFS('Données Suivi'!$J$2:$J$3000,'Données Suivi'!$A$2:$A$3000,$A12,'Données Suivi'!$O$2:$O$3000,"INVESTISSEMENT",'Données Suivi'!$H$2:$H$3000,"PREENGAGE") -> 27705715 | J12: =SUMIFS('Données Suivi'!$J$2:$J$3000,'Données Suivi'!$A$2:$A$3000,$A12,'Données Suivi'!$O$2:$O$3000,"INVESTISSEMENT",'Données Suivi'!$H$2:$H$3000,"EN COURS D'ENGAGEMENT") -> 2017741.2 | K12: =SUMIFS('Données Suivi'!$J$2:$J$3000,'Données Suivi'!$A$2:$A$3000,$A12,'Données Suivi'!$O$2:$O$3000,"INVESTISSEMENT",'Données Suivi'!$H$2:$H$3000,"EN COURS DE PREENGAGEMENT") -> 11556000 | L12: =SUMIFS('Données Suivi'!$J$2:$J$3000,'Données Suivi'!$A$2:$A$3000,$A12,'Données Suivi'!$O$2:$O$3000,"INVESTISSEMENT",'Données Suivi'!$H$2:$H$3000,"NON ENGAGE") -> 24966744 | M12: =H12+I12+J12+K12+L12 -> 76605632 | N12: =G12+M12 -> 87273264
A13: DG | B13: =SUMIFS('Données Suivi'!$J$2:$J$3000,'Données Suivi'!$A$2:$A$3000,$A13,'Données Suivi'!$O$2:$O$3000,"FONCTIONNEMENT",'Données Suivi'!$H$2:$H$3000,"ENGAGE") -> 576000 | C13: =SUMIFS('Données Suivi'!$J$2:$J$3000,'Données Suivi'!$A$2:$A$3000,$A13,'Données Suivi'!$O$2:$O$3000,"FONCTIONNEMENT",'Données Suivi'!$H$2:$H$3000,"PREENGAGE") -> 0 | D13: =SUMIFS('Données Suivi'!$J$2:$J$3000,'Données Suivi'!$A$2:$A$3000,$A13,'Données Suivi'!$O$2:$O$3000,"FONCTIONNEMENT",'Données Suivi'!$H$2:$H$3000,"EN COURS D'ENGAGEMENT") -> 0 | E13: =SUMIFS('Données Suivi'!$J$2:$J$3000,'Données Suivi'!$A$2:$A$3000,$A13,'Données Suivi'!$O$2:$O$3000,"FONCTIONNEMENT",'Données Suivi'!$H$2:$H$3000,"EN COURS DE PREENGAGEMENT") -> 0 | F13: =SUMIFS('Données Suivi'!$J$2:$J$3000,'Données Suivi'!$A$2:$A$3000,$A13,'Données Suivi'!$O$2:$O$3000,"FONCTIONNEMENT",'Données Suivi'!$H$2:$H$3000,"NON ENGAGE") -> 0 | G13: =B13+C13+D13+E13+F13 -> 576000 | H13: =SUMIFS('Données Suivi'!$J$2:$J$3000,'Données Suivi'!$A$2:$A$3000,$A13,'Données Suivi'!$O$2:$O$3000,"INVESTISSEMENT",'Données Suivi'!$H$2:$H$3000,"ENGAGE") -> 0 | I13: =SUMIFS('Données Suivi'!$J$2:$J$3000,'Données Suivi'!$A$2:$A$3000,$A13,'Données Suivi'!$O$2:$O$3000,"INVESTISSEMENT",'Données Suivi'!$H$2:$H$3000,"PREENGAGE") -> 0 | J13: =SUMIFS('Données Suivi'!$J$2:$J$3000,'Données Suivi'!$A$2:$A$3000,$A13,'Données Suivi'!$O$2:$O$3000,"INVESTISSEMENT",'Données Suivi'!$H$2:$H$3000,"EN COURS D'ENGAGEMENT") -> 0 | K13: =SUMIFS('Données Suivi'!$J$2:$J$3000,'Données Suivi'!$A$2:$A$3000,$A13,'Données Suivi'!$O$2:$O$3000,"INVESTISSEMENT",'Données Suivi'!$H$2:$H$3000,"EN COURS DE PREENGAGEMENT") -> 0 | L13: =SUMIFS('Données Suivi'!$J$2:$J$3000,'Données Suivi'!$A$2:$A$3000,$A13,'Données Suivi'!$O$2:$O$3000,"INVESTISSEMENT",'Données Suivi'!$H$2:$H$3000,"NON ENGAGE") -> 0 | M13: =H13+I13+J13+K13+L13 -> 0 | N13: =G13+M13 -> 576000
A14: DINFORADIO | B14: =SUMIFS('Données Suivi'!$J$2:$J$3000,'Données Suivi'!$A$2:$A$3000,$A14,'Données Suivi'!$O$2:$O$3000,"FONCTIONNEMENT",'Données Suivi'!$H$2:$H$3000,"ENGAGE") -> 2648832.5 | C14: =SUMIFS('Données Suivi'!$J$2:$J$3000,'Données Suivi'!$A$2:$A$3000,$A14,'Données Suivi'!$O$2:$O$3000,"FONCTIONNEMENT",'Données Suivi'!$H$2:$H$3000,"PREENGAGE") -> 0 | D14: =SUMIFS('Données Suivi'!$J$2:$J$3000,'Données Suivi'!$A$2:$A$3000,$A14,'Données Suivi'!$O$2:$O$3000,"FONCTIONNEMENT",'Données Suivi'!$H$2:$H$3000,"EN COURS D'ENGAGEMENT") -> 0 | E14: =SUMIFS('Données Suivi'!$J$2:$J$3000,'Données Suivi'!$A$2:$A$3000,$A14,'Données Suivi'!$O$2:$O$3000,"FONCTIONNEMENT",'Données Suivi'!$H$2:$H$3000,"EN COURS DE PREENGAGEMENT") -> 0 | F14: =SUMIFS('Données Suivi'!$J$2:$J$3000,'Données Suivi'!$A$2:$A$3000,$A14,'Données Suivi'!$O$2:$O$3000,"FONCTIONNEMENT",'Données Suivi'!$H$2:$H$3000,"NON ENGAGE") -> 0 | G14: =B14+C14+D14+E14+F14 -> 2648832.5 | H14: =SUMIFS('Données Suivi'!$J$2:$J$3000,'Données Suivi'!$A$2:$A$3000,$A14,'Données Suivi'!$O$2:$O$3000,"INVESTISSEMENT",'Données Suivi'!$H$2:$H$3000,"ENGAGE") -> 0 | I14: =SUMIFS('Données Suivi'!$J$2:$J$3000,'Données Suivi'!$A$2:$A$3000,$A14,'Données Suivi'!$O$2:$O$3000,"INVESTISSEMENT",'Données Suivi'!$H$2:$H$3000,"PREENGAGE") -> 0 | J14: =SUMIFS('Données Suivi'!$J$2:$J$3000,'Données Suivi'!$A$2:$A$3000,$A14,'Données Suivi'!$O$2:$O$3000,"INVESTISSEMENT",'Données Suivi'!$H$2:$H$3000,"EN COURS D'ENGAGEMENT") -> 0 | K14: =SUMIFS('Données Suivi'!$J$2:$J$3000,'Données Suivi'!$A$2:$A$3000,$A14,'Données Suivi'!$O$2:$O$3000,"INVESTISSEMENT",'Données Suivi'!$H$2:$H$3000,"EN COURS DE PREENGAGEMENT") -> 0 | L14: =SUMIFS('Données Suivi'!$J$2:$J$3000,'Données Suivi'!$A$2:$A$3000,$A14,'Données Suivi'!$O$2:$O$3000,"INVESTISSEMENT",'Données Suivi'!$H$2:$H$3000,"NON ENGAGE") -> 0 | M14: =H14+I14+J14+K14+L14 -> 0 | N14: =G14+M14 -> 2648832.5
A15: DINFOTV | B15: =SUMIFS('Données Suivi'!$J$2:$J$3000,'Données Suivi'!$A$2:$A$3000,$A15,'Données Suivi'!$O$2:$O$3000,"FONCTIONNEMENT",'Données Suivi'!$H$2:$H$3000,"ENGAGE") -> 10711701 | C15: =SUMIFS('Données Suivi'!$J$2:$J$3000,'Données Suivi'!$A$2:$A$3000,$A15,'Données Suivi'!$O$2:$O$3000,"FONCTIONNEMENT",'Données Suivi'!$H$2:$H$3000,"PREENGAGE") -> 0 | D15: =SUMIFS('Données Suivi'!$J$2:$J$3000,'Données Suivi'!$A$2:$A$3000,$A15,'Données Suivi'!$O$2:$O$3000,"FONCTIONNEMENT",'Données Suivi'!$H$2:$H$3000,"EN COURS D'ENGAGEMENT") -> 1508695.3 | E15: =SUMIFS('Données Suivi'!$J$2:$J$3000,'Données Suivi'!$A$2:$A$3000,$A15,'Données Suivi'!$O$2:$O$3000,"FONCTIONNEMENT",'Données Suivi'!$H$2:$H$3000,"EN COURS DE PREENGAGEMENT") -> 0 | F15: =SUMIFS('Données Suivi'!$J$2:$J$3000,'Données Suivi'!$A$2:$A$3000,$A15,'Données Suivi'!$O$2:$O$3000,"FONCTIONNEMENT",'Données Suivi'!$H$2:$H$3000,"NON ENGAGE") -> 0 | G15: =B15+C15+D15+E15+F15 -> 12220397 | H15: =SUMIFS('Données Suivi'!$J$2:$J$3000,'Données Suivi'!$A$2:$A$3000,$A15,'Données Suivi'!$O$2:$O$3000,"INVESTISSEMENT",'Données Suivi'!$H$2:$H$3000,"ENGAGE") -> 0 | I15: =SUMIFS('Données Suivi'!$J$2:$J$3000,'Données Suivi'!$A$2:$A$3000,$A15,'Données Suivi'!$O$2:$O$3000,"INVESTISSEMENT",'Données Suivi'!$H$2:$H$3000,"PREENGAGE") -> 0 | J15: =SUMIFS('Données Suivi'!$J$2:$J$3000,'Données Suivi'!$A$2:$A$3000,$A15,'Données Suivi'!$O$2:$O$3000,"INVESTISSEMENT",'Données Suivi'!$H$2:$H$3000,"EN COURS D'ENGAGEMENT") -> 0 | K15: =SUMIFS('Données Suivi'!$J$2:$J$3000,'Données Suivi'!$A$2:$A$3000,$A15,'Données Suivi'!$O$2:$O$3000,"INVESTISSEMENT",'Données Suivi'!$H$2:$H$3000,"EN COURS DE PREENGAGEMENT") -> 0 | L15: =SUMIFS('Données Suivi'!$J$2:$J$3000,'Données Suivi'!$A$2:$A$3000,$A15,'Données Suivi'!$O$2:$O$3000,"INVESTISSEMENT",'Données Suivi'!$H$2:$H$3000,"NON ENGAGE") -> 0 | M15: =H15+I15+J15+K15+L15 -> 0 | N15: =G15+M15 -> 12220397
A16: DJURIDIQUE | B16: =SUMIFS('Données Suivi'!$J$2:$J$3000,'Données Suivi'!$A$2:$A$3000,$A16,'Données Suivi'!$O$2:$O$3000,"FONCTIONNEMENT",'Données Suivi'!$H$2:$H$3000,"ENGAGE") -> 8551887.7 | C16: =SUMIFS('Données Suivi'!$J$2:$J$3000,'Données Suivi'!$A$2:$A$3000,$A16,'Données Suivi'!$O$2:$O$3000,"FONCTIONNEMENT",'Données Suivi'!$H$2:$H$3000,"PREENGAGE") -> 0 | D16: =SUMIFS('Données Suivi'!$J$2:$J$3000,'Données Suivi'!$A$2:$A$3000,$A16,'Données Suivi'!$O$2:$O$3000,"FONCTIONNEMENT",'Données Suivi'!$H$2:$H$3000,"EN COURS D'ENGAGEMENT") -> 9600 | E16: =SUMIFS('Données Suivi'!$J$2:$J$3000,'Données Suivi'!$A$2:$A$3000,$A16,'Données Suivi'!$O$2:$O$3000,"FONCTIONNEMENT",'Données Suivi'!$H$2:$H$3000,"EN COURS DE PREENGAGEMENT") -> 0 | F16: =SUMIFS('Données Suivi'!$J$2:$J$3000,'Données Suivi'!$A$2:$A$3000,$A16,'Données Suivi'!$O$2:$O$3000,"FONCTIONNEMENT",'Données Suivi'!$H$2:$H$3000,"NON ENGAGE") -> 0 | G16: =B16+C16+D16+E16+F16 -> 8561487.7 | H16: =SUMIFS('Données Suivi'!$J$2:$J$3000,'Données Suivi'!$A$2:$A$3000,$A16,'Données Suivi'!$O$2:$O$3000,"INVESTISSEMENT",'Données Suivi'!$H$2:$H$3000,"ENGAGE") -> 0 | I16: =SUMIFS('Données Suivi'!$J$2:$J$3000,'Données Suivi'!$A$2:$A$3000,$A16,'Données Suivi'!$O$2:$O$3000,"INVESTISSEMENT",'Données Suivi'!$H$2:$H$3000,"PREENGAGE") -> 0 | J16: =SUMIFS('Données Suivi'!$J$2:$J$3000,'Données Suivi'!$A$2:$A$3000,$A16,'Données Suivi'!$O$2:$O$3000,"INVESTISSEMENT",'Données Suivi'!$H$2:$H$3000,"EN COURS D'ENGAGEMENT") -> 0 | K16: =SUMIFS('Données Suivi'!$J$2:$J$3000,'Données Suivi'!$A$2:$A$3000,$A16,'Données Suivi'!$O$2:$O$3000,"INVESTISSEMENT",'Données Suivi'!$H$2:$H$3000,"EN COURS DE PREENGAGEMENT") -> 0 | L16: =SUMIFS('Données Suivi'!$J$2:$J$3000,'Données Suivi'!$A$2:$A$3000,$A16,'Données Suivi'!$O$2:$O$3000,"INVESTISSEMENT",'Données Suivi'!$H$2:$H$3000,"NON ENGAGE") -> 0 | M16: =H16+I16+J16+K16+L16 -> 0 | N16: =G16+M16 -> 8561487.7
... A27: TV LAAYOUNE | B27: =SUMIFS('Données Suivi'!$J$2:$J$3000,'Données Suivi'!$A$2:$A$3000,$A27,'Données Suivi'!$O$2:$O$3000,"FONCTIONNEMENT",'Données Suivi'!$H$2:$H$3000,"ENGAGE") -> 22592636 | C27: =SUMIFS('Données Suivi'!$J$2:$J$3000,'Données Suivi'!$A$2:$A$3000,$A27,'Données Suivi'!$O$2:$O$3000,"FONCTIONNEMENT",'Données Suivi'!$H$2:$H$3000,"PREENGAGE") -> 102000 | D27: =SUMIFS('Données Suivi'!$J$2:$J$3000,'Données Suivi'!$A$2:$A$3000,$A27,'Données Suivi'!$O$2:$O$3000,"FONCTIONNEMENT",'Données Suivi'!$H$2:$H$3000,"EN COURS D'ENGAGEMENT") -> 0 | E27: =SUMIFS('Données Suivi'!$J$2:$J$3000,'Données Suivi'!$A$2:$A$3000,$A27,'Données Suivi'!$O$2:$O$3000,"FONCTIONNEMENT",'Données Suivi'!$H$2:$H$3000,"EN COURS DE PREENGAGEMENT") -> 0 | F27: =SUMIFS('Données Suivi'!$J$2:$J$3000,'Données Suivi'!$A$2:$A$3000,$A27,'Données Suivi'!$O$2:$O$3000,"FONCTIONNEMENT",'Données Suivi'!$H$2:$H$3000,"NON ENGAGE") -> 0 | G27: =B27+C27+D27+E27+F27 -> 22694636 | H27: =SUMIFS('Données Suivi'!$J$2:$J$3000,'Données Suivi'!$A$2:$A$3000,$A27,'Données Suivi'!$O$2:$O$3000,"INVESTISSEMENT",'Données Suivi'!$H$2:$H$3000,"ENGAGE") -> 0 | I27: =SUMIFS('Données Suivi'!$J$2:$J$3000,'Données Suivi'!$A$2:$A$3000,$A27,'Données Suivi'!$O$2:$O$3000,"INVESTISSEMENT",'Données Suivi'!$H$2:$H$3000,"PREENGAGE") -> 0 | J27: =SUMIFS('Données Suivi'!$J$2:$J$3000,'Données Suivi'!$A$2:$A$3000,$A27,'Données Suivi'!$O$2:$O$3000,"INVESTISSEMENT",'Données Suivi'!$H$2:$H$3000,"EN COURS D'ENGAGEMENT") -> 0 | K27: =SUMIFS('Données Suivi'!$J$2:$J$3000,'Données Suivi'!$A$2:$A$3000,$A27,'Données Suivi'!$O$2:$O$3000,"INVESTISSEMENT",'Données Suivi'!$H$2:$H$3000,"EN COURS DE PREENGAGEMENT") -> 0 | L27: =SUMIFS('Données Suivi'!$J$2:$J$3000,'Données Suivi'!$A$2:$A$3000,$A27,'Données Suivi'!$O$2:$O$3000,"INVESTISSEMENT",'Données Suivi'!$H$2:$H$3000,"NON ENGAGE") -> 0 | M27: =H27+I27+J27+K27+L27 -> 0 | N27: =G27+M27 -> 22694636
A28: TOTAL GÉNÉRAL | B28: =SUM(B5:B27) -> 6.0709519e+08 | C28: =SUM(C5:C27) -> 32722158 | D28: =SUM(D5:D27) -> 22263126 | E28: =SUM(E5:E27) -> 9329928 | F28: =SUM(F5:F27) -> 7563008 | G28: =SUM(G5:G27) -> 6.7897341e+08 | H28: =SUM(H5:H27) -> 38663865 | I28: =SUM(I5:I27) -> 49004401 | ... N28: =SUM(N5:N27) -> 8.2113096e+08

Sheet Filtre Interactif
A1: FILTRE INTERACTIF — DIRECTION / BCI / STATUT D'ENGAGEMENT
A3: 1) Choisir une Direction : | C3: DCT
A5: 2) Choisir un Type de BCI (à partir de la répartition ci-dessous) : | C5: CONTRAT
A7: Nombre de dossiers par Type de BCI — Direction sélectionnée
A8: Type de BCI | B8: Nb dossiers | C8: Montant (MAD) | D8: NATURE BUDGET | F8: CATEGORIE
D9: Fonctionnement | E9: Investissement | F9: Général | G9: PME | H9: Non concerné
A10: CONTRAT | B10: =COUNTIFS('Données Suivi'!$A$2:$A$3000,$C$3,'Données Suivi'!$C$2:$C$3000,$A10) -> 11 | C10: =SUMIFS('Données Suivi'!$J$2:$J$3000,'Données Suivi'!$A$2:$A$3000,$C$3,'Données Suivi'!$C$2:$C$3000,$A10) -> 3339526.8 | D10: =COUNTIFS('Données Suivi'!$A$2:$A$3000,$C$3,'Données Suivi'!$C$2:$C$3000,$A10,'Données Suivi'!$O$2:$O$3000,"FONCTIONNEMENT") -> 11 | E10: =COUNTIFS('Données Suivi'!$A$2:$A$3000,$C$3,'Données Suivi'!$C$2:$C$3000,$A10,'Données Suivi'!$O$2:$O$3000,"INVESTISSEMENT") -> 0 | F10: =COUNTIFS('Données Suivi'!$A$2:$A$3000,$C$3,'Données Suivi'!$C$2:$C$3000,$A10,'Données Suivi'!$P$2:$P$3000,"GENERAL") -> 0 | G10: =COUNTIFS('Données Suivi'!$A$2:$A$3000,$C$3,'Données Suivi'!$C$2:$C$3000,$A10,'Données Suivi'!$P$2:$P$3000,"PME") -> 0 | H10: =COUNTIFS('Données Suivi'!$A$2:$A$3000,$C$3,'Données Suivi'!$C$2:$C$3000,$A10,'Données Suivi'!$P$2:$P$3000,"NON CONCERNE") -> 11
A11: AOO-M | B11: =COUNTIFS('Données Suivi'!$A$2:$A$3000,$C$3,'Données Suivi'!$C$2:$C$3000,$A11) -> 42 | C11: =SUMIFS('Données Suivi'!$J$2:$J$3000,'Données Suivi'!$A$2:$A$3000,$C$3,'Données Suivi'!$C$2:$C$3000,$A11) -> 82870899 | D11: =COUNTIFS('Données Suivi'!$A$2:$A$3000,$C$3,'Données Suivi'!$C$2:$C$3000,$A11,'Données Suivi'!$O$2:$O$3000,"FONCTIONNEMENT") -> 13 | E11: =COUNTIFS('Données Suivi'!$A$2:$A$3000,$C$3,'Données Suivi'!$C$2:$C$3000,$A11,'Données Suivi'!$O$2:$O$3000,"INVESTISSEMENT") -> 29 | F11: =COUNTIFS('Données Suivi'!$A$2:$A$3000,$C$3,'Données Suivi'!$C$2:$C$3000,$A11,'Données Suivi'!$P$2:$P$3000,"GENERAL") -> 28 | G11: =COUNTIFS('Données Suivi'!$A$2:$A$3000,$C$3,'Données Suivi'!$C$2:$C$3000,$A11,'Données Suivi'!$P$2:$P$3000,"PME") -> 9 | H11: =COUNTIFS('Données Suivi'!$A$2:$A$3000,$C$3,'Données Suivi'!$C$2:$C$3000,$A11,'Données Suivi'!$P$2:$P$3000,"NON CONCERNE") -> 5
A12: AOO-CT | B12: =COUNTIFS('Données Suivi'!$A$2:$A$3000,$C$3,'Données Suivi'!$C$2:$C$3000,$A12) -> 0 | C12: =SUMIFS('Données Suivi'!$J$2:$J$3000,'Données Suivi'!$A$2:$A$3000,$C$3,'Données Suivi'!$C$2:$C$3000,$A12) -> 0 | D12: =COUNTIFS('Données Suivi'!$A$2:$A$3000,$C$3,'Données Suivi'!$C$2:$C$3000,$A12,'Données Suivi'!$O$2:$O$3000,"FONCTIONNEMENT") -> 0 | E12: =COUNTIFS('Données Suivi'!$A$2:$A$3000,$C$3,'Données Suivi'!$C$2:$C$3000,$A12,'Données Suivi'!$O$2:$O$3000,"INVESTISSEMENT") -> 0 | F12: =COUNTIFS('Données Suivi'!$A$2:$A$3000,$C$3,'Données Suivi'!$C$2:$C$3000,$A12,'Données Suivi'!$P$2:$P$3000,"GENERAL") -> 0 | G12: =COUNTIFS('Données Suivi'!$A$2:$A$3000,$C$3,'Données Suivi'!$C$2:$C$3000,$A12,'Données Suivi'!$P$2:$P$3000,"PME") -> 0 | H12: =COUNTIFS('Données Suivi'!$A$2:$A$3000,$C$3,'Données Suivi'!$C$2:$C$3000,$A12,'Données Suivi'!$P$2:$P$3000,"NON CONCERNE") -> 0
A13: BCL | B13: =COUNTIFS('Données Suivi'!$A$2:$A$3000,$C$3,'Données Suivi'!$C$2:$C$3000,$A13) -> 4 | C13: =SUMIFS('Données Suivi'!$J$2:$J$3000,'Données Suivi'!$A$2:$A$3000,$C$3,'Données Suivi'!$C$2:$C$3000,$A13) -> 928548.96 | D13: =COUNTIFS('Données Suivi'!$A$2:$A$3000,$C$3,'Données Suivi'!$C$2:$C$3000,$A13,'Données Suivi'!$O$2:$O$3000,"FONCTIONNEMENT") -> 2 | E13: =COUNTIFS('Données Suivi'!$A$2:$A$3000,$C$3,'Données Suivi'!$C$2:$C$3000,$A13,'Données Suivi'!$O$2:$O$3000,"INVESTISSEMENT") -> 2 | F13: =COUNTIFS('Données Suivi'!$A$2:$A$3000,$C$3,'Données Suivi'!$C$2:$C$3000,$A13,'Données Suivi'!$P$2:$P$3000,"GENERAL") -> 1 | G13: =COUNTIFS('Données Suivi'!$A$2:$A$3000,$C$3,'Données Suivi'!$C$2:$C$3000,$A13,'Données Suivi'!$P$2:$P$3000,"PME") -> 0 | H13: =COUNTIFS('Données Suivi'!$A$2:$A$3000,$C$3,'Données Suivi'!$C$2:$C$3000,$A13,'Données Suivi'!$P$2:$P$3000,"NON CONCERNE") -> 3
A14: BCI | B14: =COUNTIFS('Données Suivi'!$A$2:$A$3000,$C$3,'Données Suivi'!$C$2:$C$3000,$A14) -> 1 | C14: =SUMIFS('Données Suivi'!$J$2:$J$3000,'Données Suivi'!$A$2:$A$3000,$C$3,'Données Suivi'!$C$2:$C$3000,$A14) -> 134289.08 | D14: =COUNTIFS('Données Suivi'!$A$2:$A$3000,$C$3,'Données Suivi'!$C$2:$C$3000,$A14,'Données Suivi'!$O$2:$O$3000,"FONCTIONNEMENT") -> 1 | E14: =COUNTIFS('Données Suivi'!$A$2:$A$3000,$C$3,'Données Suivi'!$C$2:$C$3000,$A14,'Données Suivi'!$O$2:$O$3000,"INVESTISSEMENT") -> 0 | F14: =COUNTIFS('Données Suivi'!$A$2:$A$3000,$C$3,'Données Suivi'!$C$2:$C$3000,$A14,'Données Suivi'!$P$2:$P$3000,"GENERAL") -> 1 | G14: =COUNTIFS('Données Suivi'!$A$2:$A$3000,$C$3,'Données Suivi'!$C$2:$C$3000,$A14,'Données Suivi'!$P$2:$P$3000,"PME") -> 0 | H14: =COUNTIFS('Données Suivi'!$A$2:$A$3000,$C$3,'Données Suivi'!$C$2:$C$3000,$A14,'Données Suivi'!$P$2:$P$3000,"NON CONCERNE") -> 0
A15: CA | B15: =COUNTIFS('Données Suivi'!$A$2:$A$3000,$C$3,'Données Suivi'!$C$2:$C$3000,$A15) -> 0 | C15: =SUMIFS('Données Suivi'!$J$2:$J$3000,'Données Suivi'!$A$2:$A$3000,$C$3,'Données Suivi'!$C$2:$C$3000,$A15) -> 0 | D15: =COUNTIFS('Données Suivi'!$A$2:$A$3000,$C$3,'Données Suivi'!$C$2:$C$3000,$A15,'Données Suivi'!$O$2:$O$3000,"FONCTIONNEMENT") -> 0 | E15: =COUNTIFS('Données Suivi'!$A$2:$A$3000,$C$3,'Données Suivi'!$C$2:$C$3000,$A15,'Données Suivi'!$O$2:$O$3000,"INVESTISSEMENT") -> 0 | F15: =COUNTIFS('Données Suivi'!$A$2:$A$3000,$C$3,'Données Suivi'!$C$2:$C$3000,$A15,'Données Suivi'!$P$2:$P$3000,"GENERAL") -> 0 | G15: =COUNTIFS('Données Suivi'!$A$2:$A$3000,$C$3,'Données Suivi'!$C$2:$C$3000,$A15,'Données Suivi'!$P$2:$P$3000,"PME") -> 0 | H15: =COUNTIFS('Données Suivi'!$A$2:$A$3000,$C$3,'Données Suivi'!$C$2:$C$3000,$A15,'Données Suivi'!$P$2:$P$3000,"NON CONCERNE") -> 0
A16: TOTAL direction | B16: =SUM(B10:B15) -> 58 | C16: =SUM(C10:C15) -> 87273264 | D16: =SUM(D10:D15) -> 27 | E16: =SUM(E10:E15) -> 31 | F16: =SUM(F10:F15) -> 30 | G16: =SUM(G10:G15) -> 9 | H16: =SUM(H10:H15) -> 19
A18: Répartition par Statut d'Engagement — Direction + Type de BCI sélectionnés
A19: Statut d'Engagement | B19: Nb dossiers | C19: Montant Fonctionnement (MAD) | D19: Montant Investissement (MAD)
A20: NON ENGAGE | B20: =COUNTIFS('Données Suivi'!$A$2:$A$3000,$C$3,'Données Suivi'!$C$2:$C$3000,$C$5,'Données Suivi'!$H$2:$H$3000,$A20) -> 1 | C20: =SUMIFS('Données Suivi'!$J$2:$J$3000,'Données Suivi'!$A$2:$A$3000,$C$3,'Données Suivi'!$C$2:$C$3000,$C$5,'Données Suivi'!$H$2:$H$3000,$A20,'Données Suivi'!$O$2:$O$3000,"FONCTIONNEMENT") -> 96000 | D20: =SUMIFS('Données Suivi'!$J$2:$J$3000,'Données Suivi'!$A$2:$A$3000,$C$3,'Données Suivi'!$C$2:$C$3000,$C$5,'Données Suivi'!$H$2:$H$3000,$A20,'Données Suivi'!$O$2:$O$3000,"INVESTISSEMENT") -> 0
A21: EN COURS DE PREENGAGEMENT | B21: =COUNTIFS('Données Suivi'!$A$2:$A$3000,$C$3,'Données Suivi'!$C$2:$C$3000,$C$5,'Données Suivi'!$H$2:$H$3000,$A21) -> 0 | C21: =SUMIFS('Données Suivi'!$J$2:$J$3000,'Données Suivi'!$A$2:$A$3000,$C$3,'Données Suivi'!$C$2:$C$3000,$C$5,'Données Suivi'!$H$2:$H$3000,$A21,'Données Suivi'!$O$2:$O$3000,"FONCTIONNEMENT") -> 0 | D21: =SUMIFS('Données Suivi'!$J$2:$J$3000,'Données Suivi'!$A$2:$A$3000,$C$3,'Données Suivi'!$C$2:$C$3000,$C$5,'Données Suivi'!$H$2:$H$3000,$A21,'Données Suivi'!$O$2:$O$3000,"INVESTISSEMENT") -> 0
A22: PREENGAGE | B22: =COUNTIFS('Données Suivi'!$A$2:$A$3000,$C$3,'Données Suivi'!$C$2:$C$3000,$C$5,'Données Suivi'!$H$2:$H$3000,$A22) -> 0 | C22: =SUMIFS('Données Suivi'!$J$2:$J$3000,'Données Suivi'!$A$2:$A$3000,$C$3,'Données Suivi'!$C$2:$C$3000,$C$5,'Données Suivi'!$H$2:$H$3000,$A22,'Données Suivi'!$O$2:$O$3000,"FONCTIONNEMENT") -> 0 | D22: =SUMIFS('Données Suivi'!$J$2:$J$3000,'Données Suivi'!$A$2:$A$3000,$C$3,'Données Suivi'!$C$2:$C$3000,$C$5,'Données Suivi'!$H$2:$H$3000,$A22,'Données Suivi'!$O$2:$O$3000,"INVESTISSEMENT") -> 0
A23: EN COURS D'ENGAGEMENT | B23: =COUNTIFS('Données Suivi'!$A$2:$A$3000,$C$3,'Données Suivi'!$C$2:$C$3000,$C$5,'Données Suivi'!$H$2:$H$3000,$A23) -> 0 | C23: =SUMIFS('Données Suivi'!$J$2:$J$3000,'Données Suivi'!$A$2:$A$3000,$C$3,'Données Suivi'!$C$2:$C$3000,$C$5,'Données Suivi'!$H$2:$H$3000,$A23,'Données Suivi'!$O$2:$O$3000,"FONCTIONNEMENT") -> 0 | D23: =SUMIFS('Données Suivi'!$J$2:$J$3000,'Données Suivi'!$A$2:$A$3000,$C$3,'Données Suivi'!$C$2:$C$3000,$C$5,'Données Suivi'!$H$2:$H$3000,$A23,'Données Suivi'!$O$2:$O$3000,"INVESTISSEMENT") -> 0
A24: ENGAGE | B24: =COUNTIFS('Données Suivi'!$A$2:$A$3000,$C$3,'Données Suivi'!$C$2:$C$3000,$C$5,'Données Suivi'!$H$2:$H$3000,$A24) -> 10 | C24: =SUMIFS('Données Suivi'!$J$2:$J$3000,'Données Suivi'!$A$2:$A$3000,$C$3,'Données Suivi'!$C$2:$C$3000,$C$5,'Données Suivi'!$H$2:$H$3000,$A24,'Données Suivi'!$O$2:$O$3000,"FONCTIONNEMENT") -> 3243526.8 | D24: =SUMIFS('Données Suivi'!$J$2:$J$3000,'Données Suivi'!$A$2:$A$3000,$C$3,'Données Suivi'!$C$2:$C$3000,$C$5,'Données Suivi'!$H$2:$H$3000,$A24,'Données Suivi'!$O$2:$O$3000,"INVESTISSEMENT") -> 0
A25: TOTAL direction + BCI | B25: =SUM(B20:B24) -> 11 | C25: =SUM(C20:C24) -> 3339526.8 | D25: =SUM(D20:D24) -> 0
A27: Détail des dossiers Non Engagé (Statut Support d'Engagement) — Direction sélectionnée
A28: Statut Support (Non Engagé) | B28: Nb dossiers | C28: Montant (MAD)
A29: INFRUCTUEUX | B29: =COUNTIFS('Données Suivi'!$A$2:$A$3000,$C$3,'Données Suivi'!$H$2:$H$3000,"NON ENGAGE",'Données Suivi'!$E$2:$E$3000,$A29) -> 14 | C29: =SUMIFS('Données Suivi'!$J$2:$J$3000,'Données Suivi'!$A$2:$A$3000,$C$3,'Données Suivi'!$H$2:$H$3000,"NON ENGAGE",'Données Suivi'!$E$2:$E$3000,$A29) -> 23580168
A30: ANNULE | B30: =COUNTIFS('Données Suivi'!$A$2:$A$3000,$C$3,'Données Suivi'!$H$2:$H$3000,"NON ENGAGE",'Données Suivi'!$E$2:$E$3000,$A30) -> 2 | C30: =SUMIFS('Données Suivi'!$J$2:$J$3000,'Données Suivi'!$A$2:$A$3000,$C$3,'Données Suivi'!$H$2:$H$3000,"NON ENGAGE",'Données Suivi'!$E$2:$E$3000,$A30) -> 2002704
A31: EN SIGNATURE | B31: =COUNTIFS('Données Suivi'!$A$2:$A$3000,$C$3,'Données Suivi'!$H$2:$H$3000,"NON ENGAGE",'Données Suivi'!$E$2:$E$3000,$A31) -> 0 | C31: =SUMIFS('Données Suivi'!$J$2:$J$3000,'Données Suivi'!$A$2:$A$3000,$C$3,'Données Suivi'!$H$2:$H$3000,"NON ENGAGE",'Données Suivi'!$E$2:$E$3000,$A31) -> 0
A32: TOTAL Non Engagé — direction | B32: =SUM(B29:B31) -> 16 | C32: =SUM(C29:C31) -> 25582872
A34: Détail des dossiers Infructueux / Annulé — Direction sélectionnée
A35: Objet | B35: Réf | C35: BCI | D35: Statut Support | E35: Montant (MAD) | F35: Date Fiche
A36: =IF($T36="","",INDEX('Données Suivi'!$D$2:$D$3000,$T36)) -> ISMAIL MESKINE - Assistant cameraman | B36: =IF($T36="","",INDEX('Données Suivi'!$B$2:$B$3000,$T36)) -> PV N° : 02RC2025- DCT | C36: =IF($T36="","",INDEX('Données Suivi'!$C$2:$C$3000,$T36)) -> CONTRAT | D36: =IF($T36="","",INDEX('Données Suivi'!$E$2:$E$3000,$T36)) -> ANNULE | E36: =IF($T36="","",INDEX('Données Suivi'!$J$2:$J$3000,$T36)) -> 96000 | F36: =IF($T36="","",INDEX('Données Suivi'!$K$2:$K$3000,$T36)) -> 46387 | T36: =IFERROR(MATCH($C$3&"|"&1,'Données Suivi'!$Q$2:$Q$3000,0),"") -> 255
A37: =IF($T37="","",INDEX('Données Suivi'!$D$2:$D$3000,$T37)) -> La fourniture et la mise en service de serveurs haute performance destinés aux applications d’intelligence artificielle et d’apprentissage automatique pour les besoins de la SNRT | B37: =IF($T37="","",INDEX('Données Suivi'!$B$2:$B$3000,$T37)) -> 15 AOM/SNRT | C37: =IF($T37="","",INDEX('Données Suivi'!$C$2:$C$3000,$T37)) -> AOO-M | D37: =IF($T37="","",INDEX('Données Suivi'!$E$2:$E$3000,$T37)) -> ANNULE | E37: =IF($T37="","",INDEX('Données Suivi'!$J$2:$J$3000,$T37)) -> 1906704 | F37: =IF($T37="","",INDEX('Données Suivi'!$K$2:$K$3000,$T37)) -> 46073 | T37: =IFERROR(MATCH($C$3&"|"&2,'Données Suivi'!$Q$2:$Q$3000,0),"") -> 369
A38: =IF($T38="","",INDEX('Données Suivi'!$D$2:$D$3000,$T38)) -> La fourniture et la mise en service d’infrastructures informatiques haute performance pour les applications d’intelligences artificielle pour les besoins de la SNRT | B38: =IF($T38="","",INDEX('Données Suivi'!$B$2:$B$3000,$T38)) -> 15 AOM/SNRT | C38: =IF($T38="","",INDEX('Données Suivi'!$C$2:$C$3000,$T38)) -> AOO-M | D38: =IF($T38="","",INDEX('Données Suivi'!$E$2:$E$3000,$T38)) -> INFRUCTUEUX | E38: =IF($T38="","",INDEX('Données Suivi'!$J$2:$J$3000,$T38)) -> 677484 | F38: =IF($T38="","",INDEX('Données Suivi'!$K$2:$K$3000,$T38)) -> 46073 | T38: =IFERROR(MATCH($C$3&"|"&3,'Données Suivi'!$Q$2:$Q$3000,0),"") -> 370
A39: =IF($T39="","",INDEX('Données Suivi'!$D$2:$D$3000,$T39)) -> La fourniture et la mise en service d'équipement informatiques les besoins de SNRT new de la SNRT | B39: =IF($T39="","",INDEX('Données Suivi'!$B$2:$B$3000,$T39)) -> 21 AOM/SNRT | C39: =IF($T39="","",INDEX('Données Suivi'!$C$2:$C$3000,$T39)) -> AOO-M | D39: =IF($T39="","",INDEX('Données Suivi'!$E$2:$E$3000,$T39)) -> INFRUCTUEUX | E39: =IF($T39="","",INDEX('Données Suivi'!$J$2:$J$3000,$T39)) -> 1896696 | F39: =IF($T39="","",INDEX('Données Suivi'!$K$2:$K$3000,$T39)) -> 46114 | T39: =IFERROR(MATCH($C$3&"|"&4,'Données Suivi'!$Q$2:$Q$3000,0),"") -> 424
A40: =IF($T40="","",INDEX('Données Suivi'!$D$2:$D$3000,$T40)) -> La fourniture et la mise en service d'accessoires,pièces de rechange et outillage informatique pour les besoins de la SNRT | B40: =IF($T40="","",INDEX('Données Suivi'!$B$2:$B$3000,$T40)) -> 06 AOM/SNRT | C40: =IF($T40="","",INDEX('Données Suivi'!$C$2:$C$3000,$T40)) -> AOO-M | D40: =IF($T40="","",INDEX('Données Suivi'!$E$2:$E$3000,$T40)) -> INFRUCTUEUX | E40: =IF($T40="","",INDEX('Données Suivi'!$J$2:$J$3000,$T40)) -> 407304 | F40: =IF($T40="","",INDEX('Données Suivi'!$K$2:$K$3000,$T40)) -> 46114 | T40: =IFERROR(MATCH($C$3&"|"&5,'Données Suivi'!$Q$2:$Q$3000,0),"") -> 427
A41: =IF($T41="","",INDEX('Données Suivi'!$D$2:$D$3000,$T41)) -> La fourniture et la mise en service d'une solution de transport des communications intercom via des coules audio IP BROADCAST pour les besoins des unités mobiles de la SNRT | B41: =IF($T41="","",INDEX('Données Suivi'!$B$2:$B$3000,$T41)) -> 23 AOM/SNRT | C41: =IF($T41="","",INDEX('Données Suivi'!$C$2:$C$3000,$T41)) -> AOO-M | D41: =IF($T41="","",INDEX('Données Suivi'!$E$2:$E$3000,$T41)) -> INFRUCTUEUX | E41: =IF($T41="","",INDEX('Données Suivi'!$J$2:$J$3000,$T41)) -> 291156 | F41: =IF($T41="","",INDEX('Données Suivi'!$K$2:$K$3000,$T41)) -> 46119 | T41: =IFERROR(MATCH($C$3&"|"&6,'Données Suivi'!$Q$2:$Q$3000,0),"") -> 430
A42: =IF($T42="","",INDEX('Données Suivi'!$D$2:$D$3000,$T42)) -> Fourniture et mise en service d’équipements audio vidéo au profit de la DCRPSD de la SNRT | B42: =IF($T42="","",INDEX('Données Suivi'!$B$2:$B$3000,$T42)) -> 26 AOM/SNRT | C42: =IF($T42="","",INDEX('Données Suivi'!$C$2:$C$3000,$T42)) -> AOO-M | D42: =IF($T42="","",INDEX('Données Suivi'!$E$2:$E$3000,$T42)) -> INFRUCTUEUX | E42: =IF($T42="","",INDEX('Données Suivi'!$J$2:$J$3000,$T42)) -> 287676 | F42: =IF($T42="","",INDEX('Données Suivi'!$K$2:$K$3000,$T42)) -> 46121 | T42: =IFERROR(MATCH($C$3&"|"&7,'Données Suivi'!$Q$2:$Q$3000,0),"") -> 431
A43: =IF($T43="","",INDEX('Données Suivi'!$D$2:$D$3000,$T43)) -> La fourniture et la mise en service de serveurs pour renouvellement de serveurs d’enregistrement et de replay pour les besoins de la production TV des manifestations sportives | B43: =IF($T43="","",INDEX('Données Suivi'!$B$2:$B$3000,$T43)) -> 30 AOM/SNRT | C43: =IF($T43="","",INDEX('Données Suivi'!$C$2:$C$3000,$T43)) -> AOO-M | D43: =IF($T43="","",INDEX('Données Suivi'!$E$2:$E$3000,$T43)) -> INFRUCTUEUX | E43: =IF($T43="","",INDEX('Données Suivi'!$J$2:$J$3000,$T43)) -> 8948880 | F43: =IF($T43="","",INDEX('Données Suivi'!$K$2:$K$3000,$T43)) -> 46129 | T43: =IFERROR(MATCH($C$3&"|"&8,'Données Suivi'!$Q$2:$Q$3000,0),"") -> 536
A44: =IF($T44="","",INDEX('Données Suivi'!$D$2:$D$3000,$T44)) -> La fourniture et la mise en service de serveurs haute performance destinés aux applications d’intelligence artificielle et d’apprentissage automatique pour les besoins de la SNRT | B44: =IF($T44="","",INDEX('Données Suivi'!$B$2:$B$3000,$T44)) -> 33 AOM/SNRT | C44: =IF($T44="","",INDEX('Données Suivi'!$C$2:$C$3000,$T44)) -> AOO-M | D44: =IF($T44="","",INDEX('Données Suivi'!$E$2:$E$3000,$T44)) -> INFRUCTUEUX | E44: =IF($T44="","",INDEX('Données Suivi'!$J$2:$J$3000,$T44)) -> 1906704 | F44: =IF($T44="","",INDEX('Données Suivi'!$K$2:$K$3000,$T44)) -> 46140 | T44: =IFERROR(MATCH($C$3&"|"&9,'Données Suivi'!$Q$2:$Q$3000,0),"") -> 550
A45: =IF($T45="","",INDEX('Données Suivi'!$D$2:$D$3000,$T45)) -> La fourniture et la mise en service de lecteurs LTO destinés aux besoins d’archivage de la SNRT | B45: =IF($T45="","",INDEX('Données Suivi'!$B$2:$B$3000,$T45)) -> 38 AOM/SNRT | C45: =IF($T45="","",INDEX('Données Suivi'!$C$2:$C$3000,$T45)) -> AOO-M | D45: =IF($T45="","",INDEX('Données Suivi'!$E$2:$E$3000,$T45)) -> INFRUCTUEUX | E45: =IF($T45="","",INDEX('Données Suivi'!$J$2:$J$3000,$T45)) -> 367296 | F45: =IF($T45="","",INDEX('Données Suivi'!$K$2:$K$3000,$T45)) -> 46147 | T45: =IFERROR(MATCH($C$3&"|"&10,'Données Suivi'!$Q$2:$Q$3000,0),"") -> 557
A46: =IF($T46="","",INDEX('Données Suivi'!$D$2:$D$3000,$T46)) -> La fourniture et la mise en service de véhicules fourgon aménagés en rayonnage pour les besoins de la production de la SNRT | B46: =IF($T46="","",INDEX('Données Suivi'!$B$2:$B$3000,$T46)) -> 52 AOM/SNRT | C46: =IF($T46="","",INDEX('Données Suivi'!$C$2:$C$3000,$T46)) -> AOO-M | D46: =IF($T46="","",INDEX('Données Suivi'!$E$2:$E$3000,$T46)) -> INFRUCTUEUX | E46: =IF($T46="","",INDEX('Données Suivi'!$J$2:$J$3000,$T46)) -> 2054700 | F46: =IF($T46="","",INDEX('Données Suivi'!$K$2:$K$3000,$T46)) -> 46175 | T46: =IFERROR(MATCH($C$3&"|"&11,'Données Suivi'!$Q$2:$Q$3000,0),"") -> 575
A47: =IF($T47="","",INDEX('Données Suivi'!$D$2:$D$3000,$T47)) -> Renouvellement des licences de la solution de gestion financière pour les besoins de la SNRT | B47: =IF($T47="","",INDEX('Données Suivi'!$B$2:$B$3000,$T47)) -> 46 AOM/SNRT | C47: =IF($T47="","",INDEX('Données Suivi'!$C$2:$C$3000,$T47)) -> AOO-M | D47: =IF($T47="","",INDEX('Données Suivi'!$E$2:$E$3000,$T47)) -> INFRUCTUEUX | E47: =IF($T47="","",INDEX('Données Suivi'!$J$2:$J$3000,$T47)) -> 112824 | F47: =IF($T47="","",INDEX('Données Suivi'!$K$2:$K$3000,$T47)) -> 46175 | T47: =IFERROR(MATCH($C$3&"|"&12,'Données Suivi'!$Q$2:$Q$3000,0),"") -> 576
A48: =IF($T48="","",INDEX('Données Suivi'!$D$2:$D$3000,$T48)) -> La fourniture et la mise en service de lecteurs LTO destinés aux besoins d’archivage de la SNRT | B48: =IF($T48="","",INDEX('Données Suivi'!$B$2:$B$3000,$T48)) -> 44 AOM | C48: =IF($T48="","",INDEX('Données Suivi'!$C$2:$C$3000,$T48)) -> AOO-M | D48: =IF($T48="","",INDEX('Données Suivi'!$E$2:$E$3000,$T48)) -> INFRUCTUEUX | E48: =IF($T48="","",INDEX('Données Suivi'!$J$2:$J$3000,$T48)) -> 422256 | F48: =IF($T48="","",INDEX('Données Suivi'!$K$2:$K$3000,$T48)) -> 46185 | T48: =IFERROR(MATCH($C$3&"|"&13,'Données Suivi'!$Q$2:$Q$3000,0),"") -> 585
A49: =IF($T49="","",INDEX('Données Suivi'!$D$2:$D$3000,$T49)) -> La fourniture et la mise en service d'équipement informatiques les besoins de SNRT new de la SNRT | B49: =IF($T49="","",INDEX('Données Suivi'!$B$2:$B$3000,$T49)) -> 53 AOM/SNRT | C49: =IF($T49="","",INDEX('Données Suivi'!$C$2:$C$3000,$T49)) -> AOO-M | D49: =IF($T49="","",INDEX('Données Suivi'!$E$2:$E$3000,$T49)) -> INFRUCTUEUX | E49: =IF($T49="","",INDEX('Données Suivi'!$J$2:$J$3000,$T49)) -> 2086500 | F49: =IF($T49="","",INDEX('Données Suivi'!$K$2:$K$3000,$T49)) -> 46191 | T49: =IFERROR(MATCH($C$3&"|"&14,'Données Suivi'!$Q$2:$Q$3000,0),"") -> 592
A50: =IF($T50="","",INDEX('Données Suivi'!$D$2:$D$3000,$T50)) -> La fourniture et la mise en service de logiciels et de licences de solutions IT pour les besoins de la Société Nationale de Radiodiffusion et de Télévision | B50: =IF($T50="","",INDEX('Données Suivi'!$B$2:$B$3000,$T50)) -> 40AOM/SNRT/2026 | C50: =IF($T50="","",INDEX('Données Suivi'!$C$2:$C$3000,$T50)) -> AOO-M | D50: =IF($T50="","",INDEX('Données Suivi'!$E$2:$E$3000,$T50)) -> INFRUCTUEUX | E50: =IF($T50="","",INDEX('Données Suivi'!$J$2:$J$3000,$T50)) -> 988416 | F50: =IF($T50="","",INDEX('Données Suivi'!$K$2:$K$3000,$T50)) -> 46209 | T50: =IFERROR(MATCH($C$3&"|"&15,'Données Suivi'!$Q$2:$Q$3000,0),"") -> 613
A51: =IF($T51="","",INDEX('Données Suivi'!$D$2:$D$3000,$T51)) -> Fourniture et mise en service d'un système de traveling robotisé pour les besoins de la production de la SNRT | B51: =IF($T51="","",INDEX('Données Suivi'!$B$2:$B$3000,$T51)) -> 64AOM/SNRT/2026 | C51: =IF($T51="","",INDEX('Données Suivi'!$C$2:$C$3000,$T51)) -> AOO-M | D51: =IF($T51="","",INDEX('Données Suivi'!$E$2:$E$3000,$T51)) -> INFRUCTUEUX | E51: =IF($T51="","",INDEX('Données Suivi'!$J$2:$J$3000,$T51)) -> 3132276 | F51: =IF($T51="","",INDEX('Données Suivi'!$K$2:$K$3000,$T51)) -> 46127 | T51: =IFERROR(MATCH($C$3&"|"&16,'Données Suivi'!$Q$2:$Q$3000,0),"") -> 619
A52: =IF($T52="","",INDEX('Données Suivi'!$D$2:$D$3000,$T52)) | B52: =IF($T52="","",INDEX('Données Suivi'!$B$2:$B$3000,$T52)) | C52: =IF($T52="","",INDEX('Données Suivi'!$C$2:$C$3000,$T52)) | D52: =IF($T52="","",INDEX('Données Suivi'!$E$2:$E$3000,$T52)) | E52: =IF($T52="","",INDEX('Données Suivi'!$J$2:$J$3000,$T52)) | F52: =IF($T52="","",INDEX('Données Suivi'!$K$2:$K$3000,$T52)) | T52: =IFERROR(MATCH($C$3&"|"&17,'Données Suivi'!$Q$2:$Q$3000,0),"")
A53: =IF($T53="","",INDEX('Données Suivi'!$D$2:$D$3000,$T53)) | B53: =IF($T53="","",INDEX('Données Suivi'!$B$2:$B$3000,$T53)) | C53: =IF($T53="","",INDEX('Données Suivi'!$C$2:$C$3000,$T53)) | D53: =IF($T53="","",INDEX('Données Suivi'!$E$2:$E$3000,$T53)) | E53: =IF($T53="","",INDEX('Données Suivi'!$J$2:$J$3000,$T53)) | F53: =IF($T53="","",INDEX('Données Suivi'!$K$2:$K$3000,$T53)) | T53: =IFERROR(MATCH($C$3&"|"&18,'Données Suivi'!$Q$2:$Q$3000,0),"")
A54: =IF($T54="","",INDEX('Données Suivi'!$D$2:$D$3000,$T54)) | B54: =IF($T54="","",INDEX('Données Suivi'!$B$2:$B$3000,$T54)) | C54: =IF($T54="","",INDEX('Données Suivi'!$C$2:$C$3000,$T54)) | D54: =IF($T54="","",INDEX('Données Suivi'!$E$2:$E$3000,$T54)) | E54: =IF($T54="","",INDEX('Données Suivi'!$J$2:$J$3000,$T54)) | F54: =IF($T54="","",INDEX('Données Suivi'!$K$2:$K$3000,$T54)) | T54: =IFERROR(MATCH($C$3&"|"&19,'Données Suivi'!$Q$2:$Q$3000,0),"")
A55: =IF($T55="","",INDEX('Données Suivi'!$D$2:$D$3000,$T55)) | B55: =IF($T55="","",INDEX('Données Suivi'!$B$2:$B$3000,$T55)) | C55: =IF($T55="","",INDEX('Données Suivi'!$C$2:$C$3000,$T55)) | D55: =IF($T55="","",INDEX('Données Suivi'!$E$2:$E$3000,$T55)) | E55: =IF($T55="","",INDEX('Données Suivi'!$J$2:$J$3000,$T55)) | F55: =IF($T55="","",INDEX('Données Suivi'!$K$2:$K$3000,$T55)) | T55: =IFERROR(MATCH($C$3&"|"&20,'Données Suivi'!$Q$2:$Q$3000,0),"")

Sheet Tableau de Bord Suivi
A1: TABLEAU DE BORD DE SUIVI — ETAT D'ENGAGEMENTS 2026
A3: Nb dossiers total | C3: Montant total (MAD) | E3: Nb directions | G3: Taux d'engagement (montant) | I3: Montant restant à engager | K3: Nb dossiers en cours (à suivre)
A4: =COUNTIF('Données Suivi'!A2:A3000,"?*") -> 684 | C4: =SUM('Données Suivi'!J2:J3000) -> 8.2113096e+08 | E4: =SUMPRODUCT(('Données Suivi'!$A$2:$A$3000<>"")/COUNTIF('Données Suivi'!$A$2:$A$3000,'Données Suivi'!$A$2:$A$3000&"")) -> 23 | G4: =SUMIF('Données Suivi'!M2:M3000,"Engagé",'Données Suivi'!J2:J3000)/SUM('Données Suivi'!J2:J3000) -> 0.7864264 | I4: =SUMIF('Données Suivi'!M2:M3000,"En cours",'Données Suivi'!J2:J3000) -> 1.4607226e+08 | K4: =COUNTIF('Données Suivi'!M2:M3000,"En cours") -> 81
A6: Nb clôturés sans suite | C6: Ancienneté moy. dossiers en cours (j)
A7: =COUNTIF('Données Suivi'!M2:M3000,"Clôturé sans suite") -> 20 | C7: =AVERAGEIFS('Données Suivi'!L2:L3000,'Données Suivi'!M2:M3000,"En cours",'Données Suivi'!L2:L3000,">=0") -> 100.48889
A10: Répartition des dossiers par Direction et par BCI (type d'achat) — Nombre de dossiers
A11: Direction | B11: CONTRAT | C11: AOO-M | D11: AOO-CT | E11: BCL | F11: BCI | G11: CA | H11: TOTAL
A12: ARRIYADIA | B12: =COUNTIFS('Données Suivi'!$A$2:$A$3000,$A12,'Données Suivi'!$C$2:$C$3000,"CONTRAT") -> 77 | C12: =COUNTIFS('Données Suivi'!$A$2:$A$3000,$A12,'Données Suivi'!$C$2:$C$3000,"AOO-M") -> 0 | D12: =COUNTIFS('Données Suivi'!$A$2:$A$3000,$A12,'Données Suivi'!$C$2:$C$3000,"AOO-CT") -> 0 | E12: =COUNTIFS('Données Suivi'!$A$2:$A$3000,$A12,'Données Suivi'!$C$2:$C$3000,"BCL") -> 0 | F12: =COUNTIFS('Données Suivi'!$A$2:$A$3000,$A12,'Données Suivi'!$C$2:$C$3000,"BCI") -> 0 | G12: =COUNTIFS('Données Suivi'!$A$2:$A$3000,$A12,'Données Suivi'!$C$2:$C$3000,"CA") -> 0 | H12: =COUNTIF('Données Suivi'!$A$2:$A$3000,$A12) -> 77
A13: ASSADISSA | B13: =COUNTIFS('Données Suivi'!$A$2:$A$3000,$A13,'Données Suivi'!$C$2:$C$3000,"CONTRAT") -> 81 | C13: =COUNTIFS('Données Suivi'!$A$2:$A$3000,$A13,'Données Suivi'!$C$2:$C$3000,"AOO-M") -> 0 | D13: =COUNTIFS('Données Suivi'!$A$2:$A$3000,$A13,'Données Suivi'!$C$2:$C$3000,"AOO-CT") -> 0 | E13: =COUNTIFS('Données Suivi'!$A$2:$A$3000,$A13,'Données Suivi'!$C$2:$C$3000,"BCL") -> 0 | F13: =COUNTIFS('Données Suivi'!$A$2:$A$3000,$A13,'Données Suivi'!$C$2:$C$3000,"BCI") -> 0 | G13: =COUNTIFS('Données Suivi'!$A$2:$A$3000,$A13,'Données Suivi'!$C$2:$C$3000,"CA") -> 0 | H13: =COUNTIF('Données Suivi'!$A$2:$A$3000,$A13) -> 81
A14: DA | B14: =COUNTIFS('Données Suivi'!$A$2:$A$3000,$A14,'Données Suivi'!$C$2:$C$3000,"CONTRAT") -> 5 | C14: =COUNTIFS('Données Suivi'!$A$2:$A$3000,$A14,'Données Suivi'!$C$2:$C$3000,"AOO-M") -> 0 | D14: =COUNTIFS('Données Suivi'!$A$2:$A$3000,$A14,'Données Suivi'!$C$2:$C$3000,"AOO-CT") -> 0 | E14: =COUNTIFS('Données Suivi'!$A$2:$A$3000,$A14,'Données Suivi'!$C$2:$C$3000,"BCL") -> 0 | F14: =COUNTIFS('Données Suivi'!$A$2:$A$3000,$A14,'Données Suivi'!$C$2:$C$3000,"BCI") -> 0 | G14: =COUNTIFS('Données Suivi'!$A$2:$A$3000,$A14,'Données Suivi'!$C$2:$C$3000,"CA") -> 0 | H14: =COUNTIF('Données Suivi'!$A$2:$A$3000,$A14) -> 5
A15: DACG | B15: =COUNTIFS('Données Suivi'!$A$2:$A$3000,$A15,'Données Suivi'!$C$2:$C$3000,"CONTRAT") -> 3 | C15: =COUNTIFS('Données Suivi'!$A$2:$A$3000,$A15,'Données Suivi'!$C$2:$C$3000,"AOO-M") -> 1 | D15: =COUNTIFS('Données Suivi'!$A$2:$A$3000,$A15,'Données Suivi'!$C$2:$C$3000,"AOO-CT") -> 0 | E15: =COUNTIFS('Données Suivi'!$A$2:$A$3000,$A15,'Données Suivi'!$C$2:$C$3000,"BCL") -> 0 | F15: =COUNTIFS('Données Suivi'!$A$2:$A$3000,$A15,'Données Suivi'!$C$2:$C$3000,"BCI") -> 0 | G15: =COUNTIFS('Données Suivi'!$A$2:$A$3000,$A15,'Données Suivi'!$C$2:$C$3000,"CA") -> 0 | H15: =COUNTIF('Données Suivi'!$A$2:$A$3000,$A15) -> 4
A16: DAR | B16: =COUNTIFS('Données Suivi'!$A$2:$A$3000,$A16,'Données Suivi'!$C$2:$C$3000,"CONTRAT") -> 1 | C16: =COUNTIFS('Données Suivi'!$A$2:$A$3000,$A16,'Données Suivi'!$C$2:$C$3000,"AOO-M") -> 0 | D16: =COUNTIFS('Données Suivi'!$A$2:$A$3000,$A16,'Données Suivi'!$C$2:$C$3000,"AOO-CT") -> 0 | E16: =COUNTIFS('Données Suivi'!$A$2:$A$3000,$A16,'Données Suivi'!$C$2:$C$3000,"BCL") -> 0 | F16: =COUNTIFS('Données Suivi'!$A$2:$A$3000,$A16,'Données Suivi'!$C$2:$C$3000,"BCI") -> 0 | G16: =COUNTIFS('Données Suivi'!$A$2:$A$3000,$A16,'Données Suivi'!$C$2:$C$3000,"CA") -> 0 | H16: =COUNTIF('Données Suivi'!$A$2:$A$3000,$A16) -> 1
A17: DCPA | B17: =COUNTIFS('Données Suivi'!$A$2:$A$3000,$A17,'Données Suivi'!$C$2:$C$3000,"CONTRAT") -> 23 | C17: =COUNTIFS('Données Suivi'!$A$2:$A$3000,$A17,'Données Suivi'!$C$2:$C$3000,"AOO-M") -> 0 | D17: =COUNTIFS('Données Suivi'!$A$2:$A$3000,$A17,'Données Suivi'!$C$2:$C$3000,"AOO-CT") -> 14 | E17: =COUNTIFS('Données Suivi'!$A$2:$A$3000,$A17,'Données Suivi'!$C$2:$C$3000,"BCL") -> 2 | F17: =COUNTIFS('Données Suivi'!$A$2:$A$3000,$A17,'Données Suivi'!$C$2:$C$3000,"BCI") -> 0 | G17: =COUNTIFS('Données Suivi'!$A$2:$A$3000,$A17,'Données Suivi'!$C$2:$C$3000,"CA") -> 4 | H17: =COUNTIF('Données Suivi'!$A$2:$A$3000,$A17) -> 43
A18: DCRI | B18: =COUNTIFS('Données Suivi'!$A$2:$A$3000,$A18,'Données Suivi'!$C$2:$C$3000,"CONTRAT") -> 1 | C18: =COUNTIFS('Données Suivi'!$A$2:$A$3000,$A18,'Données Suivi'!$C$2:$C$3000,"AOO-M") -> 0 | D18: =COUNTIFS('Données Suivi'!$A$2:$A$3000,$A18,'Données Suivi'!$C$2:$C$3000,"AOO-CT") -> 0 | E18: =COUNTIFS('Données Suivi'!$A$2:$A$3000,$A18,'Données Suivi'!$C$2:$C$3000,"BCL") -> 0 | F18: =COUNTIFS('Données Suivi'!$A$2:$A$3000,$A18,'Données Suivi'!$C$2:$C$3000,"BCI") -> 0 | G18: =COUNTIFS('Données Suivi'!$A$2:$A$3000,$A18,'Données Suivi'!$C$2:$C$3000,"CA") -> 0 | H18: =COUNTIF('Données Suivi'!$A$2:$A$3000,$A18) -> 1
A19: DCT | B19: =COUNTIFS('Données Suivi'!$A$2:$A$3000,$A19,'Données Suivi'!$C$2:$C$3000,"CONTRAT") -> 11 | C19: =COUNTIFS('Données Suivi'!$A$2:$A$3000,$A19,'Données Suivi'!$C$2:$C$3000,"AOO-M") -> 42 | D19: =COUNTIFS('Données Suivi'!$A$2:$A$3000,$A19,'Données Suivi'!$C$2:$C$3000,"AOO-CT") -> 0 | E19: =COUNTIFS('Données Suivi'!$A$2:$A$3000,$A19,'Données Suivi'!$C$2:$C$3000,"BCL") -> 4 | F19: =COUNTIFS('Données Suivi'!$A$2:$A$3000,$A19,'Données Suivi'!$C$2:$C$3000,"BCI") -> 1 | G19: =COUNTIFS('Données Suivi'!$A$2:$A$3000,$A19,'Données Suivi'!$C$2:$C$3000,"CA") -> 0 | H19: =COUNTIF('Données Suivi'!$A$2:$A$3000,$A19) -> 58
A20: DG | B20: =COUNTIFS('Données Suivi'!$A$2:$A$3000,$A20,'Données Suivi'!$C$2:$C$3000,"CONTRAT") -> 1 | C20: =COUNTIFS('Données Suivi'!$A$2:$A$3000,$A20,'Données Suivi'!$C$2:$C$3000,"AOO-M") -> 0 | D20: =COUNTIFS('Données Suivi'!$A$2:$A$3000,$A20,'Données Suivi'!$C$2:$C$3000,"AOO-CT") -> 0 | E20: =COUNTIFS('Données Suivi'!$A$2:$A$3000,$A20,'Données Suivi'!$C$2:$C$3000,"BCL") -> 0 | F20: =COUNTIFS('Données Suivi'!$A$2:$A$3000,$A20,'Données Suivi'!$C$2:$C$3000,"BCI") -> 0 | G20: =COUNTIFS('Données Suivi'!$A$2:$A$3000,$A20,'Données Suivi'!$C$2:$C$3000,"CA") -> 0 | H20: =COUNTIF('Données Suivi'!$A$2:$A$3000,$A20) -> 1
A21: DINFORADIO | B21: =COUNTIFS('Données Suivi'!$A$2:$A$3000,$A21,'Données Suivi'!$C$2:$C$3000,"CONTRAT") -> 7 | C21: =COUNTIFS('Données Suivi'!$A$2:$A$3000,$A21,'Données Suivi'!$C$2:$C$3000,"AOO-M") -> 0 | D21: =COUNTIFS('Données Suivi'!$A$2:$A$3000,$A21,'Données Suivi'!$C$2:$C$3000,"AOO-CT") -> 0 | E21: =COUNTIFS('Données Suivi'!$A$2:$A$3000,$A21,'Données Suivi'!$C$2:$C$3000,"BCL") -> 0 | F21: =COUNTIFS('Données Suivi'!$A$2:$A$3000,$A21,'Données Suivi'!$C$2:$C$3000,"BCI") -> 0 | G21: =COUNTIFS('Données Suivi'!$A$2:$A$3000,$A21,'Données Suivi'!$C$2:$C$3000,"CA") -> 0 | H21: =COUNTIF('Données Suivi'!$A$2:$A$3000,$A21) -> 7
A22: DINFOTV | B22: =COUNTIFS('Données Suivi'!$A$2:$A$3000,$A22,'Données Suivi'!$C$2:$C$3000,"CONTRAT") -> 32 | C22: =COUNTIFS('Données Suivi'!$A$2:$A$3000,$A22,'Données Suivi'!$C$2:$C$3000,"AOO-M") -> 1 | D22: =COUNTIFS('Données Suivi'!$A$2:$A$3000,$A22,'Données Suivi'!$C$2:$C$3000,"AOO-CT") -> 0 | E22: =COUNTIFS('Données Suivi'!$A$2:$A$3000,$A22,'Données Suivi'!$C$2:$C$3000,"BCL") -> 0 | F22: =COUNTIFS('Données Suivi'!$A$2:$A$3000,$A22,'Données Suivi'!$C$2:$C$3000,"BCI") -> 0 | G22: =COUNTIFS('Données Suivi'!$A$2:$A$3000,$A22,'Données Suivi'!$C$2:$C$3000,"CA") -> 0 | H22: =COUNTIF('Données Suivi'!$A$2:$A$3000,$A22) -> 33
A23: DJURIDIQUE | B23: =COUNTIFS('Données Suivi'!$A$2:$A$3000,$A23,'Données Suivi'!$C$2:$C$3000,"CONTRAT") -> 8 | C23: =COUNTIFS('Données Suivi'!$A$2:$A$3000,$A23,'Données Suivi'!$C$2:$C$3000,"AOO-M") -> 0 | D23: =COUNTIFS('Données Suivi'!$A$2:$A$3000,$A23,'Données Suivi'!$C$2:$C$3000,"AOO-CT") -> 0 | E23: =COUNTIFS('Données Suivi'!$A$2:$A$3000,$A23,'Données Suivi'!$C$2:$C$3000,"BCL") -> 1 | F23: =COUNTIFS('Données Suivi'!$A$2:$A$3000,$A23,'Données Suivi'!$C$2:$C$3000,"BCI") -> 0 | G23: =COUNTIFS('Données Suivi'!$A$2:$A$3000,$A23,'Données Suivi'!$C$2:$C$3000,"CA") -> 0 | H23: =COUNTIF('Données Suivi'!$A$2:$A$3000,$A23) -> 9
... A34: TV LAAYOUNE | B34: =COUNTIFS('Données Suivi'!$A$2:$A$3000,$A34,'Données Suivi'!$C$2:$C$3000,"CONTRAT") -> 5 | C34: =COUNTIFS('Données Suivi'!$A$2:$A$3000,$A34,'Données Suivi'!$C$2:$C$3000,"AOO-M") -> 1 | D34: =COUNTIFS('Données Suivi'!$A$2:$A$3000,$A34,'Données Suivi'!$C$2:$C$3000,"AOO-CT") -> 18 | E34: =COUNTIFS('Données Suivi'!$A$2:$A$3000,$A34,'Données Suivi'!$C$2:$C$3000,"BCL") -> 3 | F34: =COUNTIFS('Données Suivi'!$A$2:$A$3000,$A34,'Données Suivi'!$C$2:$C$3000,"BCI") -> 0 | G34: =COUNTIFS('Données Suivi'!$A$2:$A$3000,$A34,'Données Suivi'!$C$2:$C$3000,"CA") -> 0 | H34: =COUNTIF('Données Suivi'!$A$2:$A$3000,$A34) -> 27
A35: TOTAL | B35: =SUM(B12:B34) -> 475 | C35: =SUM(C12:C34) -> 131 | D35: =SUM(D12:D34) -> 32 | E35: =SUM(E12:E34) -> 39 | F35: =SUM(F12:F34) -> 2 | G35: =SUM(G12:G34) -> 5 | H35: =SUM(H12:H34) -> 684
A37: Répartition des dossiers par Direction et par Statut d'Engagement — Nombre de dossiers
A38: Direction | B38: NON ENGAGE | C38: EN COURS DE PREENGAGEMENT | D38: PREENGAGE | E38: EN COURS D'ENGAGEMENT | F38: ENGAGE | G38: TOTAL
A39: ARRIYADIA | B39: =COUNTIFS('Données Suivi'!$A$2:$A$3000,$A39,'Données Suivi'!$H$2:$H$3000,"NON ENGAGE") -> 0 | C39: =COUNTIFS('Données Suivi'!$A$2:$A$3000,$A39,'Données Suivi'!$H$2:$H$3000,"EN COURS DE PREENGAGEMENT") -> 0 | D39: =COUNTIFS('Données Suivi'!$A$2:$A$3000,$A39,'Données Suivi'!$H$2:$H$3000,"PREENGAGE") -> 0 | E39: =COUNTIFS('Données Suivi'!$A$2:$A$3000,$A39,'Données Suivi'!$H$2:$H$3000,"EN COURS D'ENGAGEMENT") -> 3 | F39: =COUNTIFS('Données Suivi'!$A$2:$A$3000,$A39,'Données Suivi'!$H$2:$H$3000,"ENGAGE") -> 74 | G39: =COUNTIF('Données Suivi'!$A$2:$A$3000,$A39) -> 77
A40: ASSADISSA | B40: =COUNTIFS('Données Suivi'!$A$2:$A$3000,$A40,'Données Suivi'!$H$2:$H$3000,"NON ENGAGE") -> 0 | C40: =COUNTIFS('Données Suivi'!$A$2:$A$3000,$A40,'Données Suivi'!$H$2:$H$3000,"EN COURS DE PREENGAGEMENT") -> 0 | D40: =COUNTIFS('Données Suivi'!$A$2:$A$3000,$A40,'Données Suivi'!$H$2:$H$3000,"PREENGAGE") -> 0 | E40: =COUNTIFS('Données Suivi'!$A$2:$A$3000,$A40,'Données Suivi'!$H$2:$H$3000,"EN COURS D'ENGAGEMENT") -> 0 | F40: =COUNTIFS('Données Suivi'!$A$2:$A$3000,$A40,'Données Suivi'!$H$2:$H$3000,"ENGAGE") -> 81 | G40: =COUNTIF('Données Suivi'!$A$2:$A$3000,$A40) -> 81
A41: DA | B41: =COUNTIFS('Données Suivi'!$A$2:$A$3000,$A41,'Données Suivi'!$H$2:$H$3000,"NON ENGAGE") -> 0 | C41: =COUNTIFS('Données Suivi'!$A$2:$A$3000,$A41,'Données Suivi'!$H$2:$H$3000,"EN COURS DE PREENGAGEMENT") -> 0 | D41: =COUNTIFS('Données Suivi'!$A$2:$A$3000,$A41,'Données Suivi'!$H$2:$H$3000,"PREENGAGE") -> 0 | E41: =COUNTIFS('Données Suivi'!$A$2:$A$3000,$A41,'Données Suivi'!$H$2:$H$3000,"EN COURS D'ENGAGEMENT") -> 0 | F41: =COUNTIFS('Données Suivi'!$A$2:$A$3000,$A41,'Données Suivi'!$H$2:$H$3000,"ENGAGE") -> 5 | G41: =COUNTIF('Données Suivi'!$A$2:$A$3000,$A41) -> 5
A42: DACG | B42: =COUNTIFS('Données Suivi'!$A$2:$A$3000,$A42,'Données Suivi'!$H$2:$H$3000,"NON ENGAGE") -> 0 | C42: =COUNTIFS('Données Suivi'!$A$2:$A$3000,$A42,'Données Suivi'!$H$2:$H$3000,"EN COURS DE PREENGAGEMENT") -> 1 | D42: =COUNTIFS('Données Suivi'!$A$2:$A$3000,$A42,'Données Suivi'!$H$2:$H$3000,"PREENGAGE") -> 0 | E42: =COUNTIFS('Données Suivi'!$A$2:$A$3000,$A42,'Données Suivi'!$H$2:$H$3000,"EN COURS D'ENGAGEMENT") -> 0 | F42: =COUNTIFS('Données Suivi'!$A$2:$A$3000,$A42,'Données Suivi'!$H$2:$H$3000,"ENGAGE") -> 3 | G42: =COUNTIF('Données Suivi'!$A$2:$A$3000,$A42) -> 4
A43: DAR | B43: =COUNTIFS('Données Suivi'!$A$2:$A$3000,$A43,'Données Suivi'!$H$2:$H$3000,"NON ENGAGE") -> 0 | C43: =COUNTIFS('Données Suivi'!$A$2:$A$3000,$A43,'Données Suivi'!$H$2:$H$3000,"EN COURS DE PREENGAGEMENT") -> 0 | D43: =COUNTIFS('Données Suivi'!$A$2:$A$3000,$A43,'Données Suivi'!$H$2:$H$3000,"PREENGAGE") -> 0 | E43: =COUNTIFS('Données Suivi'!$A$2:$A$3000,$A43,'Données Suivi'!$H$2:$H$3000,"EN COURS D'ENGAGEMENT") -> 0 | F43: =COUNTIFS('Données Suivi'!$A$2:$A$3000,$A43,'Données Suivi'!$H$2:$H$3000,"ENGAGE") -> 1 | G43: =COUNTIF('Données Suivi'!$A$2:$A$3000,$A43) -> 1
A44: DCPA | B44: =COUNTIFS('Données Suivi'!$A$2:$A$3000,$A44,'Données Suivi'!$H$2:$H$3000,"NON ENGAGE") -> 1 | C44: =COUNTIFS('Données Suivi'!$A$2:$A$3000,$A44,'Données Suivi'!$H$2:$H$3000,"EN COURS DE PREENGAGEMENT") -> 0 | D44: =COUNTIFS('Données Suivi'!$A$2:$A$3000,$A44,'Données Suivi'!$H$2:$H$3000,"PREENGAGE") -> 0 | E44: =COUNTIFS('Données Suivi'!$A$2:$A$3000,$A44,'Données Suivi'!$H$2:$H$3000,"EN COURS D'ENGAGEMENT") -> 4 | F44: =COUNTIFS('Données Suivi'!$A$2:$A$3000,$A44,'Données Suivi'!$H$2:$H$3000,"ENGAGE") -> 38 | G44: =COUNTIF('Données Suivi'!$A$2:$A$3000,$A44) -> 43
A45: DCRI | B45: =COUNTIFS('Données Suivi'!$A$2:$A$3000,$A45,'Données Suivi'!$H$2:$H$3000,"NON ENGAGE") -> 0 | C45: =COUNTIFS('Données Suivi'!$A$2:$A$3000,$A45,'Données Suivi'!$H$2:$H$3000,"EN COURS DE PREENGAGEMENT") -> 0 | D45: =COUNTIFS('Données Suivi'!$A$2:$A$3000,$A45,'Données Suivi'!$H$2:$H$3000,"PREENGAGE") -> 0 | E45: =COUNTIFS('Données Suivi'!$A$2:$A$3000,$A45,'Données Suivi'!$H$2:$H$3000,"EN COURS D'ENGAGEMENT") -> 0 | F45: =COUNTIFS('Données Suivi'!$A$2:$A$3000,$A45,'Données Suivi'!$H$2:$H$3000,"ENGAGE") -> 1 | G45: =COUNTIF('Données Suivi'!$A$2:$A$3000,$A45) -> 1
A46: DCT | B46: =COUNTIFS('Données Suivi'!$A$2:$A$3000,$A46,'Données Suivi'!$H$2:$H$3000,"NON ENGAGE") -> 16 | C46: =COUNTIFS('Données Suivi'!$A$2:$A$3000,$A46,'Données Suivi'!$H$2:$H$3000,"EN COURS DE PREENGAGEMENT") -> 1 | D46: =COUNTIFS('Données Suivi'!$A$2:$A$3000,$A46,'Données Suivi'!$H$2:$H$3000,"PREENGAGE") -> 10 | E46: =COUNTIFS('Données Suivi'!$A$2:$A$3000,$A46,'Données Suivi'!$H$2:$H$3000,"EN COURS D'ENGAGEMENT") -> 2 | F46: =COUNTIFS('Données Suivi'!$A$2:$A$3000,$A46,'Données Suivi'!$H$2:$H$3000,"ENGAGE") -> 29 | G46: =COUNTIF('Données Suivi'!$A$2:$A$3000,$A46) -> 58
A47: DG | B47: =COUNTIFS('Données Suivi'!$A$2:$A$3000,$A47,'Données Suivi'!$H$2:$H$3000,"NON ENGAGE") -> 0 | C47: =COUNTIFS('Données Suivi'!$A$2:$A$3000,$A47,'Données Suivi'!$H$2:$H$3000,"EN COURS DE PREENGAGEMENT") -> 0 | D47: =COUNTIFS('Données Suivi'!$A$2:$A$3000,$A47,'Données Suivi'!$H$2:$H$3000,"PREENGAGE") -> 0 | E47: =COUNTIFS('Données Suivi'!$A$2:$A$3000,$A47,'Données Suivi'!$H$2:$H$3000,"EN COURS D'ENGAGEMENT") -> 0 | F47: =COUNTIFS('Données Suivi'!$A$2:$A$3000,$A47,'Données Suivi'!$H$2:$H$3000,"ENGAGE") -> 1 | G47: =COUNTIF('Données Suivi'!$A$2:$A$3000,$A47) -> 1
A48: DINFORADIO | B48: =COUNTIFS('Données Suivi'!$A$2:$A$3000,$A48,'Données Suivi'!$H$2:$H$3000,"NON ENGAGE") -> 0 | C48: =COUNTIFS('Données Suivi'!$A$2:$A$3000,$A48,'Données Suivi'!$H$2:$H$3000,"EN COURS DE PREENGAGEMENT") -> 0 | D48: =COUNTIFS('Données Suivi'!$A$2:$A$3000,$A48,'Données Suivi'!$H$2:$H$3000,"PREENGAGE") -> 0 | E48: =COUNTIFS('Données Suivi'!$A$2:$A$3000,$A48,'Données Suivi'!$H$2:$H$3000,"EN COURS D'ENGAGEMENT") -> 0 | F48: =COUNTIFS('Données Suivi'!$A$2:$A$3000,$A48,'Données Suivi'!$H$2:$H$3000,"ENGAGE") -> 7 | G48: =COUNTIF('Données Suivi'!$A$2:$A$3000,$A48) -> 7
A49: DINFOTV | B49: =COUNTIFS('Données Suivi'!$A$2:$A$3000,$A49,'Données Suivi'!$H$2:$H$3000,"NON ENGAGE") -> 0 | C49: =COUNTIFS('Données Suivi'!$A$2:$A$3000,$A49,'Données Suivi'!$H$2:$H$3000,"EN COURS DE PREENGAGEMENT") -> 0 | D49: =COUNTIFS('Données Suivi'!$A$2:$A$3000,$A49,'Données Suivi'!$H$2:$H$3000,"PREENGAGE") -> 0 | E49: =COUNTIFS('Données Suivi'!$A$2:$A$3000,$A49,'Données Suivi'!$H$2:$H$3000,"EN COURS D'ENGAGEMENT") -> 3 | F49: =COUNTIFS('Données Suivi'!$A$2:$A$3000,$A49,'Données Suivi'!$H$2:$H$3000,"ENGAGE") -> 30 | G49: =COUNTIF('Données Suivi'!$A$2:$A$3000,$A49) -> 33
A50: DJURIDIQUE | B50: =COUNTIFS('Données Suivi'!$A$2:$A$3000,$A50,'Données Suivi'!$H$2:$H$3000,"NON ENGAGE") -> 0 | C50: =COUNTIFS('Données Suivi'!$A$2:$A$3000,$A50,'Données Suivi'!$H$2:$H$3000,"EN COURS DE PREENGAGEMENT") -> 0 | D50: =COUNTIFS('Données Suivi'!$A$2:$A$3000,$A50,'Données Suivi'!$H$2:$H$3000,"PREENGAGE") -> 0 | E50: =COUNTIFS('Données Suivi'!$A$2:$A$3000,$A50,'Données Suivi'!$H$2:$H$3000,"EN COURS D'ENGAGEMENT") -> 1 | F50: =COUNTIFS('Données Suivi'!$A$2:$A$3000,$A50,'Données Suivi'!$H$2:$H$3000,"ENGAGE") -> 8 | G50: =COUNTIF('Données Suivi'!$A$2:$A$3000,$A50) -> 9
... A61: TV LAAYOUNE | B61: =COUNTIFS('Données Suivi'!$A$2:$A$3000,$A61,'Données Suivi'!$H$2:$H$3000,"NON ENGAGE") -> 0 | C61: =COUNTIFS('Données Suivi'!$A$2:$A$3000,$A61,'Données Suivi'!$H$2:$H$3000,"EN COURS DE PREENGAGEMENT") -> 0 | D61: =COUNTIFS('Données Suivi'!$A$2:$A$3000,$A61,'Données Suivi'!$H$2:$H$3000,"PREENGAGE") -> 1 | E61: =COUNTIFS('Données Suivi'!$A$2:$A$3000,$A61,'Données Suivi'!$H$2:$H$3000,"EN COURS D'ENGAGEMENT") -> 0 | F61: =COUNTIFS('Données Suivi'!$A$2:$A$3000,$A61,'Données Suivi'!$H$2:$H$3000,"ENGAGE") -> 26 | G61: =COUNTIF('Données Suivi'!$A$2:$A$3000,$A61) -> 27
A62: TOTAL | B62: =SUM(B39:B61) -> 29 | C62: =SUM(C39:C61) -> 16 | D62: =SUM(D39:D61) -> 30 | E62: =SUM(E39:E61) -> 26 | F62: =SUM(F39:F61) -> 583 | G62: =SUM(G39:G61) -> 684
A64: Taux d'engagement par Direction (montant)
A65: Direction | B65: Montant total (MAD) | C65: Montant engagé (MAD) | D65: Taux d'engagement
A66: ARRIYADIA | B66: =SUMIF('Données Suivi'!$A$2:$A$3000,$A66,'Données Suivi'!$J$2:$J$3000) -> 1.805427e+08 | C66: =SUMIFS('Données Suivi'!$J$2:$J$3000,'Données Suivi'!$A$2:$A$3000,$A66,'Données Suivi'!$M$2:$M$3000,"Engagé") -> 1.8046948e+08 | D66: =IF(B66=0,"",C66/B66) -> 0.99959442
A67: ASSADISSA | B67: =SUMIF('Données Suivi'!$A$2:$A$3000,$A67,'Données Suivi'!$J$2:$J$3000) -> 8022706.3 | C67: =SUMIFS('Données Suivi'!$J$2:$J$3000,'Données Suivi'!$A$2:$A$3000,$A67,'Données Suivi'!$M$2:$M$3000,"Engagé") -> 8022706.3 | D67: =IF(B67=0,"",C67/B67) -> 1
A68: DA | B68: =SUMIF('Données Suivi'!$A$2:$A$3000,$A68,'Données Suivi'!$J$2:$J$3000) -> 427760 | C68: =SUMIFS('Données Suivi'!$J$2:$J$3000,'Données Suivi'!$A$2:$A$3000,$A68,'Données Suivi'!$M$2:$M$3000,"Engagé") -> 427760 | D68: =IF(B68=0,"",C68/B68) -> 1
A69: DACG | B69: =SUMIF('Données Suivi'!$A$2:$A$3000,$A69,'Données Suivi'!$J$2:$J$3000) -> 462500 | C69: =SUMIFS('Données Suivi'!$J$2:$J$3000,'Données Suivi'!$A$2:$A$3000,$A69,'Données Suivi'!$M$2:$M$3000,"Engagé") -> 318500 | D69: =IF(B69=0,"",C69/B69) -> 0.68864865
A70: DAR | B70: =SUMIF('Données Suivi'!$A$2:$A$3000,$A70,'Données Suivi'!$J$2:$J$3000) -> 108000 | C70: =SUMIFS('Données Suivi'!$J$2:$J$3000,'Données Suivi'!$A$2:$A$3000,$A70,'Données Suivi'!$M$2:$M$3000,"Engagé") -> 108000 | D70: =IF(B70=0,"",C70/B70) -> 1
A71: DCPA | B71: =SUMIF('Données Suivi'!$A$2:$A$3000,$A71,'Données Suivi'!$J$2:$J$3000) -> 71378140 | C71: =SUMIFS('Données Suivi'!$J$2:$J$3000,'Données Suivi'!$A$2:$A$3000,$A71,'Données Suivi'!$M$2:$M$3000,"Engagé") -> 61489072 | D71: =IF(B71=0,"",C71/B71) -> 0.86145523
A72: DCRI | B72: =SUMIF('Données Suivi'!$A$2:$A$3000,$A72,'Données Suivi'!$J$2:$J$3000) -> 318240 | C72: =SUMIFS('Données Suivi'!$J$2:$J$3000,'Données Suivi'!$A$2:$A$3000,$A72,'Données Suivi'!$M$2:$M$3000,"Engagé") -> 318240 | D72: =IF(B72=0,"",C72/B72) -> 1
A73: DCT | B73: =SUMIF('Données Suivi'!$A$2:$A$3000,$A73,'Données Suivi'!$J$2:$J$3000) -> 87273264 | C73: =SUMIFS('Données Suivi'!$J$2:$J$3000,'Données Suivi'!$A$2:$A$3000,$A73,'Données Suivi'!$M$2:$M$3000,"Engagé") -> 19305387 | D73: =IF(B73=0,"",C73/B73) -> 0.2212062
A74: DG | B74: =SUMIF('Données Suivi'!$A$2:$A$3000,$A74,'Données Suivi'!$J$2:$J$3000) -> 576000 | C74: =SUMIFS('Données Suivi'!$J$2:$J$3000,'Données Suivi'!$A$2:$A$3000,$A74,'Données Suivi'!$M$2:$M$3000,"Engagé") -> 576000 | D74: =IF(B74=0,"",C74/B74) -> 1
A75: DINFORADIO | B75: =SUMIF('Données Suivi'!$A$2:$A$3000,$A75,'Données Suivi'!$J$2:$J$3000) -> 2648832.5 | C75: =SUMIFS('Données Suivi'!$J$2:$J$3000,'Données Suivi'!$A$2:$A$3000,$A75,'Données Suivi'!$M$2:$M$3000,"Engagé") -> 2648832.5 | D75: =IF(B75=0,"",C75/B75) -> 1
A76: DINFOTV | B76: =SUMIF('Données Suivi'!$A$2:$A$3000,$A76,'Données Suivi'!$J$2:$J$3000) -> 12220397 | C76: =SUMIFS('Données Suivi'!$J$2:$J$3000,'Données Suivi'!$A$2:$A$3000,$A76,'Données Suivi'!$M$2:$M$3000,"Engagé") -> 10711701 | D76: =IF(B76=0,"",C76/B76) -> 0.87654285
A77: DJURIDIQUE | B77: =SUMIF('Données Suivi'!$A$2:$A$3000,$A77,'Données Suivi'!$J$2:$J$3000) -> 8561487.7 | C77: =SUMIFS('Données Suivi'!$J$2:$J$3000,'Données Suivi'!$A$2:$A$3000,$A77,'Données Suivi'!$M$2:$M$3000,"Engagé") -> 8551887.7 | D77: =IF(B77=0,"",C77/B77) -> 0.9988787
... A88: TV LAAYOUNE | B88: =SUMIF('Données Suivi'!$A$2:$A$3000,$A88,'Données Suivi'!$J$2:$J$3000) -> 22694636 | C88: =SUMIFS('Données Suivi'!$J$2:$J$3000,'Données Suivi'!$A$2:$A$3000,$A88,'Données Suivi'!$M$2:$M$3000,"Engagé") -> 22592636 | D88: =IF(B88=0,"",C88/B88) -> 0.99550555
A90: Dossiers en cours à relancer (triés par ancienneté décroissante)
A91: Direction | B91: Réf | C91: BCI | D91: Objet | E91: Statut Support | F91: Statut d'Engagement | G91: Montant (MAD) | H91: Date Fiche | I91: Ancienneté (j)
A92: ='Données Suivi'!A327 -> DPMG | B92: ='Données Suivi'!B327 -> 13AOM/SNRT | C92: ='Données Suivi'!C327 -> AOO-M | D92: ='Données Suivi'!D327 -> Travaux d’aménagement des locaux technique de la SNRT a Rabat : Lot 1 : Aménagement et Agencement | E92: ='Données Suivi'!E327 -> ATTRIBUE | F92: ='Données Suivi'!H327 -> PREENGAGE | G92: ='Données Suivi'!J327 -> 1959240 | H92: ='Données Suivi'!K327 -> 46041 | I92: ='Données Suivi'!L327 -> 247
A93: ='Données Suivi'!A328 -> DPMG | B93: ='Données Suivi'!B328 -> 13AOM/SNRT | C93: ='Données Suivi'!C328 -> AOO-M | D93: ='Données Suivi'!D328 -> Travaux d’aménagement des locaux technique de la SNRT a Rabat : Lot 2 : Electricité – Lustries – Climatisation | E93: ='Données Suivi'!E328 -> INFRUCTUEUX | F93: ='Données Suivi'!H328 -> NON ENGAGE | G93: ='Données Suivi'!J328 -> 489516 | H93: ='Données Suivi'!K328 -> 46041 | I93: ='Données Suivi'!L328 -> 247
A94: ='Données Suivi'!A359 -> DRPSD | B94: ='Données Suivi'!B359 -> 0 | C94: ='Données Suivi'!C359 -> AOO-M | D94: ='Données Suivi'!D359 -> Assistance et maintenance de la Solution BI | E94: ='Données Suivi'!E359 -> EN SIGNATURE | F94: ='Données Suivi'!H359 -> EN COURS DE PREENGAGEMENT | G94: ='Données Suivi'!J359 -> 240000 | H94: ='Données Suivi'!K359 -> 46077 | I94: ='Données Suivi'!L359 -> 211
A95: ='Données Suivi'!A378 -> DPMG | B95: ='Données Suivi'!B378 -> 58AOM/SNRT/2026 | C95: ='Données Suivi'!C378 -> AOO-M | D95: ='Données Suivi'!D378 -> Extension et mise à jour de la solution de la vidéosurveillance de la SNRT à Rabat et Casablanca | E95: ='Données Suivi'!E378 -> ATTRIBUE | F95: ='Données Suivi'!H378 -> PREENGAGE | G95: ='Données Suivi'!J378 -> 1003598.4 | H95: ='Données Suivi'!K378 -> 46086 | I95: ='Données Suivi'!L378 -> 202
A96: ='Données Suivi'!A379 -> DPMG | B96: ='Données Suivi'!B379 -> 58AOM/SNRT/2026 | C96: ='Données Suivi'!C379 -> AOO-M | D96: ='Données Suivi'!D379 -> Extension et mise à jour de la solution de la vidéosurveillance de la SNRT à Station TV LAAYOUNE | E96: ='Données Suivi'!E379 -> ATTRIBUE | F96: ='Données Suivi'!H379 -> PREENGAGE | G96: ='Données Suivi'!J379 -> 531787.2 | H96: ='Données Suivi'!K379 -> 46086 | I96: ='Données Suivi'!L379 -> 202
A97: ='Données Suivi'!A430 -> DCT | B97: ='Données Suivi'!B430 -> 10 AOM/SNRT | C97: ='Données Suivi'!C430 -> AOO-M | D97: ='Données Suivi'!D430 -> La fourniture et la mise en service des équipements d’éclairage pour les besoins de la production de la SNRT | E97: ='Données Suivi'!E430 -> ATTRIBUE | F97: ='Données Suivi'!H430 -> EN COURS D'ENGAGEMENT | G97: ='Données Suivi'!J430 -> 2017741.2 | H97: ='Données Suivi'!K430 -> 46121 | I97: ='Données Suivi'!L430 -> 167
A98: ='Données Suivi'!A410 -> DINFOTV | B98: ='Données Suivi'!B410 -> 20 AOM/SNRT | C98: ='Données Suivi'!C410 -> AOO-M | D98: ='Données Suivi'!D410 -> Préstation de blanchisserie du linge et services associés au profit des journalistes présentateurs du Journal Télévisé (JT) de la chaine Al Aoula de la SNRT-Rabat | E98: ='Données Suivi'!E410 -> ATTRIBUE | F98: ='Données Suivi'!H410 -> EN COURS D'ENGAGEMENT | G98: ='Données Suivi'!J410 -> 76464 | H98: ='Données Suivi'!K410 -> 46126 | I98: ='Données Suivi'!L410 -> 162
A99: ='Données Suivi'!A620 -> DCT | B99: ='Données Suivi'!B620 -> 64AOM/SNRT/2026 | C99: ='Données Suivi'!C620 -> AOO-M | D99: ='Données Suivi'!D620 -> Fourniture et mise en service d'un système de traveling robotisé pour les besoins de la production de la SNRT | E99: ='Données Suivi'!E620 -> INFRUCTUEUX | F99: ='Données Suivi'!H620 -> NON ENGAGE | G99: ='Données Suivi'!J620 -> 3132276 | H99: ='Données Suivi'!K620 -> 46127 | I99: ='Données Suivi'!L620 -> 161
A100: ='Données Suivi'!A557 -> DCT | B100: ='Données Suivi'!B557 -> 37 AOM/SNRT | C100: ='Données Suivi'!C557 -> AOO-M | D100: ='Données Suivi'!D557 -> L'élaboration du Schéma Directeur des Systèmes d'information (SDSI) de la Société Nationale de Radiodiffusion et de Télévision. | E100: ='Données Suivi'!E557 -> ATTRIBUE | F100: ='Données Suivi'!H557 -> PREENGAGE | G100: ='Données Suivi'!J557 -> 705900 | H100: ='Données Suivi'!K557 -> 46147 | I100: ='Données Suivi'!L557 -> 141
A101: ='Données Suivi'!A329 -> DPMG | B101: ='Données Suivi'!B329 -> 41AOM/AOM | C101: ='Données Suivi'!C329 -> AOO-M | D101: ='Données Suivi'!D329 -> Travaux d’aménagement et d’agencement de la Régie Publicitaire et des solutions digitales à Casablanca | E101: ='Données Suivi'!E329 -> INFRUCTUEUX | F101: ='Données Suivi'!H329 -> NON ENGAGE | G101: ='Données Suivi'!J329 -> 1189290 | H101: ='Données Suivi'!K329 -> 46154 | I101: ='Données Suivi'!L329 -> 134
A102: ='Données Suivi'!A573 -> DPMG | B102: ='Données Suivi'!B573 -> 22 AOM/SNRT | C102: ='Données Suivi'!C573 -> AOO-M | D102: ='Données Suivi'!D573 -> Fourniture et installation du matériel de bureau : Photocopieurs, Fax, Toners, Drums et Fours | E102: ='Données Suivi'!E573 -> APPROUVE | F102: ='Données Suivi'!H573 -> ENGAGE | G102: ='Données Suivi'!J573 -> 868200 | H102: ='Données Suivi'!K573 -> 46175 | I102: ='Données Suivi'!L573 -> 113
A103: ='Données Suivi'!A574 -> DPMG | B103: ='Données Suivi'!B574 -> 22 AOM/SNRT | C103: ='Données Suivi'!C574 -> AOO-M | D103: ='Données Suivi'!D574 -> Achat du consommable pour photocopieur et fax : Toners, Drums et Fours | E103: ='Données Suivi'!E574 -> ATTRIBUE | F103: ='Données Suivi'!H574 -> EN COURS D'ENGAGEMENT | G103: ='Données Suivi'!J574 -> 223140 | H103: ='Données Suivi'!K574 -> 46175 | I103: ='Données Suivi'!L574 -> 113
A104: ='Données Suivi'!A577 -> DCT | B104: ='Données Suivi'!B577 -> 46 AOM/SNRT | C104: ='Données Suivi'!C577 -> AOO-M | D104: ='Données Suivi'!D577 -> Renouvellement des licences de la solution de gestion financière pour les besoins de la SNRT | E104: ='Données Suivi'!E577 -> INFRUCTUEUX | F104: ='Données Suivi'!H577 -> NON ENGAGE | G104: ='Données Suivi'!J577 -> 112824 | H104: ='Données Suivi'!K577 -> 46175 | I104: ='Données Suivi'!L577 -> 113
A105: ='Données Suivi'!A578 -> DCT | B105: ='Données Suivi'!B578 -> 16 AOM/SNRT | C105: ='Données Suivi'!C578 -> AOO-M | D105: ='Données Suivi'!D578 -> La numérisation des anciennes archives télévisuelles stockées sur des supports analogiques de type cassette U-MATIC pour les besoins des archives TV de la SNRT | E105: ='Données Suivi'!E578 -> ATTRIBUE | F105: ='Données Suivi'!H578 -> EN COURS D'ENGAGEMENT | G105: ='Données Suivi'!J578 -> 970159.68 | H105: ='Données Suivi'!K578 -> 46175 | I105: ='Données Suivi'!L578 -> 113
A106: ='Données Suivi'!A579 -> TDF-EXP&MAIN | B106: ='Données Suivi'!B579 -> 51 AOM | C106: ='Données Suivi'!C579 -> AOO-M | D106: ='Données Suivi'!D579 -> Fourniture des modules et pièces de rechange pour les émetteurs FM de marque RVR | E106: ='Données Suivi'!E579 -> ATTRIBUE | F106: ='Données Suivi'!H579 -> EN COURS D'ENGAGEMENT | G106: ='Données Suivi'!J579 -> 2700386.4 | H106: ='Données Suivi'!K579 -> 46175 | I106: ='Données Suivi'!L579 -> 113
A107: ='Données Suivi'!A582 -> TDF-EXP&MAIN | B107: ='Données Suivi'!B582 -> 47AOM/SNRT/2026 | C107: ='Données Suivi'!C582 -> AOO-M | D107: ='Données Suivi'!D582 -> Fourniture des modules et piéces de rechange pour les émetteurs TNT de puissance 250 Watts de marque EUROTEK | E107: ='Données Suivi'!E582 -> ATTRIBUE | F107: ='Données Suivi'!H582 -> EN COURS D'ENGAGEMENT | G107: ='Données Suivi'!J582 -> 2190688.8 | H107: ='Données Suivi'!K582 -> 46185 | I107: ='Données Suivi'!L582 -> 103
A108: ='Données Suivi'!A583 -> TDF-EXP&MAIN | B108: ='Données Suivi'!B583 -> 47AOM/SNRT/2026 | C108: ='Données Suivi'!C583 -> AOO-M | D108: ='Données Suivi'!D583 -> Fourniture des modules et piéces de rechange des émetteurs TNT de marque ITELSIS | E108: ='Données Suivi'!E583 -> ATTRIBUE | F108: ='Données Suivi'!H583 -> EN COURS D'ENGAGEMENT | G108: ='Données Suivi'!J583 -> 2217600 | H108: ='Données Suivi'!K583 -> 46185 | I108: ='Données Suivi'!L583 -> 103
A109: ='Données Suivi'!A584 -> TDF-EXP&MAIN | B109: ='Données Suivi'!B584 -> 47AOM/SNRT/2026 | C109: ='Données Suivi'!C584 -> AOO-M | D109: ='Données Suivi'!D584 -> Fourniture des modules et piéces de rechange des émetteurs TNT de marque EGATEL de puissance 10KW | E109: ='Données Suivi'!E584 -> ATTRIBUE | F109: ='Données Suivi'!H584 -> EN COURS D'ENGAGEMENT | G109: ='Données Suivi'!J584 -> 1792788 | H109: ='Données Suivi'!K584 -> 46185 | I109: ='Données Suivi'!L584 -> 103
A110: ='Données Suivi'!A585 -> DCT | B110: ='Données Suivi'!B585 -> 29 AOM | C110: ='Données Suivi'!C585 -> AOO-M | D110: ='Données Suivi'!D585 -> La fourniture et la mise en service d'encodeurs et décodeurs SRT pour les besoins des unités mobiles de la SNRT | E110: ='Données Suivi'!E585 -> APPROUVE | F110: ='Données Suivi'!H585 -> ENGAGE | G110: ='Données Suivi'!J585 -> 3486881 | H110: ='Données Suivi'!K585 -> 46185 | I110: ='Données Suivi'!L585 -> 103
A111: ='Données Suivi'!A586 -> DCT | B111: ='Données Suivi'!B586 -> 44 AOM | C111: ='Données Suivi'!C586 -> AOO-M | D111: ='Données Suivi'!D586 -> La fourniture et la mise en service de lecteurs LTO destinés aux besoins d’archivage de la SNRT | E111: ='Données Suivi'!E586 -> INFRUCTUEUX | F111: ='Données Suivi'!H586 -> NON ENGAGE | G111: ='Données Suivi'!J586 -> 422256 | H111: ='Données Suivi'!K586 -> 46185 | I111: ='Données Suivi'!L586 -> 103
A112: ='Données Suivi'!A587 -> DCT | B112: ='Données Suivi'!B587 -> 35 AOM | C112: ='Données Suivi'!C587 -> AOO-M | D112: ='Données Suivi'!D587 -> La fourniture et la mise en service de serveurs haute performance destinés aux applications d’intelligence artificielle et d’apprentissage automatique pour les besoins de la SNRT | E112: ='Données Suivi'!E587 -> APPROUVE | F112: ='Données Suivi'!H587 -> ENGAGE | G112: ='Données Suivi'!J587 -> 2880000 | H112: ='Données Suivi'!K587 -> 46185 | I112: ='Données Suivi'!L587 -> 103
A113: ='Données Suivi'!A588 -> DRPSD | B113: ='Données Suivi'!B588 -> 49 AOM | C113: ='Données Suivi'!C588 -> AOO-M | D113: ='Données Suivi'!D588 -> La maintenance de messagerie Lotus Notes/Domino | E113: ='Données Suivi'!E588 -> EN SIGNATURE | F113: ='Données Suivi'!H588 -> EN COURS DE PREENGAGEMENT | G113: ='Données Suivi'!J588 -> 61200 | H113: ='Données Suivi'!K588 -> 46191 | I113: ='Données Suivi'!L588 -> 97
A114: ='Données Suivi'!A589 -> DRPSD | B114: ='Données Suivi'!B589 -> 48 AOM | C114: ='Données Suivi'!C589 -> AOO-M | D114: ='Données Suivi'!D589 -> Prestation de maintenance et assitance / Support du logiciel de gestion des campagnes publicitaires des support TV et Radio de la SNRT | E114: ='Données Suivi'!E589 -> EN SIGNATURE | F114: ='Données Suivi'!H589 -> EN COURS DE PREENGAGEMENT | G114: ='Données Suivi'!J589 -> 904728 | H114: ='Données Suivi'!K589 -> 46191 | I114: ='Données Suivi'!L589 -> 97
A115: ='Données Suivi'!A590 -> DCT | B115: ='Données Suivi'!B590 -> 25 AOM/SNRT | C115: ='Données Suivi'!C590 -> AOO-M | D115: ='Données Suivi'!D590 -> La fourniture et la mise en service d'une solution de transport des communications intercom via des coules audio IP BROADCAST pour les besoins des unités mobiles de la SNRT | E115: ='Données Suivi'!E590 -> ATTRIBUE | F115: ='Données Suivi'!H590 -> PREENGAGE | G115: ='Données Suivi'!J590 -> 346250.28 | H115: ='Données Suivi'!K590 -> 46191 | I115: ='Données Suivi'!L590 -> 97
A116: ='Données Suivi'!A592 -> TDF -SITES | B116: ='Données Suivi'!B592 -> 50 AOM/SNRT | C116: ='Données Suivi'!C592 -> AOO-M | D116: ='Données Suivi'!D592 -> Fourniture, installation et mise en service d'un nouveau groupe électrogène de puissance 200KW/PRP pour le centre SNRT de PALOMAS (P.EL HOCEIMA), ainsi que le transfert de quelques groupes électrogènes entre des centres SNRT y compris leurs mises à niveau | E116: ='Données Suivi'!E592 -> PHASE AOO | F116: ='Données Suivi'!H592 -> PREENGAGE | G116: ='Données Suivi'!J592 -> 1512000 | H116: ='Données Suivi'!K592 -> 46191 | I116: ='Données Suivi'!L592 -> 97
A117: ='Données Suivi'!A593 -> DCT | B117: ='Données Suivi'!B593 -> 53 AOM/SNRT | C117: ='Données Suivi'!C593 -> AOO-M | D117: ='Données Suivi'!D593 -> La fourniture et la mise en service d'équipement informatiques les besoins de SNRT new de la SNRT | E117: ='Données Suivi'!E593 -> INFRUCTUEUX | F117: ='Données Suivi'!H593 -> NON ENGAGE | G117: ='Données Suivi'!J593 -> 2086500 | H117: ='Données Suivi'!K593 -> 46191 | I117: ='Données Suivi'!L593 -> 97
A118: ='Données Suivi'!A563 -> DACG | B118: ='Données Suivi'!B563 -> AOM/SNRT | C118: ='Données Suivi'!C563 -> AOO-M | D118: ='Données Suivi'!D563 -> Élaboration de la cartographie des risques de la SNRT et déploiement du dispositif de suivi et de mise à jour y afférent | E118: ='Données Suivi'!E563 -> EN SIGNATURE | F118: ='Données Suivi'!H563 -> EN COURS DE PREENGAGEMENT | G118: ='Données Suivi'!J563 -> 144000 | H118: ='Données Suivi'!K563 -> 46192 | I118: ='Données Suivi'!L563 -> 96
A119: ='Données Suivi'!A572 -> DPMG | B119: ='Données Suivi'!B572 -> 45AOM/SNRT/2026 | C119: ='Données Suivi'!C572 -> AOO-M | D119: ='Données Suivi'!D572 -> Peinture des facades et des locaux de la SNRT | E119: ='Données Suivi'!E572 -> ATTRIBUE | F119: ='Données Suivi'!H572 -> EN COURS D'ENGAGEMENT | G119: ='Données Suivi'!J572 -> 457560 | H119: ='Données Suivi'!K572 -> 46195 | I119: ='Données Suivi'!L572 -> 93
A120: ='Données Suivi'!A598 -> DPMG | B120: ='Données Suivi'!B598 -> 26000043 CL | C120: ='Données Suivi'!C598 -> BCL | D120: ='Données Suivi'!D598 -> LOT n°1: Etude des travaux d'aménagement du nouveau siège de la radio de Tétouane | E120: ='Données Suivi'!E598 -> APPROUVE | F120: ='Données Suivi'!H598 -> EN COURS D'ENGAGEMENT | G120: ='Données Suivi'!J598 -> 45000 | H120: ='Données Suivi'!K598 -> 46197 | I120: ='Données Suivi'!L598 -> 91
A121: ='Données Suivi'!A434 -> TDF -SITES | B121: ='Données Suivi'!B434 -> ancien 17AOM/SNRT | C121: ='Données Suivi'!C434 -> AOO-M | D121: ='Données Suivi'!D434 -> Élaboration des études techniques et suivi des travaux d’achèvement d’installation d’un pylone auto-stable de 30+10m de hauteur au site SNRT TANAKOUB (P.CHEFCHAOUEN) | E121: ='Données Suivi'!E434 -> EN SIGNATURE | F121: ='Données Suivi'!H434 -> EN COURS DE PREENGAGEMENT | G121: ='Données Suivi'!J434 -> 86400 | H121: ='Données Suivi'!K434 -> 46198 | I121: ='Données Suivi'!L434 -> 90
A122: ='Données Suivi'!A560 -> TDF -SITES | B122: ='Données Suivi'!B560 -> 0 | C122: ='Données Suivi'!C560 -> AOO-M | D122: ='Données Suivi'!D560 -> Élaboration des études techniques et suivi des travaux d’installation d’un pylône auto-stable de 55m de hauteur au site SNRT TAOURIRT (P.TAOURIRT) | E122: ='Données Suivi'!E560 -> EN SIGNATURE | F122: ='Données Suivi'!H560 -> EN COURS DE PREENGAGEMENT | G122: ='Données Suivi'!J560 -> 86400 | H122: ='Données Suivi'!K560 -> 46198 | I122: ='Données Suivi'!L560 -> 90
A123: ='Données Suivi'!A601 -> TDF -SITES | B123: ='Données Suivi'!B601 -> ancien 43AOM/SNRT | C123: ='Données Suivi'!C601 -> AOO-M | D123: ='Données Suivi'!D601 -> Elaboration des études techniques et suivi des travaux d'aménagement de l'ancien site de diffusion TV/FM de la SNRT à Jbel Hammat Moulay Hachem (P.Midelt) | E123: ='Données Suivi'!E601 -> EN SIGNATURE | F123: ='Données Suivi'!H601 -> EN COURS DE PREENGAGEMENT | G123: ='Données Suivi'!J601 -> 86400 | H123: ='Données Suivi'!K601 -> 46198 | I123: ='Données Suivi'!L601 -> 90
A124: ='Données Suivi'!A602 -> TDF -SITES | B124: ='Données Suivi'!B602 -> ancien 43AOM/SNRT | C124: ='Données Suivi'!C602 -> AOO-M | D124: ='Données Suivi'!D602 -> Elaboration des études techniques et suivi des travaux de construction du site de diffusion TV/FM de la SNRT à Msissi(P.Tinghir) | E124: ='Données Suivi'!E602 -> EN SIGNATURE | F124: ='Données Suivi'!H602 -> EN COURS DE PREENGAGEMENT | G124: ='Données Suivi'!J602 -> 86400 | H124: ='Données Suivi'!K602 -> 46198 | I124: ='Données Suivi'!L602 -> 90
A125: ='Données Suivi'!A608 -> DCT | B125: ='Données Suivi'!B608 -> 57AOM/SNRT/2026 | C125: ='Données Suivi'!C608 -> AOO-M | D125: ='Données Suivi'!D608 -> La fourniture et la mise en service de serveurs pour renouvellement de serveurs d’enregistrement et de replay pour les besoins de la production TV des manifestations sportives | E125: ='Données Suivi'!E608 -> ATTRIBUE | F125: ='Données Suivi'!H608 -> PREENGAGE | G125: ='Données Suivi'!J608 -> 10979856 | H125: ='Données Suivi'!K608 -> 46206 | I125: ='Données Suivi'!L608 -> 82
A126: ='Données Suivi'!A614 -> DCT | B126: ='Données Suivi'!B614 -> 40AOM/SNRT/2026 | C126: ='Données Suivi'!C614 -> AOO-M | D126: ='Données Suivi'!D614 -> La fourniture et la mise en service de logiciels et de licences de solutions IT pour les besoins de la Société Nationale de Radiodiffusion et de Télévision | E126: ='Données Suivi'!E614 -> INFRUCTUEUX | F126: ='Données Suivi'!H614 -> NON ENGAGE | G126: ='Données Suivi'!J614 -> 988416 | H126: ='Données Suivi'!K614 -> 46209 | I126: ='Données Suivi'!L614 -> 79
A127: ='Données Suivi'!A615 -> DJURIDIQUE | B127: ='Données Suivi'!B615 -> 26000057 CL | C127: ='Données Suivi'!C615 -> BCL | D127: ='Données Suivi'!D615 -> Publications des comptes annuels de la SNRT 2025 au Bulletin Officiel | E127: ='Données Suivi'!E615 -> EN SIGNATURE | F127: ='Données Suivi'!H615 -> EN COURS D'ENGAGEMENT | G127: ='Données Suivi'!J615 -> 9600 | H127: ='Données Suivi'!K615 -> 46212 | I127: ='Données Suivi'!L615 -> 76
A128: ='Données Suivi'!A547 -> DPMG | B128: ='Données Suivi'!B547 -> 61AOM/SNRT | C128: ='Données Suivi'!C547 -> AOO-M | D128: ='Données Suivi'!D547 -> Maintenance et entretien des appareils de climatisation (Pièce et main d’œuvre) : Rabat et Casablanca | E128: ='Données Suivi'!E547 -> PHASE AOO | F128: ='Données Suivi'!H547 -> PREENGAGE | G128: ='Données Suivi'!J547 -> 600696 | H128: ='Données Suivi'!K547 -> 46213 | I128: ='Données Suivi'!L547 -> 75
A129: ='Données Suivi'!A619 -> DCT | B129: ='Données Suivi'!B619 -> 63AOM/SNRT/2026 | C129: ='Données Suivi'!C619 -> AOO-M | D129: ='Données Suivi'!D619 -> Fourniture et mise en service d'équipements audio vidéo au profit de la Direction de la Régie Publicitaire et Solutions Digitales de la Société Nationale de la Radiodiffusion et de la Télévision | E129: ='Données Suivi'!E619 -> PHASE AOO | F129: ='Données Suivi'!H619 -> PREENGAGE | G129: ='Données Suivi'!J619 -> 388353.6 | H129: ='Données Suivi'!K619 -> 46218 | I129: ='Données Suivi'!L619 -> 70
A130: ='Données Suivi'!A622 -> DPMG | B130: ='Données Suivi'!B622 -> 26000068 CL | C130: ='Données Suivi'!C622 -> BCL | D130: ='Données Suivi'!D622 -> Acquisition de mini-refrigerateurs pour les directions de la SNRT | E130: ='Données Suivi'!E622 -> EN SIGNATURE | F130: ='Données Suivi'!H622 -> EN COURS D'ENGAGEMENT | G130: ='Données Suivi'!J622 -> 13992 | H130: ='Données Suivi'!K622 -> 46223 | I130: ='Données Suivi'!L622 -> 65
A131: ='Données Suivi'!A664 -> DPMG | B131: ='Données Suivi'!B664 -> 26000075 CL | C131: ='Données Suivi'!C664 -> BCL | D131: ='Données Suivi'!D664 -> La mise à niveau des blocs sanitaires au siège de la SNRT à Rabat | E131: ='Données Suivi'!E664 -> APPROUVE | F131: ='Données Suivi'!H664 -> ENGAGE | G131: ='Données Suivi'!J664 -> 99312 | H131: ='Données Suivi'!K664 -> 46261 | I131: ='Données Suivi'!L664 -> 27
A132: ='Données Suivi'!A665 -> DPMG | B132: ='Données Suivi'!B665 -> 26000082 CL | C132: ='Données Suivi'!C665 -> BCL | D132: ='Données Suivi'!D665 -> Aménagement de la salle serveur de la station radio régionale Meknes : Aménagement - électricité - climatisation | E132: ='Données Suivi'!E665 -> EN SIGNATURE | F132: ='Données Suivi'!H665 -> EN COURS D'ENGAGEMENT | G132: ='Données Suivi'!J665 -> 160000.8 | H132: ='Données Suivi'!K665 -> 46261 | I132: ='Données Suivi'!L665 -> 27
A133: ='Données Suivi'!A666 -> TDF -SITES | B133: ='Données Suivi'!B666 -> 71AOM/SNRT/2026 | C133: ='Données Suivi'!C666 -> AOO-M | D133: ='Données Suivi'!D666 -> Fourniture installation et mise en service de deux onduleurs de puissance 200 KVA chacun de type modulaire y compris des systèmes de climatisation associés aux sites SNRT d'Oukaimden (P,EL HAOUZ) et de BOUKOUALI(P,TAOURIRT) | E133: ='Données Suivi'!E666 -> PHASE AOO | F133: ='Données Suivi'!H666 -> PREENGAGE | G133: ='Données Suivi'!J666 -> 4332960 | H133: ='Données Suivi'!K666 -> 46262 | I133: ='Données Suivi'!L666 -> 26
A134: ='Données Suivi'!A667 -> ARRIYADIA | B134: ='Données Suivi'!B667 -> 26000618 CT | C134: ='Données Suivi'!C667 -> CONTRAT | D134: ='Données Suivi'!D667 -> Achat droits d'un documentaire des jeux méditéranneens | E134: ='Données Suivi'!E667 -> EN SIGNATURE | F134: ='Données Suivi'!H667 -> EN COURS D'ENGAGEMENT | G134: ='Données Suivi'!J667 -> 16653.24 | H134: ='Données Suivi'!K667 -> 46262 | I134: ='Données Suivi'!L667 -> 26
A135: ='Données Suivi'!A668 -> TDF-EXP&MAIN | B135: ='Données Suivi'!B668 -> 0 | C135: ='Données Suivi'!C668 -> AOO-M | D135: ='Données Suivi'!D668 -> Entretien et maintenance du syteme d'antennes du centre radio AM d'Ait Melloul | E135: ='Données Suivi'!E668 -> EN SIGNATURE | F135: ='Données Suivi'!H668 -> EN COURS DE PREENGAGEMENT | G135: ='Données Suivi'!J668 -> 3120000 | H135: ='Données Suivi'!K668 -> 46265 | I135: ='Données Suivi'!L668 -> 23
A136: ='Données Suivi'!A669 -> TDF-EXP&MAIN | B136: ='Données Suivi'!B669 -> 73AOM/SNRT/2026 | C136: ='Données Suivi'!C669 -> AOO-M | D136: ='Données Suivi'!D669 -> Fourniture des feeders antennes distributeurs de puissance RF connecteurs adaptateurs et accessoires de raccordement | E136: ='Données Suivi'!E669 -> PHASE AOO | F136: ='Données Suivi'!H669 -> PREENGAGE | G136: ='Données Suivi'!J669 -> 3971520 | H136: ='Données Suivi'!K669 -> 46265 | I136: ='Données Suivi'!L669 -> 23
A137: ='Données Suivi'!A670 -> TDF-EXP&MAIN | B137: ='Données Suivi'!B670 -> 73AOM/SNRT/2026 | C137: ='Données Suivi'!C670 -> AOO-M | D137: ='Données Suivi'!D670 -> Fourniture de duplexeurs filtres combiners et patch panels | E137: ='Données Suivi'!E670 -> PHASE AOO | F137: ='Données Suivi'!H670 -> PREENGAGE | G137: ='Données Suivi'!J670 -> 1920000 | H137: ='Données Suivi'!K670 -> 46265 | I137: ='Données Suivi'!L670 -> 23
...

Sheet Parametres
A1: Type de Budget
A2: REPORT BUDGET ANNEE ANTERIEURE
A3: REPORT BUDGET EXCEP ANNEE ANTERIEURE
A4: Ordinaire
A5: Exceptionnel
A6: BUDGET
A7: FONCTIONNEMENT
A8: INVESTISSEMENT | C8: =IFERROR(B8/(B7+B8),0) -> 0
A9: Lignes Budget Fonctionnement
A10: Achats de productions et de programmes: Acquis définitive Programmes TV externes
A11: Achats de productions et de programmes: Acquis définitive pgm Radio externes
A12: Achats de productions et de programmes: Achats des programmes en co-production
A13: Achats de productions et de programmes: Achat des programmes en production interne - personnes physiques
A14: Achats de droits: Achats des droits de captation
A15: Achats de droits: Cession de Droits de sport
A16: Achats de matières et fournitures consommables
A17: Achats non stockés de matières et fournitures
A18: Prestations de service: Achat d'études
A19: Prestations de service: Achat prestations de services locales - personnes physiques
A20: Prestations de service: Achat prestations de services locales - sociétés
... A44: Autre Matériel et mobilier de bureau
A45: Estimation | B45: MAD | C45: %
A46: Estimation Total HT
A47: Ecart
A48: MNT Partiel | C48: =IFERROR(MTP/MTT,0) -> 0
A49: Total Marché HT
A50: DIRECTION | B50: PPA | C50: Marche
A51: TDF
A52: TDF -SITES
A53: TDF-EXP&MAIN
A54: DG
A55: DCT
A56: RSSI
A57: DPMG
A58: DRPSD
A59: DINFORADIO
A60: ARRIYADIA
A61: TV LAAYOUNE
A62: MAGHRIBIA
... A78: DSI
A79: LIGNES BUDGETAIRES | B79: PPA | C79: AOO/BC
A80: Aménagement et construction de bâtiments à usage technique
A81: Aménagement et construction de bâtiments administratifs
A82: Electrification et installations techniques
A83: Equipements audiovisuels RADIO
A84: Equipements audiovisuels TV
A85: Frais d'acquisition
A86: Habillage Radio
A87: Logiciels
A88: Matériel de bureau
A89: Matériel de diffusion
A90: Matériel de transmission
A91: Matériel informatique
... A126: CONTRAT
A127: STATUT SUPPORT D'ENGAGEMENT | B127: MONTANT
A128: APPROUVE
A129: ATTRIBUE
A130: NON ATTRIBUE
A131: REJET
A132: INFRUCTUEUX
A133: ANNULE
A134: PHASE AOO
A135: EN SIGNATURE
A136: CATEGORIES
A137: PME
A138: GENERAL
A139: NON CONCERNE
... A150: Nature type PPA

Sheet ENGAGEMENTS 2026
A1: ÉTAT | B1: ANNEE LANCEMENT | C1: DIRECTION | D1: REF | E1: BCI | F1: LOTS | G1: OBJET | H1: STATUT 1 | I1: STATUT SUPPORT D'ENGAGEMENT | J1: N° SUPPORT D'ENGAGEMENT | K1: CATEGORIES | L1: TYPE BUDGET | M1: BUDGET | N1: LIGNES BUDGETAIRES | O1: MONTANT PREENGAGE INITIAL | P1: ESTIMATION TTC | Q1: ESTIMATION HT | R1: NATURE BESOIN | S1: DEBUT REC | T1: FIN REC | U1: ADJUDICATAIRE / FRS | V1: ANNEE APPROBATION | W1: DATE DE LA FICHE | X1: DATE VISA | Y1: DATE APPROB | Z1: MONTANT MARCHE HT PART EN MAD | AA1: MONTANT MARCHE HT PART EN DEVISES | AB1: MONTANT MARCHE TTC PART EN MAD | AC1: MONTANT MARCHE TTC PART EN DEVISES | AD1: TOTAL MARCHE HT TOTAL ENGAGE HT | AE1: TOTAL MARCHE TTC TOTAL ENGAGE TTC | AF1: STATUT D'ENGAGEMENT | AG1: Remarque (archive) | AH1: Reserve | AI1: PREVISION PPA HT | AJ1: ECART ESTIMATION HT-PPA HT | AK1: ECART ENGAGEMENT HT-PPA HT | AL1: ECART ESTIMATION eng/estim | AM1: ECART PPA enga/ppa | AN1: REMARQUE
A2: =IF(AF2="ENGAGE","✔",IF(AF2="EN COURS D'ENGAGEMENT","◕",IF(AF2="PREENGAGE","◑",IF(AF2="EN COURS DE PREENGAGEMENT","◔",IF(AF2="NON ENGAGE","✖",""))))) -> ✔ | B2: 2026 | C2: DRH | D2: EXCLUSIVITÉ | E2: CONTRAT | F2: 1 | G2: Convention SNRT-OFPPT pour la réalisation des EAP | H2: VALIDE | I2: APPROUVE | J2: 01/OFPPT/SNRT/2026 | K2: NON CONCERNE | L2: Ordinaire | M2: FONCTIONNEMENT | N2: Charges sociales diverses | R2: BESOIN RECURRENT | U2: OFPPT | V2: 2026 | W2: 46030 | Y2: 46066 | Z2: 829202 | AA2: 0 | AB2: 995042.4 | AC2: 0 | AD2: 829202 | AE2: 995042.4 | AF2: ENGAGE | AN2: « + 287 001 » - Budget PPA = 708 041,40 Dhs
A3: =IF(AF3="ENGAGE","✔",IF(AF3="EN COURS D'ENGAGEMENT","◕",IF(AF3="PREENGAGE","◑",IF(AF3="EN COURS DE PREENGAGEMENT","◔",IF(AF3="NON ENGAGE","✖",""))))) -> ✔ | B3: 2026 | C3: DCPA | D3: PV N° : 01RC2025- DCPA | E3: CONTRAT | G3: IKRAM BENNANI RTAL - Préparation et animation de l’émission «نور و بصائر" | H3: VALIDE | I3: APPROUVE | J3: 185 CT/SNRT/2026 | K3: NON CONCERNE | L3: Ordinaire | M3: FONCTIONNEMENT | N3: Achats de productions et de programmes Achat des programmes en production interne | R3: RECONDUCTION | U3: IKRAM BENNANI RTAL | V3: 2026 | W3: 46022 | Y3: 46024 | Z3: 154000 | AA3: 0 | AB3: =+Z3 -> 154000 | AC3: =+AA3 -> 0 | AD3: =+Z3 -> 154000 | AE3: =+AB3 -> 154000 | AF3: ENGAGE | AN3: RAS
A4: =IF(AF4="ENGAGE","✔",IF(AF4="EN COURS D'ENGAGEMENT","◕",IF(AF4="PREENGAGE","◑",IF(AF4="EN COURS DE PREENGAGEMENT","◔",IF(AF4="NON ENGAGE","✖",""))))) -> ✔ | B4: 2026 | C4: DCPA | D4: PV N° : 01RC2025- DCPA | E4: CONTRAT | G4: AMINE BENADDI - LA PREPARATION DE L'EMISSION " شباب في الواجهة" | H4: VALIDE | I4: APPROUVE | J4: 186 CT/SNRT/2026 | K4: NON CONCERNE | L4: Ordinaire | M4: FONCTIONNEMENT | N4: Achats de productions et de programmes Achat des programmes en production interne | R4: RECONDUCTION | U4: AMINE BENADDI | V4: 2026 | W4: 46387 | Y4: 46024 | Z4: 375000 | AA4: 0 | AB4: =Z4 -> 375000 | AC4: 0 | AD4: =Z4 -> 375000 | AE4: =Z4 -> 375000 | AF4: ENGAGE | AN4: RAS
A5: =IF(AF5="ENGAGE","✔",IF(AF5="EN COURS D'ENGAGEMENT","◕",IF(AF5="PREENGAGE","◑",IF(AF5="EN COURS DE PREENGAGEMENT","◔",IF(AF5="NON ENGAGE","✖",""))))) -> ✔ | B5: 2026 | C5: DCPA | D5: PV N° : 01RC2025- DCPA | E5: CONTRAT | G5: MOHAMMED ALI BENMAKHLOUF - Conception et présentation de l’émission " علم و حضارة" | H5: VALIDE | I5: APPROUVE | J5: 190 CT/SNRT/2026 | K5: NON CONCERNE | L5: Ordinaire | M5: FONCTIONNEMENT | N5: Achats de productions et de programmes Achat des programmes en production interne | R5: RECONDUCTION | U5: MOHAMMED ALI BENMAKHLOUF | V5: 2026 | W5: 46387 | Y5: 46024 | Z5: 445714.08 | AA5: 0 | AB5: =Z5 -> 445714.08 | AC5: 0 | AD5: =Z5 -> 445714.08 | AE5: =Z5 -> 445714.08 | AF5: ENGAGE | AN5: RAS
A6: =IF(AF6="ENGAGE","✔",IF(AF6="EN COURS D'ENGAGEMENT","◕",IF(AF6="PREENGAGE","◑",IF(AF6="EN COURS DE PREENGAGEMENT","◔",IF(AF6="NON ENGAGE","✖",""))))) -> ✔ | B6: 2026 | C6: DCPA | D6: PV N° : 01RC2025- DCPA | E6: CONTRAT | G6: ACHABI MORAD - Préparation et animation de l'émission " مع الفاميلة" | H6: VALIDE | I6: APPROUVE | J6: 187 CT/SNRT/2026 | K6: NON CONCERNE | L6: Ordinaire | M6: FONCTIONNEMENT | N6: Achats de productions et de programmes Achat des programmes en production interne | R6: RECONDUCTION | U6: ACHABI MORAD | V6: 2026 | W6: 46387 | Y6: 46024 | Z6: 880000 | AA6: 0 | AB6: =Z6 -> 880000 | AC6: 0 | AD6: =Z6 -> 880000 | AE6: =Z6 -> 880000 | AF6: ENGAGE | AN6: RAS
A7: =IF(AF7="ENGAGE","✔",IF(AF7="EN COURS D'ENGAGEMENT","◕",IF(AF7="PREENGAGE","◑",IF(AF7="EN COURS DE PREENGAGEMENT","◔",IF(AF7="NON ENGAGE","✖",""))))) -> ✔ | B7: 2026 | C7: DCPA | D7: PV N° : 01RC2025- DCPA | E7: CONTRAT | G7: MOHAMED BOUMLI - Préparation de l'émission " مع الفاميلة" | H7: VALIDE | I7: APPROUVE | J7: 188 CT/SNRT/2026 | K7: NON CONCERNE | L7: Ordinaire | M7: FONCTIONNEMENT | N7: Achats de productions et de programmes Achat des programmes en production interne | R7: RECONDUCTION | U7: MOHAMED BOUMLI | V7: 2026 | W7: 46387 | Y7: 46024 | Z7: 176000 | AA7: 0 | AB7: =Z7 -> 176000 | AC7: 0 | AD7: =Z7 -> 176000 | AE7: =Z7 -> 176000 | AF7: ENGAGE | AN7: RAS
A8: =IF(AF8="ENGAGE","✔",IF(AF8="EN COURS D'ENGAGEMENT","◕",IF(AF8="PREENGAGE","◑",IF(AF8="EN COURS DE PREENGAGEMENT","◔",IF(AF8="NON ENGAGE","✖",""))))) -> ✔ | B8: 2026 | C8: DCPA | D8: PV N° : 01RC2025- DCPA | E8: CONTRAT | G8: KABBAJ SEDDIK - Coordination, préparation et supervision artistique de l’émission " مدن عتيقة" | H8: VALIDE | I8: APPROUVE | J8: 189 CT/SNRT/2026 | K8: NON CONCERNE | L8: Ordinaire | M8: FONCTIONNEMENT | N8: Achats de productions et de programmes Achat des programmes en production interne | R8: RECONDUCTION | U8: KABBAJ SEDDIK | V8: 2026 | W8: 46387 | Y8: 46024 | Z8: 342857 | AA8: 0 | AB8: =Z8 -> 342857 | AC8: 0 | AD8: =Z8 -> 342857 | AE8: =Z8 -> 342857 | AF8: ENGAGE | AN8: RAS
A9: =IF(AF9="ENGAGE","✔",IF(AF9="EN COURS D'ENGAGEMENT","◕",IF(AF9="PREENGAGE","◑",IF(AF9="EN COURS DE PREENGAGEMENT","◔",IF(AF9="NON ENGAGE","✖",""))))) -> ✔ | B9: 2026 | C9: ARRIYADIA | D9: PV N° : 01RC2025- DCCCA | E9: CONTRAT | G9: BELMAHEDI MOHAMED - Cadreur plateau | H9: VALIDE | I9: APPROUVE | K9: NON CONCERNE | L9: Ordinaire | M9: FONCTIONNEMENT | N9: Prestations de service Achat prestations de services locales - personnes physiques | R9: RECONDUCTION | U9: BELMAHEDI MOHAMED | V9: 2026 | W9: 46022 | Y9: 46024 | Z9: 113142.48 | AA9: 0 | AB9: =Z9 -> 113142.48 | AC9: 0 | AD9: =Z9 -> 113142.48 | AE9: =Z9 -> 113142.48 | AF9: ENGAGE | AN9: Manque n° contrat
A10: =IF(AF10="ENGAGE","✔",IF(AF10="EN COURS D'ENGAGEMENT","◕",IF(AF10="PREENGAGE","◑",IF(AF10="EN COURS DE PREENGAGEMENT","◔",IF(AF10="NON ENGAGE","✖",""))))) -> ✔ | B10: 2026 | C10: ARRIYADIA | D10: PV N° : 01RC2025- DCCCA | E10: CONTRAT | G10: BIOUD ABDELHAK – Cadreur plateau | H10: VALIDE | I10: APPROUVE | K10: NON CONCERNE | L10: Ordinaire | M10: FONCTIONNEMENT | N10: Prestations de service Achat prestations de services locales - personnes physiques | R10: RECONDUCTION | U10: BIOUD ABDELHAK | V10: 2026 | W10: 46022 | Y10: 46024 | Z10: 113142.48 | AA10: 0 | AB10: =Z10 -> 113142.48 | AC10: 0 | AD10: =Z10 -> 113142.48 | AE10: =Z10 -> 113142.48 | AF10: ENGAGE | AN10: Manque n° contrat
A11: =IF(AF11="ENGAGE","✔",IF(AF11="EN COURS D'ENGAGEMENT","◕",IF(AF11="PREENGAGE","◑",IF(AF11="EN COURS DE PREENGAGEMENT","◔",IF(AF11="NON ENGAGE","✖",""))))) -> ✔ | B11: 2026 | C11: ARRIYADIA | D11: PV N° : 01RC2025- DCCCA | E11: CONTRAT | G11: IHAB JAMAL EDDINE - Cadreur plateau | H11: VALIDE | I11: APPROUVE | K11: NON CONCERNE | L11: Ordinaire | M11: FONCTIONNEMENT | N11: Prestations de service Achat prestations de services locales - personnes physiques | R11: RECONDUCTION | U11: IHAB JAMAL EDDINE | V11: 2026 | W11: 46022 | Y11: 46024 | Z11: 113142.48 | AA11: 0 | AB11: =Z11 -> 113142.48 | AC11: 0 | AD11: =Z11 -> 113142.48 | AE11: =Z11 -> 113142.48 | AF11: ENGAGE | AN11: Manque n° contrat
A12: =IF(AF12="ENGAGE","✔",IF(AF12="EN COURS D'ENGAGEMENT","◕",IF(AF12="PREENGAGE","◑",IF(AF12="EN COURS DE PREENGAGEMENT","◔",IF(AF12="NON ENGAGE","✖",""))))) -> ✔ | B12: 2026 | C12: ARRIYADIA | D12: PV N° : 01RC2025- DCCCA | E12: CONTRAT | G12: YOUSSEF JOUMARI - Cadreur plateau | H12: VALIDE | I12: APPROUVE | K12: NON CONCERNE | L12: Ordinaire | M12: FONCTIONNEMENT | N12: Prestations de service Achat prestations de services locales - personnes physiques | R12: RECONDUCTION | U12: IHAB JAMAL EDDINE | V12: 2026 | W12: 46022 | Y12: 46024 | Z12: 113142.48 | AA12: 0 | AB12: =Z12 -> 113142.48 | AC12: 0 | AD12: =Z12 -> 113142.48 | AE12: =Z12 -> 113142.48 | AF12: ENGAGE | AN12: Manque n° contrat
A13: =IF(AF13="ENGAGE","✔",IF(AF13="EN COURS D'ENGAGEMENT","◕",IF(AF13="PREENGAGE","◑",IF(AF13="EN COURS DE PREENGAGEMENT","◔",IF(AF13="NON ENGAGE","✖",""))))) -> ✔ | B13: 2026 | C13: ARRIYADIA | D13: PV N° : 01RC2025- DCCCA | E13: CONTRAT | G13: MUSTAPHA SKALLI - Cadreur plateau | H13: VALIDE | I13: APPROUVE | K13: NON CONCERNE | L13: Ordinaire | M13: FONCTIONNEMENT | N13: Prestations de service Achat prestations de services locales - personnes physiques | R13: RECONDUCTION | U13: MUSTAPHA SKALLI | V13: 2026 | W13: 46022 | Y13: 46024 | Z13: 113142.48 | AA13: 0 | AB13: =Z13 -> 113142.48 | AC13: 0 | AD13: =Z13 -> 113142.48 | AE13: =Z13 -> 113142.48 | AF13: ENGAGE | AN13: Manque n° contrat
A14: =IF(AF14="ENGAGE","✔",IF(AF14="EN COURS D'ENGAGEMENT","◕",IF(AF14="PREENGAGE","◑",IF(AF14="EN COURS DE PREENGAGEMENT","◔",IF(AF14="NON ENGAGE","✖",""))))) -> ✔ | B14: 2026 | C14: ARRIYADIA | D14: PV N° : 01RC2025- DCCCA | E14: CONTRAT | G14: YOUSSEF EL FERNANI - Cadreur plateau | H14: VALIDE | I14: APPROUVE | K14: NON CONCERNE | L14: Ordinaire | M14: FONCTIONNEMENT | N14: Prestations de service Achat prestations de services locales - personnes physiques | R14: RECONDUCTION | U14: YOUSSEF EL FERNANI | V14: 2026 | W14: 46022 | Y14: 46024 | Z14: 113142.48 | AA14: 0 | AB14: =Z14 -> 113142.48 | AC14: 0 | AD14: =Z14 -> 113142.48 | AE14: =Z14 -> 113142.48 | AF14: ENGAGE | AN14: Manque n° contrat
A15: =IF(AF15="ENGAGE","✔",IF(AF15="EN COURS D'ENGAGEMENT","◕",IF(AF15="PREENGAGE","◑",IF(AF15="EN COURS DE PREENGAGEMENT","◔",IF(AF15="NON ENGAGE","✖",""))))) -> ✔ | B15: 2026 | C15: ARRIYADIA | D15: PV N° : 01RC2025- DCCCA | E15: CONTRAT | G15: YOUNES ZARIR - Cameraman/reporteur | H15: VALIDE | I15: APPROUVE | K15: NON CONCERNE | L15: Ordinaire | M15: FONCTIONNEMENT | N15: Prestations de service Achat prestations de services locales - personnes physiques | R15: RECONDUCTION | U15: YOUNES ZARIR | V15: 2026 | W15: 46022 | Y15: 46024 | Z15: 113142.48 | AA15: 0 | AB15: =Z15 -> 113142.48 | AC15: 0 | AD15: =Z15 -> 113142.48 | AE15: =Z15 -> 113142.48 | AF15: ENGAGE | AN15: Manque n° contrat
A16: =IF(AF16="ENGAGE","✔",IF(AF16="EN COURS D'ENGAGEMENT","◕",IF(AF16="PREENGAGE","◑",IF(AF16="EN COURS DE PREENGAGEMENT","◔",IF(AF16="NON ENGAGE","✖",""))))) -> ✔ | B16: 2026 | C16: ARRIYADIA | D16: PV N° : 01RC2025- DCCCA | E16: CONTRAT | G16: AZEDDINE ESSATOURI - Cameraman/reporteur | H16: VALIDE | I16: APPROUVE | K16: NON CONCERNE | L16: Ordinaire | M16: FONCTIONNEMENT | N16: Prestations de service Achat prestations de services locales - personnes physiques | R16: RECONDUCTION | U16: AZEDDINE ESSATOURI | V16: 2026 | W16: 46022 | Y16: 46024 | Z16: 113142.48 | AA16: 0 | AB16: =Z16 -> 113142.48 | AC16: 0 | AD16: =Z16 -> 113142.48 | AE16: =Z16 -> 113142.48 | AF16: ENGAGE | AN16: Manque n° contrat
A17: =IF(AF17="ENGAGE","✔",IF(AF17="EN COURS D'ENGAGEMENT","◕",IF(AF17="PREENGAGE","◑",IF(AF17="EN COURS DE PREENGAGEMENT","◔",IF(AF17="NON ENGAGE","✖",""))))) -> ✔ | B17: 2026 | C17: ARRIYADIA | D17: PV N° : 01RC2025- DCCCA | E17: CONTRAT | G17: SOUFIANE ZIAT - Cameraman/reporteur | H17: VALIDE | I17: APPROUVE | K17: NON CONCERNE | L17: Ordinaire | M17: FONCTIONNEMENT | N17: Prestations de service Achat prestations de services locales - personnes physiques | R17: RECONDUCTION | U17: SOUFIANE ZIAT | V17: 2026 | W17: 46022 | Y17: 46024 | Z17: 113142.48 | AA17: 0 | AB17: =Z17 -> 113142.48 | AC17: 0 | AD17: =Z17 -> 113142.48 | AE17: =Z17 -> 113142.48 | AF17: ENGAGE | AN17: Manque n° contrat
A18: =IF(AF18="ENGAGE","✔",IF(AF18="EN COURS D'ENGAGEMENT","◕",IF(AF18="PREENGAGE","◑",IF(AF18="EN COURS DE PREENGAGEMENT","◔",IF(AF18="NON ENGAGE","✖",""))))) -> ✔ | B18: 2026 | C18: ARRIYADIA | D18: PV N° : 01RC2025- DCCCA | E18: CONTRAT | G18: ABDELHAK EL GANTITI - Cameraman/reporteur | H18: VALIDE | I18: APPROUVE | K18: NON CONCERNE | L18: Ordinaire | M18: FONCTIONNEMENT | N18: Prestations de service Achat prestations de services locales - personnes physiques | R18: RECONDUCTION | U18: ABDELHAK EL GANTITI | V18: 2026 | W18: 46022 | Y18: 46024 | Z18: 113142.48 | AA18: 0 | AB18: =Z18 -> 113142.48 | AC18: 0 | AD18: =Z18 -> 113142.48 | AE18: =Z18 -> 113142.48 | AF18: ENGAGE | AN18: Manque n° contrat
A19: =IF(AF19="ENGAGE","✔",IF(AF19="EN COURS D'ENGAGEMENT","◕",IF(AF19="PREENGAGE","◑",IF(AF19="EN COURS DE PREENGAGEMENT","◔",IF(AF19="NON ENGAGE","✖",""))))) -> ✔ | B19: 2026 | C19: ARRIYADIA | D19: PV N° : 01RC2025- DCCCA | E19: CONTRAT | G19: MOHAMED RAFIQ – Cadreur plateau/technicien coordinateur d’antenne TV | H19: VALIDE | I19: APPROUVE | K19: NON CONCERNE | L19: Ordinaire | M19: FONCTIONNEMENT | N19: Prestations de service Achat prestations de services locales - personnes physiques | R19: RECONDUCTION | U19: MOHAMED RAFIQ | V19: 2026 | W19: 46022 | Y19: 46024 | Z19: 113142.48 | AA19: 0 | AB19: =Z19 -> 113142.48 | AC19: 0 | AD19: =Z19 -> 113142.48 | AE19: =Z19 -> 113142.48 | AF19: ENGAGE | AN19: Manque n° contrat
A20: =IF(AF20="ENGAGE","✔",IF(AF20="EN COURS D'ENGAGEMENT","◕",IF(AF20="PREENGAGE","◑",IF(AF20="EN COURS DE PREENGAGEMENT","◔",IF(AF20="NON ENGAGE","✖",""))))) -> ✔ | B20: 2026 | C20: ARRIYADIA | D20: PV N° : 01RC2025- DCCCA | E20: CONTRAT | G20: ASMAA ADDAR - Monteur truquiste | H20: VALIDE | I20: APPROUVE | K20: NON CONCERNE | L20: Ordinaire | M20: FONCTIONNEMENT | N20: Prestations de service Achat prestations de services locales - personnes physiques | R20: RECONDUCTION | U20: ASMAA ADDAR | V20: 2026 | W20: 46022 | Y20: 46024 | Z20: 113142.48 | AA20: 0 | AB20: =Z20 -> 113142.48 | AC20: 0 | AD20: =Z20 -> 113142.48 | AE20: =Z20 -> 113142.48 | AF20: ENGAGE | AN20: Manque n° contrat
... A22: =IF(AF22="ENGAGE","✔",IF(AF22="EN COURS D'ENGAGEMENT","◕",IF(AF22="PREENGAGE","◑",IF(AF22="EN COURS DE PREENGAGEMENT","◔",IF(AF22="NON ENGAGE","✖",""))))) -> ✔ | B22: 2026 | C22: ARRIYADIA | D22: PV N° : 01RC2025- DCCCA | E22: CONTRAT | G22: DOUAA HMIMOU - Monteur truquiste | H22: VALIDE | I22: APPROUVE | K22: NON CONCERNE | L22: Ordinaire | M22: FONCTIONNEMENT | N22: Prestations de service Achat prestations de services locales - personnes physiques | R22: RECONDUCTION | U22: DOUAA HMIMOU | V22: 2026 | W22: 46022 | Y22: 46024 | Z22: 113142.48 | AA22: 0 | AB22: =Z22 -> 113142.48 | AC22: 0 | AD22: =Z22 -> 113142.48 | AE22: =Z22 -> 113142.48 | AF22: ENGAGE | AN22: Manque n° contrat
A23: =IF(AF23="ENGAGE","✔",IF(AF23="EN COURS D'ENGAGEMENT","◕",IF(AF23="PREENGAGE","◑",IF(AF23="EN COURS DE PREENGAGEMENT","◔",IF(AF23="NON ENGAGE","✖",""))))) -> ✔ | B23: 2026 | C23: ARRIYADIA | D23: PV N° : 01RC2025- DCCCA | E23: CONTRAT | G23: ROUZZAQ ANIS – Monteur truquiste /bande d’annonce | H23: VALIDE | I23: APPROUVE | K23: NON CONCERNE | L23: Ordinaire | M23: FONCTIONNEMENT | N23: Prestations de service Achat prestations de services locales - personnes physiques | R23: RECONDUCTION | U23: ROUZZAQ ANIS | V23: 2026 | W23: 46022 | Y23: 46024 | Z23: 156000 | AB23: =Z23 -> 156000 | AD23: =Z23 -> 156000 | AE23: =Z23 -> 156000 | AF23: ENGAGE | AN23: Manque n° contrat
A24: =IF(AF24="ENGAGE","✔",IF(AF24="EN COURS D'ENGAGEMENT","◕",IF(AF24="PREENGAGE","◑",IF(AF24="EN COURS DE PREENGAGEMENT","◔",IF(AF24="NON ENGAGE","✖",""))))) -> ✔ | B24: 2026 | C24: ARRIYADIA | D24: PV N° : 01RC2025- DCCCA | E24: CONTRAT | G24: SAFAE BOUHLAL - Monteur truquiste /technicien coordinateur d’antenne TV | H24: VALIDE | I24: APPROUVE | K24: NON CONCERNE | L24: Ordinaire | M24: FONCTIONNEMENT | N24: Prestations de service Achat prestations de services locales - personnes physiques | R24: RECONDUCTION | U24: SAFAE BOUHLAL | V24: 2026 | W24: 46022 | Y24: 46024 | Z24: 113142.48 | AA24: 0 | AB24: =Z24 -> 113142.48 | AC24: 0 | AD24: =Z24 -> 113142.48 | AE24: =Z24 -> 113142.48 | AF24: ENGAGE | AN24: Manque n° contrat
A25: =IF(AF25="ENGAGE","✔",IF(AF25="EN COURS D'ENGAGEMENT","◕",IF(AF25="PREENGAGE","◑",IF(AF25="EN COURS DE PREENGAGEMENT","◔",IF(AF25="NON ENGAGE","✖",""))))) -> ✔ | B25: 2026 | C25: ARRIYADIA | D25: PV N° : 01RC2025- DCCCA | E25: CONTRAT | G25: OUSSAMA EZZABBAR - Monteur truquiste | H25: VALIDE | I25: APPROUVE | K25: NON CONCERNE | L25: Ordinaire | M25: FONCTIONNEMENT | N25: Prestations de service Achat prestations de services locales - personnes physiques | R25: RECONDUCTION | U25: OUSSAMA EZZABBAR | V25: 2026 | W25: 46022 | Y25: 46024 | Z25: 113142.48 | AA25: 0 | AB25: =Z25 -> 113142.48 | AC25: 0 | AD25: =Z25 -> 113142.48 | AE25: =Z25 -> 113142.48 | AF25: ENGAGE | AN25: Manque n° contrat
A26: =IF(AF26="ENGAGE","✔",IF(AF26="EN COURS D'ENGAGEMENT","◕",IF(AF26="PREENGAGE","◑",IF(AF26="EN COURS DE PREENGAGEMENT","◔",IF(AF26="NON ENGAGE","✖",""))))) -> ✔ | B26: 2026 | C26: ARRIYADIA | D26: PV N° : 01RC2025- DCCCA | E26: CONTRAT | G26: AMINE IMANE - Opérateur synthétiseur | H26: VALIDE | I26: APPROUVE | K26: NON CONCERNE | L26: Ordinaire | M26: FONCTIONNEMENT | N26: Prestations de service Achat prestations de services locales - personnes physiques | R26: RECONDUCTION | U26: AMINE IMANE | V26: 2026 | W26: 46022 | Y26: 46024 | Z26: 113142.48 | AA26: 0 | AB26: =Z26 -> 113142.48 | AC26: 0 | AD26: =Z26 -> 113142.48 | AE26: =Z26 -> 113142.48 | AF26: ENGAGE | AN26: Manque n° contrat
A27: =IF(AF27="ENGAGE","✔",IF(AF27="EN COURS D'ENGAGEMENT","◕",IF(AF27="PREENGAGE","◑",IF(AF27="EN COURS DE PREENGAGEMENT","◔",IF(AF27="NON ENGAGE","✖",""))))) -> ✔ | B27: 2026 | C27: ARRIYADIA | D27: PV N° : 01RC2025- DCCCA | E27: CONTRAT | G27: BRAHIM ABASALAH - Opérateur synthétiseur/créateur de pages de textes et logos destinés à l’habillage au titre et au sous-titrage des programmes de l’antenne. | H27: VALIDE | I27: APPROUVE | K27: NON CONCERNE | L27: Ordinaire | M27: FONCTIONNEMENT | N27: Prestations de service Achat prestations de services locales - personnes physiques | R27: RECONDUCTION | U27: BRAHIM ABASALAH | V27: 2026 | W27: 46022 | Y27: 46024 | Z27: 144000 | AA27: 0 | AB27: =Z27 -> 144000 | AC27: 0 | AD27: =Z27 -> 144000 | AE27: =Z27 -> 144000 | AF27: ENGAGE | AN27: Manque n° contrat
A28: =IF(AF28="ENGAGE","✔",IF(AF28="EN COURS D'ENGAGEMENT","◕",IF(AF28="PREENGAGE","◑",IF(AF28="EN COURS DE PREENGAGEMENT","◔",IF(AF28="NON ENGAGE","✖",""))))) -> ✔ | B28: 2026 | C28: ARRIYADIA | D28: PV N° : 01RC2025- DCCCA | E28: CONTRAT | G28: YASSINE STITOU - Opérateur synthétiseur | H28: VALIDE | I28: APPROUVE | K28: NON CONCERNE | L28: Ordinaire | M28: FONCTIONNEMENT | N28: Prestations de service Achat prestations de services locales - personnes physiques | R28: RECONDUCTION | U28: YASSINE STITOU | V28: 2026 | W28: 46022 | Y28: 46024 | Z28: 113142.48 | AA28: 0 | AB28: =Z28 -> 113142.48 | AC28: 0 | AD28: =Z28 -> 113142.48 | AE28: =Z28 -> 113142.48 | AF28: ENGAGE | AN28: Manque n° contrat
A29: =IF(AF29="ENGAGE","✔",IF(AF29="EN COURS D'ENGAGEMENT","◕",IF(AF29="PREENGAGE","◑",IF(AF29="EN COURS DE PREENGAGEMENT","◔",IF(AF29="NON ENGAGE","✖",""))))) -> ✔ | B29: 2026 | C29: ARRIYADIA | D29: PV N° : 01RC2025- DCCCA | E29: CONTRAT | G29: RACHID ABKARI - Opérateur de prise de son | H29: VALIDE | I29: APPROUVE | K29: NON CONCERNE | L29: Ordinaire | M29: FONCTIONNEMENT | N29: Prestations de service Achat prestations de services locales - personnes physiques | R29: RECONDUCTION | U29: RACHID ABKARI | V29: 2026 | W29: 46022 | Y29: 46024 | Z29: 113142.48 | AA29: 0 | AB29: =Z29 -> 113142.48 | AC29: 0 | AD29: =Z29 -> 113142.48 | AE29: =Z29 -> 113142.48 | AF29: ENGAGE | AN29: Manque n° contrat
A30: =IF(AF30="ENGAGE","✔",IF(AF30="EN COURS D'ENGAGEMENT","◕",IF(AF30="PREENGAGE","◑",IF(AF30="EN COURS DE PREENGAGEMENT","◔",IF(AF30="NON ENGAGE","✖",""))))) -> ✔ | B30: 2026 | C30: ARRIYADIA | D30: PV N° : 01RC2025- DCCCA | E30: CONTRAT | G30: AMINE NEKI - Technicien coordinateur d'antenne TV | H30: VALIDE | I30: APPROUVE | K30: NON CONCERNE | L30: Ordinaire | M30: FONCTIONNEMENT | N30: Prestations de service Achat prestations de services locales - personnes physiques | R30: RECONDUCTION | U30: AMINE NEKI | V30: 2026 | W30: 46022 | Y30: 46024 | Z30: 113142.48 | AA30: 0 | AB30: =Z30 -> 113142.48 | AC30: 0 | AD30: =Z30 -> 113142.48 | AE30: =Z30 -> 113142.48 | AF30: ENGAGE | AN30: Manque n° contrat
A31: =IF(AF31="ENGAGE","✔",IF(AF31="EN COURS D'ENGAGEMENT","◕",IF(AF31="PREENGAGE","◑",IF(AF31="EN COURS DE PREENGAGEMENT","◔",IF(AF31="NON ENGAGE","✖",""))))) -> ✔ | B31: 2026 | C31: ARRIYADIA | D31: PV N° : 01RC2025- DCCCA | E31: CONTRAT | G31: ANISS BENRIANE - Technicien coordinateur d'antenne TV | H31: VALIDE | I31: APPROUVE | K31: NON CONCERNE | L31: Ordinaire | M31: FONCTIONNEMENT | N31: Prestations de service Achat prestations de services locales - personnes physiques | R31: RECONDUCTION | U31: ANISS BENRIANE | V31: 2026 | W31: 46022 | Y31: 46024 | Z31: 113142.48 | AA31: 0 | AB31: =Z31 -> 113142.48 | AC31: 0 | AD31: =Z31 -> 113142.48 | AE31: =Z31 -> 113142.48 | AF31: ENGAGE | AN31: Manque n° contrat
A32: =IF(AF32="ENGAGE","✔",IF(AF32="EN COURS D'ENGAGEMENT","◕",IF(AF32="PREENGAGE","◑",IF(AF32="EN COURS DE PREENGAGEMENT","◔",IF(AF32="NON ENGAGE","✖",""))))) -> ✔ | B32: 2026 | C32: ARRIYADIA | D32: PV N° : 01RC2025- DCCCA | E32: CONTRAT | G32: AHMED HOUBBANE - Journaliste présentateur TV/reporteur | H32: VALIDE | I32: APPROUVE | K32: NON CONCERNE | L32: Ordinaire | M32: FONCTIONNEMENT | N32: Prestations de service Achat prestations de services locales - personnes physiques | R32: RECONDUCTION | U32: AHMED HOUBBANE | V32: 2026 | W32: 46022 | Y32: 46024 | Z32: 144000 | AA32: 0 | AB32: =Z32 -> 144000 | AC32: 0 | AD32: =Z32 -> 144000 | AE32: =Z32 -> 144000 | AF32: ENGAGE | AN32: Manque n° contrat
A33: =IF(AF33="ENGAGE","✔",IF(AF33="EN COURS D'ENGAGEMENT","◕",IF(AF33="PREENGAGE","◑",IF(AF33="EN COURS DE PREENGAGEMENT","◔",IF(AF33="NON ENGAGE","✖",""))))) -> ✔ | B33: 2026 | C33: ARRIYADIA | D33: PV N° : 01RC2025- DCCCA | E33: CONTRAT | G33: OMAYRA MOUKRAM - Journaliste présentateur TV | H33: VALIDE | I33: APPROUVE | K33: NON CONCERNE | L33: Ordinaire | M33: FONCTIONNEMENT | N33: Prestations de service Achat prestations de services locales - personnes physiques | R33: RECONDUCTION | U33: OMAYRA MOUKRAM | V33: 2026 | W33: 46022 | Y33: 46024 | Z33: 113142.48 | AA33: 0 | AB33: =Z33 -> 113142.48 | AC33: 0 | AD33: =Z33 -> 113142.48 | AE33: =Z33 -> 113142.48 | AF33: ENGAGE | AN33: Manque n° contrat
A34: =IF(AF34="ENGAGE","✔",IF(AF34="EN COURS D'ENGAGEMENT","◕",IF(AF34="PREENGAGE","◑",IF(AF34="EN COURS DE PREENGAGEMENT","◔",IF(AF34="NON ENGAGE","✖",""))))) -> ✔ | B34: 2026 | C34: ARRIYADIA | D34: PV N° : 01RC2025- DCCCA | E34: CONTRAT | G34: AYOUB ADIB - Journaliste animateur | H34: VALIDE | I34: APPROUVE | K34: NON CONCERNE | L34: Ordinaire | M34: FONCTIONNEMENT | N34: Prestations de service Achat prestations de services locales - personnes physiques | R34: RECONDUCTION | U34: AYOUB ADIB | V34: 2026 | W34: 46022 | Y34: 46024 | Z34: 113142.48 | AA34: 0 | AB34: =Z34 -> 113142.48 | AC34: 0 | AD34: =Z34 -> 113142.48 | AE34: =Z34 -> 113142.48 | AF34: ENGAGE | AN34: Manque n° contrat
A35: =IF(AF35="ENGAGE","✔",IF(AF35="EN COURS D'ENGAGEMENT","◕",IF(AF35="PREENGAGE","◑",IF(AF35="EN COURS DE PREENGAGEMENT","◔",IF(AF35="NON ENGAGE","✖",""))))) -> ✔ | B35: 2026 | C35: ARRIYADIA | D35: PV N° : 01RC2025- DCCCA | E35: CONTRAT | G35: ABDELOUAHED INCHA-ALLAH - Journaliste reporteur d'image | H35: VALIDE | I35: APPROUVE | K35: NON CONCERNE | L35: Ordinaire | M35: FONCTIONNEMENT | N35: Prestations de service Achat prestations de services locales - personnes physiques | R35: RECONDUCTION | U35: ABDELOUAHED INCHA-ALLAH | V35: 2026 | W35: 46022 | Y35: 46024 | Z35: 113142.48 | AA35: 0 | AB35: =Z35 -> 113142.48 | AC35: 0 | AD35: =Z35 -> 113142.48 | AE35: =Z35 -> 113142.48 | AF35: ENGAGE | AN35: Manque n° contrat
... A56: =IF(AF56="ENGAGE","✔",IF(AF56="EN COURS D'ENGAGEMENT","◕",IF(AF56="PREENGAGE","◑",IF(AF56="EN COURS DE PREENGAGEMENT","◔",IF(AF56="NON ENGAGE","✖",""))))) -> ✔ | B56: 2026 | C56: ARRIYADIA | D56: PV N° : 01RC2025- DCCCA | E56: CONTRAT | G56: ABDELOUAHED CHAMMAMI - Consultant football | H56: VALIDE | I56: APPROUVE | K56: NON CONCERNE | L56: Ordinaire | M56: FONCTIONNEMENT | N56: Prestations de service Achat prestations de services locales - personnes physiques | R56: RECONDUCTION | U56: ABDELOUAHED CHAMMAMI | V56: 2026 | W56: 46022 | Y56: 46024 | Z56: 150000 | AA56: 0 | AB56: =Z56 -> 150000 | AC56: 0 | AD56: =Z56 -> 150000 | AE56: =Z56 -> 150000 | AF56: ENGAGE | AN56: Manque n° contrat
A57: =IF(AF57="ENGAGE","✔",IF(AF57="EN COURS D'ENGAGEMENT","◕",IF(AF57="PREENGAGE","◑",IF(AF57="EN COURS DE PREENGAGEMENT","◔",IF(AF57="NON ENGAGE","✖",""))))) -> ◕ | B57: 2026 | C57: ARRIYADIA | D57: PVN°: 02RE2026-DCSA | E57: CONTRAT | G57: MOHAMED SAAD -cadreur plateau/technicien coordinateur d'antenne TV/Digital | H57: EN SIGNATURE | I57: EN SIGNATURE | K57: NON CONCERNE | L57: Ordinaire | M57: FONCTIONNEMENT | N57: Prestations de service Achat prestations de services locales - personnes physiques | R57: RECONDUCTION | U57: MOHAMED SAAD | V57: 2026 | Z57: 28285.62 | AB57: =Z57 -> 28285.62 | AD57: =Z57 -> 28285.62 | AE57: =Z57 -> 28285.62 | AF57: EN COURS D'ENGAGEMENT
A58: =IF(AF58="ENGAGE","✔",IF(AF58="EN COURS D'ENGAGEMENT","◕",IF(AF58="PREENGAGE","◑",IF(AF58="EN COURS DE PREENGAGEMENT","◔",IF(AF58="NON ENGAGE","✖",""))))) -> ◕ | B58: 2026 | C58: ARRIYADIA | D58: PVN°: 02RE2026-DCSA | E58: CONTRAT | G58: ABDELILAH AIT AHMED - Monteur truquiste /technicien coordinateur d'antenne TV | H58: EN SIGNATURE | I58: EN SIGNATURE | K58: NON CONCERNE | L58: Ordinaire | M58: FONCTIONNEMENT | N58: Prestations de service Achat prestations de services locales - personnes physiques | R58: RECONDUCTION | U58: ABDELILAH AIT AHMED | V58: 2026 | Z58: 28285.62 | AB58: =Z58 -> 28285.62 | AD58: =Z58 -> 28285.62 | AE58: =Z58 -> 28285.62 | AF58: EN COURS D'ENGAGEMENT
A59: =IF(AF59="ENGAGE","✔",IF(AF59="EN COURS D'ENGAGEMENT","◕",IF(AF59="PREENGAGE","◑",IF(AF59="EN COURS DE PREENGAGEMENT","◔",IF(AF59="NON ENGAGE","✖",""))))) -> ✔ | B59: 2026 | C59: ARRIYADIA | D59: PV N° : 01RC2025- DCCCA | E59: CONTRAT | G59: KHALID AFIF - Consultant Tennis | H59: VALIDE | I59: APPROUVE | K59: NON CONCERNE | L59: Ordinaire | M59: FONCTIONNEMENT | N59: Prestations de service Achat prestations de services locales - personnes physiques | R59: RECONDUCTION | U59: KHALID AFIF | V59: 2026 | W59: 46022 | Y59: 46024 | Z59: 150500 | AA59: 0 | AB59: =Z59 -> 150500 | AC59: 0 | AD59: =Z59 -> 150500 | AE59: =Z59 -> 150500 | AF59: ENGAGE | AN59: Manque n° contrat
A60: =IF(AF60="ENGAGE","✔",IF(AF60="EN COURS D'ENGAGEMENT","◕",IF(AF60="PREENGAGE","◑",IF(AF60="EN COURS DE PREENGAGEMENT","◔",IF(AF60="NON ENGAGE","✖",""))))) -> ✔ | B60: 2026 | C60: ARRIYADIA | D60: PV N° : 01RC2025- DCCCA | E60: CONTRAT | G60: MOHSIN CHERGUI - Consultant omnisport | H60: VALIDE | I60: APPROUVE | K60: NON CONCERNE | L60: Ordinaire | M60: FONCTIONNEMENT | N60: Prestations de service Achat prestations de services locales - personnes physiques | R60: RECONDUCTION | U60: MOHSIN CHERGUI | V60: 2026 | W60: 46022 | Y60: 46024 | Z60: 150000 | AA60: 0 | AB60: =Z60 -> 150000 | AC60: 0 | AD60: =Z60 -> 150000 | AE60: =Z60 -> 150000 | AF60: ENGAGE | AN60: Manque n° contrat
A61: =IF(AF61="ENGAGE","✔",IF(AF61="EN COURS D'ENGAGEMENT","◕",IF(AF61="PREENGAGE","◑",IF(AF61="EN COURS DE PREENGAGEMENT","◔",IF(AF61="NON ENGAGE","✖",""))))) -> ✔ | B61: 2026 | C61: ASSADISSA | D61: PV N° : 01RC2025- DPPCCRTV | E61: CONTRAT | G61: ZERHOUNI RABIA - Réalisatrice : Montage, mixage, animation des émissions RD et programmation RD | H61: VALIDE | I61: APPROUVE | K61: NON CONCERNE | L61: Ordinaire | M61: FONCTIONNEMENT | N61: Prestations de service Achat prestations de services locales - personnes physiques | R61: RECONDUCTION | U61: ZERHOUNI RABIA | V61: 2026 | W61: 46387 | Y61: 46024 | Z61: 108000 | AA61: 0 | AB61: =Z61 -> 108000 | AC61: 0 | AD61: =Z61 -> 108000 | AE61: =Z61 -> 108000 | AF61: ENGAGE | AN61: Manque n° contrat
A62: =IF(AF62="ENGAGE","✔",IF(AF62="EN COURS D'ENGAGEMENT","◕",IF(AF62="PREENGAGE","◑",IF(AF62="EN COURS DE PREENGAGEMENT","◔",IF(AF62="NON ENGAGE","✖",""))))) -> ✔ | B62: 2026 | C62: ASSADISSA | D62: PV N° : 01RC2025- DPPCCRTV | E62: CONTRAT | G62: BENIKES KARIMA - Réalisatrice : Montage, mixage et programmation RD | H62: VALIDE | I62: APPROUVE | K62: NON CONCERNE | L62: Ordinaire | M62: FONCTIONNEMENT | N62: Prestations de service Achat prestations de services locales - personnes physiques | R62: RECONDUCTION | U62: BENIKES KARIMA | V62: 2026 | W62: 46387 | Y62: 46024 | Z62: 72000 | AA62: 0 | AB62: =Z62 -> 72000 | AC62: 0 | AD62: =Z62 -> 72000 | AE62: =Z62 -> 72000 | AF62: ENGAGE | AN62: Manque n° contrat
A63: =IF(AF63="ENGAGE","✔",IF(AF63="EN COURS D'ENGAGEMENT","◕",IF(AF63="PREENGAGE","◑",IF(AF63="EN COURS DE PREENGAGEMENT","◔",IF(AF63="NON ENGAGE","✖",""))))) -> ✔ | B63: 2026 | C63: ASSADISSA | D63: PV N° : 01RC2025- DPPCCRTV | E63: CONTRAT | G63: LAHKIM OUMAIMA - Programmatrice : Programmation TV (Conducteur quotidien) | H63: VALIDE | I63: APPROUVE | K63: NON CONCERNE | L63: Ordinaire | M63: FONCTIONNEMENT | N63: Prestations de service Achat prestations de services locales - personnes physiques | R63: RECONDUCTION | U63: LAHKIM OUMAIMA | V63: 2026 | W63: 46387 | Y63: 46024 | Z63: 84000 | AA63: 0 | AB63: =Z63 -> 84000 | AC63: 0 | AD63: =Z63 -> 84000 | AE63: =Z63 -> 84000 | AF63: ENGAGE | AN63: Manque n° contrat
A64: =IF(AF64="ENGAGE","✔",IF(AF64="EN COURS D'ENGAGEMENT","◕",IF(AF64="PREENGAGE","◑",IF(AF64="EN COURS DE PREENGAGEMENT","◔",IF(AF64="NON ENGAGE","✖",""))))) -> ✔ | B64: 2026 | C64: ASSADISSA | D64: PV N° : 01RC2025- DPPCCRTV | E64: CONTRAT | G64: DEHROUR OUSSAMA - Infographiste : le montage, l'infographie et la coordination du portail de la Chaîne, | H64: VALIDE | I64: APPROUVE | K64: NON CONCERNE | L64: Ordinaire | M64: FONCTIONNEMENT | N64: Prestations de service Achat prestations de services locales - personnes physiques | R64: RECONDUCTION | U64: DEHROUR OUSSAMA | V64: 2026 | W64: 46387 | Y64: 46024 | Z64: 84000 | AA64: 0 | AB64: =Z64 -> 84000 | AC64: 0 | AD64: =Z64 -> 84000 | AE64: =Z64 -> 84000 | AF64: ENGAGE | AN64: Manque n° contrat
A65: =IF(AF65="ENGAGE","✔",IF(AF65="EN COURS D'ENGAGEMENT","◕",IF(AF65="PREENGAGE","◑",IF(AF65="EN COURS DE PREENGAGEMENT","◔",IF(AF65="NON ENGAGE","✖",""))))) -> ✔ | B65: 2026 | C65: ASSADISSA | D65: PV N° : 01RC2025- DPPCCRTV | E65: CONTRAT | G65: NASREDDINE MOUHCINE - Prise de vue et Prise de son TV (OPV/OPS) | H65: VALIDE | I65: APPROUVE | K65: NON CONCERNE | L65: Ordinaire | M65: FONCTIONNEMENT | N65: Prestations de service Achat prestations de services locales - personnes physiques | R65: RECONDUCTION | U65: NASREDDINE MOUHCINE | V65: 2026 | W65: 46387 | Y65: 46024 | Z65: 84000 | AA65: 0 | AB65: =Z65 -> 84000 | AC65: 0 | AD65: =Z65 -> 84000 | AE65: =Z65 -> 84000 | AF65: ENGAGE | AN65: Manque n° contrat
A66: =IF(AF66="ENGAGE","✔",IF(AF66="EN COURS D'ENGAGEMENT","◕",IF(AF66="PREENGAGE","◑",IF(AF66="EN COURS DE PREENGAGEMENT","◔",IF(AF66="NON ENGAGE","✖",""))))) -> ✔ | B66: 2026 | C66: ASSADISSA | D66: PV N° : 01RC2025- DPPCCRTV | E66: CONTRAT | G66: HAJJOUJI YOUSSEF - Prise de vue (OPV) et le montage TV | H66: VALIDE | I66: APPROUVE | K66: NON CONCERNE | L66: Ordinaire | M66: FONCTIONNEMENT | N66: Prestations de service Achat prestations de services locales - personnes physiques | R66: RECONDUCTION | U66: HAJJOUJI YOUSSEF | V66: 2026 | W66: 46387 | Y66: 46024 | Z66: 84000 | AA66: 0 | AB66: =Z66 -> 84000 | AC66: 0 | AD66: =Z66 -> 84000 | AE66: =Z66 -> 84000 | AF66: ENGAGE | AN66: Manque n° contrat
A67: =IF(AF67="ENGAGE","✔",IF(AF67="EN COURS D'ENGAGEMENT","◕",IF(AF67="PREENGAGE","◑",IF(AF67="EN COURS DE PREENGAGEMENT","◔",IF(AF67="NON ENGAGE","✖",""))))) -> ✔ | B67: 2026 | C67: ASSADISSA | D67: PV N° : 01RC2025- DPPCCRTV | E67: CONTRAT | G67: DRISSI WALID - Prise de vue et Prise de son TV (OPV/OPS) | H67: VALIDE | I67: APPROUVE | K67: NON CONCERNE | L67: Ordinaire | M67: FONCTIONNEMENT | N67: Prestations de service Achat prestations de services locales - personnes physiques | R67: RECONDUCTION | U67: DRISSI WALID | V67: 2026 | W67: 46387 | Y67: 46024 | Z67: 84000 | AA67: 0 | AB67: =Z67 -> 84000 | AC67: 0 | AD67: =Z67 -> 84000 | AE67: =Z67 -> 84000 | AF67: ENGAGE | AN67: Manque n° contrat
A68: =IF(AF68="ENGAGE","✔",IF(AF68="EN COURS D'ENGAGEMENT","◕",IF(AF68="PREENGAGE","◑",IF(AF68="EN COURS DE PREENGAGEMENT","◔",IF(AF68="NON ENGAGE","✖",""))))) -> ✔ | B68: 2026 | C68: ASSADISSA | D68: PV N° : 01RC2025- DPPCCRTV | E68: CONTRAT | G68: EZ-ZHR MOHAMED - Prise de vue et Prise de son TV (OPV/OPS) | H68: VALIDE | I68: APPROUVE | K68: NON CONCERNE | L68: Ordinaire | M68: FONCTIONNEMENT | N68: Prestations de service Achat prestations de services locales - personnes physiques | R68: RECONDUCTION | U68: EZ-ZHR MOHAMED | V68: 2026 | W68: 46387 | Y68: 46024 | Z68: 84000 | AA68: 0 | AB68: =Z68 -> 84000 | AC68: 0 | AD68: =Z68 -> 84000 | AE68: =Z68 -> 84000 | AF68: ENGAGE | AN68: Manque n° contrat
A69: =IF(AF69="ENGAGE","✔",IF(AF69="EN COURS D'ENGAGEMENT","◕",IF(AF69="PREENGAGE","◑",IF(AF69="EN COURS DE PREENGAGEMENT","◔",IF(AF69="NON ENGAGE","✖",""))))) -> ✔ | B69: 2026 | C69: ASSADISSA | D69: PV N° : 01RC2025- DPPCCRTV | E69: CONTRAT | G69: ABIDA ILIAS - Prise de vue TV et Prise de son TV (OPV/OPS) | H69: VALIDE | I69: APPROUVE | K69: NON CONCERNE | L69: Ordinaire | M69: FONCTIONNEMENT | N69: Prestations de service Achat prestations de services locales - personnes physiques | R69: RECONDUCTION | U69: ABIDA ILIAS | V69: 2026 | W69: 46387 | Y69: 46024 | Z69: 84000 | AA69: 0 | AB69: =Z69 -> 84000 | AC69: 0 | AD69: =Z69 -> 84000 | AE69: =Z69 -> 84000 | AF69: ENGAGE | AN69: Manque n° contrat
A70: =IF(AF70="ENGAGE","✔",IF(AF70="EN COURS D'ENGAGEMENT","◕",IF(AF70="PREENGAGE","◑",IF(AF70="EN COURS DE PREENGAGEMENT","◔",IF(AF70="NON ENGAGE","✖",""))))) -> ✔ | B70: 2026 | C70: ASSADISSA | D70: PV N° : 01RC2025- DPPCCRTV | E70: CONTRAT | G70: ELMHAMDI BADR - Prise de vue et Prise de son TV (OPV/OPS) | H70: VALIDE | I70: APPROUVE | K70: NON CONCERNE | L70: Ordinaire | M70: FONCTIONNEMENT | N70: Prestations de service Achat prestations de services locales - personnes physiques | R70: RECONDUCTION | U70: ELMHAMDI BADR | V70: 2026 | W70: 46387 | Y70: 46024 | Z70: 84000 | AA70: 0 | AB70: =Z70 -> 84000 | AC70: 0 | AD70: =Z70 -> 84000 | AE70: =Z70 -> 84000 | AF70: ENGAGE | AN70: Manque n° contrat
... A81: =IF(AF81="ENGAGE","✔",IF(AF81="EN COURS D'ENGAGEMENT","◕",IF(AF81="PREENGAGE","◑",IF(AF81="EN COURS DE PREENGAGEMENT","◔",IF(AF81="NON ENGAGE","✖",""))))) -> ✔ | B81: 2026 | C81: DPMG | D81: PV N° : 01RC2025- DPMG | E81: CONTRAT | G81: MOHAMED CHERTI - Métreur en BTP | H81: VALIDE | I81: APPROUVE | K81: NON CONCERNE | L81: Ordinaire | M81: FONCTIONNEMENT | N81: Prestations de service Achat prestations de services locales - personnes physiques | R81: RECONDUCTION | U81: MOHAMED CHERTI | V81: 2026 | W81: 46387 | Y81: 46024 | Z81: 28000 | AA81: 0 | AB81: =Z81 -> 28000 | AC81: 0 | AD81: =Z81 -> 28000 | AE81: =Z81 -> 28000 | AF81: ENGAGE | AN81: Manque n° contrat
A82: =IF(AF82="ENGAGE","✔",IF(AF82="EN COURS D'ENGAGEMENT","◕",IF(AF82="PREENGAGE","◑",IF(AF82="EN COURS DE PREENGAGEMENT","◔",IF(AF82="NON ENGAGE","✖",""))))) -> ✔ | B82: 2026 | C82: DINFORADIO | D82: RECONDUCTIBLE | E82: CONTRAT | G82: Abonnement MAP | H82: VALIDE | I82: APPROUVE | K82: NON CONCERNE | L82: Ordinaire | M82: FONCTIONNEMENT | N82: Redevances et cotisations Abonnements | R82: RECONDUCTIBLE | U82: MAP | V82: - | W82: - | Y82: - | Z82: 1837404 | AA82: 0 | AB82: 1837404 | AC82: 0 | AD82: 1837404 | AE82: 1837404 | AF82: ENGAGE
A83: =IF(AF83="ENGAGE","✔",IF(AF83="EN COURS D'ENGAGEMENT","◕",IF(AF83="PREENGAGE","◑",IF(AF83="EN COURS DE PREENGAGEMENT","◔",IF(AF83="NON ENGAGE","✖",""))))) -> ✔ | B83: 2026 | C83: DINFORADIO | D83: PV N° : 01RC2025- DIR | E83: CONTRAT | G83: YOUSSEF LAHLALI - Journaliste correspondant chargé de la préparation des magazines d'information et reportages RD et la couverture des événements internationaux | H83: VALIDE | I83: APPROUVE | K83: NON CONCERNE | L83: Ordinaire | M83: FONCTIONNEMENT | N83: Prestations de service Achat prestations de services locales - personnes physiques | R83: RECONDUCTION | U83: YOUSSEF LAHLALI | V83: 2026 | W83: 46387 | Y83: 46024 | Z83: 171428.52 | AA83: 0 | AB83: =Z83 -> 171428.52 | AC83: 0 | AD83: =Z83 -> 171428.52 | AE83: =Z83 -> 171428.52 | AF83: ENGAGE | AN83: Manque n° contrat
A84: =IF(AF84="ENGAGE","✔",IF(AF84="EN COURS D'ENGAGEMENT","◕",IF(AF84="PREENGAGE","◑",IF(AF84="EN COURS DE PREENGAGEMENT","◔",IF(AF84="NON ENGAGE","✖",""))))) -> ✔ | B84: 2026 | C84: DINFORADIO | D84: PV N° : 01RC2025- DIR | E84: CONTRAT | G84: SAFI RIM - Journaliste, présentateur radio francophone/ anglophone | H84: VALIDE | I84: APPROUVE | K84: NON CONCERNE | L84: Ordinaire | M84: FONCTIONNEMENT | N84: Prestations de service Achat prestations de services locales - personnes physiques | R84: RECONDUCTION | U84: SAFI RIM | V84: 2026 | W84: 46387 | Y84: 46024 | Z84: 132000 | AA84: 0 | AB84: =Z84 -> 132000 | AC84: 0 | AD84: =Z84 -> 132000 | AE84: =Z84 -> 132000 | AF84: ENGAGE | AN84: Manque n° contrat
A85: =IF(AF85="ENGAGE","✔",IF(AF85="EN COURS D'ENGAGEMENT","◕",IF(AF85="PREENGAGE","◑",IF(AF85="EN COURS DE PREENGAGEMENT","◔",IF(AF85="NON ENGAGE","✖",""))))) -> ✔ | B85: 2026 | C85: DINFORADIO | D85: PV N° : 01RC2025- DIR | E85: CONTRAT | G85: BENCAID KENZA - Journaliste et présentateur radio francophone | H85: VALIDE | I85: APPROUVE | K85: NON CONCERNE | L85: Ordinaire | M85: FONCTIONNEMENT | N85: Prestations de service Achat prestations de services locales - personnes physiques | R85: RECONDUCTION | U85: BENCAID KENZA | V85: 2026 | W85: 46387 | Y85: 46024 | Z85: 156000 | AA85: 0 | AB85: =Z85 -> 156000 | AC85: 0 | AD85: =Z85 -> 156000 | AE85: =Z85 -> 156000 | AF85: ENGAGE | AN85: Manque n° contrat
A86: =IF(AF86="ENGAGE","✔",IF(AF86="EN COURS D'ENGAGEMENT","◕",IF(AF86="PREENGAGE","◑",IF(AF86="EN COURS DE PREENGAGEMENT","◔",IF(AF86="NON ENGAGE","✖",""))))) -> ✔ | B86: 2026 | C86: DINFORADIO | D86: PV N° : 01RC2025- DIR | E86: CONTRAT | G86: AHMED CHAINA - Journaliste, Présentateur radio amazigh/animateur de débats (expression tachelhit) | H86: VALIDE | I86: APPROUVE | K86: NON CONCERNE | L86: Ordinaire | M86: FONCTIONNEMENT | N86: Prestations de service Achat prestations de services locales - personnes physiques | R86: RECONDUCTION | U86: AHMED CHAINA | V86: 2026 | W86: 46387 | Y86: 46024 | Z86: 132000 | AA86: 0 | AB86: 132000 | AC86: 0 | AD86: =Z86 -> 132000 | AE86: =Z86 -> 132000 | AF86: ENGAGE | AN86: Manque n° contrat
A87: =IF(AF87="ENGAGE","✔",IF(AF87="EN COURS D'ENGAGEMENT","◕",IF(AF87="PREENGAGE","◑",IF(AF87="EN COURS DE PREENGAGEMENT","◔",IF(AF87="NON ENGAGE","✖",""))))) -> ✔ | B87: 2026 | C87: DINFORADIO | D87: PV N° : 01RC2025- DIR | E87: CONTRAT | G87: BADDOU KHALID - Journaliste, Présentateur radio amazigh/animateur de débats (expression tachelhit) | H87: VALIDE | I87: APPROUVE | K87: NON CONCERNE | L87: Ordinaire | M87: FONCTIONNEMENT | N87: Prestations de service Achat prestations de services locales - personnes physiques | R87: RECONDUCTION | U87: BADDOU KHALID | V87: 2026 | W87: 46387 | Y87: 46024 | Z87: 132000 | AA87: 0 | AB87: 132000 | AC87: 0 | AD87: =Z87 -> 132000 | AE87: =Z87 -> 132000 | AF87: ENGAGE | AN87: Manque n° contrat
A88: =IF(AF88="ENGAGE","✔",IF(AF88="EN COURS D'ENGAGEMENT","◕",IF(AF88="PREENGAGE","◑",IF(AF88="EN COURS DE PREENGAGEMENT","◔",IF(AF88="NON ENGAGE","✖",""))))) -> ✔ | B88: 2026 | C88: DINFOTV | D88: PV N° : 01RC2025- DITV | E88: CONTRAT | G88: EZZAHER ANASS - Scripte des journaux télévisés et toutes les émissions produites par la direction de l'information TV | H88: VALIDE | I88: APPROUVE | K88: NON CONCERNE | L88: Ordinaire | M88: FONCTIONNEMENT | N88: Prestations de service Achat prestations de services locales - personnes physiques | R88: RECONDUCTION | U88: EZZAHER ANASS | V88: 2026 | W88: 46387 | Y88: 46024 | Z88: 96000 | AA88: 0 | AB88: =Z88 -> 96000 | AC88: 0 | AD88: =Z88 -> 96000 | AE88: =Z88 -> 96000 | AF88: ENGAGE | AN88: Manque n° contrat
A89: =IF(AF89="ENGAGE","✔",IF(AF89="EN COURS D'ENGAGEMENT","◕",IF(AF89="PREENGAGE","◑",IF(AF89="EN COURS DE PREENGAGEMENT","◔",IF(AF89="NON ENGAGE","✖",""))))) -> ✔ | B89: 2026 | C89: DINFOTV | D89: PV N° : 01RC2025- DITV | E89: CONTRAT | G89: AOUAD MARIA - Journaliste chargée de la préparation et la réalisation des reportages news en français au journal télévisé de la chaine AL Aoula | H89: VALIDE | I89: APPROUVE | K89: NON CONCERNE | L89: Ordinaire | M89: FONCTIONNEMENT | N89: Prestations de service Achat prestations de services locales - personnes physiques | R89: RECONDUCTION | U89: AOUAD MARIA | V89: 2026 | W89: 46387 | Y89: 46024 | Z89: 144000 | AA89: 0 | AB89: =Z89 -> 144000 | AC89: 0 | AD89: =Z89 -> 144000 | AE89: =Z89 -> 144000 | AF89: ENGAGE | AN89: Manque n° contrat
A90: =IF(AF90="ENGAGE","✔",IF(AF90="EN COURS D'ENGAGEMENT","◕",IF(AF90="PREENGAGE","◑",IF(AF90="EN COURS DE PREENGAGEMENT","◔",IF(AF90="NON ENGAGE","✖",""))))) -> ✔ | B90: 2026 | C90: DINFOTV | D90: PV N° : 01RC2025- DITV | E90: CONTRAT | G90: KETTANI MOHAMMED - Interprète en langue des signes | H90: VALIDE | I90: APPROUVE | K90: NON CONCERNE | L90: Ordinaire | M90: FONCTIONNEMENT | N90: Prestations de service Achat prestations de services locales - personnes physiques | R90: RECONDUCTION | U90: KETTANI MOHAMMED | V90: 2026 | W90: 46387 | Y90: 46024 | Z90: 154285.68 | AA90: 0 | AB90: =Z90 -> 154285.68 | AC90: 0 | AD90: =Z90 -> 154285.68 | AE90: =Z90 -> 154285.68 | AF90: ENGAGE | AN90: Manque n° contrat
A91: =IF(AF91="ENGAGE","✔",IF(AF91="EN COURS D'ENGAGEMENT","◕",IF(AF91="PREENGAGE","◑",IF(AF91="EN COURS DE PREENGAGEMENT","◔",IF(AF91="NON ENGAGE","✖",""))))) -> ✔ | B91: 2026 | C91: DINFOTV | D91: PV N° : 01RC2025- DITV | E91: CONTRAT | G91: NOUINI NOURREDDINE - Coiffeur et maquilleur des animateurs et des invités participants au journal télévisé de la chaine Al Aoula | H91: VALIDE | I91: APPROUVE | K91: NON CONCERNE | L91: Ordinaire | M91: FONCTIONNEMENT | N91: Prestations de service Achat prestations de services locales - personnes physiques | R91: RECONDUCTION | U91: NOUINI NOURREDDINE | V91: 2026 | W91: 46387 | Y91: 46024 | Z91: 72000 | AA91: 0 | AB91: =Z91 -> 72000 | AC91: 0 | AD91: =Z91 -> 72000 | AE91: =Z91 -> 72000 | AF91: ENGAGE | AN91: Manque n° contrat
A92: =IF(AF92="ENGAGE","✔",IF(AF92="EN COURS D'ENGAGEMENT","◕",IF(AF92="PREENGAGE","◑",IF(AF92="EN COURS DE PREENGAGEMENT","◔",IF(AF92="NON ENGAGE","✖",""))))) -> ✔ | B92: 2026 | C92: DINFOTV | D92: PV N° : 01RC2025- DITV | E92: CONTRAT | G92: WIAM MOUDDOUN - Journaliste chargée de la préparation des magazines d'information, reportages, rédaction des JT et couverture du factuel | H92: VALIDE | I92: APPROUVE | K92: NON CONCERNE | L92: Ordinaire | M92: FONCTIONNEMENT | N92: Prestations de service Achat prestations de services locales - personnes physiques | R92: RECONDUCTION | U92: WIAM MOUDDOUN | V92: 2026 | W92: 46387 | Y92: 46024 | Z92: 120000 | AA92: 0 | AB92: =Z92 -> 120000 | AC92: 0 | AD92: =Z92 -> 120000 | AE92: =Z92 -> 120000 | AF92: ENGAGE | AN92: Manque n° contrat
A93: =IF(AF93="ENGAGE","✔",IF(AF93="EN COURS D'ENGAGEMENT","◕",IF(AF93="PREENGAGE","◑",IF(AF93="EN COURS DE PREENGAGEMENT","◔",IF(AF93="NON ENGAGE","✖",""))))) -> ✔ | B93: 2026 | C93: DINFOTV | D93: PV N° : 01RC2025- DITV | E93: CONTRAT | G93: HOUDA NEJJAR - Scripte des journaux télévisés et toutes les émissions produites par la direction de l'Information TV | H93: VALIDE | I93: APPROUVE | K93: NON CONCERNE | L93: Ordinaire | M93: FONCTIONNEMENT | N93: Prestations de service Achat prestations de services locales - personnes physiques | R93: RECONDUCTION | U93: HOUDA NEJJAR | V93: 2026 | W93: 46387 | Y93: 46024 | Z93: 24000 | AA93: 0 | AB93: 24000 | AC93: 0 | AD93: 24000 | AE93: 24000 | AF93: ENGAGE | AN93: Manque n° contrat
A94: =IF(AF94="ENGAGE","✔",IF(AF94="EN COURS D'ENGAGEMENT","◕",IF(AF94="PREENGAGE","◑",IF(AF94="EN COURS DE PREENGAGEMENT","◔",IF(AF94="NON ENGAGE","✖",""))))) -> ✔ | B94: 2026 | C94: DINFOTV | D94: PV N° : 01RC2025- DITV | E94: CONTRAT | G94: TAHRAOUI ABDELHGANI - Preneur de vue chargé de la réalisation de reportages et couvertures TV dans la province d'Essaouira et régions | H94: VALIDE | I94: APPROUVE | K94: NON CONCERNE | L94: Ordinaire | M94: FONCTIONNEMENT | N94: Prestations de service Achat prestations de services locales - personnes physiques | R94: RECONDUCTION | U94: TAHRAOUI ABDELHGANI | V94: 2026 | W94: 46387 | Y94: 46024 | Z94: 44571.36 | AA94: 0 | AB94: =Z94 -> 44571.36 | AC94: 0 | AD94: =Z94 -> 44571.36 | AE94: =Z94 -> 44571.36 | AF94: ENGAGE | AN94: Manque n° contrat
A95: =IF(AF95="ENGAGE","✔",IF(AF95="EN COURS D'ENGAGEMENT","◕",IF(AF95="PREENGAGE","◑",IF(AF95="EN COURS DE PREENGAGEMENT","◔",IF(AF95="NON ENGAGE","✖",""))))) -> ✔ | B95: 2026 | C95: DINFOTV | D95: PV N° : 01RC2025- DITV | E95: CONTRAT | G95: FADILI AHMED - Preneur de vue chargé de la réalisation de reportages et couvertures TV dans la province d’Ifran Azrou | H95: VALIDE | I95: APPROUVE | K95: NON CONCERNE | L95: Ordinaire | M95: FONCTIONNEMENT | N95: Prestations de service Achat prestations de services locales - personnes physiques | R95: RECONDUCTION | U95: FADILI AHMED | V95: 2026 | W95: 46387 | Y95: 46024 | Z95: 72000 | AA95: 0 | AB95: =Z95 -> 72000 | AC95: 0 | AD95: =Z95 -> 72000 | AE95: =Z95 -> 72000 | AF95: ENGAGE | AN95: Manque n° contrat
A96: =IF(AF96="ENGAGE","✔",IF(AF96="EN COURS D'ENGAGEMENT","◕",IF(AF96="PREENGAGE","◑",IF(AF96="EN COURS DE PREENGAGEMENT","◔",IF(AF96="NON ENGAGE","✖",""))))) -> ✔ | B96: 2026 | C96: DINFOTV | D96: PV N° : 01RC2025- DITV | E96: CONTRAT | G96: KHALID AIT HSSAIN - Coiffeur et maquilleur des animateurs et des invités participants au journal télévisé de la chaine ALOULA. | H96: VALIDE | I96: APPROUVE | K96: NON CONCERNE | L96: Ordinaire | M96: FONCTIONNEMENT | N96: Prestations de service Achat prestations de services locales - personnes physiques | R96: RECONDUCTION | U96: KHALID AIT HSSAIN | V96: 2026 | W96: 46387 | Y96: 46024 | Z96: 72000 | AA96: 0 | AB96: =Z96 -> 72000 | AC96: 0 | AD96: =Z96 -> 72000 | AE96: =Z96 -> 72000 | AF96: ENGAGE | AN96: Manque n° contrat
A97: =IF(AF97="ENGAGE","✔",IF(AF97="EN COURS D'ENGAGEMENT","◕",IF(AF97="PREENGAGE","◑",IF(AF97="EN COURS DE PREENGAGEMENT","◔",IF(AF97="NON ENGAGE","✖",""))))) -> ✔ | B97: 2026 | C97: DINFOTV | D97: PV N° : 01RC2025- DITV | E97: CONTRAT | G97: SOUKAINA HACHIMI - Journaliste chargée de la préparation des magazines d'information, reportages, rédaction des JT et couverture du factuel | H97: VALIDE | I97: APPROUVE | K97: NON CONCERNE | L97: Ordinaire | M97: FONCTIONNEMENT | N97: Prestations de service Achat prestations de services locales - personnes physiques | R97: RECONDUCTION | U97: SOUKAINA HACHIMI | V97: 2026 | W97: 46387 | Y97: 46024 | Z97: 120000 | AA97: 0 | AB97: =Z97 -> 120000 | AC97: 0 | AD97: =Z97 -> 120000 | AE97: =Z97 -> 120000 | AF97: ENGAGE | AN97: Manque n° contrat
A98: =IF(AF98="ENGAGE","✔",IF(AF98="EN COURS D'ENGAGEMENT","◕",IF(AF98="PREENGAGE","◑",IF(AF98="EN COURS DE PREENGAGEMENT","◔",IF(AF98="NON ENGAGE","✖",""))))) -> ✔ | B98: 2026 | C98: DINFOTV | D98: PV N° : 01RC2025- DITV | E98: CONTRAT | G98: MAHDI KARRAKCHOU - Le montage des journaux télévisés et toutes les émissions produites par la direction de l'Information TV | H98: VALIDE | I98: APPROUVE | K98: NON CONCERNE | L98: Ordinaire | M98: FONCTIONNEMENT | N98: Prestations de service Achat prestations de services locales - personnes physiques | R98: RECONDUCTION | U98: MAHDI KARRAKCHOU | V98: 2026 | W98: 46387 | Y98: 46024 | Z98: 108000 | AA98: 0 | AB98: =Z98 -> 108000 | AC98: 0 | AD98: =Z98 -> 108000 | AE98: =Z98 -> 108000 | AF98: ENGAGE | AN98: Manque n° contrat
A99: =IF(AF99="ENGAGE","✔",IF(AF99="EN COURS D'ENGAGEMENT","◕",IF(AF99="PREENGAGE","◑",IF(AF99="EN COURS DE PREENGAGEMENT","◔",IF(AF99="NON ENGAGE","✖",""))))) -> ✔ | B99: 2026 | C99: DINFOTV | D99: PV N° : 01RC2025- DITV | E99: CONTRAT | G99: MOUNIR LAHSAIEN - Coiffeur et maquilleur des animateurs et des invités participants au journal télévisé de la chaine Al Aoula | H99: VALIDE | I99: APPROUVE | K99: NON CONCERNE | L99: Ordinaire | M99: FONCTIONNEMENT | N99: Prestations de service Achat prestations de services locales - personnes physiques | R99: RECONDUCTION | U99: MOUNIR LAHSAIEN | V99: 2026 | W99: 46387 | Y99: 46024 | Z99: 72000 | AA99: 0 | AB99: =Z99 -> 72000 | AC99: 0 | AD99: =Z99 -> 72000 | AE99: =Z99 -> 72000 | AF99: ENGAGE | AN99: Manque n° contrat
A100: =IF(AF100="ENGAGE","✔",IF(AF100="EN COURS D'ENGAGEMENT","◕",IF(AF100="PREENGAGE","◑",IF(AF100="EN COURS DE PREENGAGEMENT","◔",IF(AF100="NON ENGAGE","✖",""))))) -> ✔ | B100: 2026 | C100: DINFOTV | D100: PV N° : 01RC2025- DITV | E100: CONTRAT | G100: EL AAZIZ ABDERRAZZAQ - Chef d'édition des journaux télévisés | H100: VALIDE | I100: APPROUVE | K100: NON CONCERNE | L100: Ordinaire | M100: FONCTIONNEMENT | N100: Prestations de service Achat prestations de services locales - personnes physiques | R100: RECONDUCTION | U100: EL AAZIZ ABDERRAZZAQ | V100: 2026 | W100: 46387 | Y100: 46024 | Z100: 240000 | AA100: 0 | AB100: =Z100 -> 240000 | AC100: 0 | AD100: =Z100 -> 240000 | AE100: =Z100 -> 240000 | AF100: ENGAGE | AN100: Manque n° contrat
A101: =IF(AF101="ENGAGE","✔",IF(AF101="EN COURS D'ENGAGEMENT","◕",IF(AF101="PREENGAGE","◑",IF(AF101="EN COURS DE PREENGAGEMENT","◔",IF(AF101="NON ENGAGE","✖",""))))) -> ✔ | B101: 2026 | C101: DINFOTV | D101: PV N° : 01RC2025- DITV | E101: CONTRAT | G101: BOUJOUBBOU ABDELHAKIM - Chef d'édition des journaux télévisés | H101: VALIDE | I101: APPROUVE | K101: NON CONCERNE | L101: Ordinaire | M101: FONCTIONNEMENT | N101: Prestations de service Achat prestations de services locales - personnes physiques | R101: RECONDUCTION | U101: BOUJOUBBOU ABDELHAKIM | V101: 2026 | W101: 46387 | Y101: 46024 | Z101: 240000 | AA101: 0 | AB101: =Z101 -> 240000 | AC101: 0 | AD101: =Z101 -> 240000 | AE101: =Z101 -> 240000 | AF101: ENGAGE | AN101: Manque n° contrat
A102: =IF(AF102="ENGAGE","✔",IF(AF102="EN COURS D'ENGAGEMENT","◕",IF(AF102="PREENGAGE","◑",IF(AF102="EN COURS DE PREENGAGEMENT","◔",IF(AF102="NON ENGAGE","✖",""))))) -> ✔ | B102: 2026 | C102: DINFOTV | D102: PV N° : 01RC2025- DITV | E102: CONTRAT | G102: MOULINE LILIA - Styliste, Maquilleuse et Habilleuse des journalistes et présentateurs chargés de la présentation des émissions | H102: VALIDE | I102: APPROUVE | K102: NON CONCERNE | L102: Ordinaire | M102: FONCTIONNEMENT | N102: Prestations de service Achat prestations de services locales - personnes physiques | R102: RECONDUCTION | U102: MOULINE LILIA | V102: 2026 | W102: 46387 | Y102: 46024 | Z102: 705374.28 | AA102: 0 | AB102: 846449.14 | AC102: 0 | AD102: =Z102 -> 705374.28 | AE102: =AB102 -> 846449.14 | AF102: ENGAGE | AN102: Manque n° contrat
A103: =IF(AF103="ENGAGE","✔",IF(AF103="EN COURS D'ENGAGEMENT","◕",IF(AF103="PREENGAGE","◑",IF(AF103="EN COURS DE PREENGAGEMENT","◔",IF(AF103="NON ENGAGE","✖",""))))) -> ✔ | B103: 2026 | C103: DINFOTV | D103: PV N° : 01RC2025- DITV | E103: CONTRAT | G103: BOUBKER BEN GHABRIT - Journaliste francophone chargé de la préparation et la réalisation des reportages news en français ainsi que la présentation JT Français. | H103: VALIDE | I103: APPROUVE | K103: NON CONCERNE | L103: Ordinaire | M103: FONCTIONNEMENT | N103: Prestations de service Achat prestations de services locales - personnes physiques | R103: RECONDUCTION | U103: BOUBKER BEN GHABRIT | V103: 2026 | W103: 46387 | Y103: 46024 | Z103: 214800 | AA103: 0 | AB103: =Z103 -> 214800 | AC103: 0 | AD103: =Z103 -> 214800 | AE103: =AB103 -> 214800 | AF103: ENGAGE | AN103: Manque n° contrat
A104: =IF(AF104="ENGAGE","✔",IF(AF104="EN COURS D'ENGAGEMENT","◕",IF(AF104="PREENGAGE","◑",IF(AF104="EN COURS DE PREENGAGEMENT","◔",IF(AF104="NON ENGAGE","✖",""))))) -> ✔ | B104: 2026 | C104: DINFOTV | D104: PV N° : 01RC2025- DITV | E104: CONTRAT | G104: MOHAMED EL HAJJAM - Correspondant chargé de la réalisation de reportages et correspondances en matière d'Information Télévisée à partir des Etats Unies d’Amérique. | H104: VALIDE | I104: APPROUVE | K104: NON CONCERNE | L104: Ordinaire | M104: FONCTIONNEMENT | N104: Prestations de service Achat prestations de services locales - personnes physiques | R104: RECONDUCTION | U104: MOHAMED EL HAJJAM | V104: 2026 | W104: 46387 | Y104: 46024 | Z104: 145714.32 | AA104: 0 | AB104: =Z104 -> 145714.32 | AC104: 0 | AD104: =Z104 -> 145714.32 | AE104: =AB104 -> 145714.32 | AF104: ENGAGE | AN104: Manque n° contrat
A105: =IF(AF105="ENGAGE","✔",IF(AF105="EN COURS D'ENGAGEMENT","◕",IF(AF105="PREENGAGE","◑",IF(AF105="EN COURS DE PREENGAGEMENT","◔",IF(AF105="NON ENGAGE","✖",""))))) -> ✔ | B105: 2026 | C105: DINFOTV | D105: PV N° : 01RC2025- DITV | E105: CONTRAT | G105: MUSTAPHA SEHIMI - Consultant politique chargé de l'analyse politique et le décryptage hebdomadaire des JT en langue Française | H105: VALIDE | I105: APPROUVE | K105: NON CONCERNE | L105: Ordinaire | M105: FONCTIONNEMENT | N105: Prestations de service Achat prestations de services locales - personnes physiques | R105: RECONDUCTION | U105: MUSTAPHA SEHIMI | V105: 2026 | W105: 46387 | Y105: 46024 | Z105: 150000 | AA105: 0 | AB105: =Z105 -> 150000 | AC105: 0 | AD105: =Z105 -> 150000 | AE105: =AB105 -> 150000 | AF105: ENGAGE | AN105: Manque n° contrat
A106: =IF(AF106="ENGAGE","✔",IF(AF106="EN COURS D'ENGAGEMENT","◕",IF(AF106="PREENGAGE","◑",IF(AF106="EN COURS DE PREENGAGEMENT","◔",IF(AF106="NON ENGAGE","✖",""))))) -> ✔ | B106: 2026 | C106: DINFOTV | D106: PV N° : 01RC2025- DITV | E106: CONTRAT | G106: TOSSA MUSTAPHA - Consultant chargé de l'analyse politique et le décryptage hebdomadaire des JT en langue Française et Arabe | H106: VALIDE | I106: APPROUVE | K106: NON CONCERNE | L106: Ordinaire | M106: FONCTIONNEMENT | N106: Prestations de service Achat prestations de services locales - personnes physiques | R106: RECONDUCTION | U106: TOSSA MUSTAPHA | V106: 2026 | W106: 46387 | Y106: 46024 | Z106: 120000 | AA106: 0 | AB106: =Z106 -> 120000 | AC106: 0 | AD106: =Z106 -> 120000 | AE106: =AB106 -> 120000 | AF106: ENGAGE | AN106: Manque n° contrat
A107: =IF(AF107="ENGAGE","✔",IF(AF107="EN COURS D'ENGAGEMENT","◕",IF(AF107="PREENGAGE","◑",IF(AF107="EN COURS DE PREENGAGEMENT","◔",IF(AF107="NON ENGAGE","✖",""))))) -> ✔ | B107: 2026 | C107: TV LAAYOUNE | D107: PV N° : 01RC2025-DCL | E107: CONTRAT | G107: SALEK BOUJDOUR - Préparation et Présentation "HADITH ALMADINA" | H107: VALIDE | I107: APPROUVE | K107: NON CONCERNE | L107: Ordinaire | M107: FONCTIONNEMENT | N107: Prestations de service Achat prestations de services locales - personnes physiques | R107: RECONDUCTION | U107: SALEK BOUJDOUR | V107: 2026 | W107: 46387 | Y107: 46024 | Z107: 171428.64 | AA107: 0 | AB107: =Z107 -> 171428.64 | AC107: 0 | AD107: =AB107 -> 171428.64 | AE107: =AD107 -> 171428.64 | AF107: ENGAGE | AN107: Manque n° contrat
A108: =IF(AF108="ENGAGE","✔",IF(AF108="EN COURS D'ENGAGEMENT","◕",IF(AF108="PREENGAGE","◑",IF(AF108="EN COURS DE PREENGAGEMENT","◔",IF(AF108="NON ENGAGE","✖",""))))) -> ✔ | B108: 2026 | C108: TV LAAYOUNE | D108: PV N° : 01RC2025-DCL | E108: CONTRAT | G108: EL MOUGUAF AMGHAYER - Préparation et présentation de l'émission intitulée : " TOURATHAK LAK " | H108: VALIDE | I108: APPROUVE | K108: NON CONCERNE | L108: Ordinaire | M108: FONCTIONNEMENT | N108: Prestations de service Achat prestations de services locales - personnes physiques | R108: RECONDUCTION | U108: EL MOUGUAF AMGHAYER | V108: 2026 | W108: 46387 | Y108: 46024 | Z108: 280000 | AA108: 0 | AB108: =Z108 -> 280000 | AC108: 0 | AD108: =AB108 -> 280000 | AE108: =AD108 -> 280000 | AF108: ENGAGE | AN108: Manque n° contrat
A109: =IF(AF109="ENGAGE","✔",IF(AF109="EN COURS D'ENGAGEMENT","◕",IF(AF109="PREENGAGE","◑",IF(AF109="EN COURS DE PREENGAGEMENT","◔",IF(AF109="NON ENGAGE","✖",""))))) -> ✔ | B109: 2026 | C109: TV LAAYOUNE | D109: PV N° : 01RC2025-DCL | E109: CONTRAT | G109: YASSINE OMARI - Préparation quotidienne des revues de presses écrite nationale et Internationale | H109: VALIDE | I109: APPROUVE | K109: NON CONCERNE | L109: Ordinaire | M109: FONCTIONNEMENT | N109: Prestations de service Achat prestations de services locales - personnes physiques | R109: RECONDUCTION | U109: YASSINE OMARI | V109: 2026 | W109: 46387 | Y109: 46024 | Z109: 171429.12 | AA109: 0 | AB109: =Z109 -> 171429.12 | AC109: 0 | AD109: =AB109 -> 171429.12 | AE109: =AD109 -> 171429.12 | AF109: ENGAGE | AN109: Manque n° contrat
A110: =IF(AF110="ENGAGE","✔",IF(AF110="EN COURS D'ENGAGEMENT","◕",IF(AF110="PREENGAGE","◑",IF(AF110="EN COURS DE PREENGAGEMENT","◔",IF(AF110="NON ENGAGE","✖",""))))) -> ✔ | B110: 2026 | C110: TV LAAYOUNE | D110: PV N° : 01RC2025-DCL | E110: CONTRAT | G110: MAHMOUD AIYACH - Préparation et la présentation d'une émission produite en interne intitulée " MAA NASS " | H110: VALIDE | I110: APPROUVE | K110: NON CONCERNE | L110: Ordinaire | M110: FONCTIONNEMENT | N110: Prestations de service Achat prestations de services locales - personnes physiques | R110: RECONDUCTION | U110: MAHMOUD AIYACH | V110: 2026 | W110: 46387 | Y110: 46024 | Z110: 257142.9 | AA110: 0 | AB110: =Z110 -> 257142.9 | AC110: 0 | AD110: =AB110 -> 257142.9 | AE110: =AD110 -> 257142.9 | AF110: ENGAGE | AN110: Manque n° contrat
A111: =IF(AF111="ENGAGE","✔",IF(AF111="EN COURS D'ENGAGEMENT","◕",IF(AF111="PREENGAGE","◑",IF(AF111="EN COURS DE PREENGAGEMENT","◔",IF(AF111="NON ENGAGE","✖",""))))) -> ✔ | B111: 2026 | C111: TV LAAYOUNE | D111: PV N° : 01RC2025-DCL | E111: CONTRAT | G111: MARYAM EDDAH - Chargée de l'Autopromotion et de l’établissement de la grille et des conducteurs de diffusion. | H111: VALIDE | I111: APPROUVE | K111: NON CONCERNE | L111: Ordinaire | M111: FONCTIONNEMENT | N111: Prestations de service Achat prestations de services locales - personnes physiques | R111: RECONDUCTION | U111: MARYAM EDDAH | V111: 2026 | W111: 46387 | Y111: 46024 | Z111: 181800 | AA111: 0 | AB111: =Z111 -> 181800 | AC111: 0 | AD111: =AB111 -> 181800 | AE111: =AD111 -> 181800 | AF111: ENGAGE | AN111: Manque n° contrat
A112: =IF(AF112="ENGAGE","✔",IF(AF112="EN COURS D'ENGAGEMENT","◕",IF(AF112="PREENGAGE","◑",IF(AF112="EN COURS DE PREENGAGEMENT","◔",IF(AF112="NON ENGAGE","✖",""))))) -> ✔ | B112: 2026 | C112: MAGHRIBIA | D112: PV N° : 01RC2025-DCCMCITV | E112: CONTRAT | G112: OTHMANE RABBAH - Technicien infographiste | H112: VALIDE | I112: APPROUVE | K112: NON CONCERNE | L112: Ordinaire | M112: FONCTIONNEMENT | N112: Prestations de service Achat prestations de services locales - personnes physiques | R112: RECONDUCTION | U112: OTHMANE RABBAH | V112: 2026 | W112: 46387 | Y112: 46024 | Z112: 144000 | AA112: 0 | AB112: =Z112 -> 144000 | AC112: 0 | AD112: =AB112 -> 144000 | AE112: =AD112 -> 144000 | AF112: ENGAGE | AN112: Manque n° contrat
A113: =IF(AF113="ENGAGE","✔",IF(AF113="EN COURS D'ENGAGEMENT","◕",IF(AF113="PREENGAGE","◑",IF(AF113="EN COURS DE PREENGAGEMENT","◔",IF(AF113="NON ENGAGE","✖",""))))) -> ✔ | B113: 2026 | C113: MAGHRIBIA | D113: PV N° : 01RC2025-DCCMCITV | E113: CONTRAT | G113: HIBA TOUANINA - Technicienne Scripte | H113: VALIDE | I113: APPROUVE | K113: NON CONCERNE | L113: Ordinaire | M113: FONCTIONNEMENT | N113: Prestations de service Achat prestations de services locales - personnes physiques | R113: RECONDUCTION | U113: HIBA TOUANINA | V113: 2026 | W113: 46387 | Y113: 46024 | Z113: 100800 | AA113: 0 | AB113: =Z113 -> 100800 | AC113: 0 | AD113: =AB113 -> 100800 | AE113: =AD113 -> 100800 | AF113: ENGAGE | AN113: Manque n° contrat
A114: =IF(AF114="ENGAGE","✔",IF(AF114="EN COURS D'ENGAGEMENT","◕",IF(AF114="PREENGAGE","◑",IF(AF114="EN COURS DE PREENGAGEMENT","◔",IF(AF114="NON ENGAGE","✖",""))))) -> ✔ | B114: 2026 | C114: MAGHRIBIA | D114: PV N° : 01RC2025-DCCMCITV | E114: CONTRAT | G114: FATIMA ZAHRA BOUMBAREK - Technicienne assistante Réalisatrice | H114: VALIDE | I114: APPROUVE | K114: NON CONCERNE | L114: Ordinaire | M114: FONCTIONNEMENT | N114: Prestations de service Achat prestations de services locales - personnes physiques | R114: RECONDUCTION | U114: FATIMA ZAHRA BOUMBAREK | V114: 2026 | W114: 46387 | Y114: 46024 | Z114: 100800 | AA114: 0 | AB114: =Z114 -> 100800 | AC114: 0 | AD114: =AB114 -> 100800 | AE114: =AD114 -> 100800 | AF114: ENGAGE | AN114: Manque n° contrat
A115: =IF(AF115="ENGAGE","✔",IF(AF115="EN COURS D'ENGAGEMENT","◕",IF(AF115="PREENGAGE","◑",IF(AF115="EN COURS DE PREENGAGEMENT","◔",IF(AF115="NON ENGAGE","✖",""))))) -> ✔ | B115: 2026 | C115: MAGHRIBIA | D115: PV N° : 01RC2025-DCCMCITV | E115: CONTRAT | G115: OUMAIMA NACHAR - Journaliste présentatrice | H115: VALIDE | I115: APPROUVE | K115: NON CONCERNE | L115: Ordinaire | M115: FONCTIONNEMENT | N115: Prestations de service Achat prestations de services locales - personnes physiques | R115: RECONDUCTION | U115: OUMAIMA NACHAR | V115: 2026 | W115: 46387 | Y115: 46024 | Z115: 144000 | AA115: 0 | AB115: =Z115 -> 144000 | AC115: 0 | AD115: =AB115 -> 144000 | AE115: =AD115 -> 144000 | AF115: ENGAGE | AN115: Manque n° contrat
A116: =IF(AF116="ENGAGE","✔",IF(AF116="EN COURS D'ENGAGEMENT","◕",IF(AF116="PREENGAGE","◑",IF(AF116="EN COURS DE PREENGAGEMENT","◔",IF(AF116="NON ENGAGE","✖",""))))) -> ✔ | B116: 2026 | C116: MAGHRIBIA | D116: PV N° : 01RC2025-DCCMCITV | E116: CONTRAT | G116: NIDAL OUJIL - Journaliste présentatrice | H116: VALIDE | I116: APPROUVE | K116: NON CONCERNE | L116: Ordinaire | M116: FONCTIONNEMENT | N116: Prestations de service Achat prestations de services locales - personnes physiques | R116: RECONDUCTION | U116: NIDAL OUJI | V116: 2026 | W116: 46387 | Y116: 46024 | Z116: 144000 | AA116: 0 | AB116: =Z116 -> 144000 | AC116: 0 | AD116: =AB116 -> 144000 | AE116: =AD116 -> 144000 | AF116: ENGAGE | AN116: Manque n° contrat
A117: =IF(AF117="ENGAGE","✔",IF(AF117="EN COURS D'ENGAGEMENT","◕",IF(AF117="PREENGAGE","◑",IF(AF117="EN COURS DE PREENGAGEMENT","◔",IF(AF117="NON ENGAGE","✖",""))))) -> ✔ | B117: 2026 | C117: MAGHRIBIA | D117: PV N° : 01RC2025-DCCMCITV | E117: CONTRAT | G117: ABDELLATIF AMRANI ZERIFI - Technicien assistant réalisateur | H117: VALIDE | I117: APPROUVE | K117: NON CONCERNE | L117: Ordinaire | M117: FONCTIONNEMENT | N117: Prestations de service Achat prestations de services locales - personnes physiques | R117: RECONDUCTION | U117: ABDELLATIF AMRANI ZERIF | V117: 2026 | W117: 46387 | Y117: 46024 | Z117: 100800 | AA117: 0 | AB117: =Z117 -> 100800 | AC117: 0 | AD117: =AB117 -> 100800 | AE117: =AD117 -> 100800 | AF117: ENGAGE | AN117: Manque n° contrat
A118: =IF(AF118="ENGAGE","✔",IF(AF118="EN COURS D'ENGAGEMENT","◕",IF(AF118="PREENGAGE","◑",IF(AF118="EN COURS DE PREENGAGEMENT","◔",IF(AF118="NON ENGAGE","✖",""))))) -> ✔ | B118: 2026 | C118: MAGHRIBIA | D118: PV N° : 01RC2025-DCCMCITV | E118: CONTRAT | G118: LAMYAE KHOUADIR - Technicienne scripte | H118: VALIDE | I118: APPROUVE | K118: NON CONCERNE | L118: Ordinaire | M118: FONCTIONNEMENT | N118: Prestations de service Achat prestations de services locales - personnes physiques | R118: RECONDUCTION | U118: LAMYAE KHOUADIR | V118: 2026 | W118: 46387 | Y118: 46024 | Z118: 100800 | AA118: 0 | AB118: =Z118 -> 100800 | AC118: 0 | AD118: =AB118 -> 100800 | AE118: =AD118 -> 100800 | AF118: ENGAGE | AN118: Manque n° contrat
... A120: =IF(AF120="ENGAGE","✔",IF(AF120="EN COURS D'ENGAGEMENT","◕",IF(AF120="PREENGAGE","◑",IF(AF120="EN COURS DE PREENGAGEMENT","◔",IF(AF120="NON ENGAGE","✖",""))))) -> ✔ | B120: 2026 | C120: MAGHRIBIA | D120: PV N° : 01RC2025-DCCMCITV | E120: CONTRAT | G120: JEBRANI HAYAT - Coiffeuse, maquilleuse | H120: VALIDE | I120: APPROUVE | K120: NON CONCERNE | L120: Ordinaire | M120: FONCTIONNEMENT | N120: Prestations de service Achat prestations de services locales - personnes physiques | R120: RECONDUCTION | U120: JEBRANI HAYAT | V120: 2026 | W120: 46387 | Y120: 46024 | Z120: 72000 | AA120: 0 | AB120: =Z120 -> 72000 | AC120: 0 | AD120: =AB120 -> 72000 | AE120: =AD120 -> 72000 | AF120: ENGAGE | AN120: Manque n° contrat
A121: =IF(AF121="ENGAGE","✔",IF(AF121="EN COURS D'ENGAGEMENT","◕",IF(AF121="PREENGAGE","◑",IF(AF121="EN COURS DE PREENGAGEMENT","◔",IF(AF121="NON ENGAGE","✖",""))))) -> ✔ | B121: 2026 | C121: DMPTV | D121: PV N° : 01RC2025-DCMPTV | E121: CONTRAT | G121: ZAKARIA TIBARI - Conception de bandes annonces pour la promotion des programmes de la grille de la chaîne Al Aoula | H121: VALIDE | I121: APPROUVE | K121: NON CONCERNE | L121: Ordinaire | M121: FONCTIONNEMENT | N121: Prestations de service Achat prestations de services locales - personnes physiques | R121: RECONDUCTION | U121: ZAKARIA TIBARI | V121: 2026 | W121: 46387 | Y121: 46024 | Z121: 257142.84 | AB121: =Z121 -> 257142.84 | AD121: =Z121 -> 257142.84 | AE121: =AB121 -> 257142.84 | AF121: ENGAGE | AN121: Manque n° contrat
A122: =IF(AF122="ENGAGE","✔",IF(AF122="EN COURS D'ENGAGEMENT","◕",IF(AF122="PREENGAGE","◑",IF(AF122="EN COURS DE PREENGAGEMENT","◔",IF(AF122="NON ENGAGE","✖",""))))) -> ✔ | B122: 2026 | C122: DMPTV | D122: PV N° : 01RC2025-DCMPTV | E122: CONTRAT | G122: GHEZLANE EL MERZOUGUI - Enregistrement des voix off en arabe des bandes annonces TV et radio Al Aoula | H122: VALIDE | I122: APPROUVE | K122: NON CONCERNE | L122: Ordinaire | M122: FONCTIONNEMENT | N122: Prestations de service Achat prestations de services locales - personnes physiques | R122: RECONDUCTION | U122: GHEZLANE EL MERZOUGUI | V122: 2026 | W122: 46387 | Y122: 46024 | Z122: 84000 | AB122: =Z122 -> 84000 | AD122: =Z122 -> 84000 | AE122: =AB122 -> 84000 | AF122: ENGAGE | AN122: Manque n° contrat
A123: =IF(AF123="ENGAGE","✔",IF(AF123="EN COURS D'ENGAGEMENT","◕",IF(AF123="PREENGAGE","◑",IF(AF123="EN COURS DE PREENGAGEMENT","◔",IF(AF123="NON ENGAGE","✖",""))))) -> ✔ | B123: 2026 | C123: DMPTV | D123: PV N° : 01RC2025-DCMPTV | E123: CONTRAT | G123: HOUSSAM MOUILLAH - Monteur | H123: VALIDE | I123: APPROUVE | K123: NON CONCERNE | L123: Ordinaire | M123: FONCTIONNEMENT | N123: Prestations de service Achat prestations de services locales - personnes physiques | R123: RECONDUCTION | U123: HOUSSAM MOUILLAH | V123: 2026 | W123: 46387 | Y123: 46024 | Z123: 120000 | AB123: =Z123 -> 120000 | AD123: =Z123 -> 120000 | AE123: =AB123 -> 120000 | AF123: ENGAGE | AN123: Manque n° contrat
A124: =IF(AF124="ENGAGE","✔",IF(AF124="EN COURS D'ENGAGEMENT","◕",IF(AF124="PREENGAGE","◑",IF(AF124="EN COURS DE PREENGAGEMENT","◔",IF(AF124="NON ENGAGE","✖",""))))) -> ✔ | B124: 2026 | C124: DMPTV | D124: PV N° : 01RC2025-DCMPTV | E124: CONTRAT | G124: MSIOUAS MOHAMED DRISS - Chef de produit digital | H124: VALIDE | I124: APPROUVE | K124: NON CONCERNE | L124: Ordinaire | M124: FONCTIONNEMENT | N124: Prestations de service Achat prestations de services locales - personnes physiques | R124: RECONDUCTION | U124: MSIOUAS MOHAMED DRISS | V124: 2026 | W124: 46387 | Y124: 46024 | Z124: 264000 | AB124: =Z124 -> 264000 | AD124: =Z124 -> 264000 | AE124: =AB124 -> 264000 | AF124: ENGAGE | AN124: Manque n° contrat
A125: =IF(AF125="ENGAGE","✔",IF(AF125="EN COURS D'ENGAGEMENT","◕",IF(AF125="PREENGAGE","◑",IF(AF125="EN COURS DE PREENGAGEMENT","◔",IF(AF125="NON ENGAGE","✖",""))))) -> ✔ | B125: 2026 | C125: DMPTV | D125: PV N° : 01RC2025-DCMPTV | E125: CONTRAT | G125: ABDELOUAHED JABBAR - Monteur | H125: VALIDE | I125: APPROUVE | K125: NON CONCERNE | L125: Ordinaire | M125: FONCTIONNEMENT | N125: Prestations de service Achat prestations de services locales - personnes physiques | R125: RECONDUCTION | U125: ABDELOUAHED JABBAR | V125: 2026 | W125: 46387 | Y125: 46024 | Z125: 216000 | AB125: =Z125 -> 216000 | AD125: =Z125 -> 216000 | AE125: =AB125 -> 216000 | AF125: ENGAGE | AN125: Manque n° contrat
A126: =IF(AF126="ENGAGE","✔",IF(AF126="EN COURS D'ENGAGEMENT","◕",IF(AF126="PREENGAGE","◑",IF(AF126="EN COURS DE PREENGAGEMENT","◔",IF(AF126="NON ENGAGE","✖",""))))) -> ✔ | B126: 2026 | C126: DMPTV | D126: PV N° : 01RC2025-DCMPTV | E126: CONTRAT | G126: YASSINE KIRAMI - Monteur digital et cameraman | H126: VALIDE | I126: APPROUVE | K126: NON CONCERNE | L126: Ordinaire | M126: FONCTIONNEMENT | N126: Prestations de service Achat prestations de services locales - personnes physiques | R126: RECONDUCTION | U126: YASSINE KIRAMI | V126: 2026 | W126: 46387 | Y126: 46024 | Z126: 144000 | AB126: =Z126 -> 144000 | AD126: =Z126 -> 144000 | AE126: =AB126 -> 144000 | AF126: ENGAGE | AN126: Manque n° contrat
A127: =IF(AF127="ENGAGE","✔",IF(AF127="EN COURS D'ENGAGEMENT","◕",IF(AF127="PREENGAGE","◑",IF(AF127="EN COURS DE PREENGAGEMENT","◔",IF(AF127="NON ENGAGE","✖",""))))) -> ✔ | B127: 2026 | C127: DMPTV | D127: PV N° : 01RC2025-DCMPTV | E127: CONTRAT | G127: SAFAA SABRI - Rédactrice en arabe | H127: VALIDE | I127: APPROUVE | K127: NON CONCERNE | L127: Ordinaire | M127: FONCTIONNEMENT | N127: Prestations de service Achat prestations de services locales - personnes physiques | R127: RECONDUCTION | U127: SAFAA SABR | V127: 2026 | W127: 46387 | Y127: 46024 | Z127: 132000 | AB127: =Z127 -> 132000 | AD127: =Z127 -> 132000 | AE127: =AB127 -> 132000 | AF127: ENGAGE | AN127: Manque n° contrat
A128: =IF(AF128="ENGAGE","✔",IF(AF128="EN COURS D'ENGAGEMENT","◕",IF(AF128="PREENGAGE","◑",IF(AF128="EN COURS DE PREENGAGEMENT","◔",IF(AF128="NON ENGAGE","✖",""))))) -> ✔ | B128: 2026 | C128: DMPTV | D128: PV N° : 01RC2025-DCMPTV | E128: CONTRAT | G128: SARAH MAACHE - Rédactrice en Français | H128: VALIDE | I128: APPROUVE | K128: NON CONCERNE | L128: Ordinaire | M128: FONCTIONNEMENT | N128: Prestations de service Achat prestations de services locales - personnes physiques | R128: RECONDUCTION | U128: SARAH MAACHE | V128: 2026 | W128: 46387 | Y128: 46024 | Z128: 252000 | AB128: =Z128 -> 252000 | AD128: =Z128 -> 252000 | AE128: =AB128 -> 252000 | AF128: ENGAGE | AN128: Manque n° contrat
A129: =IF(AF129="ENGAGE","✔",IF(AF129="EN COURS D'ENGAGEMENT","◕",IF(AF129="PREENGAGE","◑",IF(AF129="EN COURS DE PREENGAGEMENT","◔",IF(AF129="NON ENGAGE","✖",""))))) -> ✔ | B129: 2026 | C129: DMPTV | D129: PV N° : 01RC2025-DCMPTV | E129: CONTRAT | G129: BASMA WAJIB - Community Manager | H129: VALIDE | I129: APPROUVE | K129: NON CONCERNE | L129: Ordinaire | M129: FONCTIONNEMENT | N129: Prestations de service Achat prestations de services locales - personnes physiques | R129: RECONDUCTION | U129: BASMA WAJIB | V129: 2026 | W129: 46387 | Y129: 46024 | Z129: 84000 | AB129: =Z129 -> 84000 | AD129: =Z129 -> 84000 | AE129: =AB129 -> 84000 | AF129: ENGAGE | AN129: Manque n° contrat
A130: =IF(AF130="ENGAGE","✔",IF(AF130="EN COURS D'ENGAGEMENT","◕",IF(AF130="PREENGAGE","◑",IF(AF130="EN COURS DE PREENGAGEMENT","◔",IF(AF130="NON ENGAGE","✖",""))))) -> ✔ | B130: 2026 | C130: DMPTV | D130: PV N° : 01RC2025-DCMPTV | E130: CONTRAT | G130: M’BARK AGNAOU - Community Manager | H130: VALIDE | I130: APPROUVE | K130: NON CONCERNE | L130: Ordinaire | M130: FONCTIONNEMENT | N130: Prestations de service Achat prestations de services locales - personnes physiques | R130: RECONDUCTION | U130: M’BARK AGNAOU | V130: 2026 | W130: 46387 | Y130: 46024 | Z130: 84000 | AB130: =Z130 -> 84000 | AD130: =Z130 -> 84000 | AE130: =AB130 -> 84000 | AF130: ENGAGE | AN130: Manque n° contrat
A131: =IF(AF131="ENGAGE","✔",IF(AF131="EN COURS D'ENGAGEMENT","◕",IF(AF131="PREENGAGE","◑",IF(AF131="EN COURS DE PREENGAGEMENT","◔",IF(AF131="NON ENGAGE","✖",""))))) -> ✔ | B131: 2026 | C131: DMPTV | D131: PV N° : 01RC2025-DCMPTV | E131: CONTRAT | G131: ESSAIFI MOHAMED SAMI - Content lead digital | H131: VALIDE | I131: APPROUVE | K131: NON CONCERNE | L131: Ordinaire | M131: FONCTIONNEMENT | N131: Prestations de service Achat prestations de services locales - personnes physiques | R131: RECONDUCTION | U131: ESSAIFI MOHAMED SAMI | V131: 2026 | W131: 46387 | Y131: 46024 | Z131: 276000 | AB131: =Z131 -> 276000 | AD131: =Z131 -> 276000 | AE131: =AB131 -> 276000 | AF131: ENGAGE | AN131: Manque n° contrat
A132: =IF(AF132="ENGAGE","✔",IF(AF132="EN COURS D'ENGAGEMENT","◕",IF(AF132="PREENGAGE","◑",IF(AF132="EN COURS DE PREENGAGEMENT","◔",IF(AF132="NON ENGAGE","✖",""))))) -> ✔ | B132: 2026 | C132: DMPTV | D132: PV N° : 01RC2025-DCMPTV | E132: CONTRAT | G132: HAJAR LAMRANI - Monteur | H132: VALIDE | I132: APPROUVE | K132: NON CONCERNE | L132: Ordinaire | M132: FONCTIONNEMENT | N132: Prestations de service Achat prestations de services locales - personnes physiques | R132: RECONDUCTION | U132: HAJAR LAMRANI | V132: 2026 | W132: 46387 | Y132: 46024 | Z132: 144000 | AB132: =Z132 -> 144000 | AD132: =Z132 -> 144000 | AE132: =AB132 -> 144000 | AF132: ENGAGE | AN132: Manque n° contrat
...

Sheet lignes
A1: Compte | B1: Libellé
A2: 212-1 | B2: Frais d'acquisition des immobilisations
A3: 212-2 | B3: Prestations de service à immobiliser
A4: 221-1 | B4: Immobilisations incorporelles (logiciels, licences, etc.)
A5: 231-1 | B5: Terrains
A6: 232-2 | B6: Agencements et aménagement constructions
A7: 233-1 | B7: Installations techniques
A8: 233-2 | B8: Matériel et outillage
A9: 233-3 | B9: Equipements de télédiffusion
A10: 233-4 | B10: Equipements techniques
A11: 235-1 | B11: Mobilier de bureau
A12: 235-2 | B12: Matériel de bureau
... A58: 617-3 | B58: Charges sociales diverses

Sheet PPM 2026
A1: PROGRAMME PREVISIONNEL DES MARCHES PAR APPELS D'OFFRES
A9: DIRECTION | B9: OBJET | C9: NATURE DE LA PRESTATION | D9: MODE DE PASSATION | E9: PERIODE PREVUE POUR LE LANCEMENT | F9: LIEU D'EXECUTION | G9: AOO RESERVES AUX PME | H9: ESTIMATION | I9: NATURE BUDGET
A10: Direction de la Télédiffusion | B10: Fourniture des modules de traitement audio et RDS pour les émetteurs FM | C10: Fournitures | D10: Appel d'offres ouvert | E10: T3 | F10: Magasin Temara | G10: Non | H10: 1800000 | I10: Investissement
A11: Direction de la Télédiffusion | B11: Fourniture, installation et mise en service de systèmes de supervision des antennes de diffusion FM et TV | C11: Fournitures | D11: Appel d'offres ouvert | E11: T2 | F11: Centres de diffusion de la SNRT | G11: Non | H11: 2755000 | I11: Investissement
A12: Direction de la Télédiffusion | B12: Fourniture et installation des équipements de contrôle audio et vidéo pour les petits centres de diffusion TV/FM | C12: Fournitures | D12: Appel d'offres ouvert | E12: T2 | F12: Centres de diffusion de la SNRT | G12: Non | H12: 1000000 | I12: Investissement
A13: Direction de la Télédiffusion | B13: Fourniture, installation et mise en service des climatiseurs aux centres de diffusion de la SNRT | C13: Fournitures | D13: Appel d'offres ouvert | E13: T3 | F13: Centres de diffusion de la SNRT | G13: Oui | H13: 3500000 | I13: Investissement
A14: Direction de la Télédiffusion | B14: Fourniture des analyseurs de réseaux électrique et les appareils de mesure électrique | C14: Fournitures | D14: Appel d'offres ouvert | E14: T2 | F14: Magasin Temara | G14: Non | H14: 800000 | I14: Investissement
A15: Direction de la Télédiffusion | B15: Fourniture,installation et mise en service des commutateurs et distributeurs des signaux ASI et IP pour les centres de diffusion TNT et FM | C15: Fournitures | D15: Appel d'offres ouvert | E15: T3 | F15: Centres de diffusion de la SNRT | G15: Non | H15: 1000000 | I15: Investissement
A16: Direction de la Télédiffusion | B16: Fourniture et installation des sondes FM et TNT pour le contrôle des signaux audios et vidéo des chaines radio et télevision de la SNRT | C16: Fournitures | D16: Appel d'offres ouvert | E16: T3 | F16: Magasin Temara | G16: Non | H16: 1200000 | I16: Investissement
A17: Direction de la Télédiffusion | B17: Fourniture des modules et pièces de rechanges des émetteurs TNT de des centres de la SNRT | C17: Fournitures | D17: Appel d'offres ouvert | E17: T2 | F17: Magasin Temara | G17: Non | H17: 6500000 | I17: Fonctionnement
A18: Direction de la Télédiffusion | B18: Fourniture des modules et pièces de rechanges des émetteurs FM des centres de la SNRT | C18: Fournitures | D18: Appel d'offres ouvert | E18: T2 | F18: Magasin Temara | G18: Non | H18: 6500000 | I18: Fonctionnement
A19: Direction de la Télédiffusion | B19: Fourniture des duplexeurs, filtres, patchs panel , commutateurs RF et adaptateurs | C19: Fournitures | D19: Appel d'offres ouvert | E19: T3 | F19: Magasin Temara | G19: Non | H19: 1600000 | I19: Fonctionnement
A20: Direction de la Télédiffusion | B20: Fourniture des distributeurs de puissance UHF et FM, combiners, feeders et antennes | C20: Fournitures | D20: Appel d'offres ouvert | E20: T3 | F20: Magasin Temara | G20: Non | H20: 3500000 | I20: Fonctionnement
A21: Direction de la Télédiffusion | B21: Fourniture des modules et pièces de rechanges hydrauliques et électriques pour les émetteurs de diffusion TNT et FM | C21: Fournitures | D21: Appel d'offres ouvert | E21: T2 | F21: Magasin Temara | G21: Non | H21: 1100000 | I21: Fonctionnement
... A169: Direction Centrale Technique | B169: Fourniture et mise en service d'un systéme d'intercom boradcast pour les besoins de la SNRT | C169: Fournitures | D169: Appel d'offres ouvert | E169: T2 | F169: Rabat | G169: Non | H169: 291156 | I169: Investissement

Sheet Données Suivi
A1: DIRECTION | B1: REF | C1: BCI (TYPE D'ACHAT) | D1: OBJET | E1: STATUT SUPPORT D'ENGAGEMENT | F1: N° SUPPORT D'ENGAGEMENT | G1: NATURE BUDGET | H1: STATUT D'ENGAGEMENT | I1: STATUT 1 | J1: MONTANT (MAD) | K1: DATE FICHE | L1: ANCIENNETE (jours) | M1: CATEGORIE SUIVI | N1: TYPE BUDGET | O1: NATURE BUDGET | P1: CATEGORIES | Q1: CLE INFR-ANNULE
A2: =IF(ISBLANK('ENGAGEMENTS 2026'!C2),"",IF('ENGAGEMENTS 2026'!C2="DTSI","DCT",'ENGAGEMENTS 2026'!C2)) -> DRH | B2: =IF(ISBLANK('ENGAGEMENTS 2026'!C2),"",'ENGAGEMENTS 2026'!D2) -> EXCLUSIVITÉ | C2: =IF(ISBLANK('ENGAGEMENTS 2026'!C2),"",'ENGAGEMENTS 2026'!E2) -> CONTRAT | D2: =IF(ISBLANK('ENGAGEMENTS 2026'!C2),"",'ENGAGEMENTS 2026'!G2) -> Convention SNRT-OFPPT pour la réalisation des EAP | E2: =IF(ISBLANK('ENGAGEMENTS 2026'!C2),"",'ENGAGEMENTS 2026'!I2) -> APPROUVE | F2: =IF(ISBLANK('ENGAGEMENTS 2026'!C2),"",'ENGAGEMENTS 2026'!J2) -> 01/OFPPT/SNRT/2026 | G2: =IF(ISBLANK('ENGAGEMENTS 2026'!C2),"",'ENGAGEMENTS 2026'!M2) -> FONCTIONNEMENT | H2: =IF(ISBLANK('ENGAGEMENTS 2026'!C2),"",'ENGAGEMENTS 2026'!AF2) -> ENGAGE | I2: =IF(ISBLANK('ENGAGEMENTS 2026'!C2),"",'ENGAGEMENTS 2026'!H2) -> VALIDE | J2: =IF(ISBLANK('ENGAGEMENTS 2026'!C2),"",IF(AND(OR($E2="INFRUCTUEUX",$E2="ANNULE"),$C2="AOO-M"),'ENGAGEMENTS 2026'!P2,IF($H2="EN COURS DE PREENGAGEMENT",'ENGAGEMENTS 2026'!O2,IF($H2="PREENGAGE",IF($E2="ATTRIBUE",'ENGAGEMENTS 2026'!AE2,'ENGAGEMENTS 2026'!O2),'ENGAGEMENTS 2026'!AE2)))) -> 995042.4 | K2: =IF(ISBLANK('ENGAGEMENTS 2026'!W2),"",'ENGAGEMENTS 2026'!W2) -> 46030 | L2: =IF($K2="","",TODAY()-$K2) -> 258 | M2: =IF($A2="","",IF($H2="ENGAGE","Engagé",IF(AND($H2="NON ENGAGE",OR($I2="INFRUCTUEUX",$I2="ANNULE")),"Clôturé sans suite","En cours"))) -> Engagé | N2: =IF(ISBLANK('ENGAGEMENTS 2026'!C2),"",'ENGAGEMENTS 2026'!L2) -> Ordinaire | O2: =IF(ISBLANK('ENGAGEMENTS 2026'!C2),"",'ENGAGEMENTS 2026'!M2) -> FONCTIONNEMENT | P2: =IF(ISBLANK('ENGAGEMENTS 2026'!C2),"",'ENGAGEMENTS 2026'!K2) -> NON CONCERNE | Q2: =IF($A2="","",IF(OR($E2="INFRUCTUEUX",$E2="ANNULE"),$A2&"|"&(COUNTIFS($A$2:$A2,$A2,$E$2:$E2,"INFRUCTUEUX")+COUNTIFS($A$2:$A2,$A2,$E$2:$E2,"ANNULE")),""))
A3: =IF(ISBLANK('ENGAGEMENTS 2026'!C3),"",IF('ENGAGEMENTS 2026'!C3="DTSI","DCT",'ENGAGEMENTS 2026'!C3)) -> DCPA | B3: =IF(ISBLANK('ENGAGEMENTS 2026'!C3),"",'ENGAGEMENTS 2026'!D3) -> PV N° : 01RC2025- DCPA | C3: =IF(ISBLANK('ENGAGEMENTS 2026'!C3),"",'ENGAGEMENTS 2026'!E3) -> CONTRAT | D3: =IF(ISBLANK('ENGAGEMENTS 2026'!C3),"",'ENGAGEMENTS 2026'!G3) -> IKRAM BENNANI RTAL - Préparation et animation de l’émission «نور و بصائر" | E3: =IF(ISBLANK('ENGAGEMENTS 2026'!C3),"",'ENGAGEMENTS 2026'!I3) -> APPROUVE | F3: =IF(ISBLANK('ENGAGEMENTS 2026'!C3),"",'ENGAGEMENTS 2026'!J3) -> 185 CT/SNRT/2026 | G3: =IF(ISBLANK('ENGAGEMENTS 2026'!C3),"",'ENGAGEMENTS 2026'!M3) -> FONCTIONNEMENT | H3: =IF(ISBLANK('ENGAGEMENTS 2026'!C3),"",'ENGAGEMENTS 2026'!AF3) -> ENGAGE | I3: =IF(ISBLANK('ENGAGEMENTS 2026'!C3),"",'ENGAGEMENTS 2026'!H3) -> VALIDE | J3: =IF(ISBLANK('ENGAGEMENTS 2026'!C3),"",IF(AND(OR($E3="INFRUCTUEUX",$E3="ANNULE"),$C3="AOO-M"),'ENGAGEMENTS 2026'!P3,IF($H3="EN COURS DE PREENGAGEMENT",'ENGAGEMENTS 2026'!O3,IF($H3="PREENGAGE",IF($E3="ATTRIBUE",'ENGAGEMENTS 2026'!AE3,'ENGAGEMENTS 2026'!O3),'ENGAGEMENTS 2026'!AE3)))) -> 154000 | K3: =IF(ISBLANK('ENGAGEMENTS 2026'!W3),"",'ENGAGEMENTS 2026'!W3) -> 46022 | L3: =IF($K3="","",TODAY()-$K3) -> 266 | M3: =IF($A3="","",IF($H3="ENGAGE","Engagé",IF(AND($H3="NON ENGAGE",OR($I3="INFRUCTUEUX",$I3="ANNULE")),"Clôturé sans suite","En cours"))) -> Engagé | N3: =IF(ISBLANK('ENGAGEMENTS 2026'!C3),"",'ENGAGEMENTS 2026'!L3) -> Ordinaire | O3: =IF(ISBLANK('ENGAGEMENTS 2026'!C3),"",'ENGAGEMENTS 2026'!M3) -> FONCTIONNEMENT | P3: =IF(ISBLANK('ENGAGEMENTS 2026'!C3),"",'ENGAGEMENTS 2026'!K3) -> NON CONCERNE | Q3: =IF($A3="","",IF(OR($E3="INFRUCTUEUX",$E3="ANNULE"),$A3&"|"&(COUNTIFS($A$2:$A3,$A3,$E$2:$E3,"INFRUCTUEUX")+COUNTIFS($A$2:$A3,$A3,$E$2:$E3,"ANNULE")),""))
A4: =IF(ISBLANK('ENGAGEMENTS 2026'!C4),"",IF('ENGAGEMENTS 2026'!C4="DTSI","DCT",'ENGAGEMENTS 2026'!C4)) -> DCPA | B4: =IF(ISBLANK('ENGAGEMENTS 2026'!C4),"",'ENGAGEMENTS 2026'!D4) -> PV N° : 01RC2025- DCPA | C4: =IF(ISBLANK('ENGAGEMENTS 2026'!C4),"",'ENGAGEMENTS 2026'!E4) -> CONTRAT | D4: =IF(ISBLANK('ENGAGEMENTS 2026'!C4),"",'ENGAGEMENTS 2026'!G4) -> AMINE BENADDI - LA PREPARATION DE L'EMISSION " شباب في الواجهة" | E4: =IF(ISBLANK('ENGAGEMENTS 2026'!C4),"",'ENGAGEMENTS 2026'!I4) -> APPROUVE | F4: =IF(ISBLANK('ENGAGEMENTS 2026'!C4),"",'ENGAGEMENTS 2026'!J4) -> 186 CT/SNRT/2026 | G4: =IF(ISBLANK('ENGAGEMENTS 2026'!C4),"",'ENGAGEMENTS 2026'!M4) -> FONCTIONNEMENT | H4: =IF(ISBLANK('ENGAGEMENTS 2026'!C4),"",'ENGAGEMENTS 2026'!AF4) -> ENGAGE | I4: =IF(ISBLANK('ENGAGEMENTS 2026'!C4),"",'ENGAGEMENTS 2026'!H4) -> VALIDE | J4: =IF(ISBLANK('ENGAGEMENTS 2026'!C4),"",IF(AND(OR($E4="INFRUCTUEUX",$E4="ANNULE"),$C4="AOO-M"),'ENGAGEMENTS 2026'!P4,IF($H4="EN COURS DE PREENGAGEMENT",'ENGAGEMENTS 2026'!O4,IF($H4="PREENGAGE",IF($E4="ATTRIBUE",'ENGAGEMENTS 2026'!AE4,'ENGAGEMENTS 2026'!O4),'ENGAGEMENTS 2026'!AE4)))) -> 375000 | K4: =IF(ISBLANK('ENGAGEMENTS 2026'!W4),"",'ENGAGEMENTS 2026'!W4) -> 46387 | L4: =IF($K4="","",TODAY()-$K4) -> -99 | M4: =IF($A4="","",IF($H4="ENGAGE","Engagé",IF(AND($H4="NON ENGAGE",OR($I4="INFRUCTUEUX",$I4="ANNULE")),"Clôturé sans suite","En cours"))) -> Engagé | N4: =IF(ISBLANK('ENGAGEMENTS 2026'!C4),"",'ENGAGEMENTS 2026'!L4) -> Ordinaire | O4: =IF(ISBLANK('ENGAGEMENTS 2026'!C4),"",'ENGAGEMENTS 2026'!M4) -> FONCTIONNEMENT | P4: =IF(ISBLANK('ENGAGEMENTS 2026'!C4),"",'ENGAGEMENTS 2026'!K4) -> NON CONCERNE | Q4: =IF($A4="","",IF(OR($E4="INFRUCTUEUX",$E4="ANNULE"),$A4&"|"&(COUNTIFS($A$2:$A4,$A4,$E$2:$E4,"INFRUCTUEUX")+COUNTIFS($A$2:$A4,$A4,$E$2:$E4,"ANNULE")),""))
A5: =IF(ISBLANK('ENGAGEMENTS 2026'!C5),"",IF('ENGAGEMENTS 2026'!C5="DTSI","DCT",'ENGAGEMENTS 2026'!C5)) -> DCPA | B5: =IF(ISBLANK('ENGAGEMENTS 2026'!C5),"",'ENGAGEMENTS 2026'!D5) -> PV N° : 01RC2025- DCPA | C5: =IF(ISBLANK('ENGAGEMENTS 2026'!C5),"",'ENGAGEMENTS 2026'!E5) -> CONTRAT | D5: =IF(ISBLANK('ENGAGEMENTS 2026'!C5),"",'ENGAGEMENTS 2026'!G5) -> MOHAMMED ALI BENMAKHLOUF - Conception et présentation de l’émission " علم و حضارة" | E5: =IF(ISBLANK('ENGAGEMENTS 2026'!C5),"",'ENGAGEMENTS 2026'!I5) -> APPROUVE | F5: =IF(ISBLANK('ENGAGEMENTS 2026'!C5),"",'ENGAGEMENTS 2026'!J5) -> 190 CT/SNRT/2026 | G5: =IF(ISBLANK('ENGAGEMENTS 2026'!C5),"",'ENGAGEMENTS 2026'!M5) -> FONCTIONNEMENT | H5: =IF(ISBLANK('ENGAGEMENTS 2026'!C5),"",'ENGAGEMENTS 2026'!AF5) -> ENGAGE | I5: =IF(ISBLANK('ENGAGEMENTS 2026'!C5),"",'ENGAGEMENTS 2026'!H5) -> VALIDE | J5: =IF(ISBLANK('ENGAGEMENTS 2026'!C5),"",IF(AND(OR($E5="INFRUCTUEUX",$E5="ANNULE"),$C5="AOO-M"),'ENGAGEMENTS 2026'!P5,IF($H5="EN COURS DE PREENGAGEMENT",'ENGAGEMENTS 2026'!O5,IF($H5="PREENGAGE",IF($E5="ATTRIBUE",'ENGAGEMENTS 2026'!AE5,'ENGAGEMENTS 2026'!O5),'ENGAGEMENTS 2026'!AE5)))) -> 445714.08 | K5: =IF(ISBLANK('ENGAGEMENTS 2026'!W5),"",'ENGAGEMENTS 2026'!W5) -> 46387 | L5: =IF($K5="","",TODAY()-$K5) -> -99 | M5: =IF($A5="","",IF($H5="ENGAGE","Engagé",IF(AND($H5="NON ENGAGE",OR($I5="INFRUCTUEUX",$I5="ANNULE")),"Clôturé sans suite","En cours"))) -> Engagé | N5: =IF(ISBLANK('ENGAGEMENTS 2026'!C5),"",'ENGAGEMENTS 2026'!L5) -> Ordinaire | O5: =IF(ISBLANK('ENGAGEMENTS 2026'!C5),"",'ENGAGEMENTS 2026'!M5) -> FONCTIONNEMENT | P5: =IF(ISBLANK('ENGAGEMENTS 2026'!C5),"",'ENGAGEMENTS 2026'!K5) -> NON CONCERNE | Q5: =IF($A5="","",IF(OR($E5="INFRUCTUEUX",$E5="ANNULE"),$A5&"|"&(COUNTIFS($A$2:$A5,$A5,$E$2:$E5,"INFRUCTUEUX")+COUNTIFS($A$2:$A5,$A5,$E$2:$E5,"ANNULE")),""))
A6: =IF(ISBLANK('ENGAGEMENTS 2026'!C6),"",IF('ENGAGEMENTS 2026'!C6="DTSI","DCT",'ENGAGEMENTS 2026'!C6)) -> DCPA | B6: =IF(ISBLANK('ENGAGEMENTS 2026'!C6),"",'ENGAGEMENTS 2026'!D6) -> PV N° : 01RC2025- DCPA | C6: =IF(ISBLANK('ENGAGEMENTS 2026'!C6),"",'ENGAGEMENTS 2026'!E6) -> CONTRAT | D6: =IF(ISBLANK('ENGAGEMENTS 2026'!C6),"",'ENGAGEMENTS 2026'!G6) -> ACHABI MORAD - Préparation et animation de l'émission " مع الفاميلة" | E6: =IF(ISBLANK('ENGAGEMENTS 2026'!C6),"",'ENGAGEMENTS 2026'!I6) -> APPROUVE | F6: =IF(ISBLANK('ENGAGEMENTS 2026'!C6),"",'ENGAGEMENTS 2026'!J6) -> 187 CT/SNRT/2026 | G6: =IF(ISBLANK('ENGAGEMENTS 2026'!C6),"",'ENGAGEMENTS 2026'!M6) -> FONCTIONNEMENT | H6: =IF(ISBLANK('ENGAGEMENTS 2026'!C6),"",'ENGAGEMENTS 2026'!AF6) -> ENGAGE | I6: =IF(ISBLANK('ENGAGEMENTS 2026'!C6),"",'ENGAGEMENTS 2026'!H6) -> VALIDE | J6: =IF(ISBLANK('ENGAGEMENTS 2026'!C6),"",IF(AND(OR($E6="INFRUCTUEUX",$E6="ANNULE"),$C6="AOO-M"),'ENGAGEMENTS 2026'!P6,IF($H6="EN COURS DE PREENGAGEMENT",'ENGAGEMENTS 2026'!O6,IF($H6="PREENGAGE",IF($E6="ATTRIBUE",'ENGAGEMENTS 2026'!AE6,'ENGAGEMENTS 2026'!O6),'ENGAGEMENTS 2026'!AE6)))) -> 880000 | K6: =IF(ISBLANK('ENGAGEMENTS 2026'!W6),"",'ENGAGEMENTS 2026'!W6) -> 46387 | L6: =IF($K6="","",TODAY()-$K6) -> -99 | M6: =IF($A6="","",IF($H6="ENGAGE","Engagé",IF(AND($H6="NON ENGAGE",OR($I6="INFRUCTUEUX",$I6="ANNULE")),"Clôturé sans suite","En cours"))) -> Engagé | N6: =IF(ISBLANK('ENGAGEMENTS 2026'!C6),"",'ENGAGEMENTS 2026'!L6) -> Ordinaire | O6: =IF(ISBLANK('ENGAGEMENTS 2026'!C6),"",'ENGAGEMENTS 2026'!M6) -> FONCTIONNEMENT | P6: =IF(ISBLANK('ENGAGEMENTS 2026'!C6),"",'ENGAGEMENTS 2026'!K6) -> NON CONCERNE | Q6: =IF($A6="","",IF(OR($E6="INFRUCTUEUX",$E6="ANNULE"),$A6&"|"&(COUNTIFS($A$2:$A6,$A6,$E$2:$E6,"INFRUCTUEUX")+COUNTIFS($A$2:$A6,$A6,$E$2:$E6,"ANNULE")),""))
A7: =IF(ISBLANK('ENGAGEMENTS 2026'!C7),"",IF('ENGAGEMENTS 2026'!C7="DTSI","DCT",'ENGAGEMENTS 2026'!C7)) -> DCPA | B7: =IF(ISBLANK('ENGAGEMENTS 2026'!C7),"",'ENGAGEMENTS 2026'!D7) -> PV N° : 01RC2025- DCPA | C7: =IF(ISBLANK('ENGAGEMENTS 2026'!C7),"",'ENGAGEMENTS 2026'!E7) -> CONTRAT | D7: =IF(ISBLANK('ENGAGEMENTS 2026'!C7),"",'ENGAGEMENTS 2026'!G7) -> MOHAMED BOUMLI - Préparation de l'émission " مع الفاميلة" | E7: =IF(ISBLANK('ENGAGEMENTS 2026'!C7),"",'ENGAGEMENTS 2026'!I7) -> APPROUVE | F7: =IF(ISBLANK('ENGAGEMENTS 2026'!C7),"",'ENGAGEMENTS 2026'!J7) -> 188 CT/SNRT/2026 | G7: =IF(ISBLANK('ENGAGEMENTS 2026'!C7),"",'ENGAGEMENTS 2026'!M7) -> FONCTIONNEMENT | H7: =IF(ISBLANK('ENGAGEMENTS 2026'!C7),"",'ENGAGEMENTS 2026'!AF7) -> ENGAGE | I7: =IF(ISBLANK('ENGAGEMENTS 2026'!C7),"",'ENGAGEMENTS 2026'!H7) -> VALIDE | J7: =IF(ISBLANK('ENGAGEMENTS 2026'!C7),"",IF(AND(OR($E7="INFRUCTUEUX",$E7="ANNULE"),$C7="AOO-M"),'ENGAGEMENTS 2026'!P7,IF($H7="EN COURS DE PREENGAGEMENT",'ENGAGEMENTS 2026'!O7,IF($H7="PREENGAGE",IF($E7="ATTRIBUE",'ENGAGEMENTS 2026'!AE7,'ENGAGEMENTS 2026'!O7),'ENGAGEMENTS 2026'!AE7)))) -> 176000 | K7: =IF(ISBLANK('ENGAGEMENTS 2026'!W7),"",'ENGAGEMENTS 2026'!W7) -> 46387 | L7: =IF($K7="","",TODAY()-$K7) -> -99 | M7: =IF($A7="","",IF($H7="ENGAGE","Engagé",IF(AND($H7="NON ENGAGE",OR($I7="INFRUCTUEUX",$I7="ANNULE")),"Clôturé sans suite","En cours"))) -> Engagé | N7: =IF(ISBLANK('ENGAGEMENTS 2026'!C7),"",'ENGAGEMENTS 2026'!L7) -> Ordinaire | O7: =IF(ISBLANK('ENGAGEMENTS 2026'!C7),"",'ENGAGEMENTS 2026'!M7) -> FONCTIONNEMENT | P7: =IF(ISBLANK('ENGAGEMENTS 2026'!C7),"",'ENGAGEMENTS 2026'!K7) -> NON CONCERNE | Q7: =IF($A7="","",IF(OR($E7="INFRUCTUEUX",$E7="ANNULE"),$A7&"|"&(COUNTIFS($A$2:$A7,$A7,$E$2:$E7,"INFRUCTUEUX")+COUNTIFS($A$2:$A7,$A7,$E$2:$E7,"ANNULE")),""))
A8: =IF(ISBLANK('ENGAGEMENTS 2026'!C8),"",IF('ENGAGEMENTS 2026'!C8="DTSI","DCT",'ENGAGEMENTS 2026'!C8)) -> DCPA | B8: =IF(ISBLANK('ENGAGEMENTS 2026'!C8),"",'ENGAGEMENTS 2026'!D8) -> PV N° : 01RC2025- DCPA | C8: =IF(ISBLANK('ENGAGEMENTS 2026'!C8),"",'ENGAGEMENTS 2026'!E8) -> CONTRAT | D8: =IF(ISBLANK('ENGAGEMENTS 2026'!C8),"",'ENGAGEMENTS 2026'!G8) -> KABBAJ SEDDIK - Coordination, préparation et supervision artistique de l’émission " مدن عتيقة" | E8: =IF(ISBLANK('ENGAGEMENTS 2026'!C8),"",'ENGAGEMENTS 2026'!I8) -> APPROUVE | F8: =IF(ISBLANK('ENGAGEMENTS 2026'!C8),"",'ENGAGEMENTS 2026'!J8) -> 189 CT/SNRT/2026 | G8: =IF(ISBLANK('ENGAGEMENTS 2026'!C8),"",'ENGAGEMENTS 2026'!M8) -> FONCTIONNEMENT | H8: =IF(ISBLANK('ENGAGEMENTS 2026'!C8),"",'ENGAGEMENTS 2026'!AF8) -> ENGAGE | I8: =IF(ISBLANK('ENGAGEMENTS 2026'!C8),"",'ENGAGEMENTS 2026'!H8) -> VALIDE | J8: =IF(ISBLANK('ENGAGEMENTS 2026'!C8),"",IF(AND(OR($E8="INFRUCTUEUX",$E8="ANNULE"),$C8="AOO-M"),'ENGAGEMENTS 2026'!P8,IF($H8="EN COURS DE PREENGAGEMENT",'ENGAGEMENTS 2026'!O8,IF($H8="PREENGAGE",IF($E8="ATTRIBUE",'ENGAGEMENTS 2026'!AE8,'ENGAGEMENTS 2026'!O8),'ENGAGEMENTS 2026'!AE8)))) -> 342857 | K8: =IF(ISBLANK('ENGAGEMENTS 2026'!W8),"",'ENGAGEMENTS 2026'!W8) -> 46387 | L8: =IF($K8="","",TODAY()-$K8) -> -99 | M8: =IF($A8="","",IF($H8="ENGAGE","Engagé",IF(AND($H8="NON ENGAGE",OR($I8="INFRUCTUEUX",$I8="ANNULE")),"Clôturé sans suite","En cours"))) -> Engagé | N8: =IF(ISBLANK('ENGAGEMENTS 2026'!C8),"",'ENGAGEMENTS 2026'!L8) -> Ordinaire | O8: =IF(ISBLANK('ENGAGEMENTS 2026'!C8),"",'ENGAGEMENTS 2026'!M8) -> FONCTIONNEMENT | P8: =IF(ISBLANK('ENGAGEMENTS 2026'!C8),"",'ENGAGEMENTS 2026'!K8) -> NON CONCERNE | Q8: =IF($A8="","",IF(OR($E8="INFRUCTUEUX",$E8="ANNULE"),$A8&"|"&(COUNTIFS($A$2:$A8,$A8,$E$2:$E8,"INFRUCTUEUX")+COUNTIFS($A$2:$A8,$A8,$E$2:$E8,"ANNULE")),""))
A9: =IF(ISBLANK('ENGAGEMENTS 2026'!C9),"",IF('ENGAGEMENTS 2026'!C9="DTSI","DCT",'ENGAGEMENTS 2026'!C9)) -> ARRIYADIA | B9: =IF(ISBLANK('ENGAGEMENTS 2026'!C9),"",'ENGAGEMENTS 2026'!D9) -> PV N° : 01RC2025- DCCCA | C9: =IF(ISBLANK('ENGAGEMENTS 2026'!C9),"",'ENGAGEMENTS 2026'!E9) -> CONTRAT | D9: =IF(ISBLANK('ENGAGEMENTS 2026'!C9),"",'ENGAGEMENTS 2026'!G9) -> BELMAHEDI MOHAMED - Cadreur plateau | E9: =IF(ISBLANK('ENGAGEMENTS 2026'!C9),"",'ENGAGEMENTS 2026'!I9) -> APPROUVE | F9: =IF(ISBLANK('ENGAGEMENTS 2026'!C9),"",'ENGAGEMENTS 2026'!J9) -> 0 | G9: =IF(ISBLANK('ENGAGEMENTS 2026'!C9),"",'ENGAGEMENTS 2026'!M9) -> FONCTIONNEMENT | H9: =IF(ISBLANK('ENGAGEMENTS 2026'!C9),"",'ENGAGEMENTS 2026'!AF9) -> ENGAGE | I9: =IF(ISBLANK('ENGAGEMENTS 2026'!C9),"",'ENGAGEMENTS 2026'!H9) -> VALIDE | J9: =IF(ISBLANK('ENGAGEMENTS 2026'!C9),"",IF(AND(OR($E9="INFRUCTUEUX",$E9="ANNULE"),$C9="AOO-M"),'ENGAGEMENTS 2026'!P9,IF($H9="EN COURS DE PREENGAGEMENT",'ENGAGEMENTS 2026'!O9,IF($H9="PREENGAGE",IF($E9="ATTRIBUE",'ENGAGEMENTS 2026'!AE9,'ENGAGEMENTS 2026'!O9),'ENGAGEMENTS 2026'!AE9)))) -> 113142.48 | K9: =IF(ISBLANK('ENGAGEMENTS 2026'!W9),"",'ENGAGEMENTS 2026'!W9) -> 46022 | L9: =IF($K9="","",TODAY()-$K9) -> 266 | M9: =IF($A9="","",IF($H9="ENGAGE","Engagé",IF(AND($H9="NON ENGAGE",OR($I9="INFRUCTUEUX",$I9="ANNULE")),"Clôturé sans suite","En cours"))) -> Engagé | N9: =IF(ISBLANK('ENGAGEMENTS 2026'!C9),"",'ENGAGEMENTS 2026'!L9) -> Ordinaire | O9: =IF(ISBLANK('ENGAGEMENTS 2026'!C9),"",'ENGAGEMENTS 2026'!M9) -> FONCTIONNEMENT | P9: =IF(ISBLANK('ENGAGEMENTS 2026'!C9),"",'ENGAGEMENTS 2026'!K9) -> NON CONCERNE | Q9: =IF($A9="","",IF(OR($E9="INFRUCTUEUX",$E9="ANNULE"),$A9&"|"&(COUNTIFS($A$2:$A9,$A9,$E$2:$E9,"INFRUCTUEUX")+COUNTIFS($A$2:$A9,$A9,$E$2:$E9,"ANNULE")),""))
A10: =IF(ISBLANK('ENGAGEMENTS 2026'!C10),"",IF('ENGAGEMENTS 2026'!C10="DTSI","DCT",'ENGAGEMENTS 2026'!C10)) -> ARRIYADIA | B10: =IF(ISBLANK('ENGAGEMENTS 2026'!C10),"",'ENGAGEMENTS 2026'!D10) -> PV N° : 01RC2025- DCCCA | C10: =IF(ISBLANK('ENGAGEMENTS 2026'!C10),"",'ENGAGEMENTS 2026'!E10) -> CONTRAT | D10: =IF(ISBLANK('ENGAGEMENTS 2026'!C10),"",'ENGAGEMENTS 2026'!G10) -> BIOUD ABDELHAK – Cadreur plateau | E10: =IF(ISBLANK('ENGAGEMENTS 2026'!C10),"",'ENGAGEMENTS 2026'!I10) -> APPROUVE | F10: =IF(ISBLANK('ENGAGEMENTS 2026'!C10),"",'ENGAGEMENTS 2026'!J10) -> 0 | G10: =IF(ISBLANK('ENGAGEMENTS 2026'!C10),"",'ENGAGEMENTS 2026'!M10) -> FONCTIONNEMENT | H10: =IF(ISBLANK('ENGAGEMENTS 2026'!C10),"",'ENGAGEMENTS 2026'!AF10) -> ENGAGE | I10: =IF(ISBLANK('ENGAGEMENTS 2026'!C10),"",'ENGAGEMENTS 2026'!H10) -> VALIDE | J10: =IF(ISBLANK('ENGAGEMENTS 2026'!C10),"",IF(AND(OR($E10="INFRUCTUEUX",$E10="ANNULE"),$C10="AOO-M"),'ENGAGEMENTS 2026'!P10,IF($H10="EN COURS DE PREENGAGEMENT",'ENGAGEMENTS 2026'!O10,IF($H10="PREENGAGE",IF($E10="ATTRIBUE",'ENGAGEMENTS 2026'!AE10,'ENGAGEMENTS 2026'!O10),'ENGAGEMENTS 2026'!AE10)))) -> 113142.48 | K10: =IF(ISBLANK('ENGAGEMENTS 2026'!W10),"",'ENGAGEMENTS 2026'!W10) -> 46022 | L10: =IF($K10="","",TODAY()-$K10) -> 266 | M10: =IF($A10="","",IF($H10="ENGAGE","Engagé",IF(AND($H10="NON ENGAGE",OR($I10="INFRUCTUEUX",$I10="ANNULE")),"Clôturé sans suite","En cours"))) -> Engagé | N10: =IF(ISBLANK('ENGAGEMENTS 2026'!C10),"",'ENGAGEMENTS 2026'!L10) -> Ordinaire | O10: =IF(ISBLANK('ENGAGEMENTS 2026'!C10),"",'ENGAGEMENTS 2026'!M10) -> FONCTIONNEMENT | P10: =IF(ISBLANK('ENGAGEMENTS 2026'!C10),"",'ENGAGEMENTS 2026'!K10) -> NON CONCERNE | Q10: =IF($A10="","",IF(OR($E10="INFRUCTUEUX",$E10="ANNULE"),$A10&"|"&(COUNTIFS($A$2:$A10,$A10,$E$2:$E10,"INFRUCTUEUX")+COUNTIFS($A$2:$A10,$A10,$E$2:$E10,"ANNULE")),""))
A11: =IF(ISBLANK('ENGAGEMENTS 2026'!C11),"",IF('ENGAGEMENTS 2026'!C11="DTSI","DCT",'ENGAGEMENTS 2026'!C11)) -> ARRIYADIA | B11: =IF(ISBLANK('ENGAGEMENTS 2026'!C11),"",'ENGAGEMENTS 2026'!D11) -> PV N° : 01RC2025- DCCCA | C11: =IF(ISBLANK('ENGAGEMENTS 2026'!C11),"",'ENGAGEMENTS 2026'!E11) -> CONTRAT | D11: =IF(ISBLANK('ENGAGEMENTS 2026'!C11),"",'ENGAGEMENTS 2026'!G11) -> IHAB JAMAL EDDINE - Cadreur plateau | E11: =IF(ISBLANK('ENGAGEMENTS 2026'!C11),"",'ENGAGEMENTS 2026'!I11) -> APPROUVE | F11: =IF(ISBLANK('ENGAGEMENTS 2026'!C11),"",'ENGAGEMENTS 2026'!J11) -> 0 | G11: =IF(ISBLANK('ENGAGEMENTS 2026'!C11),"",'ENGAGEMENTS 2026'!M11) -> FONCTIONNEMENT | H11: =IF(ISBLANK('ENGAGEMENTS 2026'!C11),"",'ENGAGEMENTS 2026'!AF11) -> ENGAGE | I11: =IF(ISBLANK('ENGAGEMENTS 2026'!C11),"",'ENGAGEMENTS 2026'!H11) -> VALIDE | J11: =IF(ISBLANK('ENGAGEMENTS 2026'!C11),"",IF(AND(OR($E11="INFRUCTUEUX",$E11="ANNULE"),$C11="AOO-M"),'ENGAGEMENTS 2026'!P11,IF($H11="EN COURS DE PREENGAGEMENT",'ENGAGEMENTS 2026'!O11,IF($H11="PREENGAGE",IF($E11="ATTRIBUE",'ENGAGEMENTS 2026'!AE11,'ENGAGEMENTS 2026'!O11),'ENGAGEMENTS 2026'!AE11)))) -> 113142.48 | K11: =IF(ISBLANK('ENGAGEMENTS 2026'!W11),"",'ENGAGEMENTS 2026'!W11) -> 46022 | L11: =IF($K11="","",TODAY()-$K11) -> 266 | M11: =IF($A11="","",IF($H11="ENGAGE","Engagé",IF(AND($H11="NON ENGAGE",OR($I11="INFRUCTUEUX",$I11="ANNULE")),"Clôturé sans suite","En cours"))) -> Engagé | N11: =IF(ISBLANK('ENGAGEMENTS 2026'!C11),"",'ENGAGEMENTS 2026'!L11) -> Ordinaire | O11: =IF(ISBLANK('ENGAGEMENTS 2026'!C11),"",'ENGAGEMENTS 2026'!M11) -> FONCTIONNEMENT | P11: =IF(ISBLANK('ENGAGEMENTS 2026'!C11),"",'ENGAGEMENTS 2026'!K11) -> NON CONCERNE | Q11: =IF($A11="","",IF(OR($E11="INFRUCTUEUX",$E11="ANNULE"),$A11&"|"&(COUNTIFS($A$2:$A11,$A11,$E$2:$E11,"INFRUCTUEUX")+COUNTIFS($A$2:$A11,$A11,$E$2:$E11,"ANNULE")),""))
A12: =IF(ISBLANK('ENGAGEMENTS 2026'!C12),"",IF('ENGAGEMENTS 2026'!C12="DTSI","DCT",'ENGAGEMENTS 2026'!C12)) -> ARRIYADIA | B12: =IF(ISBLANK('ENGAGEMENTS 2026'!C12),"",'ENGAGEMENTS 2026'!D12) -> PV N° : 01RC2025- DCCCA | C12: =IF(ISBLANK('ENGAGEMENTS 2026'!C12),"",'ENGAGEMENTS 2026'!E12) -> CONTRAT | D12: =IF(ISBLANK('ENGAGEMENTS 2026'!C12),"",'ENGAGEMENTS 2026'!G12) -> YOUSSEF JOUMARI - Cadreur plateau | E12: =IF(ISBLANK('ENGAGEMENTS 2026'!C12),"",'ENGAGEMENTS 2026'!I12) -> APPROUVE | F12: =IF(ISBLANK('ENGAGEMENTS 2026'!C12),"",'ENGAGEMENTS 2026'!J12) -> 0 | G12: =IF(ISBLANK('ENGAGEMENTS 2026'!C12),"",'ENGAGEMENTS 2026'!M12) -> FONCTIONNEMENT | H12: =IF(ISBLANK('ENGAGEMENTS 2026'!C12),"",'ENGAGEMENTS 2026'!AF12) -> ENGAGE | I12: =IF(ISBLANK('ENGAGEMENTS 2026'!C12),"",'ENGAGEMENTS 2026'!H12) -> VALIDE | J12: =IF(ISBLANK('ENGAGEMENTS 2026'!C12),"",IF(AND(OR($E12="INFRUCTUEUX",$E12="ANNULE"),$C12="AOO-M"),'ENGAGEMENTS 2026'!P12,IF($H12="EN COURS DE PREENGAGEMENT",'ENGAGEMENTS 2026'!O12,IF($H12="PREENGAGE",IF($E12="ATTRIBUE",'ENGAGEMENTS 2026'!AE12,'ENGAGEMENTS 2026'!O12),'ENGAGEMENTS 2026'!AE12)))) -> 113142.48 | K12: =IF(ISBLANK('ENGAGEMENTS 2026'!W12),"",'ENGAGEMENTS 2026'!W12) -> 46022 | L12: =IF($K12="","",TODAY()-$K12) -> 266 | M12: =IF($A12="","",IF($H12="ENGAGE","Engagé",IF(AND($H12="NON ENGAGE",OR($I12="INFRUCTUEUX",$I12="ANNULE")),"Clôturé sans suite","En cours"))) -> Engagé | N12: =IF(ISBLANK('ENGAGEMENTS 2026'!C12),"",'ENGAGEMENTS 2026'!L12) -> Ordinaire | O12: =IF(ISBLANK('ENGAGEMENTS 2026'!C12),"",'ENGAGEMENTS 2026'!M12) -> FONCTIONNEMENT | P12: =IF(ISBLANK('ENGAGEMENTS 2026'!C12),"",'ENGAGEMENTS 2026'!K12) -> NON CONCERNE | Q12: =IF($A12="","",IF(OR($E12="INFRUCTUEUX",$E12="ANNULE"),$A12&"|"&(COUNTIFS($A$2:$A12,$A12,$E$2:$E12,"INFRUCTUEUX")+COUNTIFS($A$2:$A12,$A12,$E$2:$E12,"ANNULE")),""))
A13: =IF(ISBLANK('ENGAGEMENTS 2026'!C13),"",IF('ENGAGEMENTS 2026'!C13="DTSI","DCT",'ENGAGEMENTS 2026'!C13)) -> ARRIYADIA | B13: =IF(ISBLANK('ENGAGEMENTS 2026'!C13),"",'ENGAGEMENTS 2026'!D13) -> PV N° : 01RC2025- DCCCA | C13: =IF(ISBLANK('ENGAGEMENTS 2026'!C13),"",'ENGAGEMENTS 2026'!E13) -> CONTRAT | D13: =IF(ISBLANK('ENGAGEMENTS 2026'!C13),"",'ENGAGEMENTS 2026'!G13) -> MUSTAPHA SKALLI - Cadreur plateau | E13: =IF(ISBLANK('ENGAGEMENTS 2026'!C13),"",'ENGAGEMENTS 2026'!I13) -> APPROUVE | F13: =IF(ISBLANK('ENGAGEMENTS 2026'!C13),"",'ENGAGEMENTS 2026'!J13) -> 0 | G13: =IF(ISBLANK('ENGAGEMENTS 2026'!C13),"",'ENGAGEMENTS 2026'!M13) -> FONCTIONNEMENT | H13: =IF(ISBLANK('ENGAGEMENTS 2026'!C13),"",'ENGAGEMENTS 2026'!AF13) -> ENGAGE | I13: =IF(ISBLANK('ENGAGEMENTS 2026'!C13),"",'ENGAGEMENTS 2026'!H13) -> VALIDE | J13: =IF(ISBLANK('ENGAGEMENTS 2026'!C13),"",IF(AND(OR($E13="INFRUCTUEUX",$E13="ANNULE"),$C13="AOO-M"),'ENGAGEMENTS 2026'!P13,IF($H13="EN COURS DE PREENGAGEMENT",'ENGAGEMENTS 2026'!O13,IF($H13="PREENGAGE",IF($E13="ATTRIBUE",'ENGAGEMENTS 2026'!AE13,'ENGAGEMENTS 2026'!O13),'ENGAGEMENTS 2026'!AE13)))) -> 113142.48 | K13: =IF(ISBLANK('ENGAGEMENTS 2026'!W13),"",'ENGAGEMENTS 2026'!W13) -> 46022 | L13: =IF($K13="","",TODAY()-$K13) -> 266 | M13: =IF($A13="","",IF($H13="ENGAGE","Engagé",IF(AND($H13="NON ENGAGE",OR($I13="INFRUCTUEUX",$I13="ANNULE")),"Clôturé sans suite","En cours"))) -> Engagé | N13: =IF(ISBLANK('ENGAGEMENTS 2026'!C13),"",'ENGAGEMENTS 2026'!L13) -> Ordinaire | O13: =IF(ISBLANK('ENGAGEMENTS 2026'!C13),"",'ENGAGEMENTS 2026'!M13) -> FONCTIONNEMENT | P13: =IF(ISBLANK('ENGAGEMENTS 2026'!C13),"",'ENGAGEMENTS 2026'!K13) -> NON CONCERNE | Q13: =IF($A13="","",IF(OR($E13="INFRUCTUEUX",$E13="ANNULE"),$A13&"|"&(COUNTIFS($A$2:$A13,$A13,$E$2:$E13,"INFRUCTUEUX")+COUNTIFS($A$2:$A13,$A13,$E$2:$E13,"ANNULE")),""))
... A685: =IF(ISBLANK('ENGAGEMENTS 2026'!C685),"",IF('ENGAGEMENTS 2026'!C685="DTSI","DCT",'ENGAGEMENTS 2026'!C685)) -> DCT | B685: =IF(ISBLANK('ENGAGEMENTS 2026'!C685),"",'ENGAGEMENTS 2026'!D685) -> 69AOM/SNRT/2026 | C685: =IF(ISBLANK('ENGAGEMENTS 2026'!C685),"",'ENGAGEMENTS 2026'!E685) -> AOO-M | D685: =IF(ISBLANK('ENGAGEMENTS 2026'!C685),"",'ENGAGEMENTS 2026'!G685) -> Aquisition d'un porteur pré-câblé multi-caméras pour les besoins des moyens mobiles de la SNRT | E685: =IF(ISBLANK('ENGAGEMENTS 2026'!C685),"",'ENGAGEMENTS 2026'!I685) -> EN SIGNATURE | F685: =IF(ISBLANK('ENGAGEMENTS 2026'!C685),"",'ENGAGEMENTS 2026'!J685) -> 0 | G685: =IF(ISBLANK('ENGAGEMENTS 2026'!C685),"",'ENGAGEMENTS 2026'!M685) -> INVESTISSEMENT | H685: =IF(ISBLANK('ENGAGEMENTS 2026'!C685),"",'ENGAGEMENTS 2026'!AF685) -> EN COURS DE PREENGAGEMENT | I685: =IF(ISBLANK('ENGAGEMENTS 2026'!C685),"",'ENGAGEMENTS 2026'!H685) -> EN SIGNATURE | J685: =IF(ISBLANK('ENGAGEMENTS 2026'!C685),"",IF(AND(OR($E685="INFRUCTUEUX",$E685="ANNULE"),$C685="AOO-M"),'ENGAGEMENTS 2026'!P685,IF($H685="EN COURS DE PREENGAGEMENT",'ENGAGEMENTS 2026'!O685,IF($H685="PREENGAGE",IF($E685="ATTRIBUE",'ENGAGEMENTS 2026'!AE685,'ENGAGEMENTS 2026'!O685),'ENGAGEMENTS 2026'!AE685)))) -> 11556000 | K685: =IF(ISBLANK('ENGAGEMENTS 2026'!W685),"",'ENGAGEMENTS 2026'!W685) | L685: =IF($K685="","",TODAY()-$K685) | M685: =IF($A685="","",IF($H685="ENGAGE","Engagé",IF(AND($H685="NON ENGAGE",OR($I685="INFRUCTUEUX",$I685="ANNULE")),"Clôturé sans suite","En cours"))) -> En cours | N685: =IF(ISBLANK('ENGAGEMENTS 2026'!C685),"",'ENGAGEMENTS 2026'!L685) -> REPORT BUDGET EXCEP ANNEE ANTERIEURE | O685: =IF(ISBLANK('ENGAGEMENTS 2026'!C685),"",'ENGAGEMENTS 2026'!M685) -> INVESTISSEMENT | P685: =IF(ISBLANK('ENGAGEMENTS 2026'!C685),"",'ENGAGEMENTS 2026'!K685) -> GENERAL | Q685: =IF($A685="","",IF(OR($E685="INFRUCTUEUX",$E685="ANNULE"),$A685&"|"&(COUNTIFS($A$2:$A685,$A685,$E$2:$E685,"INFRUCTUEUX")+COUNTIFS($A$2:$A685,$A685,$E$2:$E685,"ANNULE")),""))
A686: =IF(ISBLANK('ENGAGEMENTS 2026'!C687),"",IF('ENGAGEMENTS 2026'!C687="DTSI","DCT",'ENGAGEMENTS 2026'!C687)) | B686: =IF(ISBLANK('ENGAGEMENTS 2026'!C687),"",'ENGAGEMENTS 2026'!D687) | C686: =IF(ISBLANK('ENGAGEMENTS 2026'!C687),"",'ENGAGEMENTS 2026'!E687) | D686: =IF(ISBLANK('ENGAGEMENTS 2026'!C687),"",'ENGAGEMENTS 2026'!G687) | E686: =IF(ISBLANK('ENGAGEMENTS 2026'!C687),"",'ENGAGEMENTS 2026'!I687) | F686: =IF(ISBLANK('ENGAGEMENTS 2026'!C687),"",'ENGAGEMENTS 2026'!J687) | G686: =IF(ISBLANK('ENGAGEMENTS 2026'!C687),"",'ENGAGEMENTS 2026'!M687) | H686: =IF(ISBLANK('ENGAGEMENTS 2026'!C687),"",'ENGAGEMENTS 2026'!AF687) | I686: =IF(ISBLANK('ENGAGEMENTS 2026'!C687),"",'ENGAGEMENTS 2026'!H687) | J686: =IF(ISBLANK('ENGAGEMENTS 2026'!C687),"",IF(AND(OR($E686="INFRUCTUEUX",$E686="ANNULE"),$C686="AOO-M"),'ENGAGEMENTS 2026'!P687,IF($H686="EN COURS DE PREENGAGEMENT",'ENGAGEMENTS 2026'!O687,IF($H686="PREENGAGE",IF($E686="ATTRIBUE",'ENGAGEMENTS 2026'!AE687,'ENGAGEMENTS 2026'!O687),'ENGAGEMENTS 2026'!AE687)))) | K686: =IF(ISBLANK('ENGAGEMENTS 2026'!W687),"",'ENGAGEMENTS 2026'!W687) | L686: =IF($K686="","",TODAY()-$K686) | M686: =IF($A686="","",IF($H686="ENGAGE","Engagé",IF(AND($H686="NON ENGAGE",OR($I686="INFRUCTUEUX",$I686="ANNULE")),"Clôturé sans suite","En cours"))) | N686: =IF(ISBLANK('ENGAGEMENTS 2026'!C687),"",'ENGAGEMENTS 2026'!L687) | O686: =IF(ISBLANK('ENGAGEMENTS 2026'!C687),"",'ENGAGEMENTS 2026'!M687) | P686: =IF(ISBLANK('ENGAGEMENTS 2026'!C687),"",'ENGAGEMENTS 2026'!K687) | Q686: =IF($A686="","",IF(OR($E686="INFRUCTUEUX",$E686="ANNULE"),$A686&"|"&(COUNTIFS($A$2:$A686,$A686,$E$2:$E686,"INFRUCTUEUX")+COUNTIFS($A$2:$A686,$A686,$E$2:$E686,"ANNULE")),""))
A687: =IF(ISBLANK('ENGAGEMENTS 2026'!C688),"",IF('ENGAGEMENTS 2026'!C688="DTSI","DCT",'ENGAGEMENTS 2026'!C688)) | B687: =IF(ISBLANK('ENGAGEMENTS 2026'!C688),"",'ENGAGEMENTS 2026'!D688) | C687: =IF(ISBLANK('ENGAGEMENTS 2026'!C688),"",'ENGAGEMENTS 2026'!E688) | D687: =IF(ISBLANK('ENGAGEMENTS 2026'!C688),"",'ENGAGEMENTS 2026'!G688) | E687: =IF(ISBLANK('ENGAGEMENTS 2026'!C688),"",'ENGAGEMENTS 2026'!I688) | F687: =IF(ISBLANK('ENGAGEMENTS 2026'!C688),"",'ENGAGEMENTS 2026'!J688) | G687: =IF(ISBLANK('ENGAGEMENTS 2026'!C688),"",'ENGAGEMENTS 2026'!M688) | H687: =IF(ISBLANK('ENGAGEMENTS 2026'!C688),"",'ENGAGEMENTS 2026'!AF688) | I687: =IF(ISBLANK('ENGAGEMENTS 2026'!C688),"",'ENGAGEMENTS 2026'!H688) | J687: =IF(ISBLANK('ENGAGEMENTS 2026'!C688),"",IF(AND(OR($E687="INFRUCTUEUX",$E687="ANNULE"),$C687="AOO-M"),'ENGAGEMENTS 2026'!P688,IF($H687="EN COURS DE PREENGAGEMENT",'ENGAGEMENTS 2026'!O688,IF($H687="PREENGAGE",IF($E687="ATTRIBUE",'ENGAGEMENTS 2026'!AE688,'ENGAGEMENTS 2026'!O688),'ENGAGEMENTS 2026'!AE688)))) | K687: =IF(ISBLANK('ENGAGEMENTS 2026'!W688),"",'ENGAGEMENTS 2026'!W688) | L687: =IF($K687="","",TODAY()-$K687) | M687: =IF($A687="","",IF($H687="ENGAGE","Engagé",IF(AND($H687="NON ENGAGE",OR($I687="INFRUCTUEUX",$I687="ANNULE")),"Clôturé sans suite","En cours"))) | N687: =IF(ISBLANK('ENGAGEMENTS 2026'!C688),"",'ENGAGEMENTS 2026'!L688) | O687: =IF(ISBLANK('ENGAGEMENTS 2026'!C688),"",'ENGAGEMENTS 2026'!M688) | P687: =IF(ISBLANK('ENGAGEMENTS 2026'!C688),"",'ENGAGEMENTS 2026'!K688) | Q687: =IF($A687="","",IF(OR($E687="INFRUCTUEUX",$E687="ANNULE"),$A687&"|"&(COUNTIFS($A$2:$A687,$A687,$E$2:$E687,"INFRUCTUEUX")+COUNTIFS($A$2:$A687,$A687,$E$2:$E687,"ANNULE")),""))
