Workbook
Name ANN: Parametres!$A$116
Name ATR: Parametres!$A$129
Name BDG_DIR: #REF!
Name BDG_FAM: #REF!
Name BDG_MNT: #REF!
Name BDG_NAT: #REF!
Name BUDGET: 'ENGAGEMENTS 2026'!$L:$L
Name cc: Parametres!$A$80:$A$94
Name DIRECTION: #REF!
Name ENGAGE: Parametres!$A$99
Name Estimation: 'ENGAGEMENTS 2026'!$O:$O
Name Excep: Parametres!$A$5
Name FON: Parametres!$A$7
Name FONCTIONNEMENT: Parametres!$A$10:$A$32
Name INF: Parametres!$A$115
Name INV: Parametres!$A$8
Name INVESTISSEMENT: Parametres!$A$34:$A$44
Name LBDG: 'ENGAGEMENTS 2026'!$M:$M
Name MntENG: 'ENGAGEMENTS 2026'!$AD:$AD
Name MTP: Parametres!$B$48
Name MTT: Parametres!$B$46
Name NA: Parametres!$A$113
Name Ordn: Parametres!$A$4
Name PhaAo: Parametres!$A$134
Name PREENGAGE: Parametres!$A$97
Name qq: Parametres!$A$80:$A$94
Name SSENG: #REF!
Name StatutEng: 'ENGAGEMENTS 2026'!$AE:$AE
Name TypBudget: Parametres!$A$2:$A$5
Name TypeBudget: 'ENGAGEMENTS 2026'!$K:$K
Name xBesoin: Parametres!$A$146:$A$149
Name xBUDGET: Parametres!$A$7:$A$8
Name xCATEGORIES: Parametres!$A$137:$A$139
Name xDIRECTION: Parametres!$A$51:$A$78
Name xENG: Parametres!$A$99
Name XLB: Parametres!$A$80:$A$94
Name xNatype: Parametres!$A$142:$A$144
Name xRec: Parametres!$A$149
Name xStatut1: Parametres!$A$113:$A$118
Name xSTATUTSUP: Parametres!$A$128:$A$135
Name xStEng: Parametres!$A$96:$A$100
Name xTYPE1: Parametres!$A$102:$A$111
Name xTYPSUP: Parametres!$A$120:$A$126

Sheet Tableau de Bord
A1: TABLEAU DE BORD DES ENGAGEMENTS BUDGÉTAIRES 2026 — SNRT
A2: Montants en MAD TTC — calculés dynamiquement (SUMIFS) depuis la feuille « Données Suivi »
A3: DIRECTION | B3: FONCTIONNEMENT | H3: INVESTISSEMENT | N3: TOTAL GÉNÉRAL
B4: ENGAGE | C4: PREENGAGE | D4: EN COURS D'ENGAGEMENT | E4: EN COURS DE PREENGAGEMENT | F4: NON ENGAGE | G4: TOTAL FONC. | H4: ENGAGE | I4: PREENGAGE | J4: EN COURS D'ENGAGEMENT | K4: EN COURS DE PREENGAGEMENT | L4: NON ENGAGE | M4: TOTAL INVE.
A5: ARRIYADIA | B5: =SUMIFS('Données Suivi'!$J$2:$J$3000,'Données Suivi'!$A$2:$A$3000,$A5,'Données Suivi'!$O$2:$O$3000,"FONCTIONNEMENT",'Données Suivi'!$H$2:$H$3000,"ENGAGE") | C5: =SUMIFS('Données Suivi'!$J$2:$J$3000,'Données Suivi'!$A$2:$A$3000,$A5,'Données Suivi'!$O$2:$O$3000,"FONCTIONNEMENT",'Données Suivi'!$H$2:$H$3000,"PREENGAGE") | D5: =SUMIFS('Données Suivi'!$J$2:$J$3000,'Données Suivi'!$A$2:$A$3000,$A5,'Données Suivi'!$O$2:$O$3000,"FONCTIONNEMENT",'Données Suivi'!$H$2:$H$3000,"EN COURS D'ENGAGEMENT") | E5: =SUMIFS('Données Suivi'!$J$2:$J$3000,'Données Suivi'!$A$2:$A$3000,$A5,'Données Suivi'!$O$2:$O$3000,"FONCTIONNEMENT",'Données Suivi'!$H$2:$H$3000,"EN COURS DE PREENGAGEMENT") | F5: =SUMIFS('Données Suivi'!$J$2:$J$3000,'Données Suivi'!$A$2:$A$3000,$A5,'Données Suivi'!$O$2:$O$3000,"FONCTIONNEMENT",'Données Suivi'!$H$2:$H$3000,"NON ENGAGE") | G5: =B5+C5+D5+E5+F5 | H5: =SUMIFS('Données Suivi'!$J$2:$J$3000,'Données Suivi'!$A$2:$A$3000,$A5,'Données Suivi'!$O$2:$O$3000,"INVESTISSEMENT",'Données Suivi'!$H$2:$H$3000,"ENGAGE") | I5: =SUMIFS('Données Suivi'!$J$2:$J$3000,'Données Suivi'!$A$2:$A$3000,$A5,'Données Suivi'!$O$2:$O$3000,"INVESTISSEMENT",'Données Suivi'!$H$2:$H$3000,"PREENGAGE") | J5: =SUMIFS('Données Suivi'!$J$2:$J$3000,'Données Suivi'!$A$2:$A$3000,$A5,'Données Suivi'!$O$2:$O$3000,"INVESTISSEMENT",'Données Suivi'!$H$2:$H$3000,"EN COURS D'ENGAGEMENT") | K5: =SUMIFS('Données Suivi'!$J$2:$J$3000,'Données Suivi'!$A$2:$A$3000,$A5,'Données Suivi'!$O$2:$O$3000,"INVESTISSEMENT",'Données Suivi'!$H$2:$H$3000,"EN COURS DE PREENGAGEMENT") | L5: =SUMIFS('Données Suivi'!$J$2:$J$3000,'Données Suivi'!$A$2:$A$3000,$A5,'Données Suivi'!$O$2:$O$3000,"INVESTISSEMENT",'Données Suivi'!$H$2:$H$3000,"NON ENGAGE") | M5: =H5+I5+J5+K5+L5 | N5: =G5+M5
A6: ASSADISSA | B6: =SUMIFS('Données Suivi'!$J$2:$J$3000,'Données Suivi'!$A$2:$A$3000,$A6,'Données Suivi'!$O$2:$O$3000,"FONCTIONNEMENT",'Données Suivi'!$H$2:$H$3000,"ENGAGE") | C6: =SUMIFS('Données Suivi'!$J$2:$J$3000,'Données Suivi'!$A$2:$A$3000,$A6,'Données Suivi'!$O$2:$O$3000,"FONCTIONNEMENT",'Données Suivi'!$H$2:$H$3000,"PREENGAGE") | D6: =SUMIFS('Données Suivi'!$J$2:$J$3000,'Données Suivi'!$A$2:$A$3000,$A6,'Données Suivi'!$O$2:$O$3000,"FONCTIONNEMENT",'Données Suivi'!$H$2:$H$3000,"EN COURS D'ENGAGEMENT") | E6: =SUMIFS('Données Suivi'!$J$2:$J$3000,'Données Suivi'!$A$2:$A$3000,$A6,'Données Suivi'!$O$2:$O$3000,"FONCTIONNEMENT",'Données Suivi'!$H$2:$H$3000,"EN COURS DE PREENGAGEMENT") | F6: =SUMIFS('Données Suivi'!$J$2:$J$3000,'Données Suivi'!$A$2:$A$3000,$A6,'Données Suivi'!$O$2:$O$3000,"FONCTIONNEMENT",'Données Suivi'!$H$2:$H$3000,"NON ENGAGE") | G6: =B6+C6+D6+E6+F6 | H6: =SUMIFS('Données Suivi'!$J$2:$J$3000,'Données Suivi'!$A$2:$A$3000,$A6,'Données Suivi'!$O$2:$O$3000,"INVESTISSEMENT",'Données Suivi'!$H$2:$H$3000,"ENGAGE") | I6: =SUMIFS('Données Suivi'!$J$2:$J$3000,'Données Suivi'!$A$2:$A$3000,$A6,'Données Suivi'!$O$2:$O$3000,"INVESTISSEMENT",'Données Suivi'!$H$2:$H$3000,"PREENGAGE") | J6: =SUMIFS('Données Suivi'!$J$2:$J$3000,'Données Suivi'!$A$2:$A$3000,$A6,'Données Suivi'!$O$2:$O$3000,"INVESTISSEMENT",'Données Suivi'!$H$2:$H$3000,"EN COURS D'ENGAGEMENT") | K6: =SUMIFS('Données Suivi'!$J$2:$J$3000,'Données Suivi'!$A$2:$A$3000,$A6,'Données Suivi'!$O$2:$O$3000,"INVESTISSEMENT",'Données Suivi'!$H$2:$H$3000,"EN COURS DE PREENGAGEMENT") | L6: =SUMIFS('Données Suivi'!$J$2:$J$3000,'Données Suivi'!$A$2:$A$3000,$A6,'Données Suivi'!$O$2:$O$3000,"INVESTISSEMENT",'Données Suivi'!$H$2:$H$3000,"NON ENGAGE") | M6: =H6+I6+J6+K6+L6 | N6: =G6+M6
A7: DA | B7: =SUMIFS('Données Suivi'!$J$2:$J$3000,'Données Suivi'!$A$2:$A$3000,$A7,'Données Suivi'!$O$2:$O$3000,"FONCTIONNEMENT",'Données Suivi'!$H$2:$H$3000,"ENGAGE") | C7: =SUMIFS('Données Suivi'!$J$2:$J$3000,'Données Suivi'!$A$2:$A$3000,$A7,'Données Suivi'!$O$2:$O$3000,"FONCTIONNEMENT",'Données Suivi'!$H$2:$H$3000,"PREENGAGE") | D7: =SUMIFS('Données Suivi'!$J$2:$J$3000,'Données Suivi'!$A$2:$A$3000,$A7,'Données Suivi'!$O$2:$O$3000,"FONCTIONNEMENT",'Données Suivi'!$H$2:$H$3000,"EN COURS D'ENGAGEMENT") | E7: =SUMIFS('Données Suivi'!$J$2:$J$3000,'Données Suivi'!$A$2:$A$3000,$A7,'Données Suivi'!$O$2:$O$3000,"FONCTIONNEMENT",'Données Suivi'!$H$2:$H$3000,"EN COURS DE PREENGAGEMENT") | F7: =SUMIFS('Données Suivi'!$J$2:$J$3000,'Données Suivi'!$A$2:$A$3000,$A7,'Données Suivi'!$O$2:$O$3000,"FONCTIONNEMENT",'Données Suivi'!$H$2:$H$3000,"NON ENGAGE") | G7: =B7+C7+D7+E7+F7 | H7: =SUMIFS('Données Suivi'!$J$2:$J$3000,'Données Suivi'!$A$2:$A$3000,$A7,'Données Suivi'!$O$2:$O$3000,"INVESTISSEMENT",'Données Suivi'!$H$2:$H$3000,"ENGAGE") | I7: =SUMIFS('Données Suivi'!$J$2:$J$3000,'Données Suivi'!$A$2:$A$3000,$A7,'Données Suivi'!$O$2:$O$3000,"INVESTISSEMENT",'Données Suivi'!$H$2:$H$3000,"PREENGAGE") | J7: =SUMIFS('Données Suivi'!$J$2:$J$3000,'Données Suivi'!$A$2:$A$3000,$A7,'Données Suivi'!$O$2:$O$3000,"INVESTISSEMENT",'Données Suivi'!$H$2:$H$3000,"EN COURS D'ENGAGEMENT") | K7: =SUMIFS('Données Suivi'!$J$2:$J$3000,'Données Suivi'!$A$2:$A$3000,$A7,'Données Suivi'!$O$2:$O$3000,"INVESTISSEMENT",'Données Suivi'!$H$2:$H$3000,"EN COURS DE PREENGAGEMENT") | L7: =SUMIFS('Données Suivi'!$J$2:$J$3000,'Données Suivi'!$A$2:$A$3000,$A7,'Données Suivi'!$O$2:$O$3000,"INVESTISSEMENT",'Données Suivi'!$H$2:$H$3000,"NON ENGAGE") | M7: =H7+I7+J7+K7+L7 | N7: =G7+M7
A8: DACG | B8: =SUMIFS('Données Suivi'!$J$2:$J$3000,'Données Suivi'!$A$2:$A$3000,$A8,'Données Suivi'!$O$2:$O$3000,"FONCTIONNEMENT",'Données Suivi'!$H$2:$H$3000,"ENGAGE") | C8: =SUMIFS('Données Suivi'!$J$2:$J$3000,'Données Suivi'!$A$2:$A$3000,$A8,'Données Suivi'!$O$2:$O$3000,"FONCTIONNEMENT",'Données Suivi'!$H$2:$H$3000,"PREENGAGE") | D8: =SUMIFS('Données Suivi'!$J$2:$J$3000,'Données Suivi'!$A$2:$A$3000,$A8,'Données Suivi'!$O$2:$O$3000,"FONCTIONNEMENT",'Données Suivi'!$H$2:$H$3000,"EN COURS D'ENGAGEMENT") | E8: =SUMIFS('Données Suivi'!$J$2:$J$3000,'Données Suivi'!$A$2:$A$3000,$A8,'Données Suivi'!$O$2:$O$3000,"FONCTIONNEMENT",'Données Suivi'!$H$2:$H$3000,"EN COURS DE PREENGAGEMENT") | F8: =SUMIFS('Données Suivi'!$J$2:$J$3000,'Données Suivi'!$A$2:$A$3000,$A8,'Données Suivi'!$O$2:$O$3000,"FONCTIONNEMENT",'Données Suivi'!$H$2:$H$3000,"NON ENGAGE") | G8: =B8+C8+D8+E8+F8 | H8: =SUMIFS('Données Suivi'!$J$2:$J$3000,'Données Suivi'!$A$2:$A$3000,$A8,'Données Suivi'!$O$2:$O$3000,"INVESTISSEMENT",'Données Suivi'!$H$2:$H$3000,"ENGAGE") | I8: =SUMIFS('Données Suivi'!$J$2:$J$3000,'Données Suivi'!$A$2:$A$3000,$A8,'Données Suivi'!$O$2:$O$3000,"INVESTISSEMENT",'Données Suivi'!$H$2:$H$3000,"PREENGAGE") | J8: =SUMIFS('Données Suivi'!$J$2:$J$3000,'Données Suivi'!$A$2:$A$3000,$A8,'Données Suivi'!$O$2:$O$3000,"INVESTISSEMENT",'Données Suivi'!$H$2:$H$3000,"EN COURS D'ENGAGEMENT") | K8: =SUMIFS('Données Suivi'!$J$2:$J$3000,'Données Suivi'!$A$2:$A$3000,$A8,'Données Suivi'!$O$2:$O$3000,"INVESTISSEMENT",'Données Suivi'!$H$2:$H$3000,"EN COURS DE PREENGAGEMENT") | L8: =SUMIFS('Données Suivi'!$J$2:$J$3000,'Données Suivi'!$A$2:$A$3000,$A8,'Données Suivi'!$O$2:$O$3000,"INVESTISSEMENT",'Données Suivi'!$H$2:$H$3000,"NON ENGAGE") | M8: =H8+I8+J8+K8+L8 | N8: =G8+M8
A9: DAR | B9: =SUMIFS('Données Suivi'!$J$2:$J$3000,'Données Suivi'!$A$2:$A$3000,$A9,'Données Suivi'!$O$2:$O$3000,"FONCTIONNEMENT",'Données Suivi'!$H$2:$H$3000,"ENGAGE") | C9: =SUMIFS('Données Suivi'!$J$2:$J$3000,'Données Suivi'!$A$2:$A$3000,$A9,'Données Suivi'!$O$2:$O$3000,"FONCTIONNEMENT",'Données Suivi'!$H$2:$H$3000,"PREENGAGE") | D9: =SUMIFS('Données Suivi'!$J$2:$J$3000,'Données Suivi'!$A$2:$A$3000,$A9,'Données Suivi'!$O$2:$O$3000,"FONCTIONNEMENT",'Données Suivi'!$H$2:$H$3000,"EN COURS D'ENGAGEMENT") | E9: =SUMIFS('Données Suivi'!$J$2:$J$3000,'Données Suivi'!$A$2:$A$3000,$A9,'Données Suivi'!$O$2:$O$3000,"FONCTIONNEMENT",'Données Suivi'!$H$2:$H$3000,"EN COURS DE PREENGAGEMENT") | F9: =SUMIFS('Données Suivi'!$J$2:$J$3000,'Données Suivi'!$A$2:$A$3000,$A9,'Données Suivi'!$O$2:$O$3000,"FONCTIONNEMENT",'Données Suivi'!$H$2:$H$3000,"NON ENGAGE") | G9: =B9+C9+D9+E9+F9 | H9: =SUMIFS('Données Suivi'!$J$2:$J$3000,'Données Suivi'!$A$2:$A$3000,$A9,'Données Suivi'!$O$2:$O$3000,"INVESTISSEMENT",'Données Suivi'!$H$2:$H$3000,"ENGAGE") | I9: =SUMIFS('Données Suivi'!$J$2:$J$3000,'Données Suivi'!$A$2:$A$3000,$A9,'Données Suivi'!$O$2:$O$3000,"INVESTISSEMENT",'Données Suivi'!$H$2:$H$3000,"PREENGAGE") | J9: =SUMIFS('Données Suivi'!$J$2:$J$3000,'Données Suivi'!$A$2:$A$3000,$A9,'Données Suivi'!$O$2:$O$3000,"INVESTISSEMENT",'Données Suivi'!$H$2:$H$3000,"EN COURS D'ENGAGEMENT") | K9: =SUMIFS('Données Suivi'!$J$2:$J$3000,'Données Suivi'!$A$2:$A$3000,$A9,'Données Suivi'!$O$2:$O$3000,"INVESTISSEMENT",'Données Suivi'!$H$2:$H$3000,"EN COURS DE PREENGAGEMENT") | L9: =SUMIFS('Données Suivi'!$J$2:$J$3000,'Données Suivi'!$A$2:$A$3000,$A9,'Données Suivi'!$O$2:$O$3000,"INVESTISSEMENT",'Données Suivi'!$H$2:$H$3000,"NON ENGAGE") | M9: =H9+I9+J9+K9+L9 | N9: =G9+M9
A10: DCPA | B10: =SUMIFS('Données Suivi'!$J$2:$J$3000,'Données Suivi'!$A$2:$A$3000,$A10,'Données Suivi'!$O$2:$O$3000,"FONCTIONNEMENT",'Données Suivi'!$H$2:$H$3000,"ENGAGE") | C10: =SUMIFS('Données Suivi'!$J$2:$J$3000,'Données Suivi'!$A$2:$A$3000,$A10,'Données Suivi'!$O$2:$O$3000,"FONCTIONNEMENT",'Données Suivi'!$H$2:$H$3000,"PREENGAGE") | D10: =SUMIFS('Données Suivi'!$J$2:$J$3000,'Données Suivi'!$A$2:$A$3000,$A10,'Données Suivi'!$O$2:$O$3000,"FONCTIONNEMENT",'Données Suivi'!$H$2:$H$3000,"EN COURS D'ENGAGEMENT") | E10: =SUMIFS('Données Suivi'!$J$2:$J$3000,'Données Suivi'!$A$2:$A$3000,$A10,'Données Suivi'!$O$2:$O$3000,"FONCTIONNEMENT",'Données Suivi'!$H$2:$H$3000,"EN COURS DE PREENGAGEMENT") | F10: =SUMIFS('Données Suivi'!$J$2:$J$3000,'Données Suivi'!$A$2:$A$3000,$A10,'Données Suivi'!$O$2:$O$3000,"FONCTIONNEMENT",'Données Suivi'!$H$2:$H$3000,"NON ENGAGE") | G10: =B10+C10+D10+E10+F10 | H10: =SUMIFS('Données Suivi'!$J$2:$J$3000,'Données Suivi'!$A$2:$A$3000,$A10,'Données Suivi'!$O$2:$O$3000,"INVESTISSEMENT",'Données Suivi'!$H$2:$H$3000,"ENGAGE") | I10: =SUMIFS('Données Suivi'!$J$2:$J$3000,'Données Suivi'!$A$2:$A$3000,$A10,'Données Suivi'!$O$2:$O$3000,"INVESTISSEMENT",'Données Suivi'!$H$2:$H$3000,"PREENGAGE") | J10: =SUMIFS('Données Suivi'!$J$2:$J$3000,'Données Suivi'!$A$2:$A$3000,$A10,'Données Suivi'!$O$2:$O$3000,"INVESTISSEMENT",'Données Suivi'!$H$2:$H$3000,"EN COURS D'ENGAGEMENT") | K10: =SUMIFS('Données Suivi'!$J$2:$J$3000,'Données Suivi'!$A$2:$A$3000,$A10,'Données Suivi'!$O$2:$O$3000,"INVESTISSEMENT",'Données Suivi'!$H$2:$H$3000,"EN COURS DE PREENGAGEMENT") | L10: =SUMIFS('Données Suivi'!$J$2:$J$3000,'Données Suivi'!$A$2:$A$3000,$A10,'Données Suivi'!$O$2:$O$3000,"INVESTISSEMENT",'Données Suivi'!$H$2:$H$3000,"NON ENGAGE") | M10: =H10+I10+J10+K10+L10 | N10: =G10+M10
A11: DCRI | B11: =SUMIFS('Données Suivi'!$J$2:$J$3000,'Données Suivi'!$A$2:$A$3000,$A11,'Données Suivi'!$O$2:$O$3000,"FONCTIONNEMENT",'Données Suivi'!$H$2:$H$3000,"ENGAGE") | C11: =SUMIFS('Données Suivi'!$J$2:$J$3000,'Données Suivi'!$A$2:$A$3000,$A11,'Données Suivi'!$O$2:$O$3000,"FONCTIONNEMENT",'Données Suivi'!$H$2:$H$3000,"PREENGAGE") | D11: =SUMIFS('Données Suivi'!$J$2:$J$3000,'Données Suivi'!$A$2:$A$3000,$A11,'Données Suivi'!$O$2:$O$3000,"FONCTIONNEMENT",'Données Suivi'!$H$2:$H$3000,"EN COURS D'ENGAGEMENT") | E11: =SUMIFS('Données Suivi'!$J$2:$J$3000,'Données Suivi'!$A$2:$A$3000,$A11,'Données Suivi'!$O$2:$O$3000,"FONCTIONNEMENT",'Données Suivi'!$H$2:$H$3000,"EN COURS DE PREENGAGEMENT") | F11: =SUMIFS('Données Suivi'!$J$2:$J$3000,'Données Suivi'!$A$2:$A$3000,$A11,'Données Suivi'!$O$2:$O$3000,"FONCTIONNEMENT",'Données Suivi'!$H$2:$H$3000,"NON ENGAGE") | G11: =B11+C11+D11+E11+F11 | H11: =SUMIFS('Données Suivi'!$J$2:$J$3000,'Données Suivi'!$A$2:$A$3000,$A11,'Données Suivi'!$O$2:$O$3000,"INVESTISSEMENT",'Données Suivi'!$H$2:$H$3000,"ENGAGE") | I11: =SUMIFS('Données Suivi'!$J$2:$J$3000,'Données Suivi'!$A$2:$A$3000,$A11,'Données Suivi'!$O$2:$O$3000,"INVESTISSEMENT",'Données Suivi'!$H$2:$H$3000,"PREENGAGE") | J11: =SUMIFS('Données Suivi'!$J$2:$J$3000,'Données Suivi'!$A$2:$A$3000,$A11,'Données Suivi'!$O$2:$O$3000,"INVESTISSEMENT",'Données Suivi'!$H$2:$H$3000,"EN COURS D'ENGAGEMENT") | K11: =SUMIFS('Données Suivi'!$J$2:$J$3000,'Données Suivi'!$A$2:$A$3000,$A11,'Données Suivi'!$O$2:$O$3000,"INVESTISSEMENT",'Données Suivi'!$H$2:$H$3000,"EN COURS DE PREENGAGEMENT") | L11: =SUMIFS('Données Suivi'!$J$2:$J$3000,'Données Suivi'!$A$2:$A$3000,$A11,'Données Suivi'!$O$2:$O$3000,"INVESTISSEMENT",'Données Suivi'!$H$2:$H$3000,"NON ENGAGE") | M11: =H11+I11+J11+K11+L11 | N11: =G11+M11
A12: DCT | B12: =SUMIFS('Données Suivi'!$J$2:$J$3000,'Données Suivi'!$A$2:$A$3000,$A12,'Données Suivi'!$O$2:$O$3000,"FONCTIONNEMENT",'Données Suivi'!$H$2:$H$3000,"ENGAGE") | C12: =SUMIFS('Données Suivi'!$J$2:$J$3000,'Données Suivi'!$A$2:$A$3000,$A12,'Données Suivi'!$O$2:$O$3000,"FONCTIONNEMENT",'Données Suivi'!$H$2:$H$3000,"PREENGAGE") | D12: =SUMIFS('Données Suivi'!$J$2:$J$3000,'Données Suivi'!$A$2:$A$3000,$A12,'Données Suivi'!$O$2:$O$3000,"FONCTIONNEMENT",'Données Suivi'!$H$2:$H$3000,"EN COURS D'ENGAGEMENT") | E12: =SUMIFS('Données Suivi'!$J$2:$J$3000,'Données Suivi'!$A$2:$A$3000,$A12,'Données Suivi'!$O$2:$O$3000,"FONCTIONNEMENT",'Données Suivi'!$H$2:$H$3000,"EN COURS DE PREENGAGEMENT") | F12: =SUMIFS('Données Suivi'!$J$2:$J$3000,'Données Suivi'!$A$2:$A$3000,$A12,'Données Suivi'!$O$2:$O$3000,"FONCTIONNEMENT",'Données Suivi'!$H$2:$H$3000,"NON ENGAGE") | G12: =B12+C12+D12+E12+F12 | H12: =SUMIFS('Données Suivi'!$J$2:$J$3000,'Données Suivi'!$A$2:$A$3000,$A12,'Données Suivi'!$O$2:$O$3000,"INVESTISSEMENT",'Données Suivi'!$H$2:$H$3000,"ENGAGE") | I12: =SUMIFS('Données Suivi'!$J$2:$J$3000,'Données Suivi'!$A$2:$A$3000,$A12,'Données Suivi'!$O$2:$O$3000,"INVESTISSEMENT",'Données Suivi'!$H$2:$H$3000,"PREENGAGE") | J12: =SUMIFS('Données Suivi'!$J$2:$J$3000,'Données Suivi'!$A$2:$A$3000,$A12,'Données Suivi'!$O$2:$O$3000,"INVESTISSEMENT",'Données Suivi'!$H$2:$H$3000,"EN COURS D'ENGAGEMENT") | K12: =SUMIFS('Données Suivi'!$J$2:$J$3000,'Données Suivi'!$A$2:$A$3000,$A12,'Données Suivi'!$O$2:$O$3000,"INVESTISSEMENT",'Données Suivi'!$H$2:$H$3000,"EN COURS DE PREENGAGEMENT") | L12: =SUMIFS('Données Suivi'!$J$2:$J$3000,'Données Suivi'!$A$2:$A$3000,$A12,'Données Suivi'!$O$2:$O$3000,"INVESTISSEMENT",'Données Suivi'!$H$2:$H$3000,"NON ENGAGE") | M12: =H12+I12+J12+K12+L12 | N12: =G12+M12
A13: DG | B13: =SUMIFS('Données Suivi'!$J$2:$J$3000,'Données Suivi'!$A$2:$A$3000,$A13,'Données Suivi'!$O$2:$O$3000,"FONCTIONNEMENT",'Données Suivi'!$H$2:$H$3000,"ENGAGE") | C13: =SUMIFS('Données Suivi'!$J$2:$J$3000,'Données Suivi'!$A$2:$A$3000,$A13,'Données Suivi'!$O$2:$O$3000,"FONCTIONNEMENT",'Données Suivi'!$H$2:$H$3000,"PREENGAGE") | D13: =SUMIFS('Données Suivi'!$J$2:$J$3000,'Données Suivi'!$A$2:$A$3000,$A13,'Données Suivi'!$O$2:$O$3000,"FONCTIONNEMENT",'Données Suivi'!$H$2:$H$3000,"EN COURS D'ENGAGEMENT") | E13: =SUMIFS('Données Suivi'!$J$2:$J$3000,'Données Suivi'!$A$2:$A$3000,$A13,'Données Suivi'!$O$2:$O$3000,"FONCTIONNEMENT",'Données Suivi'!$H$2:$H$3000,"EN COURS DE PREENGAGEMENT") | F13: =SUMIFS('Données Suivi'!$J$2:$J$3000,'Données Suivi'!$A$2:$A$3000,$A13,'Données Suivi'!$O$2:$O$3000,"FONCTIONNEMENT",'Données Suivi'!$H$2:$H$3000,"NON ENGAGE") | G13: =B13+C13+D13+E13+F13 | H13: =SUMIFS('Données Suivi'!$J$2:$J$3000,'Données Suivi'!$A$2:$A$3000,$A13,'Données Suivi'!$O$2:$O$3000,"INVESTISSEMENT",'Données Suivi'!$H$2:$H$3000,"ENGAGE") | I13: =SUMIFS('Données Suivi'!$J$2:$J$3000,'Données Suivi'!$A$2:$A$3000,$A13,'Données Suivi'!$O$2:$O$3000,"INVESTISSEMENT",'Données Suivi'!$H$2:$H$3000,"PREENGAGE") | J13: =SUMIFS('Données Suivi'!$J$2:$J$3000,'Données Suivi'!$A$2:$A$3000,$A13,'Données Suivi'!$O$2:$O$3000,"INVESTISSEMENT",'Données Suivi'!$H$2:$H$3000,"EN COURS D'ENGAGEMENT") | K13: =SUMIFS('Données Suivi'!$J$2:$J$3000,'Données Suivi'!$A$2:$A$3000,$A13,'Données Suivi'!$O$2:$O$3000,"INVESTISSEMENT",'Données Suivi'!$H$2:$H$3000,"EN COURS DE PREENGAGEMENT") | L13: =SUMIFS('Données Suivi'!$J$2:$J$3000,'Données Suivi'!$A$2:$A$3000,$A13,'Données Suivi'!$O$2:$O$3000,"INVESTISSEMENT",'Données Suivi'!$H$2:$H$3000,"NON ENGAGE") | M13: =H13+I13+J13+K13+L13 | N13: =G13+M13
A14: DINFORADIO | B14: =SUMIFS('Données Suivi'!$J$2:$J$3000,'Données Suivi'!$A$2:$A$3000,$A14,'Données Suivi'!$O$2:$O$3000,"FONCTIONNEMENT",'Données Suivi'!$H$2:$H$3000,"ENGAGE") | C14: =SUMIFS('Données Suivi'!$J$2:$J$3000,'Données Suivi'!$A$2:$A$3000,$A14,'Données Suivi'!$O$2:$O$3000,"FONCTIONNEMENT",'Données Suivi'!$H$2:$H$3000,"PREENGAGE") | D14: =SUMIFS('Données Suivi'!$J$2:$J$3000,'Données Suivi'!$A$2:$A$3000,$A14,'Données Suivi'!$O$2:$O$3000,"FONCTIONNEMENT",'Données Suivi'!$H$2:$H$3000,"EN COURS D'ENGAGEMENT") | E14: =SUMIFS('Données Suivi'!$J$2:$J$3000,'Données Suivi'!$A$2:$A$3000,$A14,'Données Suivi'!$O$2:$O$3000,"FONCTIONNEMENT",'Données Suivi'!$H$2:$H$3000,"EN COURS DE PREENGAGEMENT") | F14: =SUMIFS('Données Suivi'!$J$2:$J$3000,'Données Suivi'!$A$2:$A$3000,$A14,'Données Suivi'!$O$2:$O$3000,"FONCTIONNEMENT",'Données Suivi'!$H$2:$H$3000,"NON ENGAGE") | G14: =B14+C14+D14+E14+F14 | H14: =SUMIFS('Données Suivi'!$J$2:$J$3000,'Données Suivi'!$A$2:$A$3000,$A14,'Données Suivi'!$O$2:$O$3000,"INVESTISSEMENT",'Données Suivi'!$H$2:$H$3000,"ENGAGE") | I14: =SUMIFS('Données Suivi'!$J$2:$J$3000,'Données Suivi'!$A$2:$A$3000,$A14,'Données Suivi'!$O$2:$O$3000,"INVESTISSEMENT",'Données Suivi'!$H$2:$H$3000,"PREENGAGE") | J14: =SUMIFS('Données Suivi'!$J$2:$J$3000,'Données Suivi'!$A$2:$A$3000,$A14,'Données Suivi'!$O$2:$O$3000,"INVESTISSEMENT",'Données Suivi'!$H$2:$H$3000,"EN COURS D'ENGAGEMENT") | K14: =SUMIFS('Données Suivi'!$J$2:$J$3000,'Données Suivi'!$A$2:$A$3000,$A14,'Données Suivi'!$O$2:$O$3000,"INVESTISSEMENT",'Données Suivi'!$H$2:$H$3000,"EN COURS DE PREENGAGEMENT") | L14: =SUMIFS('Données Suivi'!$J$2:$J$3000,'Données Suivi'!$A$2:$A$3000,$A14,'Données Suivi'!$O$2:$O$3000,"INVESTISSEMENT",'Données Suivi'!$H$2:$H$3000,"NON ENGAGE") | M14: =H14+I14+J14+K14+L14 | N14: =G14+M14
A15: DINFOTV | B15: =SUMIFS('Données Suivi'!$J$2:$J$3000,'Données Suivi'!$A$2:$A$3000,$A15,'Données Suivi'!$O$2:$O$3000,"FONCTIONNEMENT",'Données Suivi'!$H$2:$H$3000,"ENGAGE") | C15: =SUMIFS('Données Suivi'!$J$2:$J$3000,'Données Suivi'!$A$2:$A$3000,$A15,'Données Suivi'!$O$2:$O$3000,"FONCTIONNEMENT",'Données Suivi'!$H$2:$H$3000,"PREENGAGE") | D15: =SUMIFS('Données Suivi'!$J$2:$J$3000,'Données Suivi'!$A$2:$A$3000,$A15,'Données Suivi'!$O$2:$O$3000,"FONCTIONNEMENT",'Données Suivi'!$H$2:$H$3000,"EN COURS D'ENGAGEMENT") | E15: =SUMIFS('Données Suivi'!$J$2:$J$3000,'Données Suivi'!$A$2:$A$3000,$A15,'Données Suivi'!$O$2:$O$3000,"FONCTIONNEMENT",'Données Suivi'!$H$2:$H$3000,"EN COURS DE PREENGAGEMENT") | F15: =SUMIFS('Données Suivi'!$J$2:$J$3000,'Données Suivi'!$A$2:$A$3000,$A15,'Données Suivi'!$O$2:$O$3000,"FONCTIONNEMENT",'Données Suivi'!$H$2:$H$3000,"NON ENGAGE") | G15: =B15+C15+D15+E15+F15 | H15: =SUMIFS('Données Suivi'!$J$2:$J$3000,'Données Suivi'!$A$2:$A$3000,$A15,'Données Suivi'!$O$2:$O$3000,"INVESTISSEMENT",'Données Suivi'!$H$2:$H$3000,"ENGAGE") | I15: =SUMIFS('Données Suivi'!$J$2:$J$3000,'Données Suivi'!$A$2:$A$3000,$A15,'Données Suivi'!$O$2:$O$3000,"INVESTISSEMENT",'Données Suivi'!$H$2:$H$3000,"PREENGAGE") | J15: =SUMIFS('Données Suivi'!$J$2:$J$3000,'Données Suivi'!$A$2:$A$3000,$A15,'Données Suivi'!$O$2:$O$3000,"INVESTISSEMENT",'Données Suivi'!$H$2:$H$3000,"EN COURS D'ENGAGEMENT") | K15: =SUMIFS('Données Suivi'!$J$2:$J$3000,'Données Suivi'!$A$2:$A$3000,$A15,'Données Suivi'!$O$2:$O$3000,"INVESTISSEMENT",'Données Suivi'!$H$2:$H$3000,"EN COURS DE PREENGAGEMENT") | L15: =SUMIFS('Données Suivi'!$J$2:$J$3000,'Données Suivi'!$A$2:$A$3000,$A15,'Données Suivi'!$O$2:$O$3000,"INVESTISSEMENT",'Données Suivi'!$H$2:$H$3000,"NON ENGAGE") | M15: =H15+I15+J15+K15+L15 | N15: =G15+M15
A16: DJURIDIQUE | B16: =SUMIFS('Données Suivi'!$J$2:$J$3000,'Données Suivi'!$A$2:$A$3000,$A16,'Données Suivi'!$O$2:$O$3000,"FONCTIONNEMENT",'Données Suivi'!$H$2:$H$3000,"ENGAGE") | C16: =SUMIFS('Données Suivi'!$J$2:$J$3000,'Données Suivi'!$A$2:$A$3000,$A16,'Données Suivi'!$O$2:$O$3000,"FONCTIONNEMENT",'Données Suivi'!$H$2:$H$3000,"PREENGAGE") | D16: =SUMIFS('Données Suivi'!$J$2:$J$3000,'Données Suivi'!$A$2:$A$3000,$A16,'Données Suivi'!$O$2:$O$3000,"FONCTIONNEMENT",'Données Suivi'!$H$2:$H$3000,"EN COURS D'ENGAGEMENT") | E16: =SUMIFS('Données Suivi'!$J$2:$J$3000,'Données Suivi'!$A$2:$A$3000,$A16,'Données Suivi'!$O$2:$O$3000,"FONCTIONNEMENT",'Données Suivi'!$H$2:$H$3000,"EN COURS DE PREENGAGEMENT") | F16: =SUMIFS('Données Suivi'!$J$2:$J$3000,'Données Suivi'!$A$2:$A$3000,$A16,'Données Suivi'!$O$2:$O$3000,"FONCTIONNEMENT",'Données Suivi'!$H$2:$H$3000,"NON ENGAGE") | G16: =B16+C16+D16+E16+F16 | H16: =SUMIFS('Données Suivi'!$J$2:$J$3000,'Données Suivi'!$A$2:$A$3000,$A16,'Données Suivi'!$O$2:$O$3000,"INVESTISSEMENT",'Données Suivi'!$H$2:$H$3000,"ENGAGE") | I16: =SUMIFS('Données Suivi'!$J$2:$J$3000,'Données Suivi'!$A$2:$A$3000,$A16,'Données Suivi'!$O$2:$O$3000,"INVESTISSEMENT",'Données Suivi'!$H$2:$H$3000,"PREENGAGE") | J16: =SUMIFS('Données Suivi'!$J$2:$J$3000,'Données Suivi'!$A$2:$A$3000,$A16,'Données Suivi'!$O$2:$O$3000,"INVESTISSEMENT",'Données Suivi'!$H$2:$H$3000,"EN COURS D'ENGAGEMENT") | K16: =SUMIFS('Données Suivi'!$J$2:$J$3000,'Données Suivi'!$A$2:$A$3000,$A16,'Données Suivi'!$O$2:$O$3000,"INVESTISSEMENT",'Données Suivi'!$H$2:$H$3000,"EN COURS DE PREENGAGEMENT") | L16: =SUMIFS('Données Suivi'!$J$2:$J$3000,'Données Suivi'!$A$2:$A$3000,$A16,'Données Suivi'!$O$2:$O$3000,"INVESTISSEMENT",'Données Suivi'!$H$2:$H$3000,"NON ENGAGE") | M16: =H16+I16+J16+K16+L16 | N16: =G16+M16
... A27: TV LAAYOUNE | B27: =SUMIFS('Données Suivi'!$J$2:$J$3000,'Données Suivi'!$A$2:$A$3000,$A27,'Données Suivi'!$O$2:$O$3000,"FONCTIONNEMENT",'Données Suivi'!$H$2:$H$3000,"ENGAGE") | C27: =SUMIFS('Données Suivi'!$J$2:$J$3000,'Données Suivi'!$A$2:$A$3000,$A27,'Données Suivi'!$O$2:$O$3000,"FONCTIONNEMENT",'Données Suivi'!$H$2:$H$3000,"PREENGAGE") | D27: =SUMIFS('Données Suivi'!$J$2:$J$3000,'Données Suivi'!$A$2:$A$3000,$A27,'Données Suivi'!$O$2:$O$3000,"FONCTIONNEMENT",'Données Suivi'!$H$2:$H$3000,"EN COURS D'ENGAGEMENT") | E27: =SUMIFS('Données Suivi'!$J$2:$J$3000,'Données Suivi'!$A$2:$A$3000,$A27,'Données Suivi'!$O$2:$O$3000,"FONCTIONNEMENT",'Données Suivi'!$H$2:$H$3000,"EN COURS DE PREENGAGEMENT") | F27: =SUMIFS('Données Suivi'!$J$2:$J$3000,'Données Suivi'!$A$2:$A$3000,$A27,'Données Suivi'!$O$2:$O$3000,"FONCTIONNEMENT",'Données Suivi'!$H$2:$H$3000,"NON ENGAGE") | G27: =B27+C27+D27+E27+F27 | H27: =SUMIFS('Données Suivi'!$J$2:$J$3000,'Données Suivi'!$A$2:$A$3000,$A27,'Données Suivi'!$O$2:$O$3000,"INVESTISSEMENT",'Données Suivi'!$H$2:$H$3000,"ENGAGE") | I27: =SUMIFS('Données Suivi'!$J$2:$J$3000,'Données Suivi'!$A$2:$A$3000,$A27,'Données Suivi'!$O$2:$O$3000,"INVESTISSEMENT",'Données Suivi'!$H$2:$H$3000,"PREENGAGE") | J27: =SUMIFS('Données Suivi'!$J$2:$J$3000,'Données Suivi'!$A$2:$A$3000,$A27,'Données Suivi'!$O$2:$O$3000,"INVESTISSEMENT",'Données Suivi'!$H$2:$H$3000,"EN COURS D'ENGAGEMENT") | K27: =SUMIFS('Données Suivi'!$J$2:$J$3000,'Données Suivi'!$A$2:$A$3000,$A27,'Données Suivi'!$O$2:$O$3000,"INVESTISSEMENT",'Données Suivi'!$H$2:$H$3000,"EN COURS DE PREENGAGEMENT") | L27: =SUMIFS('Données Suivi'!$J$2:$J$3000,'Données Suivi'!$A$2:$A$3000,$A27,'Données Suivi'!$O$2:$O$3000,"INVESTISSEMENT",'Données Suivi'!$H$2:$H$3000,"NON ENGAGE") | M27: =H27+I27+J27+K27+L27 | N27: =G27+M27
A28: TOTAL GÉNÉRAL | B28: =SUM(B5:B27) | C28: =SUM(C5:C27) | D28: =SUM(D5:D27) | E28: =SUM(E5:E27) | F28: =SUM(F5:F27) | G28: =SUM(G5:G27) | H28: =SUM(H5:H27) | I28: =SUM(I5:I27) | ... N28: =SUM(N5:N27)

Sheet Filtre Interactif
A1: FILTRE INTERACTIF — DIRECTION / BCI / STATUT D'ENGAGEMENT
A3: 1) Choisir une Direction : | C3: DCT
A5: 2) Choisir un Type de BCI (à partir de la répartition ci-dessous) : | C5: CONTRAT
A7: Nombre de dossiers par Type de BCI — Direction sélectionnée
A8: Type de BCI | B8: Nb dossiers | C8: Montant (MAD) | D8: NATURE BUDGET | F8: CATEGORIE
D9: Fonctionnement | E9: Investissement | F9: Général | G9: PME | H9: Non concerné
A10: CONTRAT | B10: =COUNTIFS('Données Suivi'!$A$2:$A$3000,$C$3,'Données Suivi'!$C$2:$C$3000,$A10) | C10: =SUMIFS('Données Suivi'!$J$2:$J$3000,'Données Suivi'!$A$2:$A$3000,$C$3,'Données Suivi'!$C$2:$C$3000,$A10) | D10: =COUNTIFS('Données Suivi'!$A$2:$A$3000,$C$3,'Données Suivi'!$C$2:$C$3000,$A10,'Données Suivi'!$O$2:$O$3000,"FONCTIONNEMENT") | E10: =COUNTIFS('Données Suivi'!$A$2:$A$3000,$C$3,'Données Suivi'!$C$2:$C$3000,$A10,'Données Suivi'!$O$2:$O$3000,"INVESTISSEMENT") | F10: =COUNTIFS('Données Suivi'!$A$2:$A$3000,$C$3,'Données Suivi'!$C$2:$C$3000,$A10,'Données Suivi'!$P$2:$P$3000,"GENERAL") | G10: =COUNTIFS('Données Suivi'!$A$2:$A$3000,$C$3,'Données Suivi'!$C$2:$C$3000,$A10,'Données Suivi'!$P$2:$P$3000,"PME") | H10: =COUNTIFS('Données Suivi'!$A$2:$A$3000,$C$3,'Données Suivi'!$C$2:$C$3000,$A10,'Données Suivi'!$P$2:$P$3000,"NON CONCERNE")
A11: AOO-M | B11: =COUNTIFS('Données Suivi'!$A$2:$A$3000,$C$3,'Données Suivi'!$C$2:$C$3000,$A11) | C11: =SUMIFS('Données Suivi'!$J$2:$J$3000,'Données Suivi'!$A$2:$A$3000,$C$3,'Données Suivi'!$C$2:$C$3000,$A11) | D11: =COUNTIFS('Données Suivi'!$A$2:$A$3000,$C$3,'Données Suivi'!$C$2:$C$3000,$A11,'Données Suivi'!$O$2:$O$3000,"FONCTIONNEMENT") | E11: =COUNTIFS('Données Suivi'!$A$2:$A$3000,$C$3,'Données Suivi'!$C$2:$C$3000,$A11,'Données Suivi'!$O$2:$O$3000,"INVESTISSEMENT") | F11: =COUNTIFS('Données Suivi'!$A$2:$A$3000,$C$3,'Données Suivi'!$C$2:$C$3000,$A11,'Données Suivi'!$P$2:$P$3000,"GENERAL") | G11: =COUNTIFS('Données Suivi'!$A$2:$A$3000,$C$3,'Données Suivi'!$C$2:$C$3000,$A11,'Données Suivi'!$P$2:$P$3000,"PME") | H11: =COUNTIFS('Données Suivi'!$A$2:$A$3000,$C$3,'Données Suivi'!$C$2:$C$3000,$A11,'Données Suivi'!$P$2:$P$3000,"NON CONCERNE")
A12: AOO-CT | B12: =COUNTIFS('Données Suivi'!$A$2:$A$3000,$C$3,'Données Suivi'!$C$2:$C$3000,$A12) | C12: =SUMIFS('Données Suivi'!$J$2:$J$3000,'Données Suivi'!$A$2:$A$3000,$C$3,'Données Suivi'!$C$2:$C$3000,$A12) | D12: =COUNTIFS('Données Suivi'!$A$2:$A$3000,$C$3,'Données Suivi'!$C$2:$C$3000,$A12,'Données Suivi'!$O$2:$O$3000,"FONCTIONNEMENT") | E12: =COUNTIFS('Données Suivi'!$A$2:$A$3000,$C$3,'Données Suivi'!$C$2:$C$3000,$A12,'Données Suivi'!$O$2:$O$3000,"INVESTISSEMENT") | F12: =COUNTIFS('Données Suivi'!$A$2:$A$3000,$C$3,'Données Suivi'!$C$2:$C$3000,$A12,'Données Suivi'!$P$2:$P$3000,"GENERAL") | G12: =COUNTIFS('Données Suivi'!$A$2:$A$3000,$C$3,'Données Suivi'!$C$2:$C$3000,$A12,'Données Suivi'!$P$2:$P$3000,"PME") | H12: =COUNTIFS('Données Suivi'!$A$2:$A$3000,$C$3,'Données Suivi'!$C$2:$C$3000,$A12,'Données Suivi'!$P$2:$P$3000,"NON CONCERNE")
A13: BCL | B13: =COUNTIFS('Données Suivi'!$A$2:$A$3000,$C$3,'Données Suivi'!$C$2:$C$3000,$A13) | C13: =SUMIFS('Données Suivi'!$J$2:$J$3000,'Données Suivi'!$A$2:$A$3000,$C$3,'Données Suivi'!$C$2:$C$3000,$A13) | D13: =COUNTIFS('Données Suivi'!$A$2:$A$3000,$C$3,'Données Suivi'!$C$2:$C$3000,$A13,'Données Suivi'!$O$2:$O$3000,"FONCTIONNEMENT") | E13: =COUNTIFS('Données Suivi'!$A$2:$A$3000,$C$3,'Données Suivi'!$C$2:$C$3000,$A13,'Données Suivi'!$O$2:$O$3000,"INVESTISSEMENT") | F13: =COUNTIFS('Données Suivi'!$A$2:$A$3000,$C$3,'Données Suivi'!$C$2:$C$3000,$A13,'Données Suivi'!$P$2:$P$3000,"GENERAL") | G13: =COUNTIFS('Données Suivi'!$A$2:$A$3000,$C$3,'Données Suivi'!$C$2:$C$3000,$A13,'Données Suivi'!$P$2:$P$3000,"PME") | H13: =COUNTIFS('Données Suivi'!$A$2:$A$3000,$C$3,'Données Suivi'!$C$2:$C$3000,$A13,'Données Suivi'!$P$2:$P$3000,"NON CONCERNE")
A14: BCI | B14: =COUNTIFS('Données Suivi'!$A$2:$A$3000,$C$3,'Données Suivi'!$C$2:$C$3000,$A14) | C14: =SUMIFS('Données Suivi'!$J$2:$J$3000,'Données Suivi'!$A$2:$A$3000,$C$3,'Données Suivi'!$C$2:$C$3000,$A14) | D14: =COUNTIFS('Données Suivi'!$A$2:$A$3000,$C$3,'Données Suivi'!$C$2:$C$3000,$A14,'Données Suivi'!$O$2:$O$3000,"FONCTIONNEMENT") | E14: =COUNTIFS('Données Suivi'!$A$2:$A$3000,$C$3,'Données Suivi'!$C$2:$C$3000,$A14,'Données Suivi'!$O$2:$O$3000,"INVESTISSEMENT") | F14: =COUNTIFS('Données Suivi'!$A$2:$A$3000,$C$3,'Données Suivi'!$C$2:$C$3000,$A14,'Données Suivi'!$P$2:$P$3000,"GENERAL") | G14: =COUNTIFS('Données Suivi'!$A$2:$A$3000,$C$3,'Données Suivi'!$C$2:$C$3000,$A14,'Données Suivi'!$P$2:$P$3000,"PME") | H14: =COUNTIFS('Données Suivi'!$A$2:$A$3000,$C$3,'Données Suivi'!$C$2:$C$3000,$A14,'Données Suivi'!$P$2:$P$3000,"NON CONCERNE")
A15: CA | B15: =COUNTIFS('Données Suivi'!$A$2:$A$3000,$C$3,'Données Suivi'!$C$2:$C$3000,$A15) | C15: =SUMIFS('Données Suivi'!$J$2:$J$3000,'Données Suivi'!$A$2:$A$3000,$C$3,'Données Suivi'!$C$2:$C$3000,$A15) | D15: =COUNTIFS('Données Suivi'!$A$2:$A$3000,$C$3,'Données Suivi'!$C$2:$C$3000,$A15,'Données Suivi'!$O$2:$O$3000,"FONCTIONNEMENT") | E15: =COUNTIFS('Données Suivi'!$A$2:$A$3000,$C$3,'Données Suivi'!$C$2:$C$3000,$A15,'Données Suivi'!$O$2:$O$3000,"INVESTISSEMENT") | F15: =COUNTIFS('Données Suivi'!$A$2:$A$3000,$C$3,'Données Suivi'!$C$2:$C$3000,$A15,'Données Suivi'!$P$2:$P$3000,"GENERAL") | G15: =COUNTIFS('Données Suivi'!$A$2:$A$3000,$C$3,'Données Suivi'!$C$2:$C$3000,$A15,'Données Suivi'!$P$2:$P$3000,"PME") | H15: =COUNTIFS('Données Suivi'!$A$2:$A$3000,$C$3,'Données Suivi'!$C$2:$C$3000,$A15,'Données Suivi'!$P$2:$P$3000,"NON CONCERNE")
A16: TOTAL direction | B16: =SUM(B10:B15) | C16: =SUM(C10:C15) | D16: =SUM(D10:D15) | E16: =SUM(E10:E15) | F16: =SUM(F10:F15) | G16: =SUM(G10:G15) | H16: =SUM(H10:H15)
A18: Répartition par Statut d'Engagement — Direction + Type de BCI sélectionnés
A19: Statut d'Engagement | B19: Nb dossiers | C19: Montant Fonctionnement (MAD) | D19: Montant Investissement (MAD)
A20: NON ENGAGE | B20: =COUNTIFS('Données Suivi'!$A$2:$A$3000,$C$3,'Données Suivi'!$C$2:$C$3000,$C$5,'Données Suivi'!$H$2:$H$3000,$A20) | C20: =SUMIFS('Données Suivi'!$J$2:$J$3000,'Données Suivi'!$A$2:$A$3000,$C$3,'Données Suivi'!$C$2:$C$3000,$C$5,'Données Suivi'!$H$2:$H$3000,$A20,'Données Suivi'!$O$2:$O$3000,"FONCTIONNEMENT") | D20: =SUMIFS('Données Suivi'!$J$2:$J$3000,'Données Suivi'!$A$2:$A$3000,$C$3,'Données Suivi'!$C$2:$C$3000,$C$5,'Données Suivi'!$H$2:$H$3000,$A20,'Données Suivi'!$O$2:$O$3000,"INVESTISSEMENT")
A21: EN COURS DE PREENGAGEMENT | B21: =COUNTIFS('Données Suivi'!$A$2:$A$3000,$C$3,'Données Suivi'!$C$2:$C$3000,$C$5,'Données Suivi'!$H$2:$H$3000,$A21) | C21: =SUMIFS('Données Suivi'!$J$2:$J$3000,'Données Suivi'!$A$2:$A$3000,$C$3,'Données Suivi'!$C$2:$C$3000,$C$5,'Données Suivi'!$H$2:$H$3000,$A21,'Données Suivi'!$O$2:$O$3000,"FONCTIONNEMENT") | D21: =SUMIFS('Données Suivi'!$J$2:$J$3000,'Données Suivi'!$A$2:$A$3000,$C$3,'Données Suivi'!$C$2:$C$3000,$C$5,'Données Suivi'!$H$2:$H$3000,$A21,'Données Suivi'!$O$2:$O$3000,"INVESTISSEMENT")
A22: PREENGAGE | B22: =COUNTIFS('Données Suivi'!$A$2:$A$3000,$C$3,'Données Suivi'!$C$2:$C$3000,$C$5,'Données Suivi'!$H$2:$H$3000,$A22) | C22: =SUMIFS('Données Suivi'!$J$2:$J$3000,'Données Suivi'!$A$2:$A$3000,$C$3,'Données Suivi'!$C$2:$C$3000,$C$5,'Données Suivi'!$H$2:$H$3000,$A22,'Données Suivi'!$O$2:$O$3000,"FONCTIONNEMENT") | D22: =SUMIFS('Données Suivi'!$J$2:$J$3000,'Données Suivi'!$A$2:$A$3000,$C$3,'Données Suivi'!$C$2:$C$3000,$C$5,'Données Suivi'!$H$2:$H$3000,$A22,'Données Suivi'!$O$2:$O$3000,"INVESTISSEMENT")
A23: EN COURS D'ENGAGEMENT | B23: =COUNTIFS('Données Suivi'!$A$2:$A$3000,$C$3,'Données Suivi'!$C$2:$C$3000,$C$5,'Données Suivi'!$H$2:$H$3000,$A23) | C23: =SUMIFS('Données Suivi'!$J$2:$J$3000,'Données Suivi'!$A$2:$A$3000,$C$3,'Données Suivi'!$C$2:$C$3000,$C$5,'Données Suivi'!$H$2:$H$3000,$A23,'Données Suivi'!$O$2:$O$3000,"FONCTIONNEMENT") | D23: =SUMIFS('Données Suivi'!$J$2:$J$3000,'Données Suivi'!$A$2:$A$3000,$C$3,'Données Suivi'!$C$2:$C$3000,$C$5,'Données Suivi'!$H$2:$H$3000,$A23,'Données Suivi'!$O$2:$O$3000,"INVESTISSEMENT")
A24: ENGAGE | B24: =COUNTIFS('Données Suivi'!$A$2:$A$3000,$C$3,'Données Suivi'!$C$2:$C$3000,$C$5,'Données Suivi'!$H$2:$H$3000,$A24) | C24: =SUMIFS('Données Suivi'!$J$2:$J$3000,'Données Suivi'!$A$2:$A$3000,$C$3,'Données Suivi'!$C$2:$C$3000,$C$5,'Données Suivi'!$H$2:$H$3000,$A24,'Données Suivi'!$O$2:$O$3000,"FONCTIONNEMENT") | D24: =SUMIFS('Données Suivi'!$J$2:$J$3000,'Données Suivi'!$A$2:$A$3000,$C$3,'Données Suivi'!$C$2:$C$3000,$C$5,'Données Suivi'!$H$2:$H$3000,$A24,'Données Suivi'!$O$2:$O$3000,"INVESTISSEMENT")
A25: TOTAL direction + BCI | B25: =SUM(B20:B24) | C25: =SUM(C20:C24) | D25: =SUM(D20:D24)
A27: Détail des dossiers Non Engagé (Statut Support d'Engagement) — Direction sélectionnée
A28: Statut Support (Non Engagé) | B28: Nb dossiers | C28: Montant (MAD)
A29: INFRUCTUEUX | B29: =COUNTIFS('Données Suivi'!$A$2:$A$3000,$C$3,'Données Suivi'!$H$2:$H$3000,"NON ENGAGE",'Données Suivi'!$E$2:$E$3000,$A29) | C29: =SUMIFS('Données Suivi'!$J$2:$J$3000,'Données Suivi'!$A$2:$A$3000,$C$3,'Données Suivi'!$H$2:$H$3000,"NON ENGAGE",'Données Suivi'!$E$2:$E$3000,$A29)
A30: ANNULE | B30: =COUNTIFS('Données Suivi'!$A$2:$A$3000,$C$3,'Données Suivi'!$H$2:$H$3000,"NON ENGAGE",'Données Suivi'!$E$2:$E$3000,$A30) | C30: =SUMIFS('Données Suivi'!$J$2:$J$3000,'Données Suivi'!$A$2:$A$3000,$C$3,'Données Suivi'!$H$2:$H$3000,"NON ENGAGE",'Données Suivi'!$E$2:$E$3000,$A30)
A31: EN SIGNATURE | B31: =COUNTIFS('Données Suivi'!$A$2:$A$3000,$C$3,'Données Suivi'!$H$2:$H$3000,"NON ENGAGE",'Données Suivi'!$E$2:$E$3000,$A31) | C31: =SUMIFS('Données Suivi'!$J$2:$J$3000,'Données Suivi'!$A$2:$A$3000,$C$3,'Données Suivi'!$H$2:$H$3000,"NON ENGAGE",'Données Suivi'!$E$2:$E$3000,$A31)
A32: TOTAL Non Engagé — direction | B32: =SUM(B29:B31) | C32: =SUM(C29:C31)
A34: Détail des dossiers Infructueux / Annulé — Direction sélectionnée
A35: Objet | B35: Réf | C35: BCI | D35: Statut Support | E35: Montant (MAD) | F35: Date Fiche
A36: =IF($T36="","",INDEX('Données Suivi'!$D$2:$D$3000,$T36)) | B36: =IF($T36="","",INDEX('Données Suivi'!$B$2:$B$3000,$T36)) | C36: =IF($T36="","",INDEX('Données Suivi'!$C$2:$C$3000,$T36)) | D36: =IF($T36="","",INDEX('Données Suivi'!$E$2:$E$3000,$T36)) | E36: =IF($T36="","",INDEX('Données Suivi'!$J$2:$J$3000,$T36)) | F36: =IF($T36="","",INDEX('Données Suivi'!$K$2:$K$3000,$T36)) | T36: =IFERROR(MATCH($C$3&"|"&1,'Données Suivi'!$Q$2:$Q$3000,0),"")
A37: =IF($T37="","",INDEX('Données Suivi'!$D$2:$D$3000,$T37)) | B37: =IF($T37="","",INDEX('Données Suivi'!$B$2:$B$3000,$T37)) | C37: =IF($T37="","",INDEX('Données Suivi'!$C$2:$C$3000,$T37)) | D37: =IF($T37="","",INDEX('Données Suivi'!$E$2:$E$3000,$T37)) | E37: =IF($T37="","",INDEX('Données Suivi'!$J$2:$J$3000,$T37)) | F37: =IF($T37="","",INDEX('Données Suivi'!$K$2:$K$3000,$T37)) | T37: =IFERROR(MATCH($C$3&"|"&2,'Données Suivi'!$Q$2:$Q$3000,0),"")
A38: =IF($T38="","",INDEX('Données Suivi'!$D$2:$D$3000,$T38)) | B38: =IF($T38="","",INDEX('Données Suivi'!$B$2:$B$3000,$T38)) | C38: =IF($T38="","",INDEX('Données Suivi'!$C$2:$C$3000,$T38)) | D38: =IF($T38="","",INDEX('Données Suivi'!$E$2:$E$3000,$T38)) | E38: =IF($T38="","",INDEX('Données Suivi'!$J$2:$J$3000,$T38)) | F38: =IF($T38="","",INDEX('Données Suivi'!$K$2:$K$3000,$T38)) | T38: =IFERROR(MATCH($C$3&"|"&3,'Données Suivi'!$Q$2:$Q$3000,0),"")
A39: =IF($T39="","",INDEX('Données Suivi'!$D$2:$D$3000,$T39)) | B39: =IF($T39="","",INDEX('Données Suivi'!$B$2:$B$3000,$T39)) | C39: =IF($T39="","",INDEX('Données Suivi'!$C$2:$C$3000,$T39)) | D39: =IF($T39="","",INDEX('Données Suivi'!$E$2:$E$3000,$T39)) | E39: =IF($T39="","",INDEX('Données Suivi'!$J$2:$J$3000,$T39)) | F39: =IF($T39="","",INDEX('Données Suivi'!$K$2:$K$3000,$T39)) | T39: =IFERROR(MATCH($C$3&"|"&4,'Données Suivi'!$Q$2:$Q$3000,0),"")
A40: =IF($T40="","",INDEX('Données Suivi'!$D$2:$D$3000,$T40)) | B40: =IF($T40="","",INDEX('Données Suivi'!$B$2:$B$3000,$T40)) | C40: =IF($T40="","",INDEX('Données Suivi'!$C$2:$C$3000,$T40)) | D40: =IF($T40="","",INDEX('Données Suivi'!$E$2:$E$3000,$T40)) | E40: =IF($T40="","",INDEX('Données Suivi'!$J$2:$J$3000,$T40)) | F40: =IF($T40="","",INDEX('Données Suivi'!$K$2:$K$3000,$T40)) | T40: =IFERROR(MATCH($C$3&"|"&5,'Données Suivi'!$Q$2:$Q$3000,0),"")
A41: =IF($T41="","",INDEX('Données Suivi'!$D$2:$D$3000,$T41)) | B41: =IF($T41="","",INDEX('Données Suivi'!$B$2:$B$3000,$T41)) | C41: =IF($T41="","",INDEX('Données Suivi'!$C$2:$C$3000,$T41)) | D41: =IF($T41="","",INDEX('Données Suivi'!$E$2:$E$3000,$T41)) | E41: =IF($T41="","",INDEX('Données Suivi'!$J$2:$J$3000,$T41)) | F41: =IF($T41="","",INDEX('Données Suivi'!$K$2:$K$3000,$T41)) | T41: =IFERROR(MATCH($C$3&"|"&6,'Données Suivi'!$Q$2:$Q$3000,0),"")
A42: =IF($T42="","",INDEX('Données Suivi'!$D$2:$D$3000,$T42)) | B42: =IF($T42="","",INDEX('Données Suivi'!$B$2:$B$3000,$T42)) | C42: =IF($T42="","",INDEX('Données Suivi'!$C$2:$C$3000,$T42)) | D42: =IF($T42="","",INDEX('Données Suivi'!$E$2:$E$3000,$T42)) | E42: =IF($T42="","",INDEX('Données Suivi'!$J$2:$J$3000,$T42)) | F42: =IF($T42="","",INDEX('Données Suivi'!$K$2:$K$3000,$T42)) | T42: =IFERROR(MATCH($C$3&"|"&7,'Données Suivi'!$Q$2:$Q$3000,0),"")
A43: =IF($T43="","",INDEX('Données Suivi'!$D$2:$D$3000,$T43)) | B43: =IF($T43="","",INDEX('Données Suivi'!$B$2:$B$3000,$T43)) | C43: =IF($T43="","",INDEX('Données Suivi'!$C$2:$C$3000,$T43)) | D43: =IF($T43="","",INDEX('Données Suivi'!$E$2:$E$3000,$T43)) | E43: =IF($T43="","",INDEX('Données Suivi'!$J$2:$J$3000,$T43)) | F43: =IF($T43="","",INDEX('Données Suivi'!$K$2:$K$3000,$T43)) | T43: =IFERROR(MATCH($C$3&"|"&8,'Données Suivi'!$Q$2:$Q$3000,0),"")
A44: =IF($T44="","",INDEX('Données Suivi'!$D$2:$D$3000,$T44)) | B44: =IF($T44="","",INDEX('Données Suivi'!$B$2:$B$3000,$T44)) | C44: =IF($T44="","",INDEX('Données Suivi'!$C$2:$C$3000,$T44)) | D44: =IF($T44="","",INDEX('Données Suivi'!$E$2:$E$3000,$T44)) | E44: =IF($T44="","",INDEX('Données Suivi'!$J$2:$J$3000,$T44)) | F44: =IF($T44="","",INDEX('Données Suivi'!$K$2:$K$3000,$T44)) | T44: =IFERROR(MATCH($C$3&"|"&9,'Données Suivi'!$Q$2:$Q$3000,0),"")
A45: =IF($T45="","",INDEX('Données Suivi'!$D$2:$D$3000,$T45)) | B45: =IF($T45="","",INDEX('Données Suivi'!$B$2:$B$3000,$T45)) | C45: =IF($T45="","",INDEX('Données Suivi'!$C$2:$C$3000,$T45)) | D45: =IF($T45="","",INDEX('Données Suivi'!$E$2:$E$3000,$T45)) | E45: =IF($T45="","",INDEX('Données Suivi'!$J$2:$J$3000,$T45)) | F45: =IF($T45="","",INDEX('Données Suivi'!$K$2:$K$3000,$T45)) | T45: =IFERROR(MATCH($C$3&"|"&10,'Données Suivi'!$Q$2:$Q$3000,0),"")
A46: =IF($T46="","",INDEX('Données Suivi'!$D$2:$D$3000,$T46)) | B46: =IF($T46="","",INDEX('Données Suivi'!$B$2:$B$3000,$T46)) | C46: =IF($T46="","",INDEX('Données Suivi'!$C$2:$C$3000,$T46)) | D46: =IF($T46="","",INDEX('Données Suivi'!$E$2:$E$3000,$T46)) | E46: =IF($T46="","",INDEX('Données Suivi'!$J$2:$J$3000,$T46)) | F46: =IF($T46="","",INDEX('Données Suivi'!$K$2:$K$3000,$T46)) | T46: =IFERROR(MATCH($C$3&"|"&11,'Données Suivi'!$Q$2:$Q$3000,0),"")
A47: =IF($T47="","",INDEX('Données Suivi'!$D$2:$D$3000,$T47)) | B47: =IF($T47="","",INDEX('Données Suivi'!$B$2:$B$3000,$T47)) | C47: =IF($T47="","",INDEX('Données Suivi'!$C$2:$C$3000,$T47)) | D47: =IF($T47="","",INDEX('Données Suivi'!$E$2:$E$3000,$T47)) | E47: =IF($T47="","",INDEX('Données Suivi'!$J$2:$J$3000,$T47)) | F47: =IF($T47="","",INDEX('Données Suivi'!$K$2:$K$3000,$T47)) | T47: =IFERROR(MATCH($C$3&"|"&12,'Données Suivi'!$Q$2:$Q$3000,0),"")
A48: =IF($T48="","",INDEX('Données Suivi'!$D$2:$D$3000,$T48)) | B48: =IF($T48="","",INDEX('Données Suivi'!$B$2:$B$3000,$T48)) | C48: =IF($T48="","",INDEX('Données Suivi'!$C$2:$C$3000,$T48)) | D48: =IF($T48="","",INDEX('Données Suivi'!$E$2:$E$3000,$T48)) | E48: =IF($T48="","",INDEX('Données Suivi'!$J$2:$J$3000,$T48)) | F48: =IF($T48="","",INDEX('Données Suivi'!$K$2:$K$3000,$T48)) | T48: =IFERROR(MATCH($C$3&"|"&13,'Données Suivi'!$Q$2:$Q$3000,0),"")
A49: =IF($T49="","",INDEX('Données Suivi'!$D$2:$D$3000,$T49)) | B49: =IF($T49="","",INDEX('Données Suivi'!$B$2:$B$3000,$T49)) | C49: =IF($T49="","",INDEX('Données Suivi'!$C$2:$C$3000,$T49)) | D49: =IF($T49="","",INDEX('Données Suivi'!$E$2:$E$3000,$T49)) | E49: =IF($T49="","",INDEX('Données Suivi'!$J$2:$J$3000,$T49)) | F49: =IF($T49="","",INDEX('Données Suivi'!$K$2:$K$3000,$T49)) | T49: =IFERROR(MATCH($C$3&"|"&14,'Données Suivi'!$Q$2:$Q$3000,0),"")
A50: =IF($T50="","",INDEX('Données Suivi'!$D$2:$D$3000,$T50)) | B50: =IF($T50="","",INDEX('Données Suivi'!$B$2:$B$3000,$T50)) | C50: =IF($T50="","",INDEX('Données Suivi'!$C$2:$C$3000,$T50)) | D50: =IF($T50="","",INDEX('Données Suivi'!$E$2:$E$3000,$T50)) | E50: =IF($T50="","",INDEX('Données Suivi'!$J$2:$J$3000,$T50)) | F50: =IF($T50="","",INDEX('Données Suivi'!$K$2:$K$3000,$T50)) | T50: =IFERROR(MATCH($C$3&"|"&15,'Données Suivi'!$Q$2:$Q$3000,0),"")
A51: =IF($T51="","",INDEX('Données Suivi'!$D$2:$D$3000,$T51)) | B51: =IF($T51="","",INDEX('Données Suivi'!$B$2:$B$3000,$T51)) | C51: =IF($T51="","",INDEX('Données Suivi'!$C$2:$C$3000,$T51)) | D51: =IF($T51="","",INDEX('Données Suivi'!$E$2:$E$3000,$T51)) | E51: =IF($T51="","",INDEX('Données Suivi'!$J$2:$J$3000,$T51)) | F51: =IF($T51="","",INDEX('Données Suivi'!$K$2:$K$3000,$T51)) | T51: =IFERROR(MATCH($C$3&"|"&16,'Données Suivi'!$Q$2:$Q$3000,0),"")
A52: =IF($T52="","",INDEX('Données Suivi'!$D$2:$D$3000,$T52)) | B52: =IF($T52="","",INDEX('Données Suivi'!$B$2:$B$3000,$T52)) | C52: =IF($T52="","",INDEX('Données Suivi'!$C$2:$C$3000,$T52)) | D52: =IF($T52="","",INDEX('Données Suivi'!$E$2:$E$3000,$T52)) | E52: =IF($T52="","",INDEX('Données Suivi'!$J$2:$J$3000,$T52)) | F52: =IF($T52="","",INDEX('Données Suivi'!$K$2:$K$3000,$T52)) | T52: =IFERROR(MATCH($C$3&"|"&17,'Données Suivi'!$Q$2:$Q$3000,0),"")
A53: =IF($T53="","",INDEX('Données Suivi'!$D$2:$D$3000,$T53)) | B53: =IF($T53="","",INDEX('Données Suivi'!$B$2:$B$3000,$T53)) | C53: =IF($T53="","",INDEX('Données Suivi'!$C$2:$C$3000,$T53)) | D53: =IF($T53="","",INDEX('Données Suivi'!$E$2:$E$3000,$T53)) | E53: =IF($T53="","",INDEX('Données Suivi'!$J$2:$J$3000,$T53)) | F53: =IF($T53="","",INDEX('Données Suivi'!$K$2:$K$3000,$T53)) | T53: =IFERROR(MATCH($C$3&"|"&18,'Données Suivi'!$Q$2:$Q$3000,0),"")
A54: =IF($T54="","",INDEX('Données Suivi'!$D$2:$D$3000,$T54)) | B54: =IF($T54="","",INDEX('Données Suivi'!$B$2:$B$3000,$T54)) | C54: =IF($T54="","",INDEX('Données Suivi'!$C$2:$C$3000,$T54)) | D54: =IF($T54="","",INDEX('Données Suivi'!$E$2:$E$3000,$T54)) | E54: =IF($T54="","",INDEX('Données Suivi'!$J$2:$J$3000,$T54)) | F54: =IF($T54="","",INDEX('Données Suivi'!$K$2:$K$3000,$T54)) | T54: =IFERROR(MATCH($C$3&"|"&19,'Données Suivi'!$Q$2:$Q$3000,0),"")
A55: =IF($T55="","",INDEX('Données Suivi'!$D$2:$D$3000,$T55)) | B55: =IF($T55="","",INDEX('Données Suivi'!$B$2:$B$3000,$T55)) | C55: =IF($T55="","",INDEX('Données Suivi'!$C$2:$C$3000,$T55)) | D55: =IF($T55="","",INDEX('Données Suivi'!$E$2:$E$3000,$T55)) | E55: =IF($T55="","",INDEX('Données Suivi'!$J$2:$J$3000,$T55)) | F55: =IF($T55="","",INDEX('Données Suivi'!$K$2:$K$3000,$T55)) | T55: =IFERROR(MATCH($C$3&"|"&20,'Données Suivi'!$Q$2:$Q$3000,0),"")

Sheet Tableau de Bord Suivi
A1: TABLEAU DE BORD DE SUIVI — ETAT D'ENGAGEMENTS 2026
A3: Nb dossiers total | C3: Montant total (MAD) | E3: Nb directions | G3: Taux d'engagement (montant) | I3: Montant restant à engager | K3: Nb dossiers en cours (à suivre)
A4: =COUNTIF('Données Suivi'!A2:A3000,"?*") | C4: =SUM('Données Suivi'!J2:J3000) | E4: =SUMPRODUCT(('Données Suivi'!$A$2:$A$3000<>"")/COUNTIF('Données Suivi'!$A$2:$A$3000,'Données Suivi'!$A$2:$A$3000&"")) | G4: =SUMIF('Données Suivi'!M2:M3000,"Engagé",'Données Suivi'!J2:J3000)/SUM('Données Suivi'!J2:J3000) | I4: =SUMIF('Données Suivi'!M2:M3000,"En cours",'Données Suivi'!J2:J3000) | K4: =COUNTIF('Données Suivi'!M2:M3000,"En cours")
A6: Nb clôturés sans suite | C6: Ancienneté moy. dossiers en cours (j)
A7: =COUNTIF('Données Suivi'!M2:M3000,"Clôturé sans suite") | C7: =AVERAGEIFS('Données Suivi'!L2:L3000,'Données Suivi'!M2:M3000,"En cours",'Données Suivi'!L2:L3000,">=0")
A10: Répartition des dossiers par Direction et par BCI (type d'achat) — Nombre de dossiers
A11: Direction | B11: CONTRAT | C11: AOO-M | D11: AOO-CT | E11: BCL | F11: BCI | G11: CA | H11: TOTAL
A12: ARRIYADIA | B12: =COUNTIFS('Données Suivi'!$A$2:$A$3000,$A12,'Données Suivi'!$C$2:$C$3000,"CONTRAT") | C12: =COUNTIFS('Données Suivi'!$A$2:$A$3000,$A12,'Données Suivi'!$C$2:$C$3000,"AOO-M") | D12: =COUNTIFS('Données Suivi'!$A$2:$A$3000,$A12,'Données Suivi'!$C$2:$C$3000,"AOO-CT") | E12: =COUNTIFS('Données Suivi'!$A$2:$A$3000,$A12,'Données Suivi'!$C$2:$C$3000,"BCL") | F12: =COUNTIFS('Données Suivi'!$A$2:$A$3000,$A12,'Données Suivi'!$C$2:$C$3000,"BCI") | G12: =COUNTIFS('Données Suivi'!$A$2:$A$3000,$A12,'Données Suivi'!$C$2:$C$3000,"CA") | H12: =COUNTIF('Données Suivi'!$A$2:$A$3000,$A12)
A13: ASSADISSA | B13: =COUNTIFS('Données Suivi'!$A$2:$A$3000,$A13,'Données Suivi'!$C$2:$C$3000,"CONTRAT") | C13: =COUNTIFS('Données Suivi'!$A$2:$A$3000,$A13,'Données Suivi'!$C$2:$C$3000,"AOO-M") | D13: =COUNTIFS('Données Suivi'!$A$2:$A$3000,$A13,'Données Suivi'!$C$2:$C$3000,"AOO-CT") | E13: =COUNTIFS('Données Suivi'!$A$2:$A$3000,$A13,'Données Suivi'!$C$2:$C$3000,"BCL") | F13: =COUNTIFS('Données Suivi'!$A$2:$A$3000,$A13,'Données Suivi'!$C$2:$C$3000,"BCI") | G13: =COUNTIFS('Données Suivi'!$A$2:$A$3000,$A13,'Données Suivi'!$C$2:$C$3000,"CA") | H13: =COUNTIF('Données Suivi'!$A$2:$A$3000,$A13)
A14: DA | B14: =COUNTIFS('Données Suivi'!$A$2:$A$3000,$A14,'Données Suivi'!$C$2:$C$3000,"CONTRAT") | C14: =COUNTIFS('Données Suivi'!$A$2:$A$3000,$A14,'Données Suivi'!$C$2:$C$3000,"AOO-M") | D14: =COUNTIFS('Données Suivi'!$A$2:$A$3000,$A14,'Données Suivi'!$C$2:$C$3000,"AOO-CT") | E14: =COUNTIFS('Données Suivi'!$A$2:$A$3000,$A14,'Données Suivi'!$C$2:$C$3000,"BCL") | F14: =COUNTIFS('Données Suivi'!$A$2:$A$3000,$A14,'Données Suivi'!$C$2:$C$3000,"BCI") | G14: =COUNTIFS('Données Suivi'!$A$2:$A$3000,$A14,'Données Suivi'!$C$2:$C$3000,"CA") | H14: =COUNTIF('Données Suivi'!$A$2:$A$3000,$A14)
A15: DACG | B15: =COUNTIFS('Données Suivi'!$A$2:$A$3000,$A15,'Données Suivi'!$C$2:$C$3000,"CONTRAT") | C15: =COUNTIFS('Données Suivi'!$A$2:$A$3000,$A15,'Données Suivi'!$C$2:$C$3000,"AOO-M") | D15: =COUNTIFS('Données Suivi'!$A$2:$A$3000,$A15,'Données Suivi'!$C$2:$C$3000,"AOO-CT") | E15: =COUNTIFS('Données Suivi'!$A$2:$A$3000,$A15,'Données Suivi'!$C$2:$C$3000,"BCL") | F15: =COUNTIFS('Données Suivi'!$A$2:$A$3000,$A15,'Données Suivi'!$C$2:$C$3000,"BCI") | G15: =COUNTIFS('Données Suivi'!$A$2:$A$3000,$A15,'Données Suivi'!$C$2:$C$3000,"CA") | H15: =COUNTIF('Données Suivi'!$A$2:$A$3000,$A15)
A16: DAR | B16: =COUNTIFS('Données Suivi'!$A$2:$A$3000,$A16,'Données Suivi'!$C$2:$C$3000,"CONTRAT") | C16: =COUNTIFS('Données Suivi'!$A$2:$A$3000,$A16,'Données Suivi'!$C$2:$C$3000,"AOO-M") | D16: =COUNTIFS('Données Suivi'!$A$2:$A$3000,$A16,'Données Suivi'!$C$2:$C$3000,"AOO-CT") | E16: =COUNTIFS('Données Suivi'!$A$2:$A$3000,$A16,'Données Suivi'!$C$2:$C$3000,"BCL") | F16: =COUNTIFS('Données Suivi'!$A$2:$A$3000,$A16,'Données Suivi'!$C$2:$C$3000,"BCI") | G16: =COUNTIFS('Données Suivi'!$A$2:$A$3000,$A16,'Données Suivi'!$C$2:$C$3000,"CA") | H16: =COUNTIF('Données Suivi'!$A$2:$A$3000,$A16)
A17: DCPA | B17: =COUNTIFS('Données Suivi'!$A$2:$A$3000,$A17,'Données Suivi'!$C$2:$C$3000,"CONTRAT") | C17: =COUNTIFS('Données Suivi'!$A$2:$A$3000,$A17,'Données Suivi'!$C$2:$C$3000,"AOO-M") | D17: =COUNTIFS('Données Suivi'!$A$2:$A$3000,$A17,'Données Suivi'!$C$2:$C$3000,"AOO-CT") | E17: =COUNTIFS('Données Suivi'!$A$2:$A$3000,$A17,'Données Suivi'!$C$2:$C$3000,"BCL") | F17: =COUNTIFS('Données Suivi'!$A$2:$A$3000,$A17,'Données Suivi'!$C$2:$C$3000,"BCI") | G17: =COUNTIFS('Données Suivi'!$A$2:$A$3000,$A17,'Données Suivi'!$C$2:$C$3000,"CA") | H17: =COUNTIF('Données Suivi'!$A$2:$A$3000,$A17)
A18: DCRI | B18: =COUNTIFS('Données Suivi'!$A$2:$A$3000,$A18,'Données Suivi'!$C$2:$C$3000,"CONTRAT") | C18: =COUNTIFS('Données Suivi'!$A$2:$A$3000,$A18,'Données Suivi'!$C$2:$C$3000,"AOO-M") | D18: =COUNTIFS('Données Suivi'!$A$2:$A$3000,$A18,'Données Suivi'!$C$2:$C$3000,"AOO-CT") | E18: =COUNTIFS('Données Suivi'!$A$2:$A$3000,$A18,'Données Suivi'!$C$2:$C$3000,"BCL") | F18: =COUNTIFS('Données Suivi'!$A$2:$A$3000,$A18,'Données Suivi'!$C$2:$C$3000,"BCI") | G18: =COUNTIFS('Données Suivi'!$A$2:$A$3000,$A18,'Données Suivi'!$C$2:$C$3000,"CA") | H18: =COUNTIF('Données Suivi'!$A$2:$A$3000,$A18)
A19: DCT | B19: =COUNTIFS('Données Suivi'!$A$2:$A$3000,$A19,'Données Suivi'!$C$2:$C$3000,"CONTRAT") | C19: =COUNTIFS('Données Suivi'!$A$2:$A$3000,$A19,'Données Suivi'!$C$2:$C$3000,"AOO-M") | D19: =COUNTIFS('Données Suivi'!$A$2:$A$3000,$A19,'Données Suivi'!$C$2:$C$3000,"AOO-CT") | E19: =COUNTIFS('Données Suivi'!$A$2:$A$3000,$A19,'Données Suivi'!$C$2:$C$3000,"BCL") | F19: =COUNTIFS('Données Suivi'!$A$2:$A$3000,$A19,'Données Suivi'!$C$2:$C$3000,"BCI") | G19: =COUNTIFS('Données Suivi'!$A$2:$A$3000,$A19,'Données Suivi'!$C$2:$C$3000,"CA") | H19: =COUNTIF('Données Suivi'!$A$2:$A$3000,$A19)
A20: DG | B20: =COUNTIFS('Données Suivi'!$A$2:$A$3000,$A20,'Données Suivi'!$C$2:$C$3000,"CONTRAT") | C20: =COUNTIFS('Données Suivi'!$A$2:$A$3000,$A20,'Données Suivi'!$C$2:$C$3000,"AOO-M") | D20: =COUNTIFS('Données Suivi'!$A$2:$A$3000,$A20,'Données Suivi'!$C$2:$C$3000,"AOO-CT") | E20: =COUNTIFS('Données Suivi'!$A$2:$A$3000,$A20,'Données Suivi'!$C$2:$C$3000,"BCL") | F20: =COUNTIFS('Données Suivi'!$A$2:$A$3000,$A20,'Données Suivi'!$C$2:$C$3000,"BCI") | G20: =COUNTIFS('Données Suivi'!$A$2:$A$3000,$A20,'Données Suivi'!$C$2:$C$3000,"CA") | H20: =COUNTIF('Données Suivi'!$A$2:$A$3000,$A20)
A21: DINFORADIO | B21: =COUNTIFS('Données Suivi'!$A$2:$A$3000,$A21,'Données Suivi'!$C$2:$C$3000,"CONTRAT") | C21: =COUNTIFS('Données Suivi'!$A$2:$A$3000,$A21,'Données Suivi'!$C$2:$C$3000,"AOO-M") | D21: =COUNTIFS('Données Suivi'!$A$2:$A$3000,$A21,'Données Suivi'!$C$2:$C$3000,"AOO-CT") | E21: =COUNTIFS('Données Suivi'!$A$2:$A$3000,$A21,'Données Suivi'!$C$2:$C$3000,"BCL") | F21: =COUNTIFS('Données Suivi'!$A$2:$A$3000,$A21,'Données Suivi'!$C$2:$C$3000,"BCI") | G21: =COUNTIFS('Données Suivi'!$A$2:$A$3000,$A21,'Données Suivi'!$C$2:$C$3000,"CA") | H21: =COUNTIF('Données Suivi'!$A$2:$A$3000,$A21)
A22: DINFOTV | B22: =COUNTIFS('Données Suivi'!$A$2:$A$3000,$A22,'Données Suivi'!$C$2:$C$3000,"CONTRAT") | C22: =COUNTIFS('Données Suivi'!$A$2:$A$3000,$A22,'Données Suivi'!$C$2:$C$3000,"AOO-M") | D22: =COUNTIFS('Données Suivi'!$A$2:$A$3000,$A22,'Données Suivi'!$C$2:$C$3000,"AOO-CT") | E22: =COUNTIFS('Données Suivi'!$A$2:$A$3000,$A22,'Données Suivi'!$C$2:$C$3000,"BCL") | F22: =COUNTIFS('Données Suivi'!$A$2:$A$3000,$A22,'Données Suivi'!$C$2:$C$3000,"BCI") | G22: =COUNTIFS('Données Suivi'!$A$2:$A$3000,$A22,'Données Suivi'!$C$2:$C$3000,"CA") | H22: =COUNTIF('Données Suivi'!$A$2:$A$3000,$A22)
A23: DJURIDIQUE | B23: =COUNTIFS('Données Suivi'!$A$2:$A$3000,$A23,'Données Suivi'!$C$2:$C$3000,"CONTRAT") | C23: =COUNTIFS('Données Suivi'!$A$2:$A$3000,$A23,'Données Suivi'!$C$2:$C$3000,"AOO-M") | D23: =COUNTIFS('Données Suivi'!$A$2:$A$3000,$A23,'Données Suivi'!$C$2:$C$3000,"AOO-CT") | E23: =COUNTIFS('Données Suivi'!$A$2:$A$3000,$A23,'Données Suivi'!$C$2:$C$3000,"BCL") | F23: =COUNTIFS('Données Suivi'!$A$2:$A$3000,$A23,'Données Suivi'!$C$2:$C$3000,"BCI") | G23: =COUNTIFS('Données Suivi'!$A$2:$A$3000,$A23,'Données Suivi'!$C$2:$C$3000,"CA") | H23: =COUNTIF('Données Suivi'!$A$2:$A$3000,$A23)
... A34: TV LAAYOUNE | B34: =COUNTIFS('Données Suivi'!$A$2:$A$3000,$A34,'Données Suivi'!$C$2:$C$3000,"CONTRAT") | C34: =COUNTIFS('Données Suivi'!$A$2:$A$3000,$A34,'Données Suivi'!$C$2:$C$3000,"AOO-M") | D34: =COUNTIFS('Données Suivi'!$A$2:$A$3000,$A34,'Données Suivi'!$C$2:$C$3000,"AOO-CT") | E34: =COUNTIFS('Données Suivi'!$A$2:$A$3000,$A34,'Données Suivi'!$C$2:$C$3000,"BCL") | F34: =COUNTIFS('Données Suivi'!$A$2:$A$3000,$A34,'Données Suivi'!$C$2:$C$3000,"BCI") | G34: =COUNTIFS('Données Suivi'!$A$2:$A$3000,$A34,'Données Suivi'!$C$2:$C$3000,"CA") | H34: =COUNTIF('Données Suivi'!$A$2:$A$3000,$A34)
A35: TOTAL | B35: =SUM(B12:B34) | C35: =SUM(C12:C34) | D35: =SUM(D12:D34) | E35: =SUM(E12:E34) | F35: =SUM(F12:F34) | G35: =SUM(G12:G34) | H35: =SUM(H12:H34)
A37: Répartition des dossiers par Direction et par Statut d'Engagement — Nombre de dossiers
A38: Direction | B38: NON ENGAGE | C38: EN COURS DE PREENGAGEMENT | D38: PREENGAGE | E38: EN COURS D'ENGAGEMENT | F38: ENGAGE | G38: TOTAL
A39: ARRIYADIA | B39: =COUNTIFS('Données Suivi'!$A$2:$A$3000,$A39,'Données Suivi'!$H$2:$H$3000,"NON ENGAGE") | C39: =COUNTIFS('Données Suivi'!$A$2:$A$3000,$A39,'Données Suivi'!$H$2:$H$3000,"EN COURS DE PREENGAGEMENT") | D39: =COUNTIFS('Données Suivi'!$A$2:$A$3000,$A39,'Données Suivi'!$H$2:$H$3000,"PREENGAGE") | E39: =COUNTIFS('Données Suivi'!$A$2:$A$3000,$A39,'Données Suivi'!$H$2:$H$3000,"EN COURS D'ENGAGEMENT") | F39: =COUNTIFS('Données Suivi'!$A$2:$A$3000,$A39,'Données Suivi'!$H$2:$H$3000,"ENGAGE") | G39: =COUNTIF('Données Suivi'!$A$2:$A$3000,$A39)
A40: ASSADISSA | B40: =COUNTIFS('Données Suivi'!$A$2:$A$3000,$A40,'Données Suivi'!$H$2:$H$3000,"NON ENGAGE") | C40: =COUNTIFS('Données Suivi'!$A$2:$A$3000,$A40,'Données Suivi'!$H$2:$H$3000,"EN COURS DE PREENGAGEMENT") | D40: =COUNTIFS('Données Suivi'!$A$2:$A$3000,$A40,'Données Suivi'!$H$2:$H$3000,"PREENGAGE") | E40: =COUNTIFS('Données Suivi'!$A$2:$A$3000,$A40,'Données Suivi'!$H$2:$H$3000,"EN COURS D'ENGAGEMENT") | F40: =COUNTIFS('Données Suivi'!$A$2:$A$3000,$A40,'Données Suivi'!$H$2:$H$3000,"ENGAGE") | G40: =COUNTIF('Données Suivi'!$A$2:$A$3000,$A40)
A41: DA | B41: =COUNTIFS('Données Suivi'!$A$2:$A$3000,$A41,'Données Suivi'!$H$2:$H$3000,"NON ENGAGE") | C41: =COUNTIFS('Données Suivi'!$A$2:$A$3000,$A41,'Données Suivi'!$H$2:$H$3000,"EN COURS DE PREENGAGEMENT") | D41: =COUNTIFS('Données Suivi'!$A$2:$A$3000,$A41,'Données Suivi'!$H$2:$H$3000,"PREENGAGE") | E41: =COUNTIFS('Données Suivi'!$A$2:$A$3000,$A41,'Données Suivi'!$H$2:$H$3000,"EN COURS D'ENGAGEMENT") | F41: =COUNTIFS('Données Suivi'!$A$2:$A$3000,$A41,'Données Suivi'!$H$2:$H$3000,"ENGAGE") | G41: =COUNTIF('Données Suivi'!$A$2:$A$3000,$A41)
A42: DACG | B42: =COUNTIFS('Données Suivi'!$A$2:$A$3000,$A42,'Données Suivi'!$H$2:$H$3000,"NON ENGAGE") | C42: =COUNTIFS('Données Suivi'!$A$2:$A$3000,$A42,'Données Suivi'!$H$2:$H$3000,"EN COURS DE PREENGAGEMENT") | D42: =COUNTIFS('Données Suivi'!$A$2:$A$3000,$A42,'Données Suivi'!$H$2:$H$3000,"PREENGAGE") | E42: =COUNTIFS('Données Suivi'!$A$2:$A$3000,$A42,'Données Suivi'!$H$2:$H$3000,"EN COURS D'ENGAGEMENT") | F42: =COUNTIFS('Données Suivi'!$A$2:$A$3000,$A42,'Données Suivi'!$H$2:$H$3000,"ENGAGE") | G42: =COUNTIF('Données Suivi'!$A$2:$A$3000,$A42)
A43: DAR | B43: =COUNTIFS('Données Suivi'!$A$2:$A$3000,$A43,'Données Suivi'!$H$2:$H$3000,"NON ENGAGE") | C43: =COUNTIFS('Données Suivi'!$A$2:$A$3000,$A43,'Données Suivi'!$H$2:$H$3000,"EN COURS DE PREENGAGEMENT") | D43: =COUNTIFS('Données Suivi'!$A$2:$A$3000,$A43,'Données Suivi'!$H$2:$H$3000,"PREENGAGE") | E43: =COUNTIFS('Données Suivi'!$A$2:$A$3000,$A43,'Données Suivi'!$H$2:$H$3000,"EN COURS D'ENGAGEMENT") | F43: =COUNTIFS('Données Suivi'!$A$2:$A$3000,$A43,'Données Suivi'!$H$2:$H$3000,"ENGAGE") | G43: =COUNTIF('Données Suivi'!$A$2:$A$3000,$A43)
A44: DCPA | B44: =COUNTIFS('Données Suivi'!$A$2:$A$3000,$A44,'Données Suivi'!$H$2:$H$3000,"NON ENGAGE") | C44: =COUNTIFS('Données Suivi'!$A$2:$A$3000,$A44,'Données Suivi'!$H$2:$H$3000,"EN COURS DE PREENGAGEMENT") | D44: =COUNTIFS('Données Suivi'!$A$2:$A$3000,$A44,'Données Suivi'!$H$2:$H$3000,"PREENGAGE") | E44: =COUNTIFS('Données Suivi'!$A$2:$A$3000,$A44,'Données Suivi'!$H$2:$H$3000,"EN COURS D'ENGAGEMENT") | F44: =COUNTIFS('Données Suivi'!$A$2:$A$3000,$A44,'Données Suivi'!$H$2:$H$3000,"ENGAGE") | G44: =COUNTIF('Données Suivi'!$A$2:$A$3000,$A44)
A45: DCRI | B45: =COUNTIFS('Données Suivi'!$A$2:$A$3000,$A45,'Données Suivi'!$H$2:$H$3000,"NON ENGAGE") | C45: =COUNTIFS('Données Suivi'!$A$2:$A$3000,$A45,'Données Suivi'!$H$2:$H$3000,"EN COURS DE PREENGAGEMENT") | D45: =COUNTIFS('Données Suivi'!$A$2:$A$3000,$A45,'Données Suivi'!$H$2:$H$3000,"PREENGAGE") | E45: =COUNTIFS('Données Suivi'!$A$2:$A$3000,$A45,'Données Suivi'!$H$2:$H$3000,"EN COURS D'ENGAGEMENT") | F45: =COUNTIFS('Données Suivi'!$A$2:$A$3000,$A45,'Données Suivi'!$H$2:$H$3000,"ENGAGE") | G45: =COUNTIF('Données Suivi'!$A$2:$A$3000,$A45)
A46: DCT | B46: =COUNTIFS('Données Suivi'!$A$2:$A$3000,$A46,'Données Suivi'!$H$2:$H$3000,"NON ENGAGE") | C46: =COUNTIFS('Données Suivi'!$A$2:$A$3000,$A46,'Données Suivi'!$H$2:$H$3000,"EN COURS DE PREENGAGEMENT") | D46: =COUNTIFS('Données Suivi'!$A$2:$A$3000,$A46,'Données Suivi'!$H$2:$H$3000,"PREENGAGE") | E46: =COUNTIFS('Données Suivi'!$A$2:$A$3000,$A46,'Données Suivi'!$H$2:$H$3000,"EN COURS D'ENGAGEMENT") | F46: =COUNTIFS('Données Suivi'!$A$2:$A$3000,$A46,'Données Suivi'!$H$2:$H$3000,"ENGAGE") | G46: =COUNTIF('Données Suivi'!$A$2:$A$3000,$A46)
A47: DG | B47: =COUNTIFS('Données Suivi'!$A$2:$A$3000,$A47,'Données Suivi'!$H$2:$H$3000,"NON ENGAGE") | C47: =COUNTIFS('Données Suivi'!$A$2:$A$3000,$A47,'Données Suivi'!$H$2:$H$3000,"EN COURS DE PREENGAGEMENT") | D47: =COUNTIFS('Données Suivi'!$A$2:$A$3000,$A47,'Données Suivi'!$H$2:$H$3000,"PREENGAGE") | E47: =COUNTIFS('Données Suivi'!$A$2:$A$3000,$A47,'Données Suivi'!$H$2:$H$3000,"EN COURS D'ENGAGEMENT") | F47: =COUNTIFS('Données Suivi'!$A$2:$A$3000,$A47,'Données Suivi'!$H$2:$H$3000,"ENGAGE") | G47: =COUNTIF('Données Suivi'!$A$2:$A$3000,$A47)
A48: DINFORADIO | B48: =COUNTIFS('Données Suivi'!$A$2:$A$3000,$A48,'Données Suivi'!$H$2:$H$3000,"NON ENGAGE") | C48: =COUNTIFS('Données Suivi'!$A$2:$A$3000,$A48,'Données Suivi'!$H$2:$H$3000,"EN COURS DE PREENGAGEMENT") | D48: =COUNTIFS('Données Suivi'!$A$2:$A$3000,$A48,'Données Suivi'!$H$2:$H$3000,"PREENGAGE") | E48: =COUNTIFS('Données Suivi'!$A$2:$A$3000,$A48,'Données Suivi'!$H$2:$H$3000,"EN COURS D'ENGAGEMENT") | F48: =COUNTIFS('Données Suivi'!$A$2:$A$3000,$A48,'Données Suivi'!$H$2:$H$3000,"ENGAGE") | G48: =COUNTIF('Données Suivi'!$A$2:$A$3000,$A48)
A49: DINFOTV | B49: =COUNTIFS('Données Suivi'!$A$2:$A$3000,$A49,'Données Suivi'!$H$2:$H$3000,"NON ENGAGE") | C49: =COUNTIFS('Données Suivi'!$A$2:$A$3000,$A49,'Données Suivi'!$H$2:$H$3000,"EN COURS DE PREENGAGEMENT") | D49: =COUNTIFS('Données Suivi'!$A$2:$A$3000,$A49,'Données Suivi'!$H$2:$H$3000,"PREENGAGE") | E49: =COUNTIFS('Données Suivi'!$A$2:$A$3000,$A49,'Données Suivi'!$H$2:$H$3000,"EN COURS D'ENGAGEMENT") | F49: =COUNTIFS('Données Suivi'!$A$2:$A$3000,$A49,'Données Suivi'!$H$2:$H$3000,"ENGAGE") | G49: =COUNTIF('Données Suivi'!$A$2:$A$3000,$A49)
A50: DJURIDIQUE | B50: =COUNTIFS('Données Suivi'!$A$2:$A$3000,$A50,'Données Suivi'!$H$2:$H$3000,"NON ENGAGE") | C50: =COUNTIFS('Données Suivi'!$A$2:$A$3000,$A50,'Données Suivi'!$H$2:$H$3000,"EN COURS DE PREENGAGEMENT") | D50: =COUNTIFS('Données Suivi'!$A$2:$A$3000,$A50,'Données Suivi'!$H$2:$H$3000,"PREENGAGE") | E50: =COUNTIFS('Données Suivi'!$A$2:$A$3000,$A50,'Données Suivi'!$H$2:$H$3000,"EN COURS D'ENGAGEMENT") | F50: =COUNTIFS('Données Suivi'!$A$2:$A$3000,$A50,'Données Suivi'!$H$2:$H$3000,"ENGAGE") | G50: =COUNTIF('Données Suivi'!$A$2:$A$3000,$A50)
... A61: TV LAAYOUNE | B61: =COUNTIFS('Données Suivi'!$A$2:$A$3000,$A61,'Données Suivi'!$H$2:$H$3000,"NON ENGAGE") | C61: =COUNTIFS('Données Suivi'!$A$2:$A$3000,$A61,'Données Suivi'!$H$2:$H$3000,"EN COURS DE PREENGAGEMENT") | D61: =COUNTIFS('Données Suivi'!$A$2:$A$3000,$A61,'Données Suivi'!$H$2:$H$3000,"PREENGAGE") | E61: =COUNTIFS('Données Suivi'!$A$2:$A$3000,$A61,'Données Suivi'!$H$2:$H$3000,"EN COURS D'ENGAGEMENT") | F61: =COUNTIFS('Données Suivi'!$A$2:$A$3000,$A61,'Données Suivi'!$H$2:$H$3000,"ENGAGE") | G61: =COUNTIF('Données Suivi'!$A$2:$A$3000,$A61)
A62: TOTAL | B62: =SUM(B39:B61) | C62: =SUM(C39:C61) | D62: =SUM(D39:D61) | E62: =SUM(E39:E61) | F62: =SUM(F39:F61) | G62: =SUM(G39:G61)
A64: Taux d'engagement par Direction (montant)
A65: Direction | B65: Montant total (MAD) | C65: Montant engagé (MAD) | D65: Taux d'engagement
A66: ARRIYADIA | B66: =SUMIF('Données Suivi'!$A$2:$A$3000,$A66,'Données Suivi'!$J$2:$J$3000) | C66: =SUMIFS('Données Suivi'!$J$2:$J$3000,'Données Suivi'!$A$2:$A$3000,$A66,'Données Suivi'!$M$2:$M$3000,"Engagé") | D66: =IF(B66=0,"",C66/B66)
A67: ASSADISSA | B67: =SUMIF('Données Suivi'!$A$2:$A$3000,$A67,'Données Suivi'!$J$2:$J$3000) | C67: =SUMIFS('Données Suivi'!$J$2:$J$3000,'Données Suivi'!$A$2:$A$3000,$A67,'Données Suivi'!$M$2:$M$3000,"Engagé") | D67: =IF(B67=0,"",C67/B67)
A68: DA | B68: =SUMIF('Données Suivi'!$A$2:$A$3000,$A68,'Données Suivi'!$J$2:$J$3000) | C68: =SUMIFS('Données Suivi'!$J$2:$J$3000,'Données Suivi'!$A$2:$A$3000,$A68,'Données Suivi'!$M$2:$M$3000,"Engagé") | D68: =IF(B68=0,"",C68/B68)
A69: DACG | B69: =SUMIF('Données Suivi'!$A$2:$A$3000,$A69,'Données Suivi'!$J$2:$J$3000) | C69: =SUMIFS('Données Suivi'!$J$2:$J$3000,'Données Suivi'!$A$2:$A$3000,$A69,'Données Suivi'!$M$2:$M$3000,"Engagé") | D69: =IF(B69=0,"",C69/B69)
A70: DAR | B70: =SUMIF('Données Suivi'!$A$2:$A$3000,$A70,'Données Suivi'!$J$2:$J$3000) | C70: =SUMIFS('Données Suivi'!$J$2:$J$3000,'Données Suivi'!$A$2:$A$3000,$A70,'Données Suivi'!$M$2:$M$3000,"Engagé") | D70: =IF(B70=0,"",C70/B70)
A71: DCPA | B71: =SUMIF('Données Suivi'!$A$2:$A$3000,$A71,'Données Suivi'!$J$2:$J$3000) | C71: =SUMIFS('Données Suivi'!$J$2:$J$3000,'Données Suivi'!$A$2:$A$3000,$A71,'Données Suivi'!$M$2:$M$3000,"Engagé") | D71: =IF(B71=0,"",C71/B71)
A72: DCRI | B72: =SUMIF('Données Suivi'!$A$2:$A$3000,$A72,'Données Suivi'!$J$2:$J$3000) | C72: =SUMIFS('Données Suivi'!$J$2:$J$3000,'Données Suivi'!$A$2:$A$3000,$A72,'Données Suivi'!$M$2:$M$3000,"Engagé") | D72: =IF(B72=0,"",C72/B72)
A73: DCT | B73: =SUMIF('Données Suivi'!$A$2:$A$3000,$A73,'Données Suivi'!$J$2:$J$3000) | C73: =SUMIFS('Données Suivi'!$J$2:$J$3000,'Données Suivi'!$A$2:$A$3000,$A73,'Données Suivi'!$M$2:$M$3000,"Engagé") | D73: =IF(B73=0,"",C73/B73)
A74: DG | B74: =SUMIF('Données Suivi'!$A$2:$A$3000,$A74,'Données Suivi'!$J$2:$J$3000) | C74: =SUMIFS('Données Suivi'!$J$2:$J$3000,'Données Suivi'!$A$2:$A$3000,$A74,'Données Suivi'!$M$2:$M$3000,"Engagé") | D74: =IF(B74=0,"",C74/B74)
A75: DINFORADIO | B75: =SUMIF('Données Suivi'!$A$2:$A$3000,$A75,'Données Suivi'!$J$2:$J$3000) | C75: =SUMIFS('Données Suivi'!$J$2:$J$3000,'Données Suivi'!$A$2:$A$3000,$A75,'Données Suivi'!$M$2:$M$3000,"Engagé") | D75: =IF(B75=0,"",C75/B75)
A76: DINFOTV | B76: =SUMIF('Données Suivi'!$A$2:$A$3000,$A76,'Données Suivi'!$J$2:$J$3000) | C76: =SUMIFS('Données Suivi'!$J$2:$J$3000,'Données Suivi'!$A$2:$A$3000,$A76,'Données Suivi'!$M$2:$M$3000,"Engagé") | D76: =IF(B76=0,"",C76/B76)
A77: DJURIDIQUE | B77: =SUMIF('Données Suivi'!$A$2:$A$3000,$A77,'Données Suivi'!$J$2:$J$3000) | C77: =SUMIFS('Données Suivi'!$J$2:$J$3000,'Données Suivi'!$A$2:$A$3000,$A77,'Données Suivi'!$M$2:$M$3000,"Engagé") | D77: =IF(B77=0,"",C77/B77)
... A88: TV LAAYOUNE | B88: =SUMIF('Données Suivi'!$A$2:$A$3000,$A88,'Données Suivi'!$J$2:$J$3000) | C88: =SUMIFS('Données Suivi'!$J$2:$J$3000,'Données Suivi'!$A$2:$A$3000,$A88,'Données Suivi'!$M$2:$M$3000,"Engagé") | D88: =IF(B88=0,"",C88/B88)
A90: Dossiers en cours à relancer (triés par ancienneté décroissante)
A91: Direction | B91: Réf | C91: BCI | D91: Objet | E91: Statut Support | F91: Statut d'Engagement | G91: Montant (MAD) | H91: Date Fiche | I91: Ancienneté (j)
A92: ='Données Suivi'!A327 | B92: ='Données Suivi'!B327 | C92: ='Données Suivi'!C327 | D92: ='Données Suivi'!D327 | E92: ='Données Suivi'!E327 | F92: ='Données Suivi'!H327 | G92: ='Données Suivi'!J327 | H92: ='Données Suivi'!K327 | I92: ='Données Suivi'!L327
A93: ='Données Suivi'!A328 | B93: ='Données Suivi'!B328 | C93: ='Données Suivi'!C328 | D93: ='Données Suivi'!D328 | E93: ='Données Suivi'!E328 | F93: ='Données Suivi'!H328 | G93: ='Données Suivi'!J328 | H93: ='Données Suivi'!K328 | I93: ='Données Suivi'!L328
A94: ='Données Suivi'!A359 | B94: ='Données Suivi'!B359 | C94: ='Données Suivi'!C359 | D94: ='Données Suivi'!D359 | E94: ='Données Suivi'!E359 | F94: ='Données Suivi'!H359 | G94: ='Données Suivi'!J359 | H94: ='Données Suivi'!K359 | I94: ='Données Suivi'!L359
A95: ='Données Suivi'!A378 | B95: ='Données Suivi'!B378 | C95: ='Données Suivi'!C378 | D95: ='Données Suivi'!D378 | E95: ='Données Suivi'!E378 | F95: ='Données Suivi'!H378 | G95: ='Données Suivi'!J378 | H95: ='Données Suivi'!K378 | I95: ='Données Suivi'!L378
A96: ='Données Suivi'!A379 | B96: ='Données Suivi'!B379 | C96: ='Données Suivi'!C379 | D96: ='Données Suivi'!D379 | E96: ='Données Suivi'!E379 | F96: ='Données Suivi'!H379 | G96: ='Données Suivi'!J379 | H96: ='Données Suivi'!K379 | I96: ='Données Suivi'!L379
A97: ='Données Suivi'!A430 | B97: ='Données Suivi'!B430 | C97: ='Données Suivi'!C430 | D97: ='Données Suivi'!D430 | E97: ='Données Suivi'!E430 | F97: ='Données Suivi'!H430 | G97: ='Données Suivi'!J430 | H97: ='Données Suivi'!K430 | I97: ='Données Suivi'!L430
A98: ='Données Suivi'!A410 | B98: ='Données Suivi'!B410 | C98: ='Données Suivi'!C410 | D98: ='Données Suivi'!D410 | E98: ='Données Suivi'!E410 | F98: ='Données Suivi'!H410 | G98: ='Données Suivi'!J410 | H98: ='Données Suivi'!K410 | I98: ='Données Suivi'!L410
A99: ='Données Suivi'!A620 | B99: ='Données Suivi'!B620 | C99: ='Données Suivi'!C620 | D99: ='Données Suivi'!D620 | E99: ='Données Suivi'!E620 | F99: ='Données Suivi'!H620 | G99: ='Données Suivi'!J620 | H99: ='Données Suivi'!K620 | I99: ='Données Suivi'!L620
A100: ='Données Suivi'!A557 | B100: ='Données Suivi'!B557 | C100: ='Données Suivi'!C557 | D100: ='Données Suivi'!D557 | E100: ='Données Suivi'!E557 | F100: ='Données Suivi'!H557 | G100: ='Données Suivi'!J557 | H100: ='Données Suivi'!K557 | I100: ='Données Suivi'!L557
A101: ='Données Suivi'!A329 | B101: ='Données Suivi'!B329 | C101: ='Données Suivi'!C329 | D101: ='Données Suivi'!D329 | E101: ='Données Suivi'!E329 | F101: ='Données Suivi'!H329 | G101: ='Données Suivi'!J329 | H101: ='Données Suivi'!K329 | I101: ='Données Suivi'!L329
A102: ='Données Suivi'!A573 | B102: ='Données Suivi'!B573 | C102: ='Données Suivi'!C573 | D102: ='Données Suivi'!D573 | E102: ='Données Suivi'!E573 | F102: ='Données Suivi'!H573 | G102: ='Données Suivi'!J573 | H102: ='Données Suivi'!K573 | I102: ='Données Suivi'!L573
A103: ='Données Suivi'!A574 | B103: ='Données Suivi'!B574 | C103: ='Données Suivi'!C574 | D103: ='Données Suivi'!D574 | E103: ='Données Suivi'!E574 | F103: ='Données Suivi'!H574 | G103: ='Données Suivi'!J574 | H103: ='Données Suivi'!K574 | I103: ='Données Suivi'!L574
A104: ='Données Suivi'!A577 | B104: ='Données Suivi'!B577 | C104: ='Données Suivi'!C577 | D104: ='Données Suivi'!D577 | E104: ='Données Suivi'!E577 | F104: ='Données Suivi'!H577 | G104: ='Données Suivi'!J577 | H104: ='Données Suivi'!K577 | I104: ='Données Suivi'!L577
A105: ='Données Suivi'!A578 | B105: ='Données Suivi'!B578 | C105: ='Données Suivi'!C578 | D105: ='Données Suivi'!D578 | E105: ='Données Suivi'!E578 | F105: ='Données Suivi'!H578 | G105: ='Données Suivi'!J578 | H105: ='Données Suivi'!K578 | I105: ='Données Suivi'!L578
A106: ='Données Suivi'!A579 | B106: ='Données Suivi'!B579 | C106: ='Données Suivi'!C579 | D106: ='Données Suivi'!D579 | E106: ='Données Suivi'!E579 | F106: ='Données Suivi'!H579 | G106: ='Données Suivi'!J579 | H106: ='Données Suivi'!K579 | I106: ='Données Suivi'!L579
A107: ='Données Suivi'!A582 | B107: ='Données Suivi'!B582 | C107: ='Données Suivi'!C582 | D107: ='Données Suivi'!D582 | E107: ='Données Suivi'!E582 | F107: ='Données Suivi'!H582 | G107: ='Données Suivi'!J582 | H107: ='Données Suivi'!K582 | I107: ='Données Suivi'!L582
A108: ='Données Suivi'!A583 | B108: ='Données Suivi'!B583 | C108: ='Données Suivi'!C583 | D108: ='Données Suivi'!D583 | E108: ='Données Suivi'!E583 | F108: ='Données Suivi'!H583 | G108: ='Données Suivi'!J583 | H108: ='Données Suivi'!K583 | I108: ='Données Suivi'!L583
A109: ='Données Suivi'!A584 | B109: ='Données Suivi'!B584 | C109: ='Données Suivi'!C584 | D109: ='Données Suivi'!D584 | E109: ='Données Suivi'!E584 | F109: ='Données Suivi'!H584 | G109: ='Données Suivi'!J584 | H109: ='Données Suivi'!K584 | I109: ='Données Suivi'!L584
A110: ='Données Suivi'!A585 | B110: ='Données Suivi'!B585 | C110: ='Données Suivi'!C585 | D110: ='Données Suivi'!D585 | E110: ='Données Suivi'!E585 | F110: ='Données Suivi'!H585 | G110: ='Données Suivi'!J585 | H110: ='Données Suivi'!K585 | I110: ='Données Suivi'!L585
A111: ='Données Suivi'!A586 | B111: ='Données Suivi'!B586 | C111: ='Données Suivi'!C586 | D111: ='Données Suivi'!D586 | E111: ='Données Suivi'!E586 | F111: ='Données Suivi'!H586 | G111: ='Données Suivi'!J586 | H111: ='Données Suivi'!K586 | I111: ='Données Suivi'!L586
A112: ='Données Suivi'!A587 | B112: ='Données Suivi'!B587 | C112: ='Données Suivi'!C587 | D112: ='Données Suivi'!D587 | E112: ='Données Suivi'!E587 | F112: ='Données Suivi'!H587 | G112: ='Données Suivi'!J587 | H112: ='Données Suivi'!K587 | I112: ='Données Suivi'!L587
A113: ='Données Suivi'!A588 | B113: ='Données Suivi'!B588 | C113: ='Données Suivi'!C588 | D113: ='Données Suivi'!D588 | E113: ='Données Suivi'!E588 | F113: ='Données Suivi'!H588 | G113: ='Données Suivi'!J588 | H113: ='Données Suivi'!K588 | I113: ='Données Suivi'!L588
A114: ='Données Suivi'!A589 | B114: ='Données Suivi'!B589 | C114: ='Données Suivi'!C589 | D114: ='Données Suivi'!D589 | E114: ='Données Suivi'!E589 | F114: ='Données Suivi'!H589 | G114: ='Données Suivi'!J589 | H114: ='Données Suivi'!K589 | I114: ='Données Suivi'!L589
A115: ='Données Suivi'!A590 | B115: ='Données Suivi'!B590 | C115: ='Données Suivi'!C590 | D115: ='Données Suivi'!D590 | E115: ='Données Suivi'!E590 | F115: ='Données Suivi'!H590 | G115: ='Données Suivi'!J590 | H115: ='Données Suivi'!K590 | I115: ='Données Suivi'!L590
A116: ='Données Suivi'!A592 | B116: ='Données Suivi'!B592 | C116: ='Données Suivi'!C592 | D116: ='Données Suivi'!D592 | E116: ='Données Suivi'!E592 | F116: ='Données Suivi'!H592 | G116: ='Données Suivi'!J592 | H116: ='Données Suivi'!K592 | I116: ='Données Suivi'!L592
A117: ='Données Suivi'!A593 | B117: ='Données Suivi'!B593 | C117: ='Données Suivi'!C593 | D117: ='Données Suivi'!D593 | E117: ='Données Suivi'!E593 | F117: ='Données Suivi'!H593 | G117: ='Données Suivi'!J593 | H117: ='Données Suivi'!K593 | I117: ='Données Suivi'!L593
A118: ='Données Suivi'!A563 | B118: ='Données Suivi'!B563 | C118: ='Données Suivi'!C563 | D118: ='Données Suivi'!D563 | E118: ='Données Suivi'!E563 | F118: ='Données Suivi'!H563 | G118: ='Données Suivi'!J563 | H118: ='Données Suivi'!K563 | I118: ='Données Suivi'!L563
A119: ='Données Suivi'!A572 | B119: ='Données Suivi'!B572 | C119: ='Données Suivi'!C572 | D119: ='Données Suivi'!D572 | E119: ='Données Suivi'!E572 | F119: ='Données Suivi'!H572 | G119: ='Données Suivi'!J572 | H119: ='Données Suivi'!K572 | I119: ='Données Suivi'!L572
A120: ='Données Suivi'!A598 | B120: ='Données Suivi'!B598 | C120: ='Données Suivi'!C598 | D120: ='Données Suivi'!D598 | E120: ='Données Suivi'!E598 | F120: ='Données Suivi'!H598 | G120: ='Données Suivi'!J598 | H120: ='Données Suivi'!K598 | I120: ='Données Suivi'!L598
A121: ='Données Suivi'!A434 | B121: ='Données Suivi'!B434 | C121: ='Données Suivi'!C434 | D121: ='Données Suivi'!D434 | E121: ='Données Suivi'!E434 | F121: ='Données Suivi'!H434 | G121: ='Données Suivi'!J434 | H121: ='Données Suivi'!K434 | I121: ='Données Suivi'!L434
A122: ='Données Suivi'!A560 | B122: ='Données Suivi'!B560 | C122: ='Données Suivi'!C560 | D122: ='Données Suivi'!D560 | E122: ='Données Suivi'!E560 | F122: ='Données Suivi'!H560 | G122: ='Données Suivi'!J560 | H122: ='Données Suivi'!K560 | I122: ='Données Suivi'!L560
A123: ='Données Suivi'!A601 | B123: ='Données Suivi'!B601 | C123: ='Données Suivi'!C601 | D123: ='Données Suivi'!D601 | E123: ='Données Suivi'!E601 | F123: ='Données Suivi'!H601 | G123: ='Données Suivi'!J601 | H123: ='Données Suivi'!K601 | I123: ='Données Suivi'!L601
A124: ='Données Suivi'!A602 | B124: ='Données Suivi'!B602 | C124: ='Données Suivi'!C602 | D124: ='Données Suivi'!D602 | E124: ='Données Suivi'!E602 | F124: ='Données Suivi'!H602 | G124: ='Données Suivi'!J602 | H124: ='Données Suivi'!K602 | I124: ='Données Suivi'!L602
A125: ='Données Suivi'!A608 | B125: ='Données Suivi'!B608 | C125: ='Données Suivi'!C608 | D125: ='Données Suivi'!D608 | E125: ='Données Suivi'!E608 | F125: ='Données Suivi'!H608 | G125: ='Données Suivi'!J608 | H125: ='Données Suivi'!K608 | I125: ='Données Suivi'!L608
A126: ='Données Suivi'!A614 | B126: ='Données Suivi'!B614 | C126: ='Données Suivi'!C614 | D126: ='Données Suivi'!D614 | E126: ='Données Suivi'!E614 | F126: ='Données Suivi'!H614 | G126: ='Données Suivi'!J614 | H126: ='Données Suivi'!K614 | I126: ='Données Suivi'!L614
A127: ='Données Suivi'!A615 | B127: ='Données Suivi'!B615 | C127: ='Données Suivi'!C615 | D127: ='Données Suivi'!D615 | E127: ='Données Suivi'!E615 | F127: ='Données Suivi'!H615 | G127: ='Données Suivi'!J615 | H127: ='Données Suivi'!K615 | I127: ='Données Suivi'!L615
A128: ='Données Suivi'!A547 | B128: ='Données Suivi'!B547 | C128: ='Données Suivi'!C547 | D128: ='Données Suivi'!D547 | E128: ='Données Suivi'!E547 | F128: ='Données Suivi'!H547 | G128: ='Données Suivi'!J547 | H128: ='Données Suivi'!K547 | I128: ='Données Suivi'!L547
A129: ='Données Suivi'!A619 | B129: ='Données Suivi'!B619 | C129: ='Données Suivi'!C619 | D129: ='Données Suivi'!D619 | E129: ='Données Suivi'!E619 | F129: ='Données Suivi'!H619 | G129: ='Données Suivi'!J619 | H129: ='Données Suivi'!K619 | I129: ='Données Suivi'!L619
A130: ='Données Suivi'!A622 | B130: ='Données Suivi'!B622 | C130: ='Données Suivi'!C622 | D130: ='Données Suivi'!D622 | E130: ='Données Suivi'!E622 | F130: ='Données Suivi'!H622 | G130: ='Données Suivi'!J622 | H130: ='Données Suivi'!K622 | I130: ='Données Suivi'!L622
A131: ='Données Suivi'!A664 | B131: ='Données Suivi'!B664 | C131: ='Données Suivi'!C664 | D131: ='Données Suivi'!D664 | E131: ='Données Suivi'!E664 | F131: ='Données Suivi'!H664 | G131: ='Données Suivi'!J664 | H131: ='Données Suivi'!K664 | I131: ='Données Suivi'!L664
A132: ='Données Suivi'!A665 | B132: ='Données Suivi'!B665 | C132: ='Données Suivi'!C665 | D132: ='Données Suivi'!D665 | E132: ='Données Suivi'!E665 | F132: ='Données Suivi'!H665 | G132: ='Données Suivi'!J665 | H132: ='Données Suivi'!K665 | I132: ='Données Suivi'!L665
A133: ='Données Suivi'!A666 | B133: ='Données Suivi'!B666 | C133: ='Données Suivi'!C666 | D133: ='Données Suivi'!D666 | E133: ='Données Suivi'!E666 | F133: ='Données Suivi'!H666 | G133: ='Données Suivi'!J666 | H133: ='Données Suivi'!K666 | I133: ='Données Suivi'!L666
A134: ='Données Suivi'!A667 | B134: ='Données Suivi'!B667 | C134: ='Données Suivi'!C667 | D134: ='Données Suivi'!D667 | E134: ='Données Suivi'!E667 | F134: ='Données Suivi'!H667 | G134: ='Données Suivi'!J667 | H134: ='Données Suivi'!K667 | I134: ='Données Suivi'!L667
A135: ='Données Suivi'!A668 | B135: ='Données Suivi'!B668 | C135: ='Données Suivi'!C668 | D135: ='Données Suivi'!D668 | E135: ='Données Suivi'!E668 | F135: ='Données Suivi'!H668 | G135: ='Données Suivi'!J668 | H135: ='Données Suivi'!K668 | I135: ='Données Suivi'!L668
A136: ='Données Suivi'!A669 | B136: ='Données Suivi'!B669 | C136: ='Données Suivi'!C669 | D136: ='Données Suivi'!D669 | E136: ='Données Suivi'!E669 | F136: ='Données Suivi'!H669 | G136: ='Données Suivi'!J669 | H136: ='Données Suivi'!K669 | I136: ='Données Suivi'!L669
A137: ='Données Suivi'!A670 | B137: ='Données Suivi'!B670 | C137: ='Données Suivi'!C670 | D137: ='Données Suivi'!D670 | E137: ='Données Suivi'!E670 | F137: ='Données Suivi'!H670 | G137: ='Données Suivi'!J670 | H137: ='Données Suivi'!K670 | I137: ='Données Suivi'!L670
...

Sheet Parametres
A1: Type de Budget
A2: REPORT BUDGET ANNEE ANTERIEURE
A3: REPORT BUDGET EXCEP ANNEE ANTERIEURE
A4: Ordinaire
A5: Exceptionnel
A6: BUDGET
A7: FONCTIONNEMENT
A8: INVESTISSEMENT | C8: =IFERROR(B8/(B7+B8),0)
A9: Lignes Budget Fonctionnement
A10: Achats de productions et de programmes: Acquis définitive Programmes TV externes
A11: Achats de productions et de programmes: Acquis définitive pgm Radio externes
A12: Achats de productions et de programmes: Achats des programmes en co-production
A13: Achats de productions et de programmes: Achat des programmes en production interne - personnes physiques
A14: Achats de droits: Achats des droits de captation
A15: Achats de droits: Cession de Droits de sport
A16: Achats de matières et fournitures consommables
A17: Achats non stockés de matières et fournitures
A18: Prestations de service: Achat d'études
A19: Prestations de service: Achat prestations de services locales - personnes physiques
A20: Prestations de service: Achat prestations de services locales - sociétés
... A44: Autre Matériel et mobilier de bureau
A45: Estimation | B45: MAD | C45: %
A46: Estimation Total HT
A47: Ecart
A48: MNT Partiel | C48: =IFERROR(MTP/MTT,0)
A49: Total Marché HT
A50: DIRECTION | B50: PPA | C50: Marche
A51: TDF
A52: TDF -SITES
A53: TDF-EXP&MAIN
A54: DG
A55: DCT
A56: RSSI
A57: DPMG
A58: DRPSD
A59: DINFORADIO
A60: ARRIYADIA
A61: TV LAAYOUNE
A62: MAGHRIBIA
... A78: DSI
A79: LIGNES BUDGETAIRES | B79: PPA | C79: AOO/BC
A80: Aménagement et construction de bâtiments à usage technique
A81: Aménagement et construction de bâtiments administratifs
A82: Electrification et installations techniques
A83: Equipements audiovisuels RADIO
A84: Equipements audiovisuels TV
A85: Frais d'acquisition
A86: Habillage Radio
A87: Logiciels
A88: Matériel de bureau
A89: Matériel de diffusion
A90: Matériel de transmission
A91: Matériel informatique
... A126: CONTRAT
A127: STATUT SUPPORT D'ENGAGEMENT | B127: MONTANT
A128: APPROUVE
A129: ATTRIBUE
A130: NON ATTRIBUE
A131: REJET
A132: INFRUCTUEUX
A133: ANNULE
A134: PHASE AOO
A135: EN SIGNATURE
A136: CATEGORIES
A137: PME
A138: GENERAL
A139: NON CONCERNE
... A150: Nature type PPA

Sheet ENGAGEMENTS 2026
A1: ANNEE LANCEMENT | B1: DIRECTION | C1: REF | D1: BCI | E1: LOTS | F1: OBJET | G1: STATUT 1 | H1: STATUT SUPPORT D'ENGAGEMENT | I1: N° SUPPORT D'ENGAGEMENT | J1: CATEGORIES | K1: TYPE BUDGET | L1: BUDGET | M1: LIGNES BUDGETAIRES | N1: MONTANT PREENGAGE INITIAL | O1: ESTIMATION TTC | P1: ESTIMATION HT | Q1: NATURE BESOIN | R1: DEBUT REC | S1: FIN REC | T1: ADJUDICATAIRE / FRS | U1: ANNEE APPROBATION | V1: DATE DE LA FICHE | W1: DATE VISA | X1: DATE APPROB | Y1: MONTANT MARCHE HT PART EN MAD | Z1: MONTANT MARCHE HT PART EN DEVISES | AA1: MONTANT MARCHE TTC PART EN MAD | AB1: MONTANT MARCHE TTC PART EN DEVISES | AC1: TOTAL MARCHE HT TOTAL ENGAGE HT | AD1: TOTAL MARCHE TTC TOTAL ENGAGE TTC | AE1: STATUT D'ENGAGEMENT | AF1: Remarque (archive) | AG1: Reserve | AH1: PREVISION PPA HT | AI1: ECART ESTIMATION HT-PPA HT | AJ1: ECART ENGAGEMENT HT-PPA HT | AK1: ECART ESTIMATION eng/estim | AL1: ECART PPA enga/ppa | AM1: REMARQUE
A2: 2026 | B2: DRH | C2: EXCLUSIVITÉ | D2: CONTRAT | E2: 1 | F2: Convention SNRT-OFPPT pour la réalisation des EAP | G2: VALIDE | H2: APPROUVE | I2: 01/OFPPT/SNRT/2026 | J2: NON CONCERNE | K2: Ordinaire | L2: FONCTIONNEMENT | M2: Charges sociales diverses | Q2: BESOIN RECURRENT | T2: OFPPT | U2: 2026 | V2: 46030 | X2: 46066 | Y2: 829202 | Z2: 0 | AA2: 995042.4 | AB2: 0 | AC2: 829202 | AD2: 995042.4 | AE2: ENGAGE | AM2: « + 287 001 » - Budget PPA = 708 041,40 Dhs
A3: 2026 | B3: DCPA | C3: PV N° : 01RC2025- DCPA | D3: CONTRAT | F3: IKRAM BENNANI RTAL - Préparation et animation de l’émission «نور و بصائر" | G3: VALIDE | H3: APPROUVE | I3: 185 CT/SNRT/2026 | J3: NON CONCERNE | K3: Ordinaire | L3: FONCTIONNEMENT | M3: Achats de productions et de programmes Achat des programmes en production interne | Q3: RECONDUCTION | T3: IKRAM BENNANI RTAL | U3: 2026 | V3: 46022 | X3: 46024 | Y3: 154000 | Z3: 0 | AA3: =+Y3 | AB3: =+Z3 | AC3: =+Y3 | AD3: =+AA3 | AE3: ENGAGE | AM3: RAS
A4: 2026 | B4: DCPA | C4: PV N° : 01RC2025- DCPA | D4: CONTRAT | F4: AMINE BENADDI - LA PREPARATION DE L'EMISSION " شباب في الواجهة" | G4: VALIDE | H4: APPROUVE | I4: 186 CT/SNRT/2026 | J4: NON CONCERNE | K4: Ordinaire | L4: FONCTIONNEMENT | M4: Achats de productions et de programmes Achat des programmes en production interne | Q4: RECONDUCTION | T4: AMINE BENADDI | U4: 2026 | V4: 46387 | X4: 46024 | Y4: 375000 | Z4: 0 | AA4: =Y4 | AB4: 0 | AC4: =Y4 | AD4: =Y4 | AE4: ENGAGE | AM4: RAS
A5: 2026 | B5: DCPA | C5: PV N° : 01RC2025- DCPA | D5: CONTRAT | F5: MOHAMMED ALI BENMAKHLOUF - Conception et présentation de l’émission " علم و حضارة" | G5: VALIDE | H5: APPROUVE | I5: 190 CT/SNRT/2026 | J5: NON CONCERNE | K5: Ordinaire | L5: FONCTIONNEMENT | M5: Achats de productions et de programmes Achat des programmes en production interne | Q5: RECONDUCTION | T5: MOHAMMED ALI BENMAKHLOUF | U5: 2026 | V5: 46387 | X5: 46024 | Y5: 445714.08 | Z5: 0 | AA5: =Y5 | AB5: 0 | AC5: =Y5 | AD5: =Y5 | AE5: ENGAGE | AM5: RAS
A6: 2026 | B6: DCPA | C6: PV N° : 01RC2025- DCPA | D6: CONTRAT | F6: ACHABI MORAD - Préparation et animation de l'émission " مع الفاميلة" | G6: VALIDE | H6: APPROUVE | I6: 187 CT/SNRT/2026 | J6: NON CONCERNE | K6: Ordinaire | L6: FONCTIONNEMENT | M6: Achats de productions et de programmes Achat des programmes en production interne | Q6: RECONDUCTION | T6: ACHABI MORAD | U6: 2026 | V6: 46387 | X6: 46024 | Y6: 880000 | Z6: 0 | AA6: =Y6 | AB6: 0 | AC6: =Y6 | AD6: =Y6 | AE6: ENGAGE | AM6: RAS
A7: 2026 | B7: DCPA | C7: PV N° : 01RC2025- DCPA | D7: CONTRAT | F7: MOHAMED BOUMLI - Préparation de l'émission " مع الفاميلة" | G7: VALIDE | H7: APPROUVE | I7: 188 CT/SNRT/2026 | J7: NON CONCERNE | K7: Ordinaire | L7: FONCTIONNEMENT | M7: Achats de productions et de programmes Achat des programmes en production interne | Q7: RECONDUCTION | T7: MOHAMED BOUMLI | U7: 2026 | V7: 46387 | X7: 46024 | Y7: 176000 | Z7: 0 | AA7: =Y7 | AB7: 0 | AC7: =Y7 | AD7: =Y7 | AE7: ENGAGE | AM7: RAS
A8: 2026 | B8: DCPA | C8: PV N° : 01RC2025- DCPA | D8: CONTRAT | F8: KABBAJ SEDDIK - Coordination, préparation et supervision artistique de l’émission " مدن عتيقة" | G8: VALIDE | H8: APPROUVE | I8: 189 CT/SNRT/2026 | J8: NON CONCERNE | K8: Ordinaire | L8: FONCTIONNEMENT | M8: Achats de productions et de programmes Achat des programmes en production interne | Q8: RECONDUCTION | T8: KABBAJ SEDDIK | U8: 2026 | V8: 46387 | X8: 46024 | Y8: 342857 | Z8: 0 | AA8: =Y8 | AB8: 0 | AC8: =Y8 | AD8: =Y8 | AE8: ENGAGE | AM8: RAS
A9: 2026 | B9: ARRIYADIA | C9: PV N° : 01RC2025- DCCCA | D9: CONTRAT | F9: BELMAHEDI MOHAMED - Cadreur plateau | G9: VALIDE | H9: APPROUVE | J9: NON CONCERNE | K9: Ordinaire | L9: FONCTIONNEMENT | M9: Prestations de service Achat prestations de services locales - personnes physiques | Q9: RECONDUCTION | T9: BELMAHEDI MOHAMED | U9: 2026 | V9: 46022 | X9: 46024 | Y9: 113142.48 | Z9: 0 | AA9: =Y9 | AB9: 0 | AC9: =Y9 | AD9: =Y9 | AE9: ENGAGE | AM9: Manque n° contrat
A10: 2026 | B10: ARRIYADIA | C10: PV N° : 01RC2025- DCCCA | D10: CONTRAT | F10: BIOUD ABDELHAK – Cadreur plateau | G10: VALIDE | H10: APPROUVE | J10: NON CONCERNE | K10: Ordinaire | L10: FONCTIONNEMENT | M10: Prestations de service Achat prestations de services locales - personnes physiques | Q10: RECONDUCTION | T10: BIOUD ABDELHAK | U10: 2026 | V10: 46022 | X10: 46024 | Y10: 113142.48 | Z10: 0 | AA10: =Y10 | AB10: 0 | AC10: =Y10 | AD10: =Y10 | AE10: ENGAGE | AM10: Manque n° contrat
A11: 2026 | B11: ARRIYADIA | C11: PV N° : 01RC2025- DCCCA | D11: CONTRAT | F11: IHAB JAMAL EDDINE - Cadreur plateau | G11: VALIDE | H11: APPROUVE | J11: NON CONCERNE | K11: Ordinaire | L11: FONCTIONNEMENT | M11: Prestations de service Achat prestations de services locales - personnes physiques | Q11: RECONDUCTION | T11: IHAB JAMAL EDDINE | U11: 2026 | V11: 46022 | X11: 46024 | Y11: 113142.48 | Z11: 0 | AA11: =Y11 | AB11: 0 | AC11: =Y11 | AD11: =Y11 | AE11: ENGAGE | AM11: Manque n° contrat
A12: 2026 | B12: ARRIYADIA | C12: PV N° : 01RC2025- DCCCA | D12: CONTRAT | F12: YOUSSEF JOUMARI - Cadreur plateau | G12: VALIDE | H12: APPROUVE | J12: NON CONCERNE | K12: Ordinaire | L12: FONCTIONNEMENT | M12: Prestations de service Achat prestations de services locales - personnes physiques | Q12: RECONDUCTION | T12: IHAB JAMAL EDDINE | U12: 2026 | V12: 46022 | X12: 46024 | Y12: 113142.48 | Z12: 0 | AA12: =Y12 | AB12: 0 | AC12: =Y12 | AD12: =Y12 | AE12: ENGAGE | AM12: Manque n° contrat
A13: 2026 | B13: ARRIYADIA | C13: PV N° : 01RC2025- DCCCA | D13: CONTRAT | F13: MUSTAPHA SKALLI - Cadreur plateau | G13: VALIDE | H13: APPROUVE | J13: NON CONCERNE | K13: Ordinaire | L13: FONCTIONNEMENT | M13: Prestations de service Achat prestations de services locales - personnes physiques | Q13: RECONDUCTION | T13: MUSTAPHA SKALLI | U13: 2026 | V13: 46022 | X13: 46024 | Y13: 113142.48 | Z13: 0 | AA13: =Y13 | AB13: 0 | AC13: =Y13 | AD13: =Y13 | AE13: ENGAGE | AM13: Manque n° contrat
A14: 2026 | B14: ARRIYADIA | C14: PV N° : 01RC2025- DCCCA | D14: CONTRAT | F14: YOUSSEF EL FERNANI - Cadreur plateau | G14: VALIDE | H14: APPROUVE | J14: NON CONCERNE | K14: Ordinaire | L14: FONCTIONNEMENT | M14: Prestations de service Achat prestations de services locales - personnes physiques | Q14: RECONDUCTION | T14: YOUSSEF EL FERNANI | U14: 2026 | V14: 46022 | X14: 46024 | Y14: 113142.48 | Z14: 0 | AA14: =Y14 | AB14: 0 | AC14: =Y14 | AD14: =Y14 | AE14: ENGAGE | AM14: Manque n° contrat
A15: 2026 | B15: ARRIYADIA | C15: PV N° : 01RC2025- DCCCA | D15: CONTRAT | F15: YOUNES ZARIR - Cameraman/reporteur | G15: VALIDE | H15: APPROUVE | J15: NON CONCERNE | K15: Ordinaire | L15: FONCTIONNEMENT | M15: Prestations de service Achat prestations de services locales - personnes physiques | Q15: RECONDUCTION | T15: YOUNES ZARIR | U15: 2026 | V15: 46022 | X15: 46024 | Y15: 113142.48 | Z15: 0 | AA15: =Y15 | AB15: 0 | AC15: =Y15 | AD15: =Y15 | AE15: ENGAGE | AM15: Manque n° contrat
A16: 2026 | B16: ARRIYADIA | C16: PV N° : 01RC2025- DCCCA | D16: CONTRAT | F16: AZEDDINE ESSATOURI - Cameraman/reporteur | G16: VALIDE | H16: APPROUVE | J16: NON CONCERNE | K16: Ordinaire | L16: FONCTIONNEMENT | M16: Prestations de service Achat prestations de services locales - personnes physiques | Q16: RECONDUCTION | T16: AZEDDINE ESSATOURI | U16: 2026 | V16: 46022 | X16: 46024 | Y16: 113142.48 | Z16: 0 | AA16: =Y16 | AB16: 0 | AC16: =Y16 | AD16: =Y16 | AE16: ENGAGE | AM16: Manque n° contrat
A17: 2026 | B17: ARRIYADIA | C17: PV N° : 01RC2025- DCCCA | D17: CONTRAT | F17: SOUFIANE ZIAT - Cameraman/reporteur | G17: VALIDE | H17: APPROUVE | J17: NON CONCERNE | K17: Ordinaire | L17: FONCTIONNEMENT | M17: Prestations de service Achat prestations de services locales - personnes physiques | Q17: RECONDUCTION | T17: SOUFIANE ZIAT | U17: 2026 | V17: 46022 | X17: 46024 | Y17: 113142.48 | Z17: 0 | AA17: =Y17 | AB17: 0 | AC17: =Y17 | AD17: =Y17 | AE17: ENGAGE | AM17: Manque n° contrat
A18: 2026 | B18: ARRIYADIA | C18: PV N° : 01RC2025- DCCCA | D18: CONTRAT | F18: ABDELHAK EL GANTITI - Cameraman/reporteur | G18: VALIDE | H18: APPROUVE | J18: NON CONCERNE | K18: Ordinaire | L18: FONCTIONNEMENT | M18: Prestations de service Achat prestations de services locales - personnes physiques | Q18: RECONDUCTION | T18: ABDELHAK EL GANTITI | U18: 2026 | V18: 46022 | X18: 46024 | Y18: 113142.48 | Z18: 0 | AA18: =Y18 | AB18: 0 | AC18: =Y18 | AD18: =Y18 | AE18: ENGAGE | AM18: Manque n° contrat
A19: 2026 | B19: ARRIYADIA | C19: PV N° : 01RC2025- DCCCA | D19: CONTRAT | F19: MOHAMED RAFIQ – Cadreur plateau/technicien coordinateur d’antenne TV | G19: VALIDE | H19: APPROUVE | J19: NON CONCERNE | K19: Ordinaire | L19: FONCTIONNEMENT | M19: Prestations de service Achat prestations de services locales - personnes physiques | Q19: RECONDUCTION | T19: MOHAMED RAFIQ | U19: 2026 | V19: 46022 | X19: 46024 | Y19: 113142.48 | Z19: 0 | AA19: =Y19 | AB19: 0 | AC19: =Y19 | AD19: =Y19 | AE19: ENGAGE | AM19: Manque n° contrat
A20: 2026 | B20: ARRIYADIA | C20: PV N° : 01RC2025- DCCCA | D20: CONTRAT | F20: ASMAA ADDAR - Monteur truquiste | G20: VALIDE | H20: APPROUVE | J20: NON CONCERNE | K20: Ordinaire | L20: FONCTIONNEMENT | M20: Prestations de service Achat prestations de services locales - personnes physiques | Q20: RECONDUCTION | T20: ASMAA ADDAR | U20: 2026 | V20: 46022 | X20: 46024 | Y20: 113142.48 | Z20: 0 | AA20: =Y20 | AB20: 0 | AC20: =Y20 | AD20: =Y20 | AE20: ENGAGE | AM20: Manque n° contrat
... A22: 2026 | B22: ARRIYADIA | C22: PV N° : 01RC2025- DCCCA | D22: CONTRAT | F22: DOUAA HMIMOU - Monteur truquiste | G22: VALIDE | H22: APPROUVE | J22: NON CONCERNE | K22: Ordinaire | L22: FONCTIONNEMENT | M22: Prestations de service Achat prestations de services locales - personnes physiques | Q22: RECONDUCTION | T22: DOUAA HMIMOU | U22: 2026 | V22: 46022 | X22: 46024 | Y22: 113142.48 | Z22: 0 | AA22: =Y22 | AB22: 0 | AC22: =Y22 | AD22: =Y22 | AE22: ENGAGE | AM22: Manque n° contrat
A23: 2026 | B23: ARRIYADIA | C23: PV N° : 01RC2025- DCCCA | D23: CONTRAT | F23: ROUZZAQ ANIS – Monteur truquiste /bande d’annonce | G23: VALIDE | H23: APPROUVE | J23: NON CONCERNE | K23: Ordinaire | L23: FONCTIONNEMENT | M23: Prestations de service Achat prestations de services locales - personnes physiques | Q23: RECONDUCTION | T23: ROUZZAQ ANIS | U23: 2026 | V23: 46022 | X23: 46024 | Y23: 156000 | AA23: =Y23 | AC23: =Y23 | AD23: =Y23 | AE23: ENGAGE | AM23: Manque n° contrat
A24: 2026 | B24: ARRIYADIA | C24: PV N° : 01RC2025- DCCCA | D24: CONTRAT | F24: SAFAE BOUHLAL - Monteur truquiste /technicien coordinateur d’antenne TV | G24: VALIDE | H24: APPROUVE | J24: NON CONCERNE | K24: Ordinaire | L24: FONCTIONNEMENT | M24: Prestations de service Achat prestations de services locales - personnes physiques | Q24: RECONDUCTION | T24: SAFAE BOUHLAL | U24: 2026 | V24: 46022 | X24: 46024 | Y24: 113142.48 | Z24: 0 | AA24: =Y24 | AB24: 0 | AC24: =Y24 | AD24: =Y24 | AE24: ENGAGE | AM24: Manque n° contrat
A25: 2026 | B25: ARRIYADIA | C25: PV N° : 01RC2025- DCCCA | D25: CONTRAT | F25: OUSSAMA EZZABBAR - Monteur truquiste | G25: VALIDE | H25: APPROUVE | J25: NON CONCERNE | K25: Ordinaire | L25: FONCTIONNEMENT | M25: Prestations de service Achat prestations de services locales - personnes physiques | Q25: RECONDUCTION | T25: OUSSAMA EZZABBAR | U25: 2026 | V25: 46022 | X25: 46024 | Y25: 113142.48 | Z25: 0 | AA25: =Y25 | AB25: 0 | AC25: =Y25 | AD25: =Y25 | AE25: ENGAGE | AM25: Manque n° contrat
A26: 2026 | B26: ARRIYADIA | C26: PV N° : 01RC2025- DCCCA | D26: CONTRAT | F26: AMINE IMANE - Opérateur synthétiseur | G26: VALIDE | H26: APPROUVE | J26: NON CONCERNE | K26: Ordinaire | L26: FONCTIONNEMENT | M26: Prestations de service Achat prestations de services locales - personnes physiques | Q26: RECONDUCTION | T26: AMINE IMANE | U26: 2026 | V26: 46022 | X26: 46024 | Y26: 113142.48 | Z26: 0 | AA26: =Y26 | AB26: 0 | AC26: =Y26 | AD26: =Y26 | AE26: ENGAGE | AM26: Manque n° contrat
A27: 2026 | B27: ARRIYADIA | C27: PV N° : 01RC2025- DCCCA | D27: CONTRAT | F27: BRAHIM ABASALAH - Opérateur synthétiseur/créateur de pages de textes et logos destinés à l’habillage au titre et au sous-titrage des programmes de l’antenne. | G27: VALIDE | H27: APPROUVE | J27: NON CONCERNE | K27: Ordinaire | L27: FONCTIONNEMENT | M27: Prestations de service Achat prestations de services locales - personnes physiques | Q27: RECONDUCTION | T27: BRAHIM ABASALAH | U27: 2026 | V27: 46022 | X27: 46024 | Y27: 144000 | Z27: 0 | AA27: =Y27 | AB27: 0 | AC27: =Y27 | AD27: =Y27 | AE27: ENGAGE | AM27: Manque n° contrat
A28: 2026 | B28: ARRIYADIA | C28: PV N° : 01RC2025- DCCCA | D28: CONTRAT | F28: YASSINE STITOU - Opérateur synthétiseur | G28: VALIDE | H28: APPROUVE | J28: NON CONCERNE | K28: Ordinaire | L28: FONCTIONNEMENT | M28: Prestations de service Achat prestations de services locales - personnes physiques | Q28: RECONDUCTION | T28: YASSINE STITOU | U28: 2026 | V28: 46022 | X28: 46024 | Y28: 113142.48 | Z28: 0 | AA28: =Y28 | AB28: 0 | AC28: =Y28 | AD28: =Y28 | AE28: ENGAGE | AM28: Manque n° contrat
A29: 2026 | B29: ARRIYADIA | C29: PV N° : 01RC2025- DCCCA | D29: CONTRAT | F29: RACHID ABKARI - Opérateur de prise de son | G29: VALIDE | H29: APPROUVE | J29: NON CONCERNE | K29: Ordinaire | L29: FONCTIONNEMENT | M29: Prestations de service Achat prestations de services locales - personnes physiques | Q29: RECONDUCTION | T29: RACHID ABKARI | U29: 2026 | V29: 46022 | X29: 46024 | Y29: 113142.48 | Z29: 0 | AA29: =Y29 | AB29: 0 | AC29: =Y29 | AD29: =Y29 | AE29: ENGAGE | AM29: Manque n° contrat
A30: 2026 | B30: ARRIYADIA | C30: PV N° : 01RC2025- DCCCA | D30: CONTRAT | F30: AMINE NEKI - Technicien coordinateur d'antenne TV | G30: VALIDE | H30: APPROUVE | J30: NON CONCERNE | K30: Ordinaire | L30: FONCTIONNEMENT | M30: Prestations de service Achat prestations de services locales - personnes physiques | Q30: RECONDUCTION | T30: AMINE NEKI | U30: 2026 | V30: 46022 | X30: 46024 | Y30: 113142.48 | Z30: 0 | AA30: =Y30 | AB30: 0 | AC30: =Y30 | AD30: =Y30 | AE30: ENGAGE | AM30: Manque n° contrat
A31: 2026 | B31: ARRIYADIA | C31: PV N° : 01RC2025- DCCCA | D31: CONTRAT | F31: ANISS BENRIANE - Technicien coordinateur d'antenne TV | G31: VALIDE | H31: APPROUVE | J31: NON CONCERNE | K31: Ordinaire | L31: FONCTIONNEMENT | M31: Prestations de service Achat prestations de services locales - personnes physiques | Q31: RECONDUCTION | T31: ANISS BENRIANE | U31: 2026 | V31: 46022 | X31: 46024 | Y31: 113142.48 | Z31: 0 | AA31: =Y31 | AB31: 0 | AC31: =Y31 | AD31: =Y31 | AE31: ENGAGE | AM31: Manque n° contrat
A32: 2026 | B32: ARRIYADIA | C32: PV N° : 01RC2025- DCCCA | D32: CONTRAT | F32: AHMED HOUBBANE - Journaliste présentateur TV/reporteur | G32: VALIDE | H32: APPROUVE | J32: NON CONCERNE | K32: Ordinaire | L32: FONCTIONNEMENT | M32: Prestations de service Achat prestations de services locales - personnes physiques | Q32: RECONDUCTION | T32: AHMED HOUBBANE | U32: 2026 | V32: 46022 | X32: 46024 | Y32: 144000 | Z32: 0 | AA32: =Y32 | AB32: 0 | AC32: =Y32 | AD32: =Y32 | AE32: ENGAGE | AM32: Manque n° contrat
A33: 2026 | B33: ARRIYADIA | C33: PV N° : 01RC2025- DCCCA | D33: CONTRAT | F33: OMAYRA MOUKRAM - Journaliste présentateur TV | G33: VALIDE | H33: APPROUVE | J33: NON CONCERNE | K33: Ordinaire | L33: FONCTIONNEMENT | M33: Prestations de service Achat prestations de services locales - personnes physiques | Q33: RECONDUCTION | T33: OMAYRA MOUKRAM | U33: 2026 | V33: 46022 | X33: 46024 | Y33: 113142.48 | Z33: 0 | AA33: =Y33 | AB33: 0 | AC33: =Y33 | AD33: =Y33 | AE33: ENGAGE | AM33: Manque n° contrat
A34: 2026 | B34: ARRIYADIA | C34: PV N° : 01RC2025- DCCCA | D34: CONTRAT | F34: AYOUB ADIB - Journaliste animateur | G34: VALIDE | H34: APPROUVE | J34: NON CONCERNE | K34: Ordinaire | L34: FONCTIONNEMENT | M34: Prestations de service Achat prestations de services locales - personnes physiques | Q34: RECONDUCTION | T34: AYOUB ADIB | U34: 2026 | V34: 46022 | X34: 46024 | Y34: 113142.48 | Z34: 0 | AA34: =Y34 | AB34: 0 | AC34: =Y34 | AD34: =Y34 | AE34: ENGAGE | AM34: Manque n° contrat
A35: 2026 | B35: ARRIYADIA | C35: PV N° : 01RC2025- DCCCA | D35: CONTRAT | F35: ABDELOUAHED INCHA-ALLAH - Journaliste reporteur d'image | G35: VALIDE | H35: APPROUVE | J35: NON CONCERNE | K35: Ordinaire | L35: FONCTIONNEMENT | M35: Prestations de service Achat prestations de services locales - personnes physiques | Q35: RECONDUCTION | T35: ABDELOUAHED INCHA-ALLAH | U35: 2026 | V35: 46022 | X35: 46024 | Y35: 113142.48 | Z35: 0 | AA35: =Y35 | AB35: 0 | AC35: =Y35 | AD35: =Y35 | AE35: ENGAGE | AM35: Manque n° contrat
... A56: 2026 | B56: ARRIYADIA | C56: PV N° : 01RC2025- DCCCA | D56: CONTRAT | F56: ABDELOUAHED CHAMMAMI - Consultant football | G56: VALIDE | H56: APPROUVE | J56: NON CONCERNE | K56: Ordinaire | L56: FONCTIONNEMENT | M56: Prestations de service Achat prestations de services locales - personnes physiques | Q56: RECONDUCTION | T56: ABDELOUAHED CHAMMAMI | U56: 2026 | V56: 46022 | X56: 46024 | Y56: 150000 | Z56: 0 | AA56: =Y56 | AB56: 0 | AC56: =Y56 | AD56: =Y56 | AE56: ENGAGE | AM56: Manque n° contrat
A57: 2026 | B57: ARRIYADIA | C57: PVN°: 02RE2026-DCSA | D57: CONTRAT | F57: MOHAMED SAAD -cadreur plateau/technicien coordinateur d'antenne TV/Digital | G57: EN SIGNATURE | H57: EN SIGNATURE | J57: NON CONCERNE | K57: Ordinaire | L57: FONCTIONNEMENT | M57: Prestations de service Achat prestations de services locales - personnes physiques | Q57: RECONDUCTION | T57: MOHAMED SAAD | U57: 2026 | Y57: 28285.62 | AA57: =Y57 | AC57: =Y57 | AD57: =Y57 | AE57: EN COURS D'ENGAGEMENT
A58: 2026 | B58: ARRIYADIA | C58: PVN°: 02RE2026-DCSA | D58: CONTRAT | F58: ABDELILAH AIT AHMED - Monteur truquiste /technicien coordinateur d'antenne TV | G58: EN SIGNATURE | H58: EN SIGNATURE | J58: NON CONCERNE | K58: Ordinaire | L58: FONCTIONNEMENT | M58: Prestations de service Achat prestations de services locales - personnes physiques | Q58: RECONDUCTION | T58: ABDELILAH AIT AHMED | U58: 2026 | Y58: 28285.62 | AA58: =Y58 | AC58: =Y58 | AD58: =Y58 | AE58: EN COURS D'ENGAGEMENT
A59: 2026 | B59: ARRIYADIA | C59: PV N° : 01RC2025- DCCCA | D59: CONTRAT | F59: KHALID AFIF - Consultant Tennis | G59: VALIDE | H59: APPROUVE | J59: NON CONCERNE | K59: Ordinaire | L59: FONCTIONNEMENT | M59: Prestations de service Achat prestations de services locales - personnes physiques | Q59: RECONDUCTION | T59: KHALID AFIF | U59: 2026 | V59: 46022 | X59: 46024 | Y59: 150500 | Z59: 0 | AA59: =Y59 | AB59: 0 | AC59: =Y59 | AD59: =Y59 | AE59: ENGAGE | AM59: Manque n° contrat
A60: 2026 | B60: ARRIYADIA | C60: PV N° : 01RC2025- DCCCA | D60: CONTRAT | F60: MOHSIN CHERGUI - Consultant omnisport | G60: VALIDE | H60: APPROUVE | J60: NON CONCERNE | K60: Ordinaire | L60: FONCTIONNEMENT | M60: Prestations de service Achat prestations de services locales - personnes physiques | Q60: RECONDUCTION | T60: MOHSIN CHERGUI | U60: 2026 | V60: 46022 | X60: 46024 | Y60: 150000 | Z60: 0 | AA60: =Y60 | AB60: 0 | AC60: =Y60 | AD60: =Y60 | AE60: ENGAGE | AM60: Manque n° contrat
A61: 2026 | B61: ASSADISSA | C61: PV N° : 01RC2025- DPPCCRTV | D61: CONTRAT | F61: ZERHOUNI RABIA - Réalisatrice : Montage, mixage, animation des émissions RD et programmation RD | G61: VALIDE | H61: APPROUVE | J61: NON CONCERNE | K61: Ordinaire | L61: FONCTIONNEMENT | M61: Prestations de service Achat prestations de services locales - personnes physiques | Q61: RECONDUCTION | T61: ZERHOUNI RABIA | U61: 2026 | V61: 46387 | X61: 46024 | Y61: 108000 | Z61: 0 | AA61: =Y61 | AB61: 0 | AC61: =Y61 | AD61: =Y61 | AE61: ENGAGE | AM61: Manque n° contrat
A62: 2026 | B62: ASSADISSA | C62: PV N° : 01RC2025- DPPCCRTV | D62: CONTRAT | F62: BENIKES KARIMA - Réalisatrice : Montage, mixage et programmation RD | G62: VALIDE | H62: APPROUVE | J62: NON CONCERNE | K62: Ordinaire | L62: FONCTIONNEMENT | M62: Prestations de service Achat prestations de services locales - personnes physiques | Q62: RECONDUCTION | T62: BENIKES KARIMA | U62: 2026 | V62: 46387 | X62: 46024 | Y62: 72000 | Z62: 0 | AA62: =Y62 | AB62: 0 | AC62: =Y62 | AD62: =Y62 | AE62: ENGAGE | AM62: Manque n° contrat
A63: 2026 | B63: ASSADISSA | C63: PV N° : 01RC2025- DPPCCRTV | D63: CONTRAT | F63: LAHKIM OUMAIMA - Programmatrice : Programmation TV (Conducteur quotidien) | G63: VALIDE | H63: APPROUVE | J63: NON CONCERNE | K63: Ordinaire | L63: FONCTIONNEMENT | M63: Prestations de service Achat prestations de services locales - personnes physiques | Q63: RECONDUCTION | T63: LAHKIM OUMAIMA | U63: 2026 | V63: 46387 | X63: 46024 | Y63: 84000 | Z63: 0 | AA63: =Y63 | AB63: 0 | AC63: =Y63 | AD63: =Y63 | AE63: ENGAGE | AM63: Manque n° contrat
A64: 2026 | B64: ASSADISSA | C64: PV N° : 01RC2025- DPPCCRTV | D64: CONTRAT | F64: DEHROUR OUSSAMA - Infographiste : le montage, l'infographie et la coordination du portail de la Chaîne, | G64: VALIDE | H64: APPROUVE | J64: NON CONCERNE | K64: Ordinaire | L64: FONCTIONNEMENT | M64: Prestations de service Achat prestations de services locales - personnes physiques | Q64: RECONDUCTION | T64: DEHROUR OUSSAMA | U64: 2026 | V64: 46387 | X64: 46024 | Y64: 84000 | Z64: 0 | AA64: =Y64 | AB64: 0 | AC64: =Y64 | AD64: =Y64 | AE64: ENGAGE | AM64: Manque n° contrat
A65: 2026 | B65: ASSADISSA | C65: PV N° : 01RC2025- DPPCCRTV | D65: CONTRAT | F65: NASREDDINE MOUHCINE - Prise de vue et Prise de son TV (OPV/OPS) | G65: VALIDE | H65: APPROUVE | J65: NON CONCERNE | K65: Ordinaire | L65: FONCTIONNEMENT | M65: Prestations de service Achat prestations de services locales - personnes physiques | Q65: RECONDUCTION | T65: NASREDDINE MOUHCINE | U65: 2026 | V65: 46387 | X65: 46024 | Y65: 84000 | Z65: 0 | AA65: =Y65 | AB65: 0 | AC65: =Y65 | AD65: =Y65 | AE65: ENGAGE | AM65: Manque n° contrat
A66: 2026 | B66: ASSADISSA | C66: PV N° : 01RC2025- DPPCCRTV | D66: CONTRAT | F66: HAJJOUJI YOUSSEF - Prise de vue (OPV) et le montage TV | G66: VALIDE | H66: APPROUVE | J66: NON CONCERNE | K66: Ordinaire | L66: FONCTIONNEMENT | M66: Prestations de service Achat prestations de services locales - personnes physiques | Q66: RECONDUCTION | T66: HAJJOUJI YOUSSEF | U66: 2026 | V66: 46387 | X66: 46024 | Y66: 84000 | Z66: 0 | AA66: =Y66 | AB66: 0 | AC66: =Y66 | AD66: =Y66 | AE66: ENGAGE | AM66: Manque n° contrat
A67: 2026 | B67: ASSADISSA | C67: PV N° : 01RC2025- DPPCCRTV | D67: CONTRAT | F67: DRISSI WALID - Prise de vue et Prise de son TV (OPV/OPS) | G67: VALIDE | H67: APPROUVE | J67: NON CONCERNE | K67: Ordinaire | L67: FONCTIONNEMENT | M67: Prestations de service Achat prestations de services locales - personnes physiques | Q67: RECONDUCTION | T67: DRISSI WALID | U67: 2026 | V67: 46387 | X67: 46024 | Y67: 84000 | Z67: 0 | AA67: =Y67 | AB67: 0 | AC67: =Y67 | AD67: =Y67 | AE67: ENGAGE | AM67: Manque n° contrat
A68: 2026 | B68: ASSADISSA | C68: PV N° : 01RC2025- DPPCCRTV | D68: CONTRAT | F68: EZ-ZHR MOHAMED - Prise de vue et Prise de son TV (OPV/OPS) | G68: VALIDE | H68: APPROUVE | J68: NON CONCERNE | K68: Ordinaire | L68: FONCTIONNEMENT | M68: Prestations de service Achat prestations de services locales - personnes physiques | Q68: RECONDUCTION | T68: EZ-ZHR MOHAMED | U68: 2026 | V68: 46387 | X68: 46024 | Y68: 84000 | Z68: 0 | AA68: =Y68 | AB68: 0 | AC68: =Y68 | AD68: =Y68 | AE68: ENGAGE | AM68: Manque n° contrat
A69: 2026 | B69: ASSADISSA | C69: PV N° : 01RC2025- DPPCCRTV | D69: CONTRAT | F69: ABIDA ILIAS - Prise de vue TV et Prise de son TV (OPV/OPS) | G69: VALIDE | H69: APPROUVE | J69: NON CONCERNE | K69: Ordinaire | L69: FONCTIONNEMENT | M69: Prestations de service Achat prestations de services locales - personnes physiques | Q69: RECONDUCTION | T69: ABIDA ILIAS | U69: 2026 | V69: 46387 | X69: 46024 | Y69: 84000 | Z69: 0 | AA69: =Y69 | AB69: 0 | AC69: =Y69 | AD69: =Y69 | AE69: ENGAGE | AM69: Manque n° contrat
A70: 2026 | B70: ASSADISSA | C70: PV N° : 01RC2025- DPPCCRTV | D70: CONTRAT | F70: ELMHAMDI BADR - Prise de vue et Prise de son TV (OPV/OPS) | G70: VALIDE | H70: APPROUVE | J70: NON CONCERNE | K70: Ordinaire | L70: FONCTIONNEMENT | M70: Prestations de service Achat prestations de services locales - personnes physiques | Q70: RECONDUCTION | T70: ELMHAMDI BADR | U70: 2026 | V70: 46387 | X70: 46024 | Y70: 84000 | Z70: 0 | AA70: =Y70 | AB70: 0 | AC70: =Y70 | AD70: =Y70 | AE70: ENGAGE | AM70: Manque n° contrat
... A81: 2026 | B81: DPMG | C81: PV N° : 01RC2025- DPMG | D81: CONTRAT | F81: MOHAMED CHERTI - Métreur en BTP | G81: VALIDE | H81: APPROUVE | J81: NON CONCERNE | K81: Ordinaire | L81: FONCTIONNEMENT | M81: Prestations de service Achat prestations de services locales - personnes physiques | Q81: RECONDUCTION | T81: MOHAMED CHERTI | U81: 2026 | V81: 46387 | X81: 46024 | Y81: 28000 | Z81: 0 | AA81: =Y81 | AB81: 0 | AC81: =Y81 | AD81: =Y81 | AE81: ENGAGE | AM81: Manque n° contrat
A82: 2026 | B82: DINFORADIO | C82: RECONDUCTIBLE | D82: CONTRAT | F82: Abonnement MAP | G82: VALIDE | H82: APPROUVE | J82: NON CONCERNE | K82: Ordinaire | L82: FONCTIONNEMENT | M82: Redevances et cotisations Abonnements | Q82: RECONDUCTIBLE | T82: MAP | U82: - | V82: - | X82: - | Y82: 1837404 | Z82: 0 | AA82: 1837404 | AB82: 0 | AC82: 1837404 | AD82: 1837404 | AE82: ENGAGE
A83: 2026 | B83: DINFORADIO | C83: PV N° : 01RC2025- DIR | D83: CONTRAT | F83: YOUSSEF LAHLALI - Journaliste correspondant chargé de la préparation des magazines d'information et reportages RD et la couverture des événements internationaux | G83: VALIDE | H83: APPROUVE | J83: NON CONCERNE | K83: Ordinaire | L83: FONCTIONNEMENT | M83: Prestations de service Achat prestations de services locales - personnes physiques | Q83: RECONDUCTION | T83: YOUSSEF LAHLALI | U83: 2026 | V83: 46387 | X83: 46024 | Y83: 171428.52 | Z83: 0 | AA83: =Y83 | AB83: 0 | AC83: =Y83 | AD83: =Y83 | AE83: ENGAGE | AM83: Manque n° contrat
A84: 2026 | B84: DINFORADIO | C84: PV N° : 01RC2025- DIR | D84: CONTRAT | F84: SAFI RIM - Journaliste, présentateur radio francophone/ anglophone | G84: VALIDE | H84: APPROUVE | J84: NON CONCERNE | K84: Ordinaire | L84: FONCTIONNEMENT | M84: Prestations de service Achat prestations de services locales - personnes physiques | Q84: RECONDUCTION | T84: SAFI RIM | U84: 2026 | V84: 46387 | X84: 46024 | Y84: 132000 | Z84: 0 | AA84: =Y84 | AB84: 0 | AC84: =Y84 | AD84: =Y84 | AE84: ENGAGE | AM84: Manque n° contrat
A85: 2026 | B85: DINFORADIO | C85: PV N° : 01RC2025- DIR | D85: CONTRAT | F85: BENCAID KENZA - Journaliste et présentateur radio francophone | G85: VALIDE | H85: APPROUVE | J85: NON CONCERNE | K85: Ordinaire | L85: FONCTIONNEMENT | M85: Prestations de service Achat prestations de services locales - personnes physiques | Q85: RECONDUCTION | T85: BENCAID KENZA | U85: 2026 | V85: 46387 | X85: 46024 | Y85: 156000 | Z85: 0 | AA85: =Y85 | AB85: 0 | AC85: =Y85 | AD85: =Y85 | AE85: ENGAGE | AM85: Manque n° contrat
A86: 2026 | B86: DINFORADIO | C86: PV N° : 01RC2025- DIR | D86: CONTRAT | F86: AHMED CHAINA - Journaliste, Présentateur radio amazigh/animateur de débats (expression tachelhit) | G86: VALIDE | H86: APPROUVE | J86: NON CONCERNE | K86: Ordinaire | L86: FONCTIONNEMENT | M86: Prestations de service Achat prestations de services locales - personnes physiques | Q86: RECONDUCTION | T86: AHMED CHAINA | U86: 2026 | V86: 46387 | X86: 46024 | Y86: 132000 | Z86: 0 | AA86: 132000 | AB86: 0 | AC86: =Y86 | AD86: =Y86 | AE86: ENGAGE | AM86: Manque n° contrat
A87: 2026 | B87: DINFORADIO | C87: PV N° : 01RC2025- DIR | D87: CONTRAT | F87: BADDOU KHALID - Journaliste, Présentateur radio amazigh/animateur de débats (expression tachelhit) | G87: VALIDE | H87: APPROUVE | J87: NON CONCERNE | K87: Ordinaire | L87: FONCTIONNEMENT | M87: Prestations de service Achat prestations de services locales - personnes physiques | Q87: RECONDUCTION | T87: BADDOU KHALID | U87: 2026 | V87: 46387 | X87: 46024 | Y87: 132000 | Z87: 0 | AA87: 132000 | AB87: 0 | AC87: =Y87 | AD87: =Y87 | AE87: ENGAGE | AM87: Manque n° contrat
A88: 2026 | B88: DINFOTV | C88: PV N° : 01RC2025- DITV | D88: CONTRAT | F88: EZZAHER ANASS - Scripte des journaux télévisés et toutes les émissions produites par la direction de l'information TV | G88: VALIDE | H88: APPROUVE | J88: NON CONCERNE | K88: Ordinaire | L88: FONCTIONNEMENT | M88: Prestations de service Achat prestations de services locales - personnes physiques | Q88: RECONDUCTION | T88: EZZAHER ANASS | U88: 2026 | V88: 46387 | X88: 46024 | Y88: 96000 | Z88: 0 | AA88: =Y88 | AB88: 0 | AC88: =Y88 | AD88: =Y88 | AE88: ENGAGE | AM88: Manque n° contrat
A89: 2026 | B89: DINFOTV | C89: PV N° : 01RC2025- DITV | D89: CONTRAT | F89: AOUAD MARIA - Journaliste chargée de la préparation et la réalisation des reportages news en français au journal télévisé de la chaine AL Aoula | G89: VALIDE | H89: APPROUVE | J89: NON CONCERNE | K89: Ordinaire | L89: FONCTIONNEMENT | M89: Prestations de service Achat prestations de services locales - personnes physiques | Q89: RECONDUCTION | T89: AOUAD MARIA | U89: 2026 | V89: 46387 | X89: 46024 | Y89: 144000 | Z89: 0 | AA89: =Y89 | AB89: 0 | AC89: =Y89 | AD89: =Y89 | AE89: ENGAGE | AM89: Manque n° contrat
A90: 2026 | B90: DINFOTV | C90: PV N° : 01RC2025- DITV | D90: CONTRAT | F90: KETTANI MOHAMMED - Interprète en langue des signes | G90: VALIDE | H90: APPROUVE | J90: NON CONCERNE | K90: Ordinaire | L90: FONCTIONNEMENT | M90: Prestations de service Achat prestations de services locales - personnes physiques | Q90: RECONDUCTION | T90: KETTANI MOHAMMED | U90: 2026 | V90: 46387 | X90: 46024 | Y90: 154285.68 | Z90: 0 | AA90: =Y90 | AB90: 0 | AC90: =Y90 | AD90: =Y90 | AE90: ENGAGE | AM90: Manque n° contrat
A91: 2026 | B91: DINFOTV | C91: PV N° : 01RC2025- DITV | D91: CONTRAT | F91: NOUINI NOURREDDINE - Coiffeur et maquilleur des animateurs et des invités participants au journal télévisé de la chaine Al Aoula | G91: VALIDE | H91: APPROUVE | J91: NON CONCERNE | K91: Ordinaire | L91: FONCTIONNEMENT | M91: Prestations de service Achat prestations de services locales - personnes physiques | Q91: RECONDUCTION | T91: NOUINI NOURREDDINE | U91: 2026 | V91: 46387 | X91: 46024 | Y91: 72000 | Z91: 0 | AA91: =Y91 | AB91: 0 | AC91: =Y91 | AD91: =Y91 | AE91: ENGAGE | AM91: Manque n° contrat
A92: 2026 | B92: DINFOTV | C92: PV N° : 01RC2025- DITV | D92: CONTRAT | F92: WIAM MOUDDOUN - Journaliste chargée de la préparation des magazines d'information, reportages, rédaction des JT et couverture du factuel | G92: VALIDE | H92: APPROUVE | J92: NON CONCERNE | K92: Ordinaire | L92: FONCTIONNEMENT | M92: Prestations de service Achat prestations de services locales - personnes physiques | Q92: RECONDUCTION | T92: WIAM MOUDDOUN | U92: 2026 | V92: 46387 | X92: 46024 | Y92: 120000 | Z92: 0 | AA92: =Y92 | AB92: 0 | AC92: =Y92 | AD92: =Y92 | AE92: ENGAGE | AM92: Manque n° contrat
A93: 2026 | B93: DINFOTV | C93: PV N° : 01RC2025- DITV | D93: CONTRAT | F93: HOUDA NEJJAR - Scripte des journaux télévisés et toutes les émissions produites par la direction de l'Information TV | G93: VALIDE | H93: APPROUVE | J93: NON CONCERNE | K93: Ordinaire | L93: FONCTIONNEMENT | M93: Prestations de service Achat prestations de services locales - personnes physiques | Q93: RECONDUCTION | T93: HOUDA NEJJAR | U93: 2026 | V93: 46387 | X93: 46024 | Y93: 24000 | Z93: 0 | AA93: 24000 | AB93: 0 | AC93: 24000 | AD93: 24000 | AE93: ENGAGE | AM93: Manque n° contrat
A94: 2026 | B94: DINFOTV | C94: PV N° : 01RC2025- DITV | D94: CONTRAT | F94: TAHRAOUI ABDELHGANI - Preneur de vue chargé de la réalisation de reportages et couvertures TV dans la province d'Essaouira et régions | G94: VALIDE | H94: APPROUVE | J94: NON CONCERNE | K94: Ordinaire | L94: FONCTIONNEMENT | M94: Prestations de service Achat prestations de services locales - personnes physiques | Q94: RECONDUCTION | T94: TAHRAOUI ABDELHGANI | U94: 2026 | V94: 46387 | X94: 46024 | Y94: 44571.36 | Z94: 0 | AA94: =Y94 | AB94: 0 | AC94: =Y94 | AD94: =Y94 | AE94: ENGAGE | AM94: Manque n° contrat
A95: 2026 | B95: DINFOTV | C95: PV N° : 01RC2025- DITV | D95: CONTRAT | F95: FADILI AHMED - Preneur de vue chargé de la réalisation de reportages et couvertures TV dans la province d’Ifran Azrou | G95: VALIDE | H95: APPROUVE | J95: NON CONCERNE | K95: Ordinaire | L95: FONCTIONNEMENT | M95: Prestations de service Achat prestations de services locales - personnes physiques | Q95: RECONDUCTION | T95: FADILI AHMED | U95: 2026 | V95: 46387 | X95: 46024 | Y95: 72000 | Z95: 0 | AA95: =Y95 | AB95: 0 | AC95: =Y95 | AD95: =Y95 | AE95: ENGAGE | AM95: Manque n° contrat
A96: 2026 | B96: DINFOTV | C96: PV N° : 01RC2025- DITV | D96: CONTRAT | F96: KHALID AIT HSSAIN - Coiffeur et maquilleur des animateurs et des invités participants au journal télévisé de la chaine ALOULA. | G96: VALIDE | H96: APPROUVE | J96: NON CONCERNE | K96: Ordinaire | L96: FONCTIONNEMENT | M96: Prestations de service Achat prestations de services locales - personnes physiques | Q96: RECONDUCTION | T96: KHALID AIT HSSAIN | U96: 2026 | V96: 46387 | X96: 46024 | Y96: 72000 | Z96: 0 | AA96: =Y96 | AB96: 0 | AC96: =Y96 | AD96: =Y96 | AE96: ENGAGE | AM96: Manque n° contrat
A97: 2026 | B97: DINFOTV | C97: PV N° : 01RC2025- DITV | D97: CONTRAT | F97: SOUKAINA HACHIMI - Journaliste chargée de la préparation des magazines d'information, reportages, rédaction des JT et couverture du factuel | G97: VALIDE | H97: APPROUVE | J97: NON CONCERNE | K97: Ordinaire | L97: FONCTIONNEMENT | M97: Prestations de service Achat prestations de services locales - personnes physiques | Q97: RECONDUCTION | T97: SOUKAINA HACHIMI | U97: 2026 | V97: 46387 | X97: 46024 | Y97: 120000 | Z97: 0 | AA97: =Y97 | AB97: 0 | AC97: =Y97 | AD97: =Y97 | AE97: ENGAGE | AM97: Manque n° contrat
A98: 2026 | B98: DINFOTV | C98: PV N° : 01RC2025- DITV | D98: CONTRAT | F98: MAHDI KARRAKCHOU - Le montage des journaux télévisés et toutes les émissions produites par la direction de l'Information TV | G98: VALIDE | H98: APPROUVE | J98: NON CONCERNE | K98: Ordinaire | L98: FONCTIONNEMENT | M98: Prestations de service Achat prestations de services locales - personnes physiques | Q98: RECONDUCTION | T98: MAHDI KARRAKCHOU | U98: 2026 | V98: 46387 | X98: 46024 | Y98: 108000 | Z98: 0 | AA98: =Y98 | AB98: 0 | AC98: =Y98 | AD98: =Y98 | AE98: ENGAGE | AM98: Manque n° contrat
A99: 2026 | B99: DINFOTV | C99: PV N° : 01RC2025- DITV | D99: CONTRAT | F99: MOUNIR LAHSAIEN - Coiffeur et maquilleur des animateurs et des invités participants au journal télévisé de la chaine Al Aoula | G99: VALIDE | H99: APPROUVE | J99: NON CONCERNE | K99: Ordinaire | L99: FONCTIONNEMENT | M99: Prestations de service Achat prestations de services locales - personnes physiques | Q99: RECONDUCTION | T99: MOUNIR LAHSAIEN | U99: 2026 | V99: 46387 | X99: 46024 | Y99: 72000 | Z99: 0 | AA99: =Y99 | AB99: 0 | AC99: =Y99 | AD99: =Y99 | AE99: ENGAGE | AM99: Manque n° contrat
A100: 2026 | B100: DINFOTV | C100: PV N° : 01RC2025- DITV | D100: CONTRAT | F100: EL AAZIZ ABDERRAZZAQ - Chef d'édition des journaux télévisés | G100: VALIDE | H100: APPROUVE | J100: NON CONCERNE | K100: Ordinaire | L100: FONCTIONNEMENT | M100: Prestations de service Achat prestations de services locales - personnes physiques | Q100: RECONDUCTION | T100: EL AAZIZ ABDERRAZZAQ | U100: 2026 | V100: 46387 | X100: 46024 | Y100: 240000 | Z100: 0 | AA100: =Y100 | AB100: 0 | AC100: =Y100 | AD100: =Y100 | AE100: ENGAGE | AM100: Manque n° contrat
A101: 2026 | B101: DINFOTV | C101: PV N° : 01RC2025- DITV | D101: CONTRAT | F101: BOUJOUBBOU ABDELHAKIM - Chef d'édition des journaux télévisés | G101: VALIDE | H101: APPROUVE | J101: NON CONCERNE | K101: Ordinaire | L101: FONCTIONNEMENT | M101: Prestations de service Achat prestations de services locales - personnes physiques | Q101: RECONDUCTION | T101: BOUJOUBBOU ABDELHAKIM | U101: 2026 | V101: 46387 | X101: 46024 | Y101: 240000 | Z101: 0 | AA101: =Y101 | AB101: 0 | AC101: =Y101 | AD101: =Y101 | AE101: ENGAGE | AM101: Manque n° contrat
A102: 2026 | B102: DINFOTV | C102: PV N° : 01RC2025- DITV | D102: CONTRAT | F102: MOULINE LILIA - Styliste, Maquilleuse et Habilleuse des journalistes et présentateurs chargés de la présentation des émissions | G102: VALIDE | H102: APPROUVE | J102: NON CONCERNE | K102: Ordinaire | L102: FONCTIONNEMENT | M102: Prestations de service Achat prestations de services locales - personnes physiques | Q102: RECONDUCTION | T102: MOULINE LILIA | U102: 2026 | V102: 46387 | X102: 46024 | Y102: 705374.28 | Z102: 0 | AA102: 846449.14 | AB102: 0 | AC102: =Y102 | AD102: =AA102 | AE102: ENGAGE | AM102: Manque n° contrat
A103: 2026 | B103: DINFOTV | C103: PV N° : 01RC2025- DITV | D103: CONTRAT | F103: BOUBKER BEN GHABRIT - Journaliste francophone chargé de la préparation et la réalisation des reportages news en français ainsi que la présentation JT Français. | G103: VALIDE | H103: APPROUVE | J103: NON CONCERNE | K103: Ordinaire | L103: FONCTIONNEMENT | M103: Prestations de service Achat prestations de services locales - personnes physiques | Q103: RECONDUCTION | T103: BOUBKER BEN GHABRIT | U103: 2026 | V103: 46387 | X103: 46024 | Y103: 214800 | Z103: 0 | AA103: =Y103 | AB103: 0 | AC103: =Y103 | AD103: =AA103 | AE103: ENGAGE | AM103: Manque n° contrat
A104: 2026 | B104: DINFOTV | C104: PV N° : 01RC2025- DITV | D104: CONTRAT | F104: MOHAMED EL HAJJAM - Correspondant chargé de la réalisation de reportages et correspondances en matière d'Information Télévisée à partir des Etats Unies d’Amérique. | G104: VALIDE | H104: APPROUVE | J104: NON CONCERNE | K104: Ordinaire | L104: FONCTIONNEMENT | M104: Prestations de service Achat prestations de services locales - personnes physiques | Q104: RECONDUCTION | T104: MOHAMED EL HAJJAM | U104: 2026 | V104: 46387 | X104: 46024 | Y104: 145714.32 | Z104: 0 | AA104: =Y104 | AB104: 0 | AC104: =Y104 | AD104: =AA104 | AE104: ENGAGE | AM104: Manque n° contrat
A105: 2026 | B105: DINFOTV | C105: PV N° : 01RC2025- DITV | D105: CONTRAT | F105: MUSTAPHA SEHIMI - Consultant politique chargé de l'analyse politique et le décryptage hebdomadaire des JT en langue Française | G105: VALIDE | H105: APPROUVE | J105: NON CONCERNE | K105: Ordinaire | L105: FONCTIONNEMENT | M105: Prestations de service Achat prestations de services locales - personnes physiques | Q105: RECONDUCTION | T105: MUSTAPHA SEHIMI | U105: 2026 | V105: 46387 | X105: 46024 | Y105: 150000 | Z105: 0 | AA105: =Y105 | AB105: 0 | AC105: =Y105 | AD105: =AA105 | AE105: ENGAGE | AM105: Manque n° contrat
A106: 2026 | B106: DINFOTV | C106: PV N° : 01RC2025- DITV | D106: CONTRAT | F106: TOSSA MUSTAPHA - Consultant chargé de l'analyse politique et le décryptage hebdomadaire des JT en langue Française et Arabe | G106: VALIDE | H106: APPROUVE | J106: NON CONCERNE | K106: Ordinaire | L106: FONCTIONNEMENT | M106: Prestations de service Achat prestations de services locales - personnes physiques | Q106: RECONDUCTION | T106: TOSSA MUSTAPHA | U106: 2026 | V106: 46387 | X106: 46024 | Y106: 120000 | Z106: 0 | AA106: =Y106 | AB106: 0 | AC106: =Y106 | AD106: =AA106 | AE106: ENGAGE | AM106: Manque n° contrat
A107: 2026 | B107: TV LAAYOUNE | C107: PV N° : 01RC2025-DCL | D107: CONTRAT | F107: SALEK BOUJDOUR - Préparation et Présentation "HADITH ALMADINA" | G107: VALIDE | H107: APPROUVE | J107: NON CONCERNE | K107: Ordinaire | L107: FONCTIONNEMENT | M107: Prestations de service Achat prestations de services locales - personnes physiques | Q107: RECONDUCTION | T107: SALEK BOUJDOUR | U107: 2026 | V107: 46387 | X107: 46024 | Y107: 171428.64 | Z107: 0 | AA107: =Y107 | AB107: 0 | AC107: =AA107 | AD107: =AC107 | AE107: ENGAGE | AM107: Manque n° contrat
A108: 2026 | B108: TV LAAYOUNE | C108: PV N° : 01RC2025-DCL | D108: CONTRAT | F108: EL MOUGUAF AMGHAYER - Préparation et présentation de l'émission intitulée : " TOURATHAK LAK " | G108: VALIDE | H108: APPROUVE | J108: NON CONCERNE | K108: Ordinaire | L108: FONCTIONNEMENT | M108: Prestations de service Achat prestations de services locales - personnes physiques | Q108: RECONDUCTION | T108: EL MOUGUAF AMGHAYER | U108: 2026 | V108: 46387 | X108: 46024 | Y108: 280000 | Z108: 0 | AA108: =Y108 | AB108: 0 | AC108: =AA108 | AD108: =AC108 | AE108: ENGAGE | AM108: Manque n° contrat
A109: 2026 | B109: TV LAAYOUNE | C109: PV N° : 01RC2025-DCL | D109: CONTRAT | F109: YASSINE OMARI - Préparation quotidienne des revues de presses écrite nationale et Internationale | G109: VALIDE | H109: APPROUVE | J109: NON CONCERNE | K109: Ordinaire | L109: FONCTIONNEMENT | M109: Prestations de service Achat prestations de services locales - personnes physiques | Q109: RECONDUCTION | T109: YASSINE OMARI | U109: 2026 | V109: 46387 | X109: 46024 | Y109: 171429.12 | Z109: 0 | AA109: =Y109 | AB109: 0 | AC109: =AA109 | AD109: =AC109 | AE109: ENGAGE | AM109: Manque n° contrat
A110: 2026 | B110: TV LAAYOUNE | C110: PV N° : 01RC2025-DCL | D110: CONTRAT | F110: MAHMOUD AIYACH - Préparation et la présentation d'une émission produite en interne intitulée " MAA NASS " | G110: VALIDE | H110: APPROUVE | J110: NON CONCERNE | K110: Ordinaire | L110: FONCTIONNEMENT | M110: Prestations de service Achat prestations de services locales - personnes physiques | Q110: RECONDUCTION | T110: MAHMOUD AIYACH | U110: 2026 | V110: 46387 | X110: 46024 | Y110: 257142.9 | Z110: 0 | AA110: =Y110 | AB110: 0 | AC110: =AA110 | AD110: =AC110 | AE110: ENGAGE | AM110: Manque n° contrat
A111: 2026 | B111: TV LAAYOUNE | C111: PV N° : 01RC2025-DCL | D111: CONTRAT | F111: MARYAM EDDAH - Chargée de l'Autopromotion et de l’établissement de la grille et des conducteurs de diffusion. | G111: VALIDE | H111: APPROUVE | J111: NON CONCERNE | K111: Ordinaire | L111: FONCTIONNEMENT | M111: Prestations de service Achat prestations de services locales - personnes physiques | Q111: RECONDUCTION | T111: MARYAM EDDAH | U111: 2026 | V111: 46387 | X111: 46024 | Y111: 181800 | Z111: 0 | AA111: =Y111 | AB111: 0 | AC111: =AA111 | AD111: =AC111 | AE111: ENGAGE | AM111: Manque n° contrat
A112: 2026 | B112: MAGHRIBIA | C112: PV N° : 01RC2025-DCCMCITV | D112: CONTRAT | F112: OTHMANE RABBAH - Technicien infographiste | G112: VALIDE | H112: APPROUVE | J112: NON CONCERNE | K112: Ordinaire | L112: FONCTIONNEMENT | M112: Prestations de service Achat prestations de services locales - personnes physiques | Q112: RECONDUCTION | T112: OTHMANE RABBAH | U112: 2026 | V112: 46387 | X112: 46024 | Y112: 144000 | Z112: 0 | AA112: =Y112 | AB112: 0 | AC112: =AA112 | AD112: =AC112 | AE112: ENGAGE | AM112: Manque n° contrat
A113: 2026 | B113: MAGHRIBIA | C113: PV N° : 01RC2025-DCCMCITV | D113: CONTRAT | F113: HIBA TOUANINA - Technicienne Scripte | G113: VALIDE | H113: APPROUVE | J113: NON CONCERNE | K113: Ordinaire | L113: FONCTIONNEMENT | M113: Prestations de service Achat prestations de services locales - personnes physiques | Q113: RECONDUCTION | T113: HIBA TOUANINA | U113: 2026 | V113: 46387 | X113: 46024 | Y113: 100800 | Z113: 0 | AA113: =Y113 | AB113: 0 | AC113: =AA113 | AD113: =AC113 | AE113: ENGAGE | AM113: Manque n° contrat
A114: 2026 | B114: MAGHRIBIA | C114: PV N° : 01RC2025-DCCMCITV | D114: CONTRAT | F114: FATIMA ZAHRA BOUMBAREK - Technicienne assistante Réalisatrice | G114: VALIDE | H114: APPROUVE | J114: NON CONCERNE | K114: Ordinaire | L114: FONCTIONNEMENT | M114: Prestations de service Achat prestations de services locales - personnes physiques | Q114: RECONDUCTION | T114: FATIMA ZAHRA BOUMBAREK | U114: 2026 | V114: 46387 | X114: 46024 | Y114: 100800 | Z114: 0 | AA114: =Y114 | AB114: 0 | AC114: =AA114 | AD114: =AC114 | AE114: ENGAGE | AM114: Manque n° contrat
A115: 2026 | B115: MAGHRIBIA | C115: PV N° : 01RC2025-DCCMCITV | D115: CONTRAT | F115: OUMAIMA NACHAR - Journaliste présentatrice | G115: VALIDE | H115: APPROUVE | J115: NON CONCERNE | K115: Ordinaire | L115: FONCTIONNEMENT | M115: Prestations de service Achat prestations de services locales - personnes physiques | Q115: RECONDUCTION | T115: OUMAIMA NACHAR | U115: 2026 | V115: 46387 | X115: 46024 | Y115: 144000 | Z115: 0 | AA115: =Y115 | AB115: 0 | AC115: =AA115 | AD115: =AC115 | AE115: ENGAGE | AM115: Manque n° contrat
A116: 2026 | B116: MAGHRIBIA | C116: PV N° : 01RC2025-DCCMCITV | D116: CONTRAT | F116: NIDAL OUJIL - Journaliste présentatrice | G116: VALIDE | H116: APPROUVE | J116: NON CONCERNE | K116: Ordinaire | L116: FONCTIONNEMENT | M116: Prestations de service Achat prestations de services locales - personnes physiques | Q116: RECONDUCTION | T116: NIDAL OUJI | U116: 2026 | V116: 46387 | X116: 46024 | Y116: 144000 | Z116: 0 | AA116: =Y116 | AB116: 0 | AC116: =AA116 | AD116: =AC116 | AE116: ENGAGE | AM116: Manque n° contrat
A117: 2026 | B117: MAGHRIBIA | C117: PV N° : 01RC2025-DCCMCITV | D117: CONTRAT | F117: ABDELLATIF AMRANI ZERIFI - Technicien assistant réalisateur | G117: VALIDE | H117: APPROUVE | J117: NON CONCERNE | K117: Ordinaire | L117: FONCTIONNEMENT | M117: Prestations de service Achat prestations de services locales - personnes physiques | Q117: RECONDUCTION | T117: ABDELLATIF AMRANI ZERIF | U117: 2026 | V117: 46387 | X117: 46024 | Y117: 100800 | Z117: 0 | AA117: =Y117 | AB117: 0 | AC117: =AA117 | AD117: =AC117 | AE117: ENGAGE | AM117: Manque n° contrat
A118: 2026 | B118: MAGHRIBIA | C118: PV N° : 01RC2025-DCCMCITV | D118: CONTRAT | F118: LAMYAE KHOUADIR - Technicienne scripte | G118: VALIDE | H118: APPROUVE | J118: NON CONCERNE | K118: Ordinaire | L118: FONCTIONNEMENT | M118: Prestations de service Achat prestations de services locales - personnes physiques | Q118: RECONDUCTION | T118: LAMYAE KHOUADIR | U118: 2026 | V118: 46387 | X118: 46024 | Y118: 100800 | Z118: 0 | AA118: =Y118 | AB118: 0 | AC118: =AA118 | AD118: =AC118 | AE118: ENGAGE | AM118: Manque n° contrat
... A120: 2026 | B120: MAGHRIBIA | C120: PV N° : 01RC2025-DCCMCITV | D120: CONTRAT | F120: JEBRANI HAYAT - Coiffeuse, maquilleuse | G120: VALIDE | H120: APPROUVE | J120: NON CONCERNE | K120: Ordinaire | L120: FONCTIONNEMENT | M120: Prestations de service Achat prestations de services locales - personnes physiques | Q120: RECONDUCTION | T120: JEBRANI HAYAT | U120: 2026 | V120: 46387 | X120: 46024 | Y120: 72000 | Z120: 0 | AA120: =Y120 | AB120: 0 | AC120: =AA120 | AD120: =AC120 | AE120: ENGAGE | AM120: Manque n° contrat
A121: 2026 | B121: DMPTV | C121: PV N° : 01RC2025-DCMPTV | D121: CONTRAT | F121: ZAKARIA TIBARI - Conception de bandes annonces pour la promotion des programmes de la grille de la chaîne Al Aoula | G121: VALIDE | H121: APPROUVE | J121: NON CONCERNE | K121: Ordinaire | L121: FONCTIONNEMENT | M121: Prestations de service Achat prestations de services locales - personnes physiques | Q121: RECONDUCTION | T121: ZAKARIA TIBARI | U121: 2026 | V121: 46387 | X121: 46024 | Y121: 257142.84 | AA121: =Y121 | AC121: =Y121 | AD121: =AA121 | AE121: ENGAGE | AM121: Manque n° contrat
A122: 2026 | B122: DMPTV | C122: PV N° : 01RC2025-DCMPTV | D122: CONTRAT | F122: GHEZLANE EL MERZOUGUI - Enregistrement des voix off en arabe des bandes annonces TV et radio Al Aoula | G122: VALIDE | H122: APPROUVE | J122: NON CONCERNE | K122: Ordinaire | L122: FONCTIONNEMENT | M122: Prestations de service Achat prestations de services locales - personnes physiques | Q122: RECONDUCTION | T122: GHEZLANE EL MERZOUGUI | U122: 2026 | V122: 46387 | X122: 46024 | Y122: 84000 | AA122: =Y122 | AC122: =Y122 | AD122: =AA122 | AE122: ENGAGE | AM122: Manque n° contrat
A123: 2026 | B123: DMPTV | C123: PV N° : 01RC2025-DCMPTV | D123: CONTRAT | F123: HOUSSAM MOUILLAH - Monteur | G123: VALIDE | H123: APPROUVE | J123: NON CONCERNE | K123: Ordinaire | L123: FONCTIONNEMENT | M123: Prestations de service Achat prestations de services locales - personnes physiques | Q123: RECONDUCTION | T123: HOUSSAM MOUILLAH | U123: 2026 | V123: 46387 | X123: 46024 | Y123: 120000 | AA123: =Y123 | AC123: =Y123 | AD123: =AA123 | AE123: ENGAGE | AM123: Manque n° contrat
A124: 2026 | B124: DMPTV | C124: PV N° : 01RC2025-DCMPTV | D124: CONTRAT | F124: MSIOUAS MOHAMED DRISS - Chef de produit digital | G124: VALIDE | H124: APPROUVE | J124: NON CONCERNE | K124: Ordinaire | L124: FONCTIONNEMENT | M124: Prestations de service Achat prestations de services locales - personnes physiques | Q124: RECONDUCTION | T124: MSIOUAS MOHAMED DRISS | U124: 2026 | V124: 46387 | X124: 46024 | Y124: 264000 | AA124: =Y124 | AC124: =Y124 | AD124: =AA124 | AE124: ENGAGE | AM124: Manque n° contrat
A125: 2026 | B125: DMPTV | C125: PV N° : 01RC2025-DCMPTV | D125: CONTRAT | F125: ABDELOUAHED JABBAR - Monteur | G125: VALIDE | H125: APPROUVE | J125: NON CONCERNE | K125: Ordinaire | L125: FONCTIONNEMENT | M125: Prestations de service Achat prestations de services locales - personnes physiques | Q125: RECONDUCTION | T125: ABDELOUAHED JABBAR | U125: 2026 | V125: 46387 | X125: 46024 | Y125: 216000 | AA125: =Y125 | AC125: =Y125 | AD125: =AA125 | AE125: ENGAGE | AM125: Manque n° contrat
A126: 2026 | B126: DMPTV | C126: PV N° : 01RC2025-DCMPTV | D126: CONTRAT | F126: YASSINE KIRAMI - Monteur digital et cameraman | G126: VALIDE | H126: APPROUVE | J126: NON CONCERNE | K126: Ordinaire | L126: FONCTIONNEMENT | M126: Prestations de service Achat prestations de services locales - personnes physiques | Q126: RECONDUCTION | T126: YASSINE KIRAMI | U126: 2026 | V126: 46387 | X126: 46024 | Y126: 144000 | AA126: =Y126 | AC126: =Y126 | AD126: =AA126 | AE126: ENGAGE | AM126: Manque n° contrat
A127: 2026 | B127: DMPTV | C127: PV N° : 01RC2025-DCMPTV | D127: CONTRAT | F127: SAFAA SABRI - Rédactrice en arabe | G127: VALIDE | H127: APPROUVE | J127: NON CONCERNE | K127: Ordinaire | L127: FONCTIONNEMENT | M127: Prestations de service Achat prestations de services locales - personnes physiques | Q127: RECONDUCTION | T127: SAFAA SABR | U127: 2026 | V127: 46387 | X127: 46024 | Y127: 132000 | AA127: =Y127 | AC127: =Y127 | AD127: =AA127 | AE127: ENGAGE | AM127: Manque n° contrat
A128: 2026 | B128: DMPTV | C128: PV N° : 01RC2025-DCMPTV | D128: CONTRAT | F128: SARAH MAACHE - Rédactrice en Français | G128: VALIDE | H128: APPROUVE | J128: NON CONCERNE | K128: Ordinaire | L128: FONCTIONNEMENT | M128: Prestations de service Achat prestations de services locales - personnes physiques | Q128: RECONDUCTION | T128: SARAH MAACHE | U128: 2026 | V128: 46387 | X128: 46024 | Y128: 252000 | AA128: =Y128 | AC128: =Y128 | AD128: =AA128 | AE128: ENGAGE | AM128: Manque n° contrat
A129: 2026 | B129: DMPTV | C129: PV N° : 01RC2025-DCMPTV | D129: CONTRAT | F129: BASMA WAJIB - Community Manager | G129: VALIDE | H129: APPROUVE | J129: NON CONCERNE | K129: Ordinaire | L129: FONCTIONNEMENT | M129: Prestations de service Achat prestations de services locales - personnes physiques | Q129: RECONDUCTION | T129: BASMA WAJIB | U129: 2026 | V129: 46387 | X129: 46024 | Y129: 84000 | AA129: =Y129 | AC129: =Y129 | AD129: =AA129 | AE129: ENGAGE | AM129: Manque n° contrat
A130: 2026 | B130: DMPTV | C130: PV N° : 01RC2025-DCMPTV | D130: CONTRAT | F130: M’BARK AGNAOU - Community Manager | G130: VALIDE | H130: APPROUVE | J130: NON CONCERNE | K130: Ordinaire | L130: FONCTIONNEMENT | M130: Prestations de service Achat prestations de services locales - personnes physiques | Q130: RECONDUCTION | T130: M’BARK AGNAOU | U130: 2026 | V130: 46387 | X130: 46024 | Y130: 84000 | AA130: =Y130 | AC130: =Y130 | AD130: =AA130 | AE130: ENGAGE | AM130: Manque n° contrat
A131: 2026 | B131: DMPTV | C131: PV N° : 01RC2025-DCMPTV | D131: CONTRAT | F131: ESSAIFI MOHAMED SAMI - Content lead digital | G131: VALIDE | H131: APPROUVE | J131: NON CONCERNE | K131: Ordinaire | L131: FONCTIONNEMENT | M131: Prestations de service Achat prestations de services locales - personnes physiques | Q131: RECONDUCTION | T131: ESSAIFI MOHAMED SAMI | U131: 2026 | V131: 46387 | X131: 46024 | Y131: 276000 | AA131: =Y131 | AC131: =Y131 | AD131: =AA131 | AE131: ENGAGE | AM131: Manque n° contrat
A132: 2026 | B132: DMPTV | C132: PV N° : 01RC2025-DCMPTV | D132: CONTRAT | F132: HAJAR LAMRANI - Monteur | G132: VALIDE | H132: APPROUVE | J132: NON CONCERNE | K132: Ordinaire | L132: FONCTIONNEMENT | M132: Prestations de service Achat prestations de services locales - personnes physiques | Q132: RECONDUCTION | T132: HAJAR LAMRANI | U132: 2026 | V132: 46387 | X132: 46024 | Y132: 144000 | AA132: =Y132 | AC132: =Y132 | AD132: =AA132 | AE132: ENGAGE | AM132: Manque n° contrat
...

Sheet lignes
A1: Compte | B1: Libellé
A2: 212-1 | B2: Frais d'acquisition des immobilisations
A3: 212-2 | B3: Prestations de service à immobiliser
A4: 221-1 | B4: Immobilisations incorporelles (logiciels, licences, etc.)
A5: 231-1 | B5: Terrains
A6: 232-2 | B6: Agencements et aménagement constructions
A7: 233-1 | B7: Installations techniques
A8: 233-2 | B8: Matériel et outillage
A9: 233-3 | B9: Equipements de télédiffusion
A10: 233-4 | B10: Equipements techniques
A11: 235-1 | B11: Mobilier de bureau
A12: 235-2 | B12: Matériel de bureau
... A58: 617-3 | B58: Charges sociales diverses

Sheet PPM 2026
A1: PROGRAMME PREVISIONNEL DES MARCHES PAR APPELS D'OFFRES
A9: DIRECTION | B9: OBJET | C9: NATURE DE LA PRESTATION | D9: MODE DE PASSATION | E9: PERIODE PREVUE POUR LE LANCEMENT | F9: LIEU D'EXECUTION | G9: AOO RESERVES AUX PME | H9: ESTIMATION | I9: NATURE BUDGET
A10: Direction de la Télédiffusion | B10: Fourniture des modules de traitement audio et RDS pour les émetteurs FM | C10: Fournitures | D10: Appel d'offres ouvert | E10: T3 | F10: Magasin Temara | G10: Non | H10: 1800000 | I10: Investissement
A11: Direction de la Télédiffusion | B11: Fourniture, installation et mise en service de systèmes de supervision des antennes de diffusion FM et TV | C11: Fournitures | D11: Appel d'offres ouvert | E11: T2 | F11: Centres de diffusion de la SNRT | G11: Non | H11: 2755000 | I11: Investissement
A12: Direction de la Télédiffusion | B12: Fourniture et installation des équipements de contrôle audio et vidéo pour les petits centres de diffusion TV/FM | C12: Fournitures | D12: Appel d'offres ouvert | E12: T2 | F12: Centres de diffusion de la SNRT | G12: Non | H12: 1000000 | I12: Investissement
A13: Direction de la Télédiffusion | B13: Fourniture, installation et mise en service des climatiseurs aux centres de diffusion de la SNRT | C13: Fournitures | D13: Appel d'offres ouvert | E13: T3 | F13: Centres de diffusion de la SNRT | G13: Oui | H13: 3500000 | I13: Investissement
A14: Direction de la Télédiffusion | B14: Fourniture des analyseurs de réseaux électrique et les appareils de mesure électrique | C14: Fournitures | D14: Appel d'offres ouvert | E14: T2 | F14: Magasin Temara | G14: Non | H14: 800000 | I14: Investissement
A15: Direction de la Télédiffusion | B15: Fourniture,installation et mise en service des commutateurs et distributeurs des signaux ASI et IP pour les centres de diffusion TNT et FM | C15: Fournitures | D15: Appel d'offres ouvert | E15: T3 | F15: Centres de diffusion de la SNRT | G15: Non | H15: 1000000 | I15: Investissement
A16: Direction de la Télédiffusion | B16: Fourniture et installation des sondes FM et TNT pour le contrôle des signaux audios et vidéo des chaines radio et télevision de la SNRT | C16: Fournitures | D16: Appel d'offres ouvert | E16: T3 | F16: Magasin Temara | G16: Non | H16: 1200000 | I16: Investissement
A17: Direction de la Télédiffusion | B17: Fourniture des modules et pièces de rechanges des émetteurs TNT de des centres de la SNRT | C17: Fournitures | D17: Appel d'offres ouvert | E17: T2 | F17: Magasin Temara | G17: Non | H17: 6500000 | I17: Fonctionnement
A18: Direction de la Télédiffusion | B18: Fourniture des modules et pièces de rechanges des émetteurs FM des centres de la SNRT | C18: Fournitures | D18: Appel d'offres ouvert | E18: T2 | F18: Magasin Temara | G18: Non | H18: 6500000 | I18: Fonctionnement
A19: Direction de la Télédiffusion | B19: Fourniture des duplexeurs, filtres, patchs panel , commutateurs RF et adaptateurs | C19: Fournitures | D19: Appel d'offres ouvert | E19: T3 | F19: Magasin Temara | G19: Non | H19: 1600000 | I19: Fonctionnement
A20: Direction de la Télédiffusion | B20: Fourniture des distributeurs de puissance UHF et FM, combiners, feeders et antennes | C20: Fournitures | D20: Appel d'offres ouvert | E20: T3 | F20: Magasin Temara | G20: Non | H20: 3500000 | I20: Fonctionnement
A21: Direction de la Télédiffusion | B21: Fourniture des modules et pièces de rechanges hydrauliques et électriques pour les émetteurs de diffusion TNT et FM | C21: Fournitures | D21: Appel d'offres ouvert | E21: T2 | F21: Magasin Temara | G21: Non | H21: 1100000 | I21: Fonctionnement
... A169: Direction Centrale Technique | B169: Fourniture et mise en service d'un systéme d'intercom boradcast pour les besoins de la SNRT | C169: Fournitures | D169: Appel d'offres ouvert | E169: T2 | F169: Rabat | G169: Non | H169: 291156 | I169: Investissement

Sheet Données Suivi
A1: DIRECTION | B1: REF | C1: BCI (TYPE D'ACHAT) | D1: OBJET | E1: STATUT SUPPORT D'ENGAGEMENT | F1: N° SUPPORT D'ENGAGEMENT | G1: NATURE BUDGET | H1: STATUT D'ENGAGEMENT | I1: STATUT 1 | J1: MONTANT (MAD) | K1: DATE FICHE | L1: ANCIENNETE (jours) | M1: CATEGORIE SUIVI | N1: TYPE BUDGET | O1: NATURE BUDGET | P1: CATEGORIES | Q1: CLE INFR-ANNULE
A2: =IF(ISBLANK('ENGAGEMENTS 2026'!B2),"",IF('ENGAGEMENTS 2026'!B2="DTSI","DCT",'ENGAGEMENTS 2026'!B2)) | B2: =IF(ISBLANK('ENGAGEMENTS 2026'!B2),"",'ENGAGEMENTS 2026'!C2) | C2: =IF(ISBLANK('ENGAGEMENTS 2026'!B2),"",'ENGAGEMENTS 2026'!D2) | D2: =IF(ISBLANK('ENGAGEMENTS 2026'!B2),"",'ENGAGEMENTS 2026'!F2) | E2: =IF(ISBLANK('ENGAGEMENTS 2026'!B2),"",'ENGAGEMENTS 2026'!H2) | F2: =IF(ISBLANK('ENGAGEMENTS 2026'!B2),"",'ENGAGEMENTS 2026'!I2) | G2: =IF(ISBLANK('ENGAGEMENTS 2026'!B2),"",'ENGAGEMENTS 2026'!L2) | H2: =IF(ISBLANK('ENGAGEMENTS 2026'!B2),"",'ENGAGEMENTS 2026'!AE2) | I2: =IF(ISBLANK('ENGAGEMENTS 2026'!B2),"",'ENGAGEMENTS 2026'!G2) | J2: =IF(ISBLANK('ENGAGEMENTS 2026'!B2),"",IF(AND(OR($E2="INFRUCTUEUX",$E2="ANNULE"),$C2="AOO-M"),'ENGAGEMENTS 2026'!O2,IF($H2="EN COURS DE PREENGAGEMENT",'ENGAGEMENTS 2026'!N2,IF($H2="PREENGAGE",IF($E2="ATTRIBUE",'ENGAGEMENTS 2026'!AD2,'ENGAGEMENTS 2026'!N2),'ENGAGEMENTS 2026'!AD2)))) | K2: =IF(ISBLANK('ENGAGEMENTS 2026'!V2),"",'ENGAGEMENTS 2026'!V2) | L2: =IF($K2="","",TODAY()-$K2) | M2: =IF($A2="","",IF($H2="ENGAGE","Engagé",IF(AND($H2="NON ENGAGE",OR($I2="INFRUCTUEUX",$I2="ANNULE")),"Clôturé sans suite","En cours"))) | N2: =IF(ISBLANK('ENGAGEMENTS 2026'!B2),"",'ENGAGEMENTS 2026'!K2) | O2: =IF(ISBLANK('ENGAGEMENTS 2026'!B2),"",'ENGAGEMENTS 2026'!L2) | P2: =IF(ISBLANK('ENGAGEMENTS 2026'!B2),"",'ENGAGEMENTS 2026'!J2) | Q2: =IF($A2="","",IF(OR($E2="INFRUCTUEUX",$E2="ANNULE"),$A2&"|"&(COUNTIFS($A$2:$A2,$A2,$E$2:$E2,"INFRUCTUEUX")+COUNTIFS($A$2:$A2,$A2,$E$2:$E2,"ANNULE")),""))
A3: =IF(ISBLANK('ENGAGEMENTS 2026'!B3),"",IF('ENGAGEMENTS 2026'!B3="DTSI","DCT",'ENGAGEMENTS 2026'!B3)) | B3: =IF(ISBLANK('ENGAGEMENTS 2026'!B3),"",'ENGAGEMENTS 2026'!C3) | C3: =IF(ISBLANK('ENGAGEMENTS 2026'!B3),"",'ENGAGEMENTS 2026'!D3) | D3: =IF(ISBLANK('ENGAGEMENTS 2026'!B3),"",'ENGAGEMENTS 2026'!F3) | E3: =IF(ISBLANK('ENGAGEMENTS 2026'!B3),"",'ENGAGEMENTS 2026'!H3) | F3: =IF(ISBLANK('ENGAGEMENTS 2026'!B3),"",'ENGAGEMENTS 2026'!I3) | G3: =IF(ISBLANK('ENGAGEMENTS 2026'!B3),"",'ENGAGEMENTS 2026'!L3) | H3: =IF(ISBLANK('ENGAGEMENTS 2026'!B3),"",'ENGAGEMENTS 2026'!AE3) | I3: =IF(ISBLANK('ENGAGEMENTS 2026'!B3),"",'ENGAGEMENTS 2026'!G3) | J3: =IF(ISBLANK('ENGAGEMENTS 2026'!B3),"",IF(AND(OR($E3="INFRUCTUEUX",$E3="ANNULE"),$C3="AOO-M"),'ENGAGEMENTS 2026'!O3,IF($H3="EN COURS DE PREENGAGEMENT",'ENGAGEMENTS 2026'!N3,IF($H3="PREENGAGE",IF($E3="ATTRIBUE",'ENGAGEMENTS 2026'!AD3,'ENGAGEMENTS 2026'!N3),'ENGAGEMENTS 2026'!AD3)))) | K3: =IF(ISBLANK('ENGAGEMENTS 2026'!V3),"",'ENGAGEMENTS 2026'!V3) | L3: =IF($K3="","",TODAY()-$K3) | M3: =IF($A3="","",IF($H3="ENGAGE","Engagé",IF(AND($H3="NON ENGAGE",OR($I3="INFRUCTUEUX",$I3="ANNULE")),"Clôturé sans suite","En cours"))) | N3: =IF(ISBLANK('ENGAGEMENTS 2026'!B3),"",'ENGAGEMENTS 2026'!K3) | O3: =IF(ISBLANK('ENGAGEMENTS 2026'!B3),"",'ENGAGEMENTS 2026'!L3) | P3: =IF(ISBLANK('ENGAGEMENTS 2026'!B3),"",'ENGAGEMENTS 2026'!J3) | Q3: =IF($A3="","",IF(OR($E3="INFRUCTUEUX",$E3="ANNULE"),$A3&"|"&(COUNTIFS($A$2:$A3,$A3,$E$2:$E3,"INFRUCTUEUX")+COUNTIFS($A$2:$A3,$A3,$E$2:$E3,"ANNULE")),""))
A4: =IF(ISBLANK('ENGAGEMENTS 2026'!B4),"",IF('ENGAGEMENTS 2026'!B4="DTSI","DCT",'ENGAGEMENTS 2026'!B4)) | B4: =IF(ISBLANK('ENGAGEMENTS 2026'!B4),"",'ENGAGEMENTS 2026'!C4) | C4: =IF(ISBLANK('ENGAGEMENTS 2026'!B4),"",'ENGAGEMENTS 2026'!D4) | D4: =IF(ISBLANK('ENGAGEMENTS 2026'!B4),"",'ENGAGEMENTS 2026'!F4) | E4: =IF(ISBLANK('ENGAGEMENTS 2026'!B4),"",'ENGAGEMENTS 2026'!H4) | F4: =IF(ISBLANK('ENGAGEMENTS 2026'!B4),"",'ENGAGEMENTS 2026'!I4) | G4: =IF(ISBLANK('ENGAGEMENTS 2026'!B4),"",'ENGAGEMENTS 2026'!L4) | H4: =IF(ISBLANK('ENGAGEMENTS 2026'!B4),"",'ENGAGEMENTS 2026'!AE4) | I4: =IF(ISBLANK('ENGAGEMENTS 2026'!B4),"",'ENGAGEMENTS 2026'!G4) | J4: =IF(ISBLANK('ENGAGEMENTS 2026'!B4),"",IF(AND(OR($E4="INFRUCTUEUX",$E4="ANNULE"),$C4="AOO-M"),'ENGAGEMENTS 2026'!O4,IF($H4="EN COURS DE PREENGAGEMENT",'ENGAGEMENTS 2026'!N4,IF($H4="PREENGAGE",IF($E4="ATTRIBUE",'ENGAGEMENTS 2026'!AD4,'ENGAGEMENTS 2026'!N4),'ENGAGEMENTS 2026'!AD4)))) | K4: =IF(ISBLANK('ENGAGEMENTS 2026'!V4),"",'ENGAGEMENTS 2026'!V4) | L4: =IF($K4="","",TODAY()-$K4) | M4: =IF($A4="","",IF($H4="ENGAGE","Engagé",IF(AND($H4="NON ENGAGE",OR($I4="INFRUCTUEUX",$I4="ANNULE")),"Clôturé sans suite","En cours"))) | N4: =IF(ISBLANK('ENGAGEMENTS 2026'!B4),"",'ENGAGEMENTS 2026'!K4) | O4: =IF(ISBLANK('ENGAGEMENTS 2026'!B4),"",'ENGAGEMENTS 2026'!L4) | P4: =IF(ISBLANK('ENGAGEMENTS 2026'!B4),"",'ENGAGEMENTS 2026'!J4) | Q4: =IF($A4="","",IF(OR($E4="INFRUCTUEUX",$E4="ANNULE"),$A4&"|"&(COUNTIFS($A$2:$A4,$A4,$E$2:$E4,"INFRUCTUEUX")+COUNTIFS($A$2:$A4,$A4,$E$2:$E4,"ANNULE")),""))
A5: =IF(ISBLANK('ENGAGEMENTS 2026'!B5),"",IF('ENGAGEMENTS 2026'!B5="DTSI","DCT",'ENGAGEMENTS 2026'!B5)) | B5: =IF(ISBLANK('ENGAGEMENTS 2026'!B5),"",'ENGAGEMENTS 2026'!C5) | C5: =IF(ISBLANK('ENGAGEMENTS 2026'!B5),"",'ENGAGEMENTS 2026'!D5) | D5: =IF(ISBLANK('ENGAGEMENTS 2026'!B5),"",'ENGAGEMENTS 2026'!F5) | E5: =IF(ISBLANK('ENGAGEMENTS 2026'!B5),"",'ENGAGEMENTS 2026'!H5) | F5: =IF(ISBLANK('ENGAGEMENTS 2026'!B5),"",'ENGAGEMENTS 2026'!I5) | G5: =IF(ISBLANK('ENGAGEMENTS 2026'!B5),"",'ENGAGEMENTS 2026'!L5) | H5: =IF(ISBLANK('ENGAGEMENTS 2026'!B5),"",'ENGAGEMENTS 2026'!AE5) | I5: =IF(ISBLANK('ENGAGEMENTS 2026'!B5),"",'ENGAGEMENTS 2026'!G5) | J5: =IF(ISBLANK('ENGAGEMENTS 2026'!B5),"",IF(AND(OR($E5="INFRUCTUEUX",$E5="ANNULE"),$C5="AOO-M"),'ENGAGEMENTS 2026'!O5,IF($H5="EN COURS DE PREENGAGEMENT",'ENGAGEMENTS 2026'!N5,IF($H5="PREENGAGE",IF($E5="ATTRIBUE",'ENGAGEMENTS 2026'!AD5,'ENGAGEMENTS 2026'!N5),'ENGAGEMENTS 2026'!AD5)))) | K5: =IF(ISBLANK('ENGAGEMENTS 2026'!V5),"",'ENGAGEMENTS 2026'!V5) | L5: =IF($K5="","",TODAY()-$K5) | M5: =IF($A5="","",IF($H5="ENGAGE","Engagé",IF(AND($H5="NON ENGAGE",OR($I5="INFRUCTUEUX",$I5="ANNULE")),"Clôturé sans suite","En cours"))) | N5: =IF(ISBLANK('ENGAGEMENTS 2026'!B5),"",'ENGAGEMENTS 2026'!K5) | O5: =IF(ISBLANK('ENGAGEMENTS 2026'!B5),"",'ENGAGEMENTS 2026'!L5) | P5: =IF(ISBLANK('ENGAGEMENTS 2026'!B5),"",'ENGAGEMENTS 2026'!J5) | Q5: =IF($A5="","",IF(OR($E5="INFRUCTUEUX",$E5="ANNULE"),$A5&"|"&(COUNTIFS($A$2:$A5,$A5,$E$2:$E5,"INFRUCTUEUX")+COUNTIFS($A$2:$A5,$A5,$E$2:$E5,"ANNULE")),""))
A6: =IF(ISBLANK('ENGAGEMENTS 2026'!B6),"",IF('ENGAGEMENTS 2026'!B6="DTSI","DCT",'ENGAGEMENTS 2026'!B6)) | B6: =IF(ISBLANK('ENGAGEMENTS 2026'!B6),"",'ENGAGEMENTS 2026'!C6) | C6: =IF(ISBLANK('ENGAGEMENTS 2026'!B6),"",'ENGAGEMENTS 2026'!D6) | D6: =IF(ISBLANK('ENGAGEMENTS 2026'!B6),"",'ENGAGEMENTS 2026'!F6) | E6: =IF(ISBLANK('ENGAGEMENTS 2026'!B6),"",'ENGAGEMENTS 2026'!H6) | F6: =IF(ISBLANK('ENGAGEMENTS 2026'!B6),"",'ENGAGEMENTS 2026'!I6) | G6: =IF(ISBLANK('ENGAGEMENTS 2026'!B6),"",'ENGAGEMENTS 2026'!L6) | H6: =IF(ISBLANK('ENGAGEMENTS 2026'!B6),"",'ENGAGEMENTS 2026'!AE6) | I6: =IF(ISBLANK('ENGAGEMENTS 2026'!B6),"",'ENGAGEMENTS 2026'!G6) | J6: =IF(ISBLANK('ENGAGEMENTS 2026'!B6),"",IF(AND(OR($E6="INFRUCTUEUX",$E6="ANNULE"),$C6="AOO-M"),'ENGAGEMENTS 2026'!O6,IF($H6="EN COURS DE PREENGAGEMENT",'ENGAGEMENTS 2026'!N6,IF($H6="PREENGAGE",IF($E6="ATTRIBUE",'ENGAGEMENTS 2026'!AD6,'ENGAGEMENTS 2026'!N6),'ENGAGEMENTS 2026'!AD6)))) | K6: =IF(ISBLANK('ENGAGEMENTS 2026'!V6),"",'ENGAGEMENTS 2026'!V6) | L6: =IF($K6="","",TODAY()-$K6) | M6: =IF($A6="","",IF($H6="ENGAGE","Engagé",IF(AND($H6="NON ENGAGE",OR($I6="INFRUCTUEUX",$I6="ANNULE")),"Clôturé sans suite","En cours"))) | N6: =IF(ISBLANK('ENGAGEMENTS 2026'!B6),"",'ENGAGEMENTS 2026'!K6) | O6: =IF(ISBLANK('ENGAGEMENTS 2026'!B6),"",'ENGAGEMENTS 2026'!L6) | P6: =IF(ISBLANK('ENGAGEMENTS 2026'!B6),"",'ENGAGEMENTS 2026'!J6) | Q6: =IF($A6="","",IF(OR($E6="INFRUCTUEUX",$E6="ANNULE"),$A6&"|"&(COUNTIFS($A$2:$A6,$A6,$E$2:$E6,"INFRUCTUEUX")+COUNTIFS($A$2:$A6,$A6,$E$2:$E6,"ANNULE")),""))
A7: =IF(ISBLANK('ENGAGEMENTS 2026'!B7),"",IF('ENGAGEMENTS 2026'!B7="DTSI","DCT",'ENGAGEMENTS 2026'!B7)) | B7: =IF(ISBLANK('ENGAGEMENTS 2026'!B7),"",'ENGAGEMENTS 2026'!C7) | C7: =IF(ISBLANK('ENGAGEMENTS 2026'!B7),"",'ENGAGEMENTS 2026'!D7) | D7: =IF(ISBLANK('ENGAGEMENTS 2026'!B7),"",'ENGAGEMENTS 2026'!F7) | E7: =IF(ISBLANK('ENGAGEMENTS 2026'!B7),"",'ENGAGEMENTS 2026'!H7) | F7: =IF(ISBLANK('ENGAGEMENTS 2026'!B7),"",'ENGAGEMENTS 2026'!I7) | G7: =IF(ISBLANK('ENGAGEMENTS 2026'!B7),"",'ENGAGEMENTS 2026'!L7) | H7: =IF(ISBLANK('ENGAGEMENTS 2026'!B7),"",'ENGAGEMENTS 2026'!AE7) | I7: =IF(ISBLANK('ENGAGEMENTS 2026'!B7),"",'ENGAGEMENTS 2026'!G7) | J7: =IF(ISBLANK('ENGAGEMENTS 2026'!B7),"",IF(AND(OR($E7="INFRUCTUEUX",$E7="ANNULE"),$C7="AOO-M"),'ENGAGEMENTS 2026'!O7,IF($H7="EN COURS DE PREENGAGEMENT",'ENGAGEMENTS 2026'!N7,IF($H7="PREENGAGE",IF($E7="ATTRIBUE",'ENGAGEMENTS 2026'!AD7,'ENGAGEMENTS 2026'!N7),'ENGAGEMENTS 2026'!AD7)))) | K7: =IF(ISBLANK('ENGAGEMENTS 2026'!V7),"",'ENGAGEMENTS 2026'!V7) | L7: =IF($K7="","",TODAY()-$K7) | M7: =IF($A7="","",IF($H7="ENGAGE","Engagé",IF(AND($H7="NON ENGAGE",OR($I7="INFRUCTUEUX",$I7="ANNULE")),"Clôturé sans suite","En cours"))) | N7: =IF(ISBLANK('ENGAGEMENTS 2026'!B7),"",'ENGAGEMENTS 2026'!K7) | O7: =IF(ISBLANK('ENGAGEMENTS 2026'!B7),"",'ENGAGEMENTS 2026'!L7) | P7: =IF(ISBLANK('ENGAGEMENTS 2026'!B7),"",'ENGAGEMENTS 2026'!J7) | Q7: =IF($A7="","",IF(OR($E7="INFRUCTUEUX",$E7="ANNULE"),$A7&"|"&(COUNTIFS($A$2:$A7,$A7,$E$2:$E7,"INFRUCTUEUX")+COUNTIFS($A$2:$A7,$A7,$E$2:$E7,"ANNULE")),""))
A8: =IF(ISBLANK('ENGAGEMENTS 2026'!B8),"",IF('ENGAGEMENTS 2026'!B8="DTSI","DCT",'ENGAGEMENTS 2026'!B8)) | B8: =IF(ISBLANK('ENGAGEMENTS 2026'!B8),"",'ENGAGEMENTS 2026'!C8) | C8: =IF(ISBLANK('ENGAGEMENTS 2026'!B8),"",'ENGAGEMENTS 2026'!D8) | D8: =IF(ISBLANK('ENGAGEMENTS 2026'!B8),"",'ENGAGEMENTS 2026'!F8) | E8: =IF(ISBLANK('ENGAGEMENTS 2026'!B8),"",'ENGAGEMENTS 2026'!H8) | F8: =IF(ISBLANK('ENGAGEMENTS 2026'!B8),"",'ENGAGEMENTS 2026'!I8) | G8: =IF(ISBLANK('ENGAGEMENTS 2026'!B8),"",'ENGAGEMENTS 2026'!L8) | H8: =IF(ISBLANK('ENGAGEMENTS 2026'!B8),"",'ENGAGEMENTS 2026'!AE8) | I8: =IF(ISBLANK('ENGAGEMENTS 2026'!B8),"",'ENGAGEMENTS 2026'!G8) | J8: =IF(ISBLANK('ENGAGEMENTS 2026'!B8),"",IF(AND(OR($E8="INFRUCTUEUX",$E8="ANNULE"),$C8="AOO-M"),'ENGAGEMENTS 2026'!O8,IF($H8="EN COURS DE PREENGAGEMENT",'ENGAGEMENTS 2026'!N8,IF($H8="PREENGAGE",IF($E8="ATTRIBUE",'ENGAGEMENTS 2026'!AD8,'ENGAGEMENTS 2026'!N8),'ENGAGEMENTS 2026'!AD8)))) | K8: =IF(ISBLANK('ENGAGEMENTS 2026'!V8),"",'ENGAGEMENTS 2026'!V8) | L8: =IF($K8="","",TODAY()-$K8) | M8: =IF($A8="","",IF($H8="ENGAGE","Engagé",IF(AND($H8="NON ENGAGE",OR($I8="INFRUCTUEUX",$I8="ANNULE")),"Clôturé sans suite","En cours"))) | N8: =IF(ISBLANK('ENGAGEMENTS 2026'!B8),"",'ENGAGEMENTS 2026'!K8) | O8: =IF(ISBLANK('ENGAGEMENTS 2026'!B8),"",'ENGAGEMENTS 2026'!L8) | P8: =IF(ISBLANK('ENGAGEMENTS 2026'!B8),"",'ENGAGEMENTS 2026'!J8) | Q8: =IF($A8="","",IF(OR($E8="INFRUCTUEUX",$E8="ANNULE"),$A8&"|"&(COUNTIFS($A$2:$A8,$A8,$E$2:$E8,"INFRUCTUEUX")+COUNTIFS($A$2:$A8,$A8,$E$2:$E8,"ANNULE")),""))
A9: =IF(ISBLANK('ENGAGEMENTS 2026'!B9),"",IF('ENGAGEMENTS 2026'!B9="DTSI","DCT",'ENGAGEMENTS 2026'!B9)) | B9: =IF(ISBLANK('ENGAGEMENTS 2026'!B9),"",'ENGAGEMENTS 2026'!C9) | C9: =IF(ISBLANK('ENGAGEMENTS 2026'!B9),"",'ENGAGEMENTS 2026'!D9) | D9: =IF(ISBLANK('ENGAGEMENTS 2026'!B9),"",'ENGAGEMENTS 2026'!F9) | E9: =IF(ISBLANK('ENGAGEMENTS 2026'!B9),"",'ENGAGEMENTS 2026'!H9) | F9: =IF(ISBLANK('ENGAGEMENTS 2026'!B9),"",'ENGAGEMENTS 2026'!I9) | G9: =IF(ISBLANK('ENGAGEMENTS 2026'!B9),"",'ENGAGEMENTS 2026'!L9) | H9: =IF(ISBLANK('ENGAGEMENTS 2026'!B9),"",'ENGAGEMENTS 2026'!AE9) | I9: =IF(ISBLANK('ENGAGEMENTS 2026'!B9),"",'ENGAGEMENTS 2026'!G9) | J9: =IF(ISBLANK('ENGAGEMENTS 2026'!B9),"",IF(AND(OR($E9="INFRUCTUEUX",$E9="ANNULE"),$C9="AOO-M"),'ENGAGEMENTS 2026'!O9,IF($H9="EN COURS DE PREENGAGEMENT",'ENGAGEMENTS 2026'!N9,IF($H9="PREENGAGE",IF($E9="ATTRIBUE",'ENGAGEMENTS 2026'!AD9,'ENGAGEMENTS 2026'!N9),'ENGAGEMENTS 2026'!AD9)))) | K9: =IF(ISBLANK('ENGAGEMENTS 2026'!V9),"",'ENGAGEMENTS 2026'!V9) | L9: =IF($K9="","",TODAY()-$K9) | M9: =IF($A9="","",IF($H9="ENGAGE","Engagé",IF(AND($H9="NON ENGAGE",OR($I9="INFRUCTUEUX",$I9="ANNULE")),"Clôturé sans suite","En cours"))) | N9: =IF(ISBLANK('ENGAGEMENTS 2026'!B9),"",'ENGAGEMENTS 2026'!K9) | O9: =IF(ISBLANK('ENGAGEMENTS 2026'!B9),"",'ENGAGEMENTS 2026'!L9) | P9: =IF(ISBLANK('ENGAGEMENTS 2026'!B9),"",'ENGAGEMENTS 2026'!J9) | Q9: =IF($A9="","",IF(OR($E9="INFRUCTUEUX",$E9="ANNULE"),$A9&"|"&(COUNTIFS($A$2:$A9,$A9,$E$2:$E9,"INFRUCTUEUX")+COUNTIFS($A$2:$A9,$A9,$E$2:$E9,"ANNULE")),""))
A10: =IF(ISBLANK('ENGAGEMENTS 2026'!B10),"",IF('ENGAGEMENTS 2026'!B10="DTSI","DCT",'ENGAGEMENTS 2026'!B10)) | B10: =IF(ISBLANK('ENGAGEMENTS 2026'!B10),"",'ENGAGEMENTS 2026'!C10) | C10: =IF(ISBLANK('ENGAGEMENTS 2026'!B10),"",'ENGAGEMENTS 2026'!D10) | D10: =IF(ISBLANK('ENGAGEMENTS 2026'!B10),"",'ENGAGEMENTS 2026'!F10) | E10: =IF(ISBLANK('ENGAGEMENTS 2026'!B10),"",'ENGAGEMENTS 2026'!H10) | F10: =IF(ISBLANK('ENGAGEMENTS 2026'!B10),"",'ENGAGEMENTS 2026'!I10) | G10: =IF(ISBLANK('ENGAGEMENTS 2026'!B10),"",'ENGAGEMENTS 2026'!L10) | H10: =IF(ISBLANK('ENGAGEMENTS 2026'!B10),"",'ENGAGEMENTS 2026'!AE10) | I10: =IF(ISBLANK('ENGAGEMENTS 2026'!B10),"",'ENGAGEMENTS 2026'!G10) | J10: =IF(ISBLANK('ENGAGEMENTS 2026'!B10),"",IF(AND(OR($E10="INFRUCTUEUX",$E10="ANNULE"),$C10="AOO-M"),'ENGAGEMENTS 2026'!O10,IF($H10="EN COURS DE PREENGAGEMENT",'ENGAGEMENTS 2026'!N10,IF($H10="PREENGAGE",IF($E10="ATTRIBUE",'ENGAGEMENTS 2026'!AD10,'ENGAGEMENTS 2026'!N10),'ENGAGEMENTS 2026'!AD10)))) | K10: =IF(ISBLANK('ENGAGEMENTS 2026'!V10),"",'ENGAGEMENTS 2026'!V10) | L10: =IF($K10="","",TODAY()-$K10) | M10: =IF($A10="","",IF($H10="ENGAGE","Engagé",IF(AND($H10="NON ENGAGE",OR($I10="INFRUCTUEUX",$I10="ANNULE")),"Clôturé sans suite","En cours"))) | N10: =IF(ISBLANK('ENGAGEMENTS 2026'!B10),"",'ENGAGEMENTS 2026'!K10) | O10: =IF(ISBLANK('ENGAGEMENTS 2026'!B10),"",'ENGAGEMENTS 2026'!L10) | P10: =IF(ISBLANK('ENGAGEMENTS 2026'!B10),"",'ENGAGEMENTS 2026'!J10) | Q10: =IF($A10="","",IF(OR($E10="INFRUCTUEUX",$E10="ANNULE"),$A10&"|"&(COUNTIFS($A$2:$A10,$A10,$E$2:$E10,"INFRUCTUEUX")+COUNTIFS($A$2:$A10,$A10,$E$2:$E10,"ANNULE")),""))
A11: =IF(ISBLANK('ENGAGEMENTS 2026'!B11),"",IF('ENGAGEMENTS 2026'!B11="DTSI","DCT",'ENGAGEMENTS 2026'!B11)) | B11: =IF(ISBLANK('ENGAGEMENTS 2026'!B11),"",'ENGAGEMENTS 2026'!C11) | C11: =IF(ISBLANK('ENGAGEMENTS 2026'!B11),"",'ENGAGEMENTS 2026'!D11) | D11: =IF(ISBLANK('ENGAGEMENTS 2026'!B11),"",'ENGAGEMENTS 2026'!F11) | E11: =IF(ISBLANK('ENGAGEMENTS 2026'!B11),"",'ENGAGEMENTS 2026'!H11) | F11: =IF(ISBLANK('ENGAGEMENTS 2026'!B11),"",'ENGAGEMENTS 2026'!I11) | G11: =IF(ISBLANK('ENGAGEMENTS 2026'!B11),"",'ENGAGEMENTS 2026'!L11) | H11: =IF(ISBLANK('ENGAGEMENTS 2026'!B11),"",'ENGAGEMENTS 2026'!AE11) | I11: =IF(ISBLANK('ENGAGEMENTS 2026'!B11),"",'ENGAGEMENTS 2026'!G11) | J11: =IF(ISBLANK('ENGAGEMENTS 2026'!B11),"",IF(AND(OR($E11="INFRUCTUEUX",$E11="ANNULE"),$C11="AOO-M"),'ENGAGEMENTS 2026'!O11,IF($H11="EN COURS DE PREENGAGEMENT",'ENGAGEMENTS 2026'!N11,IF($H11="PREENGAGE",IF($E11="ATTRIBUE",'ENGAGEMENTS 2026'!AD11,'ENGAGEMENTS 2026'!N11),'ENGAGEMENTS 2026'!AD11)))) | K11: =IF(ISBLANK('ENGAGEMENTS 2026'!V11),"",'ENGAGEMENTS 2026'!V11) | L11: =IF($K11="","",TODAY()-$K11) | M11: =IF($A11="","",IF($H11="ENGAGE","Engagé",IF(AND($H11="NON ENGAGE",OR($I11="INFRUCTUEUX",$I11="ANNULE")),"Clôturé sans suite","En cours"))) | N11: =IF(ISBLANK('ENGAGEMENTS 2026'!B11),"",'ENGAGEMENTS 2026'!K11) | O11: =IF(ISBLANK('ENGAGEMENTS 2026'!B11),"",'ENGAGEMENTS 2026'!L11) | P11: =IF(ISBLANK('ENGAGEMENTS 2026'!B11),"",'ENGAGEMENTS 2026'!J11) | Q11: =IF($A11="","",IF(OR($E11="INFRUCTUEUX",$E11="ANNULE"),$A11&"|"&(COUNTIFS($A$2:$A11,$A11,$E$2:$E11,"INFRUCTUEUX")+COUNTIFS($A$2:$A11,$A11,$E$2:$E11,"ANNULE")),""))
A12: =IF(ISBLANK('ENGAGEMENTS 2026'!B12),"",IF('ENGAGEMENTS 2026'!B12="DTSI","DCT",'ENGAGEMENTS 2026'!B12)) | B12: =IF(ISBLANK('ENGAGEMENTS 2026'!B12),"",'ENGAGEMENTS 2026'!C12) | C12: =IF(ISBLANK('ENGAGEMENTS 2026'!B12),"",'ENGAGEMENTS 2026'!D12) | D12: =IF(ISBLANK('ENGAGEMENTS 2026'!B12),"",'ENGAGEMENTS 2026'!F12) | E12: =IF(ISBLANK('ENGAGEMENTS 2026'!B12),"",'ENGAGEMENTS 2026'!H12) | F12: =IF(ISBLANK('ENGAGEMENTS 2026'!B12),"",'ENGAGEMENTS 2026'!I12) | G12: =IF(ISBLANK('ENGAGEMENTS 2026'!B12),"",'ENGAGEMENTS 2026'!L12) | H12: =IF(ISBLANK('ENGAGEMENTS 2026'!B12),"",'ENGAGEMENTS 2026'!AE12) | I12: =IF(ISBLANK('ENGAGEMENTS 2026'!B12),"",'ENGAGEMENTS 2026'!G12) | J12: =IF(ISBLANK('ENGAGEMENTS 2026'!B12),"",IF(AND(OR($E12="INFRUCTUEUX",$E12="ANNULE"),$C12="AOO-M"),'ENGAGEMENTS 2026'!O12,IF($H12="EN COURS DE PREENGAGEMENT",'ENGAGEMENTS 2026'!N12,IF($H12="PREENGAGE",IF($E12="ATTRIBUE",'ENGAGEMENTS 2026'!AD12,'ENGAGEMENTS 2026'!N12),'ENGAGEMENTS 2026'!AD12)))) | K12: =IF(ISBLANK('ENGAGEMENTS 2026'!V12),"",'ENGAGEMENTS 2026'!V12) | L12: =IF($K12="","",TODAY()-$K12) | M12: =IF($A12="","",IF($H12="ENGAGE","Engagé",IF(AND($H12="NON ENGAGE",OR($I12="INFRUCTUEUX",$I12="ANNULE")),"Clôturé sans suite","En cours"))) | N12: =IF(ISBLANK('ENGAGEMENTS 2026'!B12),"",'ENGAGEMENTS 2026'!K12) | O12: =IF(ISBLANK('ENGAGEMENTS 2026'!B12),"",'ENGAGEMENTS 2026'!L12) | P12: =IF(ISBLANK('ENGAGEMENTS 2026'!B12),"",'ENGAGEMENTS 2026'!J12) | Q12: =IF($A12="","",IF(OR($E12="INFRUCTUEUX",$E12="ANNULE"),$A12&"|"&(COUNTIFS($A$2:$A12,$A12,$E$2:$E12,"INFRUCTUEUX")+COUNTIFS($A$2:$A12,$A12,$E$2:$E12,"ANNULE")),""))
A13: =IF(ISBLANK('ENGAGEMENTS 2026'!B13),"",IF('ENGAGEMENTS 2026'!B13="DTSI","DCT",'ENGAGEMENTS 2026'!B13)) | B13: =IF(ISBLANK('ENGAGEMENTS 2026'!B13),"",'ENGAGEMENTS 2026'!C13) | C13: =IF(ISBLANK('ENGAGEMENTS 2026'!B13),"",'ENGAGEMENTS 2026'!D13) | D13: =IF(ISBLANK('ENGAGEMENTS 2026'!B13),"",'ENGAGEMENTS 2026'!F13) | E13: =IF(ISBLANK('ENGAGEMENTS 2026'!B13),"",'ENGAGEMENTS 2026'!H13) | F13: =IF(ISBLANK('ENGAGEMENTS 2026'!B13),"",'ENGAGEMENTS 2026'!I13) | G13: =IF(ISBLANK('ENGAGEMENTS 2026'!B13),"",'ENGAGEMENTS 2026'!L13) | H13: =IF(ISBLANK('ENGAGEMENTS 2026'!B13),"",'ENGAGEMENTS 2026'!AE13) | I13: =IF(ISBLANK('ENGAGEMENTS 2026'!B13),"",'ENGAGEMENTS 2026'!G13) | J13: =IF(ISBLANK('ENGAGEMENTS 2026'!B13),"",IF(AND(OR($E13="INFRUCTUEUX",$E13="ANNULE"),$C13="AOO-M"),'ENGAGEMENTS 2026'!O13,IF($H13="EN COURS DE PREENGAGEMENT",'ENGAGEMENTS 2026'!N13,IF($H13="PREENGAGE",IF($E13="ATTRIBUE",'ENGAGEMENTS 2026'!AD13,'ENGAGEMENTS 2026'!N13),'ENGAGEMENTS 2026'!AD13)))) | K13: =IF(ISBLANK('ENGAGEMENTS 2026'!V13),"",'ENGAGEMENTS 2026'!V13) | L13: =IF($K13="","",TODAY()-$K13) | M13: =IF($A13="","",IF($H13="ENGAGE","Engagé",IF(AND($H13="NON ENGAGE",OR($I13="INFRUCTUEUX",$I13="ANNULE")),"Clôturé sans suite","En cours"))) | N13: =IF(ISBLANK('ENGAGEMENTS 2026'!B13),"",'ENGAGEMENTS 2026'!K13) | O13: =IF(ISBLANK('ENGAGEMENTS 2026'!B13),"",'ENGAGEMENTS 2026'!L13) | P13: =IF(ISBLANK('ENGAGEMENTS 2026'!B13),"",'ENGAGEMENTS 2026'!J13) | Q13: =IF($A13="","",IF(OR($E13="INFRUCTUEUX",$E13="ANNULE"),$A13&"|"&(COUNTIFS($A$2:$A13,$A13,$E$2:$E13,"INFRUCTUEUX")+COUNTIFS($A$2:$A13,$A13,$E$2:$E13,"ANNULE")),""))
... A3000: =IF(ISBLANK('ENGAGEMENTS 2026'!B3000),"",IF('ENGAGEMENTS 2026'!B3000="DTSI","DCT",'ENGAGEMENTS 2026'!B3000)) | B3000: =IF(ISBLANK('ENGAGEMENTS 2026'!B3000),"",'ENGAGEMENTS 2026'!C3000) | C3000: =IF(ISBLANK('ENGAGEMENTS 2026'!B3000),"",'ENGAGEMENTS 2026'!D3000) | D3000: =IF(ISBLANK('ENGAGEMENTS 2026'!B3000),"",'ENGAGEMENTS 2026'!F3000) | E3000: =IF(ISBLANK('ENGAGEMENTS 2026'!B3000),"",'ENGAGEMENTS 2026'!H3000) | F3000: =IF(ISBLANK('ENGAGEMENTS 2026'!B3000),"",'ENGAGEMENTS 2026'!I3000) | G3000: =IF(ISBLANK('ENGAGEMENTS 2026'!B3000),"",'ENGAGEMENTS 2026'!L3000) | H3000: =IF(ISBLANK('ENGAGEMENTS 2026'!B3000),"",'ENGAGEMENTS 2026'!AE3000) | I3000: =IF(ISBLANK('ENGAGEMENTS 2026'!B3000),"",'ENGAGEMENTS 2026'!G3000) | J3000: =IF(ISBLANK('ENGAGEMENTS 2026'!B3000),"",IF(AND(OR($E3000="INFRUCTUEUX",$E3000="ANNULE"),$C3000="AOO-M"),'ENGAGEMENTS 2026'!O3000,IF($H3000="EN COURS DE PREENGAGEMENT",'ENGAGEMENTS 2026'!N3000,IF($H3000="PREENGAGE",IF($E3000="ATTRIBUE",'ENGAGEMENTS 2026'!AD3000,'ENGAGEMENTS 2026'!N3000),'ENGAGEMENTS 2026'!AD3000)))) | K3000: =IF(ISBLANK('ENGAGEMENTS 2026'!V3000),"",'ENGAGEMENTS 2026'!V3000) | L3000: =IF($K3000="","",TODAY()-$K3000) | M3000: =IF($A3000="","",IF($H3000="ENGAGE","Engagé",IF(AND($H3000="NON ENGAGE",OR($I3000="INFRUCTUEUX",$I3000="ANNULE")),"Clôturé sans suite","En cours"))) | N3000: =IF(ISBLANK('ENGAGEMENTS 2026'!B3000),"",'ENGAGEMENTS 2026'!K3000) | O3000: =IF(ISBLANK('ENGAGEMENTS 2026'!B3000),"",'ENGAGEMENTS 2026'!L3000) | P3000: =IF(ISBLANK('ENGAGEMENTS 2026'!B3000),"",'ENGAGEMENTS 2026'!J3000) | Q3000: =IF($A3000="","",IF(OR($E3000="INFRUCTUEUX",$E3000="ANNULE"),$A3000&"|"&(COUNTIFS($A$2:$A3000,$A3000,$E$2:$E3000,"INFRUCTUEUX")+COUNTIFS($A$2:$A3000,$A3000,$E$2:$E3000,"ANNULE")),""))
