Workbook

Sheet Données
A1: DIRECTION | B1: OBJET | C1: NATURE DE LA PRESTATION | D1: MODE DE PASSATION | E1: PERIODE PREVUE | F1: LIEU D'EXECUTION | G1: RESERVE PME | H1: ESTIMATION (MAD)
A2: Direction de la Télédiffusion | B2: Fourniture des modules de traitement audio et RDS pour les émetteurs FM | C2: Fournitures | D2: Appel d'offres ouvert | E2: T3 | F2: Magasin Temara | G2: Non | H2: 1800000
A3: Direction de la Télédiffusion | B3: Fourniture, installation et mise en service de systèmes de supervision des antennes de diffusion FM et TV | C3: Fournitures | D3: Appel d'offres ouvert | E3: T2 | F3: Centres de diffusion de la SNRT | G3: Non | H3: 2755000
A4: Direction de la Télédiffusion | B4: Fourniture et installation des équipements de contrôle audio et vidéo pour les petits centres de diffusion TV/FM | C4: Fournitures | D4: Appel d'offres ouvert | E4: T2 | F4: Centres de diffusion de la SNRT | G4: Non | H4: 1000000
A5: Direction de la Télédiffusion | B5: Fourniture, installation et mise en service des climatiseurs aux centres de diffusion de la SNRT | C5: Fournitures | D5: Appel d'offres ouvert | E5: T3 | F5: Centres de diffusion de la SNRT | G5: Oui | H5: 3500000
A6: Direction de la Télédiffusion | B6: Fourniture des analyseurs de réseaux électrique et les appareils de mesure électrique | C6: Fournitures | D6: Appel d'offres ouvert | E6: T2 | F6: Magasin Temara | G6: Non | H6: 800000
A7: Direction de la Télédiffusion | B7: Fourniture,installation et mise en service des commutateurs et distributeurs des signaux ASI et IP pour les centres de diffusion TNT et FM | C7: Fournitures | D7: Appel d'offres ouvert | E7: T3 | F7: Centres de diffusion de la SNRT | G7: Non | H7: 1000000
A8: Direction de la Télédiffusion | B8: Fourniture et installation des sondes FM et TNT pour le contrôle des signaux audios et vidéo des chaines radio et télevision de la SNRT | C8: Fournitures | D8: Appel d'offres ouvert | E8: T3 | F8: Magasin Temara | G8: Non | H8: 1200000
A9: Direction de la Télédiffusion | B9: Fourniture des modules et pièces de rechanges des émetteurs TNT de des centres de la SNRT | C9: Fournitures | D9: Appel d'offres ouvert | E9: T2 | F9: Magasin Temara | G9: Non | H9: 6500000
A10: Direction de la Télédiffusion | B10: Fourniture des modules et pièces de rechanges des émetteurs FM des centres de la SNRT | C10: Fournitures | D10: Appel d'offres ouvert | E10: T2 | F10: Magasin Temara | G10: Non | H10: 6500000
A11: Direction de la Télédiffusion | B11: Fourniture des duplexeurs, filtres, patchs panel , commutateurs RF et adaptateurs | C11: Fournitures | D11: Appel d'offres ouvert | E11: T3 | F11: Magasin Temara | G11: Non | H11: 1600000
A12: Direction de la Télédiffusion | B12: Fourniture des distributeurs de puissance UHF et FM, combiners, feeders et antennes | C12: Fournitures | D12: Appel d'offres ouvert | E12: T3 | F12: Magasin Temara | G12: Non | H12: 3500000
A13: Direction de la Télédiffusion | B13: Fourniture des modules et pièces de rechanges hydrauliques et électriques pour les émetteurs de diffusion TNT et FM | C13: Fournitures | D13: Appel d'offres ouvert | E13: T2 | F13: Magasin Temara | G13: Non | H13: 1100000
... A161: Direction Centrale Technique | B161: Fourniture et mise en service d'un systéme d'intercom boradcast pour les besoins de la SNRT | C161: Fournitures | D161: Appel d'offres ouvert | E161: T2 | F161: Rabat | G161: Non | H161: 291156

Sheet Tableau de Bord
A1: TABLEAU DE BORD - PROGRAMME PREVISIONNEL DES MARCHES (PPM) 2026
A3: Nombre de marchés prévus | C3: Montant total estimé (MAD) | E3: Nombre de directions | G3: % marchés réservés PME
A4: =COUNTA(Données!A2:A161) | C4: =SUM(Données!H2:H161) | E4: =SUMPRODUCT((Données!A2:A161<>"")/COUNTIF(Données!A2:A161,Données!A2:A161&"")) | G4: =COUNTIF(Données!G2:G161,"Oui")/COUNTA(Données!A2:A161)
A7: Répartition par Direction
A8: Direction | B8: Nb marchés | C8: Montant estimé (MAD)
A9: Direction Al Maghribia | B9: =COUNTIF(Données!$A$2:$A$161,A9) | C9: =SUMIF(Données!$A$2:$A$161,A9,Données!$H$2:$H$161)
A10: Direction Attakafia | B10: =COUNTIF(Données!$A$2:$A$161,A10) | C10: =SUMIF(Données!$A$2:$A$161,A10,Données!$H$2:$H$161)
A11: Direction Audit et Contrôle et de Gestion | B11: =COUNTIF(Données!$A$2:$A$161,A11) | C11: =SUMIF(Données!$A$2:$A$161,A11,Données!$H$2:$H$161)
A12: Direction Centrale Marketing et Programmation TV | B12: =COUNTIF(Données!$A$2:$A$161,A12) | C12: =SUMIF(Données!$A$2:$A$161,A12,Données!$H$2:$H$161)
A13: Direction Centrale Technique | B13: =COUNTIF(Données!$A$2:$A$161,A13) | C13: =SUMIF(Données!$A$2:$A$161,A13,Données!$H$2:$H$161)
A14: Direction Centrale de la Production et de l'Antenne | B14: =COUNTIF(Données!$A$2:$A$161,A14) | C14: =SUMIF(Données!$A$2:$A$161,A14,Données!$H$2:$H$161)
A15: Direction Centrale de la Régie publicitaire et des Solutions Digitales | B15: =COUNTIF(Données!$A$2:$A$161,A15) | C15: =SUMIF(Données!$A$2:$A$161,A15,Données!$H$2:$H$161)
A16: Direction Financière | B16: =COUNTIF(Données!$A$2:$A$161,A16) | C16: =SUMIF(Données!$A$2:$A$161,A16,Données!$H$2:$H$161)
A17: Direction chargée des programmes Amazigh Radio et TV | B17: =COUNTIF(Données!$A$2:$A$161,A17) | C17: =SUMIF(Données!$A$2:$A$161,A17,Données!$H$2:$H$161)
A18: Direction de l'Information TV | B18: =COUNTIF(Données!$A$2:$A$161,A18) | C18: =SUMIF(Données!$A$2:$A$161,A18,Données!$H$2:$H$161)
A19: Direction de la Chaîne TV Laayoune | B19: =COUNTIF(Données!$A$2:$A$161,A19) | C19: =SUMIF(Données!$A$2:$A$161,A19,Données!$H$2:$H$161)
A20: Direction de la Télédiffusion | B20: =COUNTIF(Données!$A$2:$A$161,A20) | C20: =SUMIF(Données!$A$2:$A$161,A20,Données!$H$2:$H$161)
... A23: Responsable de la Sécurité des Systèmes d’Information (RSSI) | B23: =COUNTIF(Données!$A$2:$A$161,A23) | C23: =SUMIF(Données!$A$2:$A$161,A23,Données!$H$2:$H$161)
A25: Répartition par Nature de prestation
A26: Nature | B26: Nb marchés | C26: Montant estimé (MAD)
A27: Fournitures | B27: =COUNTIF(Données!$C$2:$C$161,A27) | C27: =SUMIF(Données!$C$2:$C$161,A27,Données!$H$2:$H$161)
A28: Services | B28: =COUNTIF(Données!$C$2:$C$161,A28) | C28: =SUMIF(Données!$C$2:$C$161,A28,Données!$H$2:$H$161)
A29: Travaux | B29: =COUNTIF(Données!$C$2:$C$161,A29) | C29: =SUMIF(Données!$C$2:$C$161,A29,Données!$H$2:$H$161)
A31: Répartition par Période d'exécution
A32: Période | B32: Nb marchés | C32: Montant estimé (MAD)
A33: T1 | B33: =COUNTIF(Données!$E$2:$E$161,A33) | C33: =SUMIF(Données!$E$2:$E$161,A33,Données!$H$2:$H$161)
A34: T2 | B34: =COUNTIF(Données!$E$2:$E$161,A34) | C34: =SUMIF(Données!$E$2:$E$161,A34,Données!$H$2:$H$161)
A35: T3 | B35: =COUNTIF(Données!$E$2:$E$161,A35) | C35: =SUMIF(Données!$E$2:$E$161,A35,Données!$H$2:$H$161)
A36: T4 | B36: =COUNTIF(Données!$E$2:$E$161,A36) | C36: =SUMIF(Données!$E$2:$E$161,A36,Données!$H$2:$H$161)
A37: T1-T2 | B37: =COUNTIF(Données!$E$2:$E$161,A37) | C37: =SUMIF(Données!$E$2:$E$161,A37,Données!$H$2:$H$161)
A38: T1-T4 | B38: =COUNTIF(Données!$E$2:$E$161,A38) | C38: =SUMIF(Données!$E$2:$E$161,A38,Données!$H$2:$H$161)
A39: T2 - T3 - T4 | B39: =COUNTIF(Données!$E$2:$E$161,A39) | C39: =SUMIF(Données!$E$2:$E$161,A39,Données!$H$2:$H$161)
A41: Marchés réservés aux PME
A42: Réservé PME | B42: Nb marchés | C42: Montant estimé (MAD)
A43: Oui | B43: =COUNTIF(Données!$G$2:$G$161,A43) | C43: =SUMIF(Données!$G$2:$G$161,A43,Données!$H$2:$H$161)
A44: Non | B44: =COUNTIF(Données!$G$2:$G$161,A44) | C44: =SUMIF(Données!$G$2:$G$161,A44,Données!$H$2:$H$161)

Sheet Détail Direction-Nature
A1: DETAIL PAR DIRECTION ET NATURE DE PRESTATION
A3: Matrice de synthèse — Direction x Nature de prestation
A4: Direction | B4: Fournitures (Nb) | C4: Fournitures (MAD) | D4: Services (Nb) | E4: Services (MAD) | F4: Travaux (Nb) | G4: Travaux (MAD) | H4: Total (Nb) | I4: Total (MAD)
A5: Direction Al Maghribia | B5: =COUNTIFS(Données!$A$2:$A$161,$A5,Données!$C$2:$C$161,"Fournitures") | C5: =SUMIFS(Données!$H$2:$H$161,Données!$A$2:$A$161,$A5,Données!$C$2:$C$161,"Fournitures") | D5: =COUNTIFS(Données!$A$2:$A$161,$A5,Données!$C$2:$C$161,"Services") | E5: =SUMIFS(Données!$H$2:$H$161,Données!$A$2:$A$161,$A5,Données!$C$2:$C$161,"Services") | F5: =COUNTIFS(Données!$A$2:$A$161,$A5,Données!$C$2:$C$161,"Travaux") | G5: =SUMIFS(Données!$H$2:$H$161,Données!$A$2:$A$161,$A5,Données!$C$2:$C$161,"Travaux") | H5: =COUNTIF(Données!$A$2:$A$161,$A5) | I5: =SUMIF(Données!$A$2:$A$161,$A5,Données!$H$2:$H$161)
A6: Direction Attakafia | B6: =COUNTIFS(Données!$A$2:$A$161,$A6,Données!$C$2:$C$161,"Fournitures") | C6: =SUMIFS(Données!$H$2:$H$161,Données!$A$2:$A$161,$A6,Données!$C$2:$C$161,"Fournitures") | D6: =COUNTIFS(Données!$A$2:$A$161,$A6,Données!$C$2:$C$161,"Services") | E6: =SUMIFS(Données!$H$2:$H$161,Données!$A$2:$A$161,$A6,Données!$C$2:$C$161,"Services") | F6: =COUNTIFS(Données!$A$2:$A$161,$A6,Données!$C$2:$C$161,"Travaux") | G6: =SUMIFS(Données!$H$2:$H$161,Données!$A$2:$A$161,$A6,Données!$C$2:$C$161,"Travaux") | H6: =COUNTIF(Données!$A$2:$A$161,$A6) | I6: =SUMIF(Données!$A$2:$A$161,$A6,Données!$H$2:$H$161)
A7: Direction Audit et Contrôle et de Gestion | B7: =COUNTIFS(Données!$A$2:$A$161,$A7,Données!$C$2:$C$161,"Fournitures") | C7: =SUMIFS(Données!$H$2:$H$161,Données!$A$2:$A$161,$A7,Données!$C$2:$C$161,"Fournitures") | D7: =COUNTIFS(Données!$A$2:$A$161,$A7,Données!$C$2:$C$161,"Services") | E7: =SUMIFS(Données!$H$2:$H$161,Données!$A$2:$A$161,$A7,Données!$C$2:$C$161,"Services") | F7: =COUNTIFS(Données!$A$2:$A$161,$A7,Données!$C$2:$C$161,"Travaux") | G7: =SUMIFS(Données!$H$2:$H$161,Données!$A$2:$A$161,$A7,Données!$C$2:$C$161,"Travaux") | H7: =COUNTIF(Données!$A$2:$A$161,$A7) | I7: =SUMIF(Données!$A$2:$A$161,$A7,Données!$H$2:$H$161)
A8: Direction Centrale Marketing et Programmation TV | B8: =COUNTIFS(Données!$A$2:$A$161,$A8,Données!$C$2:$C$161,"Fournitures") | C8: =SUMIFS(Données!$H$2:$H$161,Données!$A$2:$A$161,$A8,Données!$C$2:$C$161,"Fournitures") | D8: =COUNTIFS(Données!$A$2:$A$161,$A8,Données!$C$2:$C$161,"Services") | E8: =SUMIFS(Données!$H$2:$H$161,Données!$A$2:$A$161,$A8,Données!$C$2:$C$161,"Services") | F8: =COUNTIFS(Données!$A$2:$A$161,$A8,Données!$C$2:$C$161,"Travaux") | G8: =SUMIFS(Données!$H$2:$H$161,Données!$A$2:$A$161,$A8,Données!$C$2:$C$161,"Travaux") | H8: =COUNTIF(Données!$A$2:$A$161,$A8) | I8: =SUMIF(Données!$A$2:$A$161,$A8,Données!$H$2:$H$161)
A9: Direction Centrale Technique | B9: =COUNTIFS(Données!$A$2:$A$161,$A9,Données!$C$2:$C$161,"Fournitures") | C9: =SUMIFS(Données!$H$2:$H$161,Données!$A$2:$A$161,$A9,Données!$C$2:$C$161,"Fournitures") | D9: =COUNTIFS(Données!$A$2:$A$161,$A9,Données!$C$2:$C$161,"Services") | E9: =SUMIFS(Données!$H$2:$H$161,Données!$A$2:$A$161,$A9,Données!$C$2:$C$161,"Services") | F9: =COUNTIFS(Données!$A$2:$A$161,$A9,Données!$C$2:$C$161,"Travaux") | G9: =SUMIFS(Données!$H$2:$H$161,Données!$A$2:$A$161,$A9,Données!$C$2:$C$161,"Travaux") | H9: =COUNTIF(Données!$A$2:$A$161,$A9) | I9: =SUMIF(Données!$A$2:$A$161,$A9,Données!$H$2:$H$161)
A10: Direction Centrale de la Production et de l'Antenne | B10: =COUNTIFS(Données!$A$2:$A$161,$A10,Données!$C$2:$C$161,"Fournitures") | C10: =SUMIFS(Données!$H$2:$H$161,Données!$A$2:$A$161,$A10,Données!$C$2:$C$161,"Fournitures") | D10: =COUNTIFS(Données!$A$2:$A$161,$A10,Données!$C$2:$C$161,"Services") | E10: =SUMIFS(Données!$H$2:$H$161,Données!$A$2:$A$161,$A10,Données!$C$2:$C$161,"Services") | F10: =COUNTIFS(Données!$A$2:$A$161,$A10,Données!$C$2:$C$161,"Travaux") | G10: =SUMIFS(Données!$H$2:$H$161,Données!$A$2:$A$161,$A10,Données!$C$2:$C$161,"Travaux") | H10: =COUNTIF(Données!$A$2:$A$161,$A10) | I10: =SUMIF(Données!$A$2:$A$161,$A10,Données!$H$2:$H$161)
A11: Direction Centrale de la Régie publicitaire et des Solutions Digitales | B11: =COUNTIFS(Données!$A$2:$A$161,$A11,Données!$C$2:$C$161,"Fournitures") | C11: =SUMIFS(Données!$H$2:$H$161,Données!$A$2:$A$161,$A11,Données!$C$2:$C$161,"Fournitures") | D11: =COUNTIFS(Données!$A$2:$A$161,$A11,Données!$C$2:$C$161,"Services") | E11: =SUMIFS(Données!$H$2:$H$161,Données!$A$2:$A$161,$A11,Données!$C$2:$C$161,"Services") | F11: =COUNTIFS(Données!$A$2:$A$161,$A11,Données!$C$2:$C$161,"Travaux") | G11: =SUMIFS(Données!$H$2:$H$161,Données!$A$2:$A$161,$A11,Données!$C$2:$C$161,"Travaux") | H11: =COUNTIF(Données!$A$2:$A$161,$A11) | I11: =SUMIF(Données!$A$2:$A$161,$A11,Données!$H$2:$H$161)
A12: Direction Financière | B12: =COUNTIFS(Données!$A$2:$A$161,$A12,Données!$C$2:$C$161,"Fournitures") | C12: =SUMIFS(Données!$H$2:$H$161,Données!$A$2:$A$161,$A12,Données!$C$2:$C$161,"Fournitures") | D12: =COUNTIFS(Données!$A$2:$A$161,$A12,Données!$C$2:$C$161,"Services") | E12: =SUMIFS(Données!$H$2:$H$161,Données!$A$2:$A$161,$A12,Données!$C$2:$C$161,"Services") | F12: =COUNTIFS(Données!$A$2:$A$161,$A12,Données!$C$2:$C$161,"Travaux") | G12: =SUMIFS(Données!$H$2:$H$161,Données!$A$2:$A$161,$A12,Données!$C$2:$C$161,"Travaux") | H12: =COUNTIF(Données!$A$2:$A$161,$A12) | I12: =SUMIF(Données!$A$2:$A$161,$A12,Données!$H$2:$H$161)
A13: Direction chargée des programmes Amazigh Radio et TV | B13: =COUNTIFS(Données!$A$2:$A$161,$A13,Données!$C$2:$C$161,"Fournitures") | C13: =SUMIFS(Données!$H$2:$H$161,Données!$A$2:$A$161,$A13,Données!$C$2:$C$161,"Fournitures") | D13: =COUNTIFS(Données!$A$2:$A$161,$A13,Données!$C$2:$C$161,"Services") | E13: =SUMIFS(Données!$H$2:$H$161,Données!$A$2:$A$161,$A13,Données!$C$2:$C$161,"Services") | F13: =COUNTIFS(Données!$A$2:$A$161,$A13,Données!$C$2:$C$161,"Travaux") | G13: =SUMIFS(Données!$H$2:$H$161,Données!$A$2:$A$161,$A13,Données!$C$2:$C$161,"Travaux") | H13: =COUNTIF(Données!$A$2:$A$161,$A13) | I13: =SUMIF(Données!$A$2:$A$161,$A13,Données!$H$2:$H$161)
A14: Direction de l'Information TV | B14: =COUNTIFS(Données!$A$2:$A$161,$A14,Données!$C$2:$C$161,"Fournitures") | C14: =SUMIFS(Données!$H$2:$H$161,Données!$A$2:$A$161,$A14,Données!$C$2:$C$161,"Fournitures") | D14: =COUNTIFS(Données!$A$2:$A$161,$A14,Données!$C$2:$C$161,"Services") | E14: =SUMIFS(Données!$H$2:$H$161,Données!$A$2:$A$161,$A14,Données!$C$2:$C$161,"Services") | F14: =COUNTIFS(Données!$A$2:$A$161,$A14,Données!$C$2:$C$161,"Travaux") | G14: =SUMIFS(Données!$H$2:$H$161,Données!$A$2:$A$161,$A14,Données!$C$2:$C$161,"Travaux") | H14: =COUNTIF(Données!$A$2:$A$161,$A14) | I14: =SUMIF(Données!$A$2:$A$161,$A14,Données!$H$2:$H$161)
A15: Direction de la Chaîne TV Laayoune | B15: =COUNTIFS(Données!$A$2:$A$161,$A15,Données!$C$2:$C$161,"Fournitures") | C15: =SUMIFS(Données!$H$2:$H$161,Données!$A$2:$A$161,$A15,Données!$C$2:$C$161,"Fournitures") | D15: =COUNTIFS(Données!$A$2:$A$161,$A15,Données!$C$2:$C$161,"Services") | E15: =SUMIFS(Données!$H$2:$H$161,Données!$A$2:$A$161,$A15,Données!$C$2:$C$161,"Services") | F15: =COUNTIFS(Données!$A$2:$A$161,$A15,Données!$C$2:$C$161,"Travaux") | G15: =SUMIFS(Données!$H$2:$H$161,Données!$A$2:$A$161,$A15,Données!$C$2:$C$161,"Travaux") | H15: =COUNTIF(Données!$A$2:$A$161,$A15) | I15: =SUMIF(Données!$A$2:$A$161,$A15,Données!$H$2:$H$161)
A16: Direction de la Télédiffusion | B16: =COUNTIFS(Données!$A$2:$A$161,$A16,Données!$C$2:$C$161,"Fournitures") | C16: =SUMIFS(Données!$H$2:$H$161,Données!$A$2:$A$161,$A16,Données!$C$2:$C$161,"Fournitures") | D16: =COUNTIFS(Données!$A$2:$A$161,$A16,Données!$C$2:$C$161,"Services") | E16: =SUMIFS(Données!$H$2:$H$161,Données!$A$2:$A$161,$A16,Données!$C$2:$C$161,"Services") | F16: =COUNTIFS(Données!$A$2:$A$161,$A16,Données!$C$2:$C$161,"Travaux") | G16: =SUMIFS(Données!$H$2:$H$161,Données!$A$2:$A$161,$A16,Données!$C$2:$C$161,"Travaux") | H16: =COUNTIF(Données!$A$2:$A$161,$A16) | I16: =SUMIF(Données!$A$2:$A$161,$A16,Données!$H$2:$H$161)
... A19: Responsable de la Sécurité des Systèmes d’Information (RSSI) | B19: =COUNTIFS(Données!$A$2:$A$161,$A19,Données!$C$2:$C$161,"Fournitures") | C19: =SUMIFS(Données!$H$2:$H$161,Données!$A$2:$A$161,$A19,Données!$C$2:$C$161,"Fournitures") | D19: =COUNTIFS(Données!$A$2:$A$161,$A19,Données!$C$2:$C$161,"Services") | E19: =SUMIFS(Données!$H$2:$H$161,Données!$A$2:$A$161,$A19,Données!$C$2:$C$161,"Services") | F19: =COUNTIFS(Données!$A$2:$A$161,$A19,Données!$C$2:$C$161,"Travaux") | G19: =SUMIFS(Données!$H$2:$H$161,Données!$A$2:$A$161,$A19,Données!$C$2:$C$161,"Travaux") | H19: =COUNTIF(Données!$A$2:$A$161,$A19) | I19: =SUMIF(Données!$A$2:$A$161,$A19,Données!$H$2:$H$161)
A20: TOTAL | B20: =SUM(B5:B19) | C20: =SUM(C5:C19) | D20: =SUM(D5:D19) | E20: =SUM(E5:E19) | F20: =SUM(F5:F19) | G20: =SUM(G5:G19) | H20: =SUM(H5:H19) | I20: =SUM(I5:I19)
A22: Direction Al Maghribia
A23: < Retour à la matrice
A24: Nb marchés : 2 | Montant total estimé : 210 000 MAD
A25: Nature | B25: Nb marchés | C25: Montant estimé (MAD)
A26: Fournitures | B26: 0 | C26: 0
A27: Services | B27: 2 | C27: 210000
A28: Travaux | B28: 0 | C28: 0
A30: Objet | B30: Nature | C30: Période | D30: Lieu d'exécution | E30: PME | F30: Estimation (MAD)
A31: Prestation de blanchisserie du linge et services associés au profit des journalistes présentateurs du journal Télévisés (JT) | B31: Services | C31: T2 | D31: Rabat | E31: Oui | F31: 60000
A32: Décor Virtuel Live News | B32: Services | C32: T2 | D32: Rabat | E32: Oui | F32: 150000
A35: Direction Attakafia
A36: < Retour à la matrice
A37: Nb marchés : 1 | Montant total estimé : 60 000 MAD
A38: Nature | B38: Nb marchés | C38: Montant estimé (MAD)
A39: Fournitures | B39: 0 | C39: 0
A40: Services | B40: 1 | C40: 60000
A41: Travaux | B41: 0 | C41: 0
A43: Objet | B43: Nature | C43: Période | D43: Lieu d'exécution | E43: PME | F43: Estimation (MAD)
A44: Prestation de blanchisserie du linge et services associés au profit des journalistes présentateurs | B44: Services | C44: T2 | D44: Rabat | E44: Oui | F44: 60000
A47: Direction Audit et Contrôle et de Gestion
A48: < Retour à la matrice
A49: Nb marchés : 1 | Montant total estimé : 840 000 MAD
A50: Nature | B50: Nb marchés | C50: Montant estimé (MAD)
A51: Fournitures | B51: 0 | C51: 0
A52: Services | B52: 1 | C52: 840000
A53: Travaux | B53: 0 | C53: 0
A55: Objet | B55: Nature | C55: Période | D55: Lieu d'exécution | E55: PME | F55: Estimation (MAD)
A56: Elaboration d'une cartographie des risques couvrant les processus de la SNRT | B56: Services | C56: T2 | D56: Rabat | E56: Non | F56: 840000
A59: Direction Centrale Marketing et Programmation TV
A60: < Retour à la matrice
A61: Nb marchés : 8 | Montant total estimé : 27 980 000 MAD
A62: Nature | B62: Nb marchés | C62: Montant estimé (MAD)
A63: Fournitures | B63: 2 | C63: 6000000
A64: Services | B64: 6 | C64: 21980000
A65: Travaux | B65: 0 | C65: 0
A67: Objet | B67: Nature | C67: Période | D67: Lieu d'exécution | E67: PME | F67: Estimation (MAD)
A68: Réalisation d'études qualitatives et quantitatives marketing pour la SNRT | B68: Services | C68: T4 | D68: Royaume du Maroc | E68: Non | F68: 800000
A69: Maintenance du portail de la SNRT | B69: Services | C69: T2 | D69: Rabat | E69: Non | F69: 730000
A70: Production de flags et bonnettes pour les micros des chaînes TV et radios de la SNRT | B70: Fournitures | C70: T2 | D70: Rabat | E70: Non | F70: 500000
A71: Stratégie Marketing, conseil en communication, exécution et production des campagnes | B71: Services | C71: T4 | D71: Rabat | E71: Non | F71: 4000000
A72: Location de supports d'affichage urbain 4x3 pour la promotion des produits et services de la SNRT | B72: Services | C72: T2 | D72: Rabat | E72: Non | F72: 11700000
A73: Production de spots / films publicitaires pour la promotion des produits et services de la SNRT | B73: Services | C73: T2 | D73: Royaume du Maroc | E73: Non | F73: 2750000
A74: Décor JT Al Aoula , Laayoune, Tamazight Habillage chaînes SNRT | B74: Fournitures | C74: T2 | D74: Rabat et Laayoune | E74: Non | F74: 5500000
A75: Décors virtuels des chaînes de la SNRT | B75: Services | C75: T2 | D75: Rabat/Casablanca | E75: Non | F75: 2000000
A78: Direction Centrale Technique
A79: < Retour à la matrice
A80: Nb marchés : 33 | Montant total estimé : 133 010 036 MAD
A81: Nature | B81: Nb marchés | C81: Montant estimé (MAD)
A82: Fournitures | B82: 29 | C82: 128930036
A83: Services | B83: 4 | C83: 4080000
A84: Travaux | B84: 0 | C84: 0
A86: Objet | B86: Nature | C86: Période | D86: Lieu d'exécution | E86: PME | F86: Estimation (MAD)
A87: Acquisition de systèmes de caméras aériennes sur câbles pour répondre aux besoins de production de la SNRT. | B87: Fournitures | C87: T2 | D87: Rabat - Tanger | E87: Non | F87: 13200000
A88: Acquisition de matériel audio/vidéo pour le renouvellement des dispositifs des unités mobiles de la SNRT. | B88: Fournitures | C88: T2 | D88: Témara | E88: Non | F88: 6000000
A89: Acquisition de véhicules « Support Trucks » pour répondre aux besoins des unités mobiles de la SNRT. | B89: Fournitures | C89: T2 | D89: Témara | E89: Non | F89: 7200000
A90: Acquisition des équipements de machinerie et d'éclairage pour répondre aux besoins de production de la SNRT | B90: Fournitures | C90: T2 | D90: Témara | E90: Non | F90: 2400000
A91: Acquisition de véhicules utilitaires aménagés pour abriter les équipements d'éclairage et de machinerie pour répondre aux besoins de production de la SNRT. | B91: Fournitures | C91: T2 | D91: Témara | E91: Non | F91: 4800000
A92: Renouvellement et mise à niveau des équipements d'enregistrement, de lecture et de traitement pour les besoins du système News Room de la SNRT. | B92: Fournitures | C92: T2 | D92: Rabat | E92: Non | F92: 7200000
A93: Contrat de support logiciel du système News Room (PAM et NRCS) pour les besoins des chaines TV de la SNRT. | B93: Services | C93: T2 | D93: Rabat | E93: Non | F93: 600000
A94: Renouvellement des licences logicielles pour les stations d’habillage et de graphisme pour les besoins des chaînes TV de la SNRT. | B94: Services | C94: T2 | D94: Rabat | E94: Oui | F94: 480000
A95: Renouvellement des équipements audio/vidéo et des châssis de traitement de signaux pour répondre aux besoins des installations techniques de la SNRT. | B95: Fournitures | C95: T2 | D95: Rabat | E95: Non | F95: 2400000
A96: Mise en place d'un système d'automation TV pour répondre aux besoins de la diffusion des chaines TV de la SNRT. | B96: Fournitures | C96: T3 | D96: Rabat | E96: Non | F96: 6000000
A97: Renouvellement des équipements Audio/Vidéo pour répondre aux besoins des chaines TV de la SNRT. | B97: Fournitures | C97: T3 | D97: Rabat | E97: Non | F97: 2400000
A98: Acquisition et mise à niveau des équipements Audio/vidéo de la régie multidiffusion pour répondre aux besoins de la chaine Arryadia de la SNRT. | B98: Fournitures | C98: T2 | D98: Rabat | E98: Non | F98: 6000000
... A119: Fourniture et mise en service d'un systéme d'intercom boradcast pour les besoins de la SNRT | B119: Fournitures | C119: T2 | D119: Rabat | E119: Non | F119: 291156
A122: Direction Centrale de la Production et de l'Antenne
A123: < Retour à la matrice
A124: Nb marchés : 3 | Montant total estimé : 3 212 000 MAD
A125: Nature | B125: Nb marchés | C125: Montant estimé (MAD)
A126: Fournitures | B126: 0 | C126: 0
A127: Services | B127: 3 | C127: 3212000
A128: Travaux | B128: 0 | C128: 0
A130: Objet | B130: Nature | C130: Période | D130: Lieu d'exécution | E130: PME | F130: Estimation (MAD)
A131: Décors Emissions Internes Al Aoula | B131: Services | C131: T2 | D131: Casablanca / Rabat | E131: Oui | F131: 1620000
A132: Location Ecrans & Barres à Led | B132: Services | C132: T2 | D132: Casablanca / Rabat | E132: Oui | F132: 360000
A133: Location Matériel pour les productions internes Al Aoula | B133: Services | C133: T2 | D133: Casablanca / Rabat | E133: Oui | F133: 1232000
A136: Direction Centrale de la Régie publicitaire et des Solutions Digitales
A137: < Retour à la matrice
A138: Nb marchés : 13 | Montant total estimé : 5 454 940 MAD
A139: Nature | B139: Nb marchés | C139: Montant estimé (MAD)
A140: Fournitures | B140: 0 | C140: 0
A141: Services | B141: 13 | C141: 5454940
A142: Travaux | B142: 0 | C142: 0
...
